Workbook

Sheet Start Here
A1: MDS decision workbook — Beyond the Bottleneck (Group WGB3)
A2: Enabling smarter lunch flow by optimising queue management and capacity utilisation across Chefs Touch centres (Central CT and Munch Mess, 11:30–14:30).
A4: How to use
A5: 1. Change only BLUE cells, and almost all of them live on the Inputs tab. Black cells are formulas; GREEN cells pull values from another tab.
A6: 2. YELLOW cells are not measured yet (assumed or group estimate). Replace them with measurements (Data Collection tab).
A7: 3. Green-filled cells are the key results. The Checks tab must say ALL OK: | C7: =Checks!$C$27 -> ALL OK
A9: How the parts fit together
A10: Inputs → S15 Queuing (the analytic model) → LP Student Flow (the primary decision: students per mess per slot) → LP Food Allocation (food supports the flow)
A11: Inputs → the simulator (python -m messq.scenarios) → Scenarios, S7 Payoff Matrix, Reconciliation (why the two models differ)
A12: Decision Rule = how the screens turn estimates into advice: when Central, when Munch, when no advice
A14: Status tags
A15: Tag | B15: Meaning | C15: Example
A16: Measured | B16: From field work, CT or the group | C16: 2,960 students; seats 900 / 492; 2 stations + 1 scanner per mess
A17: Group estimate | B17: The group's figure, not yet timed | C17: Eating 14–18 min; disposal ≤ 2 min; food ready 70% of the time
A18: Assumed | B18: A placeholder until measured | C18: 10 students/min per station; MIT lab share; DLHS/MILHS size
A19: Calibrated | B19: Not measured: chosen so the model reproduces what was observed | C19: Lag from the start of a lunch break to the mess door
A20: Simulated | B20: Output of the simulator, 20 lunches per row | C20: Average wait 4.3 → 0.8 min on a busy day
A21: Policy | B21: Our design choice | C21: Minimum saving 2 min before suggesting a switch
A22: Tabs
A23: Tab | B23: Session(s) | C23: What it does
A24: Inputs | B24: — | C24: One assumptions table: value, unit, status, source, date, where it is used
A25: S2-3 Problem & Root Cause | B25: 2–3 | C25: Problem and decision; 5 Whys backtracked from the Phase 1 symptom; fishbone; issue tree
A26: S4 Biases & Ethics | B26: 4 | C26: Status quo, herding, loss aversion, missing information (hypotheses vs findings); DPDP ethics
A27: S5-6 Priority Matrix | B27: 5–6 | C27: ABC/XYZ menu matrix; tray weights; impact–effort matrix; decision dilemmas
A28: Arrival Curve | B28: 15 | C28: Department lunch breaks added up: when students arrive, and the 13:10–13:30 overlap
A29: S15 Queuing | B29: 15 | C29: M/M/1 check, utilisation curve, M/M/c + fluid queue by 10-min slot, four-stage throughput
A30: LP Student Flow | B30: 10–11 | C30: PRIMARY model: students to direct to each mess per slot; food as a constraint; shadow price
A31: LP Food Allocation | B31: 10–11 | C31: SECONDARY model: the star dish split that supports the flow; graphical method
A32: S7 Payoff Matrix | B32: 7 | C32: Five alternatives × three kinds of day, every cell simulated: maximax, maximin, Hurwicz, Laplace, EMV, regret, EVPI
A33: S18 Heuristics | B33: 18 | C33: Door-screen rule, reorder point, heuristic vs full model vs LP bound, metaheuristics
A34: Decision Rule | B34: — | C34: When the screen recommends Munch, Central, or gives no advice; worked situations
... A39: Checks | B39: — | C39: Validation: no errors, balances, constraints, calibration, response to inputs

Sheet Inputs
A1: Inputs: every assumption the workbook and the simulator use
A2: Change BLUE cells only. Yellow = not measured yet (assumed or group estimate): replace with measured data. The simulator reads the same values from config/default.toml.
A4: Parameter | B4: Value | C4: Unit | D4: Status | E4: Source / how to measure | F4: Date | G4: Used in
A5: MEASURED (Phase 1 field work, CT, the group)
A6: Students per lunch at Central CT + Munch (= plates served) | B6: 2960 | C6: students | D6: Measured | E6: Phase 1 deck: ~2,960 plates; one plate per student. Daily counts 2,810–3,465 | F6: Sep 2026 | G6: S15, LP Student Flow, all scenarios
A7: Lunch opens | B7: 11:30 | C7: time | D7: Measured | E7: Mess timings 11:30–14:30 | F7: Oct 2026 | G7: S15, LP Student Flow
A8: Lunch window length | B8: 180 | C8: minutes | D8: Measured | E8: 11:30–14:30 | F8: Oct 2026 | G8: S15
A9: Seats: Central CT | B9: 900 | C9: seats | D9: Measured | E9: Group measurement | F9: Oct 2026 | G9: S15, simulator
A10: Seats: Munch Mess | B10: 492 | C10: seats | D10: Measured | E10: Group measurement | F10: Oct 2026 | G10: S15, simulator
A11: Serving stations: Central CT | B11: 2 | C11: stations | D11: Measured | E11: Group observation | F11: Oct 2026 | G11: S15, LP, Decision Rule
A12: Serving stations: Munch Mess | B12: 2 | C12: stations | D12: Measured | E12: Group observation | F12: Oct 2026 | G12: S15, LP, Decision Rule
A13: Face scanners at the entrance: Central CT | B13: 1 | C13: scanners | D13: Measured | E13: Group observation | F13: Oct 2026 | G13: S15
A14: Face scanners at the entrance: Munch Mess | B14: 1 | C14: scanners | D14: Measured | E14: Group observation | F14: Oct 2026 | G14: S15
A15: Normal visit, scan to leaving (quiet times) | B15: 20 | C15: minutes | D15: Group estimate | E15: Group: about 20 min on a normal day | F15: Oct 2026 | G15: Checks (calibration)
A16: Throughput time range: low (quiet) | B16: 17 | C16: minutes | D16: Group estimate | E16: Group: door to leaving takes 17–35 min depending on the rush | F16: Oct 2026 | G16: Checks (calibration)
A17: Throughput time range: high (surge) | B17: 35 | C17: minutes | D17: Group estimate | E17: As above | F17: Oct 2026 | G17: Checks (calibration)
A18: Refill after the 'running low' call if the food must be made (make + send) | B18: 30 | C18: minutes | D18: Measured | E18: Group: the 30 min starts when the mess calls the kitchen | F18: Oct 2026 | G18: Decision Rule, S18, simulator
A19: Refill if the food is already made: sending only (low) | B19: 10 | C19: minutes | D19: Measured | E19: Group: 10–14 min | F19: Oct 2026 | G19: Decision Rule, simulator
... A21: Delay faced by students at the peak (observed) | B21: 15 | C21: minutes | D21: Measured | E21: Phase 1 deck: ~15 min | F21: Sep 2026 | G21: Checks (calibration)
A22: THE FOUR STAGES OF A VISIT (group estimates where given, else assumed)
A23: Stage 1: one face scan | B23: 2 | C23: seconds | D23: Assumed | E23: Stopwatch at the scanner, or gaps between scans in the logs | F23: — | G23: S15, simulator
A24: Stage 1: collect a plate after the scan (low) | B24: 28 | C24: seconds | D24: Group estimate | E24: Group: scan + plate takes 30–45 s | F24: — | G24: S15, simulator
A25: Stage 1: collect a plate after the scan (high) | B25: 43 | C25: seconds | D25: Group estimate | E25: As above | F25: — | G25: S15, simulator
A26: Stage 2: service rate per serving station | B26: 10 | C26: students/min | D26: Assumed | E26: ≈6 s per student. Must be about this fast for 2 stations to serve ~2,360 Central students, mostly within two hours. Stopwatch 20–30 students | F26: — | G26: S15, LP, Decision Rule, simulator
A27: Stage 2: rest of food collection after the station (low) | B27: 54 | C27: seconds | D27: Group estimate | E27: Group: collecting food takes 1–2 min without a queue, incl. ~6 s at the station | F27: — | G27: S15, simulator
A28: Stage 2: rest of food collection (high) | B28: 114 | C28: seconds | D28: Group estimate | E28: As above | F28: — | G28: S15, simulator
A29: Stage 3: eating at a table (low) | B29: 14 | C29: minutes | D29: Group estimate | E29: Group: 14–18 min | F29: Oct 2026 | G29: S15, simulator
A30: Stage 3: eating at a table (high) | B30: 18 | C30: minutes | D30: Group estimate | E30: As above | F30: Oct 2026 | G30: S15, simulator
A31: Stage 3: staying at the table after eating (the seat stays taken) | B31: 9 | C31: minutes | D31: Group estimate | E31: Chatting, waiting for friends: a seat is held ~25 min, which is why the hall looks full | F31: Oct 2026 | G31: S15, simulator
A32: Stage 4: dispose of leftovers and the plate (low) | B32: 1 | C32: minutes | D32: Group estimate | E32: Group: 2 min at most | F32: Oct 2026 | G32: S15, simulator
A33: Stage 4: dispose of leftovers and the plate (high) | B33: 2 | C33: minutes | D33: Group estimate | E33: As above | F33: Oct 2026 | G33: S15, simulator
A34: BEHAVIOUR AND DEMAND
A35: Share who go to Central CT by habit (no screens) | B35: 0.797 | C35: share | D35: Measured | E35: Group: ~2,360 eat at Central and ~600 at Munch of ~2,960. A day of biometric logs confirms it (Data Collection tab) | F35: Oct 2026 | G35: S15, LP, scenarios
A36: Share of students who follow the screen | B36: 0.6 | C36: share | D36: Assumed | E36: The pilot measures it; stress-tested at 30% and 100% | F36: — | G36: S15, LP, scenarios
A37: Walk between the two mess doors | B37: 0.5 | C37: minutes | D37: Assumed | E37: 30 s; walk it with a stopwatch | F37: — | G37: LP, Decision Rule, simulator
A38: Minutes from the start of a department's lunch break to the mess door: mean | B38: 20 | C38: minutes | D38: Calibrated | E38: Chosen so the no-screen simulation fits the 17–35 min visit and ~15 min peak delay. Logs + timetable measure it | F38: — | G38: Arrival Curve, simulator
A39: Same lag: spread (standard deviation); cut off at the end of the break | B39: 20 | C39: minutes | D39: Calibrated | E39: Stress-tested at 15 ± 10 min (everyone rushes at the bell) | F39: — | G39: Arrival Curve, simulator
A40: DEPARTMENT LUNCH BREAKS (sizes are rough counts, used as shares and scaled to the plates served)
A41: MIT: students (rough) | B41: 1100 | C41: students | D41: Group estimate | E41: Group: ~1,100 (rough) | F41: Oct 2026 | G41: Arrival Curve, simulator
A42: MIT: lunch break starts | B42: 0.5 | C42: time | D42: Measured | E42: Department timetable | F42: Oct 2026 | G42: Arrival Curve, simulator
A43: MIT: lunch break ends | B43: 0.54166667 | C43: time | D43: Measured | E43: Department timetable | F43: Oct 2026 | G43: Arrival Curve, simulator
A44: MIT: share eating in the lab-day break (average weekday) | B44: 0.45 | C44: share | D44: Assumed | E44: Labs: electrical 3 days/week, other branches 2. Assumed 5-day week, ~25% electrical: 0.75×2/5 + 0.25×3/5 | F44: Oct 2026 | G44: Arrival Curve, simulator
A45: MIT: lab-day break starts | B45: 0.54166667 | C45: time | D45: Measured | E45: Group: 13:00–14:00 if there is a lab | F45: Oct 2026 | G45: Arrival Curve, simulator
A46: MIT: lab-day break ends | B46: 0.58333333 | C46: time | D46: Measured | E46: As above | F46: Oct 2026 | G46: Arrival Curve, simulator
A47: TAPMI: students (rough) | B47: 850 | C47: students | D47: Group estimate | E47: Group: ~850 (rough) | F47: Oct 2026 | G47: Arrival Curve, simulator
A48: TAPMI: lunch break starts | B48: 0.54513889 | C48: time | D48: Measured | E48: Department timetable | F48: Oct 2026 | G48: Arrival Curve, simulator
A49: TAPMI: lunch break ends | B49: 0.58333333 | C49: time | D49: Measured | E49: Department timetable | F49: Oct 2026 | G49: Arrival Curve, simulator
A50: DOC/MICFE: students (rough) | B50: 550 | C50: students | D50: Group estimate | E50: Group: ~550 (rough) | F50: Oct 2026 | G50: Arrival Curve, simulator
A51: DOC/MICFE: lunch break starts | B51: 0.52083333 | C51: time | D51: Measured | E51: Department timetable | F51: Oct 2026 | G51: Arrival Curve, simulator
A52: DOC/MICFE: lunch break ends | B52: 0.5625 | C52: time | D52: Measured | E52: Department timetable | F52: Oct 2026 | G52: Arrival Curve, simulator
... A64: MIRM: lunch break ends | B64: 0.5625 | C64: time | D64: Assumed | E64: Timing not known: placed in the middle of the other breaks | F64: Oct 2026 | G64: Arrival Curve, simulator
A65: FOOD
A66: Chance the next batch is already made when the mess calls | B66: 0.7 | C66: share | D66: Group estimate | E66: Group: about 70% of the time | F66: Oct 2026 | G66: Decision Rule, simulator
A67: Food left when the manager taps 'running low' (= calls the kitchen) | B67: 20 | C67: minutes | D67: Assumed | E67: Protocol for the manager. Record tap times and run-out times to check it | F67: — | G67: Decision Rule, simulator
A68: Star-dish servings per student | B68: 1 | C68: servings | D68: Assumed | E68: Star dish is refillable: measure portions issued ÷ plates | F68: — | G68: LP Food Allocation
A69: Star-dish portions Munch can serve this lunch (plan) | B69: 1000 | C69: portions | D69: Assumed | E69: Ask CT: batches planned for Munch | F69: — | G69: LP Student Flow (food constraint)
A70: Star-dish portions the kitchen can have ready before the peak | B70: 2400 | C70: portions | D70: Assumed | E70: Ask CT | F70: — | G70: LP Food Allocation
A71: KINDS OF DAY (for the payoff matrix; from the biometric logs once available)
A72: Share of lunches that are normal (−20% students) | B72: 0.3 | C72: share | D72: Assumed | E72: Count days by arrivals in the logs | F72: — | G72: S7 Payoff Matrix
A73: Share of lunches that are busy (~2,960 students) | B73: 0.5 | C73: share | D73: Assumed | E73: As above | F73: — | G73: S7 Payoff Matrix
A74: Share of lunches with a surge and late refills | B74: 0.2 | C74: share | D74: Assumed | E74: As above | F74: — | G74: S7 Payoff Matrix
A75: POLICY SETTINGS (our choice)
A76: Target maximum utilisation per station | B76: 0.85 | C76: share | D76: Policy | E76: Above ~85% waits rise steeply (S15) | F76: — | G76: S15
A77: Minimum saving before a screen suggests switching | B77: 2 | C77: minutes | D77: Policy | E77: Prototype setting (config: layout.min_saving_min) | F77: — | G77: Decision Rule, S18, simulator
A78: Extra margin for estimate uncertainty | B78: 0.5 | C78: minutes | D78: Policy | E78: Added to the minimum saving in the decision rule | F78: — | G78: Decision Rule
A79: No advice if a scanner has sent nothing for | B79: 3 | C79: minutes | D79: Policy | E79: Data check: a silent scanner means the estimate is stale | F79: — | G79: Decision Rule
A81: DERIVED (formulas: do not type here)
A82: Serving capacity: Central CT (stations × service rate) | B82: =Inputs!$B$11*Inputs!$B$26 -> 20 | C82: students/min | D82: Derived
A83: Serving capacity: Munch Mess | B83: =Inputs!$B$12*Inputs!$B$26 -> 20 | C83: students/min | D83: Derived
A84: Scanner capacity: Central (scanners × 60 ÷ seconds per scan) | B84: =Inputs!$B$13*60/Inputs!$B$23 -> 30 | C84: students/min | D84: Derived
A85: Scanner capacity: Munch | B85: =Inputs!$B$14*60/Inputs!$B$23 -> 30 | C85: students/min | D85: Derived
A86: Stage 1 time with no queue: scan + collect a plate | B86: =(Inputs!$B$23+(Inputs!$B$24+Inputs!$B$25)/2)/60 -> 0.625 | C86: minutes | D86: Derived
A87: Stage 2 time after the station: walk the food line | B87: =(Inputs!$B$27+Inputs!$B$28)/2/60 -> 1.4 | C87: minutes | D87: Derived
A88: Stage 3 seat held: mean eating time + staying at the table | B88: =(Inputs!$B$29+Inputs!$B$30)/2+Inputs!$B$31 -> 25 | C88: minutes | D88: Derived
A89: Stage 4 mean disposal time | B89: =(Inputs!$B$32+Inputs!$B$33)/2 -> 1.5 | C89: minutes | D89: Derived
A90: Throughput with no queues: stage 1 + serving + food line + eating + disposal | B90: =Inputs!$B$86+1/Inputs!$B$26+Inputs!$B$87+Inputs!$B$88+Inputs!$B$89 -> 28.625 | C90: minutes | D90: Derived
A91: Expected refill time from the call: ready × (10–14 mean) + not ready × 30 | B91: =Inputs!$B$66*(Inputs!$B$19+Inputs!$B$20)/2+(1-Inputs!$B$66)*Inputs!$B$18 -> 17.4 | C91: minutes | D91: Derived
A92: Arrivals the seats can absorb: Central (Little's Law: seats ÷ seat time) | B92: =Inputs!$B$9/Inputs!$B$88 -> 36 | C92: students/min | D92: Derived
A93: Arrivals the seats can absorb: Munch | B93: =Inputs!$B$10/Inputs!$B$88 -> 19.68 | C93: students/min | D93: Derived

Sheet S2-3 Problem & Root Cause
A1: Problem definition, decision context and root causes
A2: Sessions 2–3: Nature of business decisions · Problem identification, structuring, root cause analysis
A4: Problem statement (Phase 2: Beyond the Bottleneck)
A5: During the 11:30–14:30 lunch window, Chefs Touch serves about 2,960 students at Central CT and Munch Mess, which serve the same menu 30 seconds apart. Total serving capacity is enough on average but is used unevenly: one mess saturates while the other has spare capacity, so students wait (~15 min observed), and star-dish run-outs at the busy mess make it worse.
A6: Primary decision (LP Student Flow): how many students should be directed to each mess in each 10-minute slot, so that waiting falls without adding staff or space? Constraints: serving capacity, food availability, walking time, compliance, demand uncertainty. Secondary decision (LP Food Allocation): how should the star dish be allocated and replenished to support that flow?
A8: Session 2: nature of the decision
A9: Dimension | B9: Classification | C9: Why
A10: Level | B10: Operational | C10: Made every lunch, minute by minute, at the mess door and in the kitchen
A11: Structure | B11: Structured / programmable | C11: The same choice repeats daily; inputs can be measured (scans, stock, stations)
A12: Certainty | B12: Under risk / uncertainty | C12: Daily demand varies; probabilities come from the biometric logs
A13: Frequency | B13: Recurring (daily) | C13: Justifies a model and a decision rule instead of ad-hoc judgement
A14: Decision makers | B14: Mess manager (food status), students (which mess) | C14: Students' choice of mess is itself a decision we can inform
A16: Session 3: 5 Whys, backtracked. Phase 1 stopped at a symptom; Phase 2 follows the chain to the root cause
A17: Why? | B17: Phase 1 answer (symptom) | C17: Phase 2 answer (after backtracking) | D17: Evidence | E17: Status
A18: 1. Why do students wait ~15 min? | B18: Food runs out at peak | C18: Central's serving stations are overloaded at peak | D18: Line was at the stations; trays and seats free (field visit) | E18: Observed
A19: 2. Why are they overloaded? | B19: — | C19: ~30 arrive/min against 20/min capacity at the 13:10 overlap, while Munch gets ~8 | D19: S15 Queuing, Scenarios (simulated) | E19: Simulated; logs will confirm
A20: 3. Why so uneven? | B20: — | C20: About 80% go to Central by habit (~2,360 of ~2,960) | D20: Inputs: habit share | E20: Measured (group)
A21: 4. Why habit? | B21: — | C21: At the moment of choosing, nobody can see how busy either mess is | D21: S4 Biases | E21: Hypothesis (survey)
A22: 5. Why not? | B22: — | C22: Every entry is already scanned, but the data is never used live | D22: Biometric system exists (COSEC) | E22: Observed
A24: Food chain: star dishes run out mid-peak → refills start only at a 'running low' call → 30 min if not already made → no forecast from live arrivals. Both chains end at the same gap: live demand data exists but nobody acts on it.
A26: Session 3: fishbone (cause-and-effect) for 'long wait at lunch'
A27: People | B27: Process | C27: Policy | D27: Information | E27: Logistics / place
A28: Students arrive together at peak | B28: 2 serving stations and 1 face scanner per mess | C28: Replenishment is reactive | D28: No live view of demand | E28: Delivery shares the student walkway
A29: Habit: same mess every day | B29: Refilling at the counter stops the line | C29: Base foods under-buffered | D29: Published menu ≠ served menu | E29: Return station not measured
A30: Herding: a long line looks better | B30: Serving rate not measured | C30: No reorder point | D30: No per-mess forecast | E30: One kitchen supplies five centres
A32: Issue tree (problem structuring)
A33: Branch | B33: Sub-question | C33: Tool in this workbook
A34: Demand | B34: When and where do students arrive? Is Central really busier? | C34: Data Collection, S15 Queuing
A35: Capacity | B35: How many stations, how fast, how much spare at Munch? | C35: S15 Queuing, Scenarios (stress tests)
A36: Allocation of students | B36: How many to send to each mess, when? | C36: LP Student Flow (primary model), Decision Rule
A37: Allocation of food | B37: How much of the star dish to each mess, and when to refill? | C37: LP Food Allocation, Decision Rule (refill clock), S18
A38: Choice of intervention | B38: Which option is best on normal, busy and surge days? | C38: S7 Payoff Matrix, Scenarios
A39: Model trust | B39: Do the spreadsheet and the simulator agree? | C39: Reconciliation, Simulation Method, Checks

Sheet S4 Biases & Ethics
A1: Decision biases and ethical decision making
A2: Session 4: Decision-making frameworks, decision biases, ethical decision making
A4: Bias | B4: Where it shows up in the mess problem | C4: How the project counters it | D4: Status
A5: Status quo / habit | B5: Students go to the same mess daily even when the other is faster | C5: Door screens show the faster option at the moment of choice | D5: Hypothesis: survey + logs
A6: Herding | B6: A long line reads as a sign the food is better; if everyone follows one signal, the 'empty' mess becomes the busy one | C6: Equal-wait split + 2-minute minimum saving (Decision Rule) | D6: Shown in simulation (Scenarios: naive vs proposal)
A7: Loss aversion | B7: The 30-second walk feels like a cost; minutes in line don't | C7: Show the saving in minutes ('save ~8 min') | D7: Hypothesis: survey
A8: No information (bounded rationality) | B8: From the door you can't see the other mess's queue | C8: Live estimates on screens and phones | D8: Observed
A9: Anchoring (planning) | B9: Kitchen plans from the published menu; the served menu differed | C9: Record the actual menu; forecast from observed arrivals | D9: Observed (field visit)
A10: Confirmation (our team) | B10: We want the screens to look good | C10: Report observed / assumed / simulated separately; if the logs show Munch is not underused, revise the diagnosis | D10: Built into this workbook
A12: Ethics checklist
A13: Principle | B13: What we do | C13: Status
A14: Data minimisation (DPDP Act 2023) | B14: Request only scan time + mess + pseudonymous ID; no face data or templates | C14: Built into data request
A15: Pseudonymisation | B15: IDs hashed on reading; names hidden by default | C15: Built into prototype
A16: Purpose limitation & retention | B16: Use for this project only; delete at semester end | C16: Committed in email
A17: Honesty to students | B17: Suggest switching only if it saves ≥ 2 min; no advice when data is stale | C17: Built into prototype
A18: Consent / approval | B18: Written approval from college and vendor before any live connection | C18: Pending
A19: Fairness | B19: Advice is the same for everyone; no priority for any group | C19: Built into prototype

Sheet S5-6 Priority Matrix
A1: Decision dilemma and priority matrices
A2: Sessions 5–6: Decision dilemma and project priority matrix
A4: 1. Menu criticality × predictability (ABC/XYZ), MDS_dataset.xlsx 'Priority Matrix', menu week 31 Aug–6 Sep
A5: Policy | B5: Class | C5: Menu entries | D5: Share | E5: What to do
A6: Tight Control | B6: AZ | C6: 28 | D6: =C6/$C$10 -> 0.27184466 | E6: Measure and model: star dishes, chapattis, curd/raitha | F6: The dataset's field notes label curd AX while its menu ratings give AZ; we follow the ratings.
A7: Calculated Issue | B7: AX | C7: 9 | D7: =C7/$C$10 -> 0.087378641 | E7: Derive from plate count: one-per-plate sweets
A8: Buffered Issue | B8: CZ | C8: 40 | D8: =C8/$C$10 -> 0.38834951 | E8: Issue with a safety margin: rice, dal, sambar, rasam, dry veg
A9: Free Issue | B9: CX | C9: 26 | D9: =C9/$C$10 -> 0.25242718 | E9: Issue without control: pickle, salt, sugar, fryums
A10: Total | C10: =SUM(C6:C9) -> 103 | D10: =SUM(D6:D9) -> 1
A12: 2. Tray weights used by the live system (config/default.toml [[tray]]): how much a tray running low or out changes the advice
A13: Tray | B13: Item type (matrix) | C13: Class | D13: Weight | E13: When OUT | F13: Why this weight
A14: Gravy sabji, Special rice | B14: Star dish | C14: AZ | D14: ★ 1.0 | E14: Outage: that mess serves nobody until the refill | F14: 'The one item everyone notices when it is gone'
A15: Roti | B15: Made fresh in batches | C15: AZ | D15: 0.5 | E15: Adds 0.5 × expected refill time | F15: Running out is a speed problem; another tawa fixes it
A16: Dessert | B16: One per plate | C16: AX | D16: 0.3 | E16: Adds 0.3 × expected refill time | F16: Demand = plate count; errors are headcount errors
A17: Curd / raita | B17: Fresh side | C17: AZ | D17: 0.3 | E17: Adds 0.3 × expected refill time | F17: Risk is surplus more than shortage
A18: Dry sabji, Dal, Rice, Sambar / rasam | B18: Base food | C18: CZ | D18: 0.1 | E18: Adds 0.1 × expected refill time | F18: Interchangeable: 'quietly absorbed by another'
A19: Salt, pickle, fryums | B19: Table item | C19: CX | D19: 0 | E19: Not tracked | F19: Free issue
A20: Running low: a tray costs a student time only if they reach the counter after it empties and before its refill (Decision Rule). Weights are the group's reading of the matrix; confirm them with the CT manager.
A22: 3. Intervention priority matrix (impact vs effort). Impact from the Scenarios tab; effort scores are the group's judgement.
A23: Quadrant threshold (score above this = high) | C23: 3
A25: Intervention | B25: Impact (1–5) | C25: Effort (1–5) | D25: Quadrant | E25: Reason (impact) | F25: Reason (effort)
A26: A2 Door screens, queue information only | B26: 4 | C26: 3 | D26: =IF(B26>$C$23,IF(C26>$C$23,"Major project","Quick win"),IF(C26>$C$23,"Thankless task","Fill-in")) -> Quick win | E26: Busy day: wait 4.3 → 1.2 min (simulated) | F26: Two screens + a laptop; needs data access
A27: A3 Screens + food status (proposal) | B27: 5 | C27: 3 | D27: =IF(B27>$C$23,IF(C27>$C$23,"Major project","Quick win"),IF(C27>$C$23,"Thankless task","Fill-in")) -> Quick win | E27: Busy day: wait 4.3 → 0.8 min (simulated) | F27: Same as A2 + manager taps food status
A28: A4 3rd serving station at Central | B28: 4 | C28: 4 | D28: =IF(B28>$C$23,IF(C28>$C$23,"Major project","Quick win"),IF(C28>$C$23,"Thankless task","Fill-in")) -> Major project | E28: Busy day: 4.3 → 0.6 min; best on normal days | F28: Staff cost every day; space at counter
A29: A6 Larger buffers for base foods (CZ) | B29: 2 | C29: 1 | D29: =IF(B29>$C$23,IF(C29>$C$23,"Major project","Quick win"),IF(C29>$C$23,"Thankless task","Fill-in")) -> Fill-in | E29: Base foods ran dry in the field visit | F29: Just send more rice/dal/sambar
A30: A7 Stagger class end times | B30: 4 | C30: 5 | D30: =IF(B30>$C$23,IF(C30>$C$23,"Major project","Quick win"),IF(C30>$C$23,"Thankless task","Fill-in")) -> Major project | E30: SMI 15 min earlier: today's wait 4.3 → 3.3 min; TAPMI 15 min later: → 1.7 (simulated) | F30: Needs academic administration
A32: 4. Decision dilemmas
A33: Dilemma | B33: Option 1 | C33: Option 2 | E33: Trade-off | F33: How we resolve it
A34: Send students to the other mess? | B34: Strong advice (risk herding) | C34: No advice (uneven load) | E34: Balance vs trust | F34: Equal-wait split + 2-min threshold (Decision Rule, S18)
A35: React to 'running low'? | B35: Redirect early (needless walks) | C35: Wait for 'out' (late) | E35: Walks vs waits | F35: Delay only for students who would reach an empty tray (Decision Rule)
A36: Add a serving station? | B36: Yes (staff every day) | C36: No (long peak waits) | E36: Staff cost vs waiting | F36: S7 Payoff Matrix (A4, A5) and Scenarios

Sheet Arrival Curve
A1: When students arrive: department lunch breaks added up
A2: Feeds S15 Queuing and the LP. The simulator uses the same curve (config/default.toml)
A3: Scale: plates served ÷ sum of the rough department sizes | E3: =Inputs!$B$6/(Inputs!$B$41+Inputs!$B$47+Inputs!$B$50+Inputs!$B$53+Inputs!$B$56+Inputs!$B$59+Inputs!$B$62) -> 0.93968254
A5: Cohort | B5: Students (scaled) | C5: Break starts (min after opening) | D5: Break ends (min) | E5: Mean arrival (min) | F5: Share of the curve inside the break
A6: MIT | B6: =Inputs!$B$41*(1-Inputs!$B$44)*$E$3 -> 568.50794 | C6: =ROUND((Inputs!$B$42-TIMEVALUE(Inputs!$B$7))*1440,0) -> 30 | D6: =ROUND((Inputs!$B$43-TIMEVALUE(Inputs!$B$7))*1440,0) -> 90 | E6: =C6+Inputs!$B$38 -> 50 | F6: =NORMDIST(D6,E6,Inputs!$B$39,TRUE())-NORMDIST(C6,E6,Inputs!$B$39,TRUE()) -> 0.81859461
A7: MIT (lab day) | B7: =Inputs!$B$41*Inputs!$B$44*$E$3 -> 465.14286 | C7: =ROUND((Inputs!$B$45-TIMEVALUE(Inputs!$B$7))*1440,0) -> 90 | D7: =ROUND((Inputs!$B$46-TIMEVALUE(Inputs!$B$7))*1440,0) -> 150 | E7: =C7+Inputs!$B$38 -> 110 | F7: =NORMDIST(D7,E7,Inputs!$B$39,TRUE())-NORMDIST(C7,E7,Inputs!$B$39,TRUE()) -> 0.81859461
A8: TAPMI | B8: =Inputs!$B$47*$E$3 -> 798.73016 | C8: =ROUND((Inputs!$B$48-TIMEVALUE(Inputs!$B$7))*1440,0) -> 95 | D8: =ROUND((Inputs!$B$49-TIMEVALUE(Inputs!$B$7))*1440,0) -> 150 | E8: =C8+Inputs!$B$38 -> 115 | F8: =NORMDIST(D8,E8,Inputs!$B$39,TRUE())-NORMDIST(C8,E8,Inputs!$B$39,TRUE()) -> 0.80128559
A9: DOC/MICFE | B9: =Inputs!$B$50*$E$3 -> 516.8254 | C9: =ROUND((Inputs!$B$51-TIMEVALUE(Inputs!$B$7))*1440,0) -> 60 | D9: =ROUND((Inputs!$B$52-TIMEVALUE(Inputs!$B$7))*1440,0) -> 120 | E9: =C9+Inputs!$B$38 -> 80 | F9: =NORMDIST(D9,E9,Inputs!$B$39,TRUE())-NORMDIST(C9,E9,Inputs!$B$39,TRUE()) -> 0.81859461
A10: SMI | B10: =Inputs!$B$53*$E$3 -> 422.85714 | C10: =ROUND((Inputs!$B$54-TIMEVALUE(Inputs!$B$7))*1440,0) -> 30 | D10: =ROUND((Inputs!$B$55-TIMEVALUE(Inputs!$B$7))*1440,0) -> 90 | E10: =C10+Inputs!$B$38 -> 50 | F10: =NORMDIST(D10,E10,Inputs!$B$39,TRUE())-NORMDIST(C10,E10,Inputs!$B$39,TRUE()) -> 0.81859461
A11: DLHS/MILHS | B11: =Inputs!$B$56*$E$3 -> 93.968254 | C11: =ROUND((Inputs!$B$57-TIMEVALUE(Inputs!$B$7))*1440,0) -> 70 | D11: =ROUND((Inputs!$B$58-TIMEVALUE(Inputs!$B$7))*1440,0) -> 130 | E11: =C11+Inputs!$B$38 -> 90 | F11: =NORMDIST(D11,E11,Inputs!$B$39,TRUE())-NORMDIST(C11,E11,Inputs!$B$39,TRUE()) -> 0.81859461
A12: MLS | B12: =Inputs!$B$59*$E$3 -> 46.984127 | C12: =ROUND((Inputs!$B$60-TIMEVALUE(Inputs!$B$7))*1440,0) -> 80 | D12: =ROUND((Inputs!$B$61-TIMEVALUE(Inputs!$B$7))*1440,0) -> 140 | E12: =C12+Inputs!$B$38 -> 100 | F12: =NORMDIST(D12,E12,Inputs!$B$39,TRUE())-NORMDIST(C12,E12,Inputs!$B$39,TRUE()) -> 0.81859461
A13: MIRM | B13: =Inputs!$B$62*$E$3 -> 46.984127 | C13: =ROUND((Inputs!$B$63-TIMEVALUE(Inputs!$B$7))*1440,0) -> 60 | D13: =ROUND((Inputs!$B$64-TIMEVALUE(Inputs!$B$7))*1440,0) -> 120 | E13: =C13+Inputs!$B$38 -> 80 | F13: =NORMDIST(D13,E13,Inputs!$B$39,TRUE())-NORMDIST(C13,E13,Inputs!$B$39,TRUE()) -> 0.81859461
A14: Total | B14: =SUM(B6:B13) -> 2960
A15: Each department starts arriving when its lunch break starts. A student's lag after the break starts is Normal(mean, spread) from the Inputs tab, cut off at the end of the break, so each cohort's arrivals add up to its size. MIT eats 13:00–14:00 on lab days. The sizes are rough and add up to more than the plates served, so they are used as shares. The biometric logs replace this whole tab once available.
A17: Arrivals per 10-minute slot
A18: Slot | B18: Minute | C18: MIT | D18: MIT (lab day) | E18: TAPMI | F18: DOC/MICFE | G18: SMI | H18: DLHS/MILHS | I18: MLS | J18: MIRM | K18: Total | L18: Share
A19: 11:30 | B19: 0 | C19: =$B$6*(NORMDIST(MIN($D$6,MAX($C$6,$B19+10)),$E$6,Inputs!$B$39,TRUE())-NORMDIST(MIN($D$6,MAX($C$6,$B19)),$E$6,Inputs!$B$39,TRUE()))/$F$6 -> 0 | D19: =$B$7*(NORMDIST(MIN($D$7,MAX($C$7,$B19+10)),$E$7,Inputs!$B$39,TRUE())-NORMDIST(MIN($D$7,MAX($C$7,$B19)),$E$7,Inputs!$B$39,TRUE()))/$F$7 -> 0 | E19: =$B$8*(NORMDIST(MIN($D$8,MAX($C$8,$B19+10)),$E$8,Inputs!$B$39,TRUE())-NORMDIST(MIN($D$8,MAX($C$8,$B19)),$E$8,Inputs!$B$39,TRUE()))/$F$8 -> 0 | F19: =$B$9*(NORMDIST(MIN($D$9,MAX($C$9,$B19+10)),$E$9,Inputs!$B$39,TRUE())-NORMDIST(MIN($D$9,MAX($C$9,$B19)),$E$9,Inputs!$B$39,TRUE()))/$F$9 -> 0 | G19: =$B$10*(NORMDIST(MIN($D$10,MAX($C$10,$B19+10)),$E$10,Inputs!$B$39,TRUE())-NORMDIST(MIN($D$10,MAX($C$10,$B19)),$E$10,Inputs!$B$39,TRUE()))/$F$10 -> 0 | H19: =$B$11*(NORMDIST(MIN($D$11,MAX($C$11,$B19+10)),$E$11,Inputs!$B$39,TRUE())-NORMDIST(MIN($D$11,MAX($C$11,$B19)),$E$11,Inputs!$B$39,TRUE()))/$F$11 -> 0 | I19: =$B$12*(NORMDIST(MIN($D$12,MAX($C$12,$B19+10)),$E$12,Inputs!$B$39,TRUE())-NORMDIST(MIN($D$12,MAX($C$12,$B19)),$E$12,Inputs!$B$39,TRUE()))/$F$12 -> 0 | J19: =$B$13*(NORMDIST(MIN($D$13,MAX($C$13,$B19+10)),$E$13,Inputs!$B$39,TRUE())-NORMDIST(MIN($D$13,MAX($C$13,$B19)),$E$13,Inputs!$B$39,TRUE()))/$F$13 -> 0 | K19: =SUM(C19:J19) -> 0 | L19: =K19/SUM($K$19:$K$36) -> 0
A20: 11:40 | B20: 10 | C20: =$B$6*(NORMDIST(MIN($D$6,MAX($C$6,$B20+10)),$E$6,Inputs!$B$39,TRUE())-NORMDIST(MIN($D$6,MAX($C$6,$B20)),$E$6,Inputs!$B$39,TRUE()))/$F$6 -> 0 | D20: =$B$7*(NORMDIST(MIN($D$7,MAX($C$7,$B20+10)),$E$7,Inputs!$B$39,TRUE())-NORMDIST(MIN($D$7,MAX($C$7,$B20)),$E$7,Inputs!$B$39,TRUE()))/$F$7 -> 0 | E20: =$B$8*(NORMDIST(MIN($D$8,MAX($C$8,$B20+10)),$E$8,Inputs!$B$39,TRUE())-NORMDIST(MIN($D$8,MAX($C$8,$B20)),$E$8,Inputs!$B$39,TRUE()))/$F$8 -> 0 | F20: =$B$9*(NORMDIST(MIN($D$9,MAX($C$9,$B20+10)),$E$9,Inputs!$B$39,TRUE())-NORMDIST(MIN($D$9,MAX($C$9,$B20)),$E$9,Inputs!$B$39,TRUE()))/$F$9 -> 0 | G20: =$B$10*(NORMDIST(MIN($D$10,MAX($C$10,$B20+10)),$E$10,Inputs!$B$39,TRUE())-NORMDIST(MIN($D$10,MAX($C$10,$B20)),$E$10,Inputs!$B$39,TRUE()))/$F$10 -> 0 | H20: =$B$11*(NORMDIST(MIN($D$11,MAX($C$11,$B20+10)),$E$11,Inputs!$B$39,TRUE())-NORMDIST(MIN($D$11,MAX($C$11,$B20)),$E$11,Inputs!$B$39,TRUE()))/$F$11 -> 0 | I20: =$B$12*(NORMDIST(MIN($D$12,MAX($C$12,$B20+10)),$E$12,Inputs!$B$39,TRUE())-NORMDIST(MIN($D$12,MAX($C$12,$B20)),$E$12,Inputs!$B$39,TRUE()))/$F$12 -> 0 | J20: =$B$13*(NORMDIST(MIN($D$13,MAX($C$13,$B20+10)),$E$13,Inputs!$B$39,TRUE())-NORMDIST(MIN($D$13,MAX($C$13,$B20)),$E$13,Inputs!$B$39,TRUE()))/$F$13 -> 0 | K20: =SUM(C20:J20) -> 0 | L20: =K20/SUM($K$19:$K$36) -> 0
A21: 11:50 | B21: 20 | C21: =$B$6*(NORMDIST(MIN($D$6,MAX($C$6,$B21+10)),$E$6,Inputs!$B$39,TRUE())-NORMDIST(MIN($D$6,MAX($C$6,$B21)),$E$6,Inputs!$B$39,TRUE()))/$F$6 -> 0 | D21: =$B$7*(NORMDIST(MIN($D$7,MAX($C$7,$B21+10)),$E$7,Inputs!$B$39,TRUE())-NORMDIST(MIN($D$7,MAX($C$7,$B21)),$E$7,Inputs!$B$39,TRUE()))/$F$7 -> 0 | E21: =$B$8*(NORMDIST(MIN($D$8,MAX($C$8,$B21+10)),$E$8,Inputs!$B$39,TRUE())-NORMDIST(MIN($D$8,MAX($C$8,$B21)),$E$8,Inputs!$B$39,TRUE()))/$F$8 -> 0 | F21: =$B$9*(NORMDIST(MIN($D$9,MAX($C$9,$B21+10)),$E$9,Inputs!$B$39,TRUE())-NORMDIST(MIN($D$9,MAX($C$9,$B21)),$E$9,Inputs!$B$39,TRUE()))/$F$9 -> 0 | G21: =$B$10*(NORMDIST(MIN($D$10,MAX($C$10,$B21+10)),$E$10,Inputs!$B$39,TRUE())-NORMDIST(MIN($D$10,MAX($C$10,$B21)),$E$10,Inputs!$B$39,TRUE()))/$F$10 -> 0 | H21: =$B$11*(NORMDIST(MIN($D$11,MAX($C$11,$B21+10)),$E$11,Inputs!$B$39,TRUE())-NORMDIST(MIN($D$11,MAX($C$11,$B21)),$E$11,Inputs!$B$39,TRUE()))/$F$11 -> 0 | I21: =$B$12*(NORMDIST(MIN($D$12,MAX($C$12,$B21+10)),$E$12,Inputs!$B$39,TRUE())-NORMDIST(MIN($D$12,MAX($C$12,$B21)),$E$12,Inputs!$B$39,TRUE()))/$F$12 -> 0 | J21: =$B$13*(NORMDIST(MIN($D$13,MAX($C$13,$B21+10)),$E$13,Inputs!$B$39,TRUE())-NORMDIST(MIN($D$13,MAX($C$13,$B21)),$E$13,Inputs!$B$39,TRUE()))/$F$13 -> 0 | K21: =SUM(C21:J21) -> 0 | L21: =K21/SUM($K$19:$K$36) -> 0
A22: 12:00 | B22: 30 | C22: =$B$6*(NORMDIST(MIN($D$6,MAX($C$6,$B22+10)),$E$6,Inputs!$B$39,TRUE())-NORMDIST(MIN($D$6,MAX($C$6,$B22)),$E$6,Inputs!$B$39,TRUE()))/$F$6 -> 104.09214 | D22: =$B$7*(NORMDIST(MIN($D$7,MAX($C$7,$B22+10)),$E$7,Inputs!$B$39,TRUE())-NORMDIST(MIN($D$7,MAX($C$7,$B22)),$E$7,Inputs!$B$39,TRUE()))/$F$7 -> 0 | E22: =$B$8*(NORMDIST(MIN($D$8,MAX($C$8,$B22+10)),$E$8,Inputs!$B$39,TRUE())-NORMDIST(MIN($D$8,MAX($C$8,$B22)),$E$8,Inputs!$B$39,TRUE()))/$F$8 -> 0 | F22: =$B$9*(NORMDIST(MIN($D$9,MAX($C$9,$B22+10)),$E$9,Inputs!$B$39,TRUE())-NORMDIST(MIN($D$9,MAX($C$9,$B22)),$E$9,Inputs!$B$39,TRUE()))/$F$9 -> 0 | G22: =$B$10*(NORMDIST(MIN($D$10,MAX($C$10,$B22+10)),$E$10,Inputs!$B$39,TRUE())-NORMDIST(MIN($D$10,MAX($C$10,$B22)),$E$10,Inputs!$B$39,TRUE()))/$F$10 -> 77.423909 | H22: =$B$11*(NORMDIST(MIN($D$11,MAX($C$11,$B22+10)),$E$11,Inputs!$B$39,TRUE())-NORMDIST(MIN($D$11,MAX($C$11,$B22)),$E$11,Inputs!$B$39,TRUE()))/$F$11 -> 0 | I22: =$B$12*(NORMDIST(MIN($D$12,MAX($C$12,$B22+10)),$E$12,Inputs!$B$39,TRUE())-NORMDIST(MIN($D$12,MAX($C$12,$B22)),$E$12,Inputs!$B$39,TRUE()))/$F$12 -> 0 | J22: =$B$13*(NORMDIST(MIN($D$13,MAX($C$13,$B22+10)),$E$13,Inputs!$B$39,TRUE())-NORMDIST(MIN($D$13,MAX($C$13,$B22)),$E$13,Inputs!$B$39,TRUE()))/$F$13 -> 0 | K22: =SUM(C22:J22) -> 181.51605 | L22: =K22/SUM($K$19:$K$36) -> 0.061322991
A23: 12:10 | B23: 40 | C23: =$B$6*(NORMDIST(MIN($D$6,MAX($C$6,$B23+10)),$E$6,Inputs!$B$39,TRUE())-NORMDIST(MIN($D$6,MAX($C$6,$B23)),$E$6,Inputs!$B$39,TRUE()))/$F$6 -> 132.96927 | D23: =$B$7*(NORMDIST(MIN($D$7,MAX($C$7,$B23+10)),$E$7,Inputs!$B$39,TRUE())-NORMDIST(MIN($D$7,MAX($C$7,$B23)),$E$7,Inputs!$B$39,TRUE()))/$F$7 -> 0 | E23: =$B$8*(NORMDIST(MIN($D$8,MAX($C$8,$B23+10)),$E$8,Inputs!$B$39,TRUE())-NORMDIST(MIN($D$8,MAX($C$8,$B23)),$E$8,Inputs!$B$39,TRUE()))/$F$8 -> 0 | F23: =$B$9*(NORMDIST(MIN($D$9,MAX($C$9,$B23+10)),$E$9,Inputs!$B$39,TRUE())-NORMDIST(MIN($D$9,MAX($C$9,$B23)),$E$9,Inputs!$B$39,TRUE()))/$F$9 -> 0 | G23: =$B$10*(NORMDIST(MIN($D$10,MAX($C$10,$B23+10)),$E$10,Inputs!$B$39,TRUE())-NORMDIST(MIN($D$10,MAX($C$10,$B23)),$E$10,Inputs!$B$39,TRUE()))/$F$10 -> 98.902763 | H23: =$B$11*(NORMDIST(MIN($D$11,MAX($C$11,$B23+10)),$E$11,Inputs!$B$39,TRUE())-NORMDIST(MIN($D$11,MAX($C$11,$B23)),$E$11,Inputs!$B$39,TRUE()))/$F$11 -> 0 | I23: =$B$12*(NORMDIST(MIN($D$12,MAX($C$12,$B23+10)),$E$12,Inputs!$B$39,TRUE())-NORMDIST(MIN($D$12,MAX($C$12,$B23)),$E$12,Inputs!$B$39,TRUE()))/$F$12 -> 0 | J23: =$B$13*(NORMDIST(MIN($D$13,MAX($C$13,$B23+10)),$E$13,Inputs!$B$39,TRUE())-NORMDIST(MIN($D$13,MAX($C$13,$B23)),$E$13,Inputs!$B$39,TRUE()))/$F$13 -> 0 | K23: =SUM(C23:J23) -> 231.87203 | L23: =K23/SUM($K$19:$K$36) -> 0.078335147
A24: 12:20 | B24: 50 | C24: =$B$6*(NORMDIST(MIN($D$6,MAX($C$6,$B24+10)),$E$6,Inputs!$B$39,TRUE())-NORMDIST(MIN($D$6,MAX($C$6,$B24)),$E$6,Inputs!$B$39,TRUE()))/$F$6 -> 132.96927 | D24: =$B$7*(NORMDIST(MIN($D$7,MAX($C$7,$B24+10)),$E$7,Inputs!$B$39,TRUE())-NORMDIST(MIN($D$7,MAX($C$7,$B24)),$E$7,Inputs!$B$39,TRUE()))/$F$7 -> 0 | E24: =$B$8*(NORMDIST(MIN($D$8,MAX($C$8,$B24+10)),$E$8,Inputs!$B$39,TRUE())-NORMDIST(MIN($D$8,MAX($C$8,$B24)),$E$8,Inputs!$B$39,TRUE()))/$F$8 -> 0 | F24: =$B$9*(NORMDIST(MIN($D$9,MAX($C$9,$B24+10)),$E$9,Inputs!$B$39,TRUE())-NORMDIST(MIN($D$9,MAX($C$9,$B24)),$E$9,Inputs!$B$39,TRUE()))/$F$9 -> 0 | G24: =$B$10*(NORMDIST(MIN($D$10,MAX($C$10,$B24+10)),$E$10,Inputs!$B$39,TRUE())-NORMDIST(MIN($D$10,MAX($C$10,$B24)),$E$10,Inputs!$B$39,TRUE()))/$F$10 -> 98.902763 | H24: =$B$11*(NORMDIST(MIN($D$11,MAX($C$11,$B24+10)),$E$11,Inputs!$B$39,TRUE())-NORMDIST(MIN($D$11,MAX($C$11,$B24)),$E$11,Inputs!$B$39,TRUE()))/$F$11 -> 0 | I24: =$B$12*(NORMDIST(MIN($D$12,MAX($C$12,$B24+10)),$E$12,Inputs!$B$39,TRUE())-NORMDIST(MIN($D$12,MAX($C$12,$B24)),$E$12,Inputs!$B$39,TRUE()))/$F$12 -> 0 | J24: =$B$13*(NORMDIST(MIN($D$13,MAX($C$13,$B24+10)),$E$13,Inputs!$B$39,TRUE())-NORMDIST(MIN($D$13,MAX($C$13,$B24)),$E$13,Inputs!$B$39,TRUE()))/$F$13 -> 0 | K24: =SUM(C24:J24) -> 231.87203 | L24: =K24/SUM($K$19:$K$36) -> 0.078335147
A25: 12:30 | B25: 60 | C25: =$B$6*(NORMDIST(MIN($D$6,MAX($C$6,$B25+10)),$E$6,Inputs!$B$39,TRUE())-NORMDIST(MIN($D$6,MAX($C$6,$B25)),$E$6,Inputs!$B$39,TRUE()))/$F$6 -> 104.09214 | D25: =$B$7*(NORMDIST(MIN($D$7,MAX($C$7,$B25+10)),$E$7,Inputs!$B$39,TRUE())-NORMDIST(MIN($D$7,MAX($C$7,$B25)),$E$7,Inputs!$B$39,TRUE()))/$F$7 -> 0 | E25: =$B$8*(NORMDIST(MIN($D$8,MAX($C$8,$B25+10)),$E$8,Inputs!$B$39,TRUE())-NORMDIST(MIN($D$8,MAX($C$8,$B25)),$E$8,Inputs!$B$39,TRUE()))/$F$8 -> 0 | F25: =$B$9*(NORMDIST(MIN($D$9,MAX($C$9,$B25+10)),$E$9,Inputs!$B$39,TRUE())-NORMDIST(MIN($D$9,MAX($C$9,$B25)),$E$9,Inputs!$B$39,TRUE()))/$F$9 -> 94.629222 | G25: =$B$10*(NORMDIST(MIN($D$10,MAX($C$10,$B25+10)),$E$10,Inputs!$B$39,TRUE())-NORMDIST(MIN($D$10,MAX($C$10,$B25)),$E$10,Inputs!$B$39,TRUE()))/$F$10 -> 77.423909 | H25: =$B$11*(NORMDIST(MIN($D$11,MAX($C$11,$B25+10)),$E$11,Inputs!$B$39,TRUE())-NORMDIST(MIN($D$11,MAX($C$11,$B25)),$E$11,Inputs!$B$39,TRUE()))/$F$11 -> 0 | I25: =$B$12*(NORMDIST(MIN($D$12,MAX($C$12,$B25+10)),$E$12,Inputs!$B$39,TRUE())-NORMDIST(MIN($D$12,MAX($C$12,$B25)),$E$12,Inputs!$B$39,TRUE()))/$F$12 -> 0 | J25: =$B$13*(NORMDIST(MIN($D$13,MAX($C$13,$B25+10)),$E$13,Inputs!$B$39,TRUE())-NORMDIST(MIN($D$13,MAX($C$13,$B25)),$E$13,Inputs!$B$39,TRUE()))/$F$13 -> 8.6026565 | K25: =SUM(C25:J25) -> 284.74793 | L25: =K25/SUM($K$19:$K$36) -> 0.096198625
A26: 12:40 | B26: 70 | C26: =$B$6*(NORMDIST(MIN($D$6,MAX($C$6,$B26+10)),$E$6,Inputs!$B$39,TRUE())-NORMDIST(MIN($D$6,MAX($C$6,$B26)),$E$6,Inputs!$B$39,TRUE()))/$F$6 -> 63.787797 | D26: =$B$7*(NORMDIST(MIN($D$7,MAX($C$7,$B26+10)),$E$7,Inputs!$B$39,TRUE())-NORMDIST(MIN($D$7,MAX($C$7,$B26)),$E$7,Inputs!$B$39,TRUE()))/$F$7 -> 0 | E26: =$B$8*(NORMDIST(MIN($D$8,MAX($C$8,$B26+10)),$E$8,Inputs!$B$39,TRUE())-NORMDIST(MIN($D$8,MAX($C$8,$B26)),$E$8,Inputs!$B$39,TRUE()))/$F$8 -> 0 | F26: =$B$9*(NORMDIST(MIN($D$9,MAX($C$9,$B26+10)),$E$9,Inputs!$B$39,TRUE())-NORMDIST(MIN($D$9,MAX($C$9,$B26)),$E$9,Inputs!$B$39,TRUE()))/$F$9 -> 120.88116 | G26: =$B$10*(NORMDIST(MIN($D$10,MAX($C$10,$B26+10)),$E$10,Inputs!$B$39,TRUE())-NORMDIST(MIN($D$10,MAX($C$10,$B26)),$E$10,Inputs!$B$39,TRUE()))/$F$10 -> 47.445469 | H26: =$B$11*(NORMDIST(MIN($D$11,MAX($C$11,$B26+10)),$E$11,Inputs!$B$39,TRUE())-NORMDIST(MIN($D$11,MAX($C$11,$B26)),$E$11,Inputs!$B$39,TRUE()))/$F$11 -> 17.205313 | I26: =$B$12*(NORMDIST(MIN($D$12,MAX($C$12,$B26+10)),$E$12,Inputs!$B$39,TRUE())-NORMDIST(MIN($D$12,MAX($C$12,$B26)),$E$12,Inputs!$B$39,TRUE()))/$F$12 -> 0 | J26: =$B$13*(NORMDIST(MIN($D$13,MAX($C$13,$B26+10)),$E$13,Inputs!$B$39,TRUE())-NORMDIST(MIN($D$13,MAX($C$13,$B26)),$E$13,Inputs!$B$39,TRUE()))/$F$13 -> 10.989196 | K26: =SUM(C26:J26) -> 260.30893 | L26: =K26/SUM($K$19:$K$36) -> 0.087942206
A27: 12:50 | B27: 80 | C27: =$B$6*(NORMDIST(MIN($D$6,MAX($C$6,$B27+10)),$E$6,Inputs!$B$39,TRUE())-NORMDIST(MIN($D$6,MAX($C$6,$B27)),$E$6,Inputs!$B$39,TRUE()))/$F$6 -> 30.59731 | D27: =$B$7*(NORMDIST(MIN($D$7,MAX($C$7,$B27+10)),$E$7,Inputs!$B$39,TRUE())-NORMDIST(MIN($D$7,MAX($C$7,$B27)),$E$7,Inputs!$B$39,TRUE()))/$F$7 -> 0 | E27: =$B$8*(NORMDIST(MIN($D$8,MAX($C$8,$B27+10)),$E$8,Inputs!$B$39,TRUE())-NORMDIST(MIN($D$8,MAX($C$8,$B27)),$E$8,Inputs!$B$39,TRUE()))/$F$8 -> 0 | F27: =$B$9*(NORMDIST(MIN($D$9,MAX($C$9,$B27+10)),$E$9,Inputs!$B$39,TRUE())-NORMDIST(MIN($D$9,MAX($C$9,$B27)),$E$9,Inputs!$B$39,TRUE()))/$F$9 -> 120.88116 | G27: =$B$10*(NORMDIST(MIN($D$10,MAX($C$10,$B27+10)),$E$10,Inputs!$B$39,TRUE())-NORMDIST(MIN($D$10,MAX($C$10,$B27)),$E$10,Inputs!$B$39,TRUE()))/$F$10 -> 22.75833 | H27: =$B$11*(NORMDIST(MIN($D$11,MAX($C$11,$B27+10)),$E$11,Inputs!$B$39,TRUE())-NORMDIST(MIN($D$11,MAX($C$11,$B27)),$E$11,Inputs!$B$39,TRUE()))/$F$11 -> 21.978392 | I27: =$B$12*(NORMDIST(MIN($D$12,MAX($C$12,$B27+10)),$E$12,Inputs!$B$39,TRUE())-NORMDIST(MIN($D$12,MAX($C$12,$B27)),$E$12,Inputs!$B$39,TRUE()))/$F$12 -> 8.6026565 | J27: =$B$13*(NORMDIST(MIN($D$13,MAX($C$13,$B27+10)),$E$13,Inputs!$B$39,TRUE())-NORMDIST(MIN($D$13,MAX($C$13,$B27)),$E$13,Inputs!$B$39,TRUE()))/$F$13 -> 10.989196 | K27: =SUM(C27:J27) -> 215.80704 | L27: =K27/SUM($K$19:$K$36) -> 0.072907784
A28: 13:00 | B28: 90 | C28: =$B$6*(NORMDIST(MIN($D$6,MAX($C$6,$B28+10)),$E$6,Inputs!$B$39,TRUE())-NORMDIST(MIN($D$6,MAX($C$6,$B28)),$E$6,Inputs!$B$39,TRUE()))/$F$6 -> 0 | D28: =$B$7*(NORMDIST(MIN($D$7,MAX($C$7,$B28+10)),$E$7,Inputs!$B$39,TRUE())-NORMDIST(MIN($D$7,MAX($C$7,$B28)),$E$7,Inputs!$B$39,TRUE()))/$F$7 -> 85.1663 | E28: =$B$8*(NORMDIST(MIN($D$8,MAX($C$8,$B28+10)),$E$8,Inputs!$B$39,TRUE())-NORMDIST(MIN($D$8,MAX($C$8,$B28)),$E$8,Inputs!$B$39,TRUE()))/$F$8 -> 67.755324 | F28: =$B$9*(NORMDIST(MIN($D$9,MAX($C$9,$B28+10)),$E$9,Inputs!$B$39,TRUE())-NORMDIST(MIN($D$9,MAX($C$9,$B28)),$E$9,Inputs!$B$39,TRUE()))/$F$9 -> 94.629222 | G28: =$B$10*(NORMDIST(MIN($D$10,MAX($C$10,$B28+10)),$E$10,Inputs!$B$39,TRUE())-NORMDIST(MIN($D$10,MAX($C$10,$B28)),$E$10,Inputs!$B$39,TRUE()))/$F$10 -> 0 | H28: =$B$11*(NORMDIST(MIN($D$11,MAX($C$11,$B28+10)),$E$11,Inputs!$B$39,TRUE())-NORMDIST(MIN($D$11,MAX($C$11,$B28)),$E$11,Inputs!$B$39,TRUE()))/$F$11 -> 21.978392 | I28: =$B$12*(NORMDIST(MIN($D$12,MAX($C$12,$B28+10)),$E$12,Inputs!$B$39,TRUE())-NORMDIST(MIN($D$12,MAX($C$12,$B28)),$E$12,Inputs!$B$39,TRUE()))/$F$12 -> 10.989196 | J28: =$B$13*(NORMDIST(MIN($D$13,MAX($C$13,$B28+10)),$E$13,Inputs!$B$39,TRUE())-NORMDIST(MIN($D$13,MAX($C$13,$B28)),$E$13,Inputs!$B$39,TRUE()))/$F$13 -> 8.6026565 | K28: =SUM(C28:J28) -> 289.12109 | L28: =K28/SUM($K$19:$K$36) -> 0.097676044
A29: 13:10 | B29: 100 | C29: =$B$6*(NORMDIST(MIN($D$6,MAX($C$6,$B29+10)),$E$6,Inputs!$B$39,TRUE())-NORMDIST(MIN($D$6,MAX($C$6,$B29)),$E$6,Inputs!$B$39,TRUE()))/$F$6 -> 0 | D29: =$B$7*(NORMDIST(MIN($D$7,MAX($C$7,$B29+10)),$E$7,Inputs!$B$39,TRUE())-NORMDIST(MIN($D$7,MAX($C$7,$B29)),$E$7,Inputs!$B$39,TRUE()))/$F$7 -> 108.79304 | E29: =$B$8*(NORMDIST(MIN($D$8,MAX($C$8,$B29+10)),$E$8,Inputs!$B$39,TRUE())-NORMDIST(MIN($D$8,MAX($C$8,$B29)),$E$8,Inputs!$B$39,TRUE()))/$F$8 -> 174.10928 | F29: =$B$9*(NORMDIST(MIN($D$9,MAX($C$9,$B29+10)),$E$9,Inputs!$B$39,TRUE())-NORMDIST(MIN($D$9,MAX($C$9,$B29)),$E$9,Inputs!$B$39,TRUE()))/$F$9 -> 57.988906 | G29: =$B$10*(NORMDIST(MIN($D$10,MAX($C$10,$B29+10)),$E$10,Inputs!$B$39,TRUE())-NORMDIST(MIN($D$10,MAX($C$10,$B29)),$E$10,Inputs!$B$39,TRUE()))/$F$10 -> 0 | H29: =$B$11*(NORMDIST(MIN($D$11,MAX($C$11,$B29+10)),$E$11,Inputs!$B$39,TRUE())-NORMDIST(MIN($D$11,MAX($C$11,$B29)),$E$11,Inputs!$B$39,TRUE()))/$F$11 -> 17.205313 | I29: =$B$12*(NORMDIST(MIN($D$12,MAX($C$12,$B29+10)),$E$12,Inputs!$B$39,TRUE())-NORMDIST(MIN($D$12,MAX($C$12,$B29)),$E$12,Inputs!$B$39,TRUE()))/$F$12 -> 10.989196 | J29: =$B$13*(NORMDIST(MIN($D$13,MAX($C$13,$B29+10)),$E$13,Inputs!$B$39,TRUE())-NORMDIST(MIN($D$13,MAX($C$13,$B29)),$E$13,Inputs!$B$39,TRUE()))/$F$13 -> 5.2717187 | K29: =SUM(C29:J29) -> 374.35746 | L29: =K29/SUM($K$19:$K$36) -> 0.12647211
A30: 13:20 | B30: 110 | C30: =$B$6*(NORMDIST(MIN($D$6,MAX($C$6,$B30+10)),$E$6,Inputs!$B$39,TRUE())-NORMDIST(MIN($D$6,MAX($C$6,$B30)),$E$6,Inputs!$B$39,TRUE()))/$F$6 -> 0 | D30: =$B$7*(NORMDIST(MIN($D$7,MAX($C$7,$B30+10)),$E$7,Inputs!$B$39,TRUE())-NORMDIST(MIN($D$7,MAX($C$7,$B30)),$E$7,Inputs!$B$39,TRUE()))/$F$7 -> 108.79304 | E30: =$B$8*(NORMDIST(MIN($D$8,MAX($C$8,$B30+10)),$E$8,Inputs!$B$39,TRUE())-NORMDIST(MIN($D$8,MAX($C$8,$B30)),$E$8,Inputs!$B$39,TRUE()))/$F$8 -> 196.78307 | F30: =$B$9*(NORMDIST(MIN($D$9,MAX($C$9,$B30+10)),$E$9,Inputs!$B$39,TRUE())-NORMDIST(MIN($D$9,MAX($C$9,$B30)),$E$9,Inputs!$B$39,TRUE()))/$F$9 -> 27.815737 | G30: =$B$10*(NORMDIST(MIN($D$10,MAX($C$10,$B30+10)),$E$10,Inputs!$B$39,TRUE())-NORMDIST(MIN($D$10,MAX($C$10,$B30)),$E$10,Inputs!$B$39,TRUE()))/$F$10 -> 0 | H30: =$B$11*(NORMDIST(MIN($D$11,MAX($C$11,$B30+10)),$E$11,Inputs!$B$39,TRUE())-NORMDIST(MIN($D$11,MAX($C$11,$B30)),$E$11,Inputs!$B$39,TRUE()))/$F$11 -> 10.543437 | I30: =$B$12*(NORMDIST(MIN($D$12,MAX($C$12,$B30+10)),$E$12,Inputs!$B$39,TRUE())-NORMDIST(MIN($D$12,MAX($C$12,$B30)),$E$12,Inputs!$B$39,TRUE()))/$F$12 -> 8.6026565 | J30: =$B$13*(NORMDIST(MIN($D$13,MAX($C$13,$B30+10)),$E$13,Inputs!$B$39,TRUE())-NORMDIST(MIN($D$13,MAX($C$13,$B30)),$E$13,Inputs!$B$39,TRUE()))/$F$13 -> 2.5287033 | K30: =SUM(C30:J30) -> 355.06664 | L30: =K30/SUM($K$19:$K$36) -> 0.11995495
... A36: 14:20 | B36: 170 | C36: =$B$6*(NORMDIST(MIN($D$6,MAX($C$6,$B36+10)),$E$6,Inputs!$B$39,TRUE())-NORMDIST(MIN($D$6,MAX($C$6,$B36)),$E$6,Inputs!$B$39,TRUE()))/$F$6 -> 0 | D36: =$B$7*(NORMDIST(MIN($D$7,MAX($C$7,$B36+10)),$E$7,Inputs!$B$39,TRUE())-NORMDIST(MIN($D$7,MAX($C$7,$B36)),$E$7,Inputs!$B$39,TRUE()))/$F$7 -> 0 | E36: =$B$8*(NORMDIST(MIN($D$8,MAX($C$8,$B36+10)),$E$8,Inputs!$B$39,TRUE())-NORMDIST(MIN($D$8,MAX($C$8,$B36)),$E$8,Inputs!$B$39,TRUE()))/$F$8 -> 0 | F36: =$B$9*(NORMDIST(MIN($D$9,MAX($C$9,$B36+10)),$E$9,Inputs!$B$39,TRUE())-NORMDIST(MIN($D$9,MAX($C$9,$B36)),$E$9,Inputs!$B$39,TRUE()))/$F$9 -> 0 | G36: =$B$10*(NORMDIST(MIN($D$10,MAX($C$10,$B36+10)),$E$10,Inputs!$B$39,TRUE())-NORMDIST(MIN($D$10,MAX($C$10,$B36)),$E$10,Inputs!$B$39,TRUE()))/$F$10 -> 0 | H36: =$B$11*(NORMDIST(MIN($D$11,MAX($C$11,$B36+10)),$E$11,Inputs!$B$39,TRUE())-NORMDIST(MIN($D$11,MAX($C$11,$B36)),$E$11,Inputs!$B$39,TRUE()))/$F$11 -> 0 | I36: =$B$12*(NORMDIST(MIN($D$12,MAX($C$12,$B36+10)),$E$12,Inputs!$B$39,TRUE())-NORMDIST(MIN($D$12,MAX($C$12,$B36)),$E$12,Inputs!$B$39,TRUE()))/$F$12 -> 0 | J36: =$B$13*(NORMDIST(MIN($D$13,MAX($C$13,$B36+10)),$E$13,Inputs!$B$39,TRUE())-NORMDIST(MIN($D$13,MAX($C$13,$B36)),$E$13,Inputs!$B$39,TRUE()))/$F$13 -> 0 | K36: =SUM(C36:J36) -> 0 | L36: =K36/SUM($K$19:$K$36) -> 0
A38: Busiest 10-minute slot | B38: =INDEX(A19:A36,MATCH(MAX(K19:K36),K19:K36,0)) -> 13:10
A39: Students arriving in it (both messes) | B39: =MAX(K19:K36) -> 374.35746
A40: Capacity of both messes in 10 min (4 stations) | B40: =(Inputs!$B$82+Inputs!$B$83)*10 -> 400
A41: Two surges: about 12:10 (MIT and SMI) and a larger one about 13:10–13:30, when MIT's lab-day batch, TAPMI, DOC/MICFE, DLHS/MILHS and MLS overlap. In the busiest slot arrivals reach about 94% of what both messes together can serve, and 80% of them head to Central, which alone can serve only 200. Balancing uses Munch's spare capacity; staggering one department's break by 15 minutes is the demand-side fix (Scenarios: stagger tests).

Sheet S15 Queuing
A1: Queuing analysis: M/M/1, M/M/c and lunch-peak overload, without vs with the screens
A2: Session 15: Introduction to queuing theory and waiting-line models
A4: 1. Check against the lecture example (Hatti Kaapi, M/M/1) | J4: 2. Why waits explode near 100% busy (M/M/1, one serving station)
A5: λ /hour | B5: μ /hour | C5: ρ | D5: Wq (hours) | E5: Wq (min) | F5: W (min) | G5: Lq | H5: L | J5: μ per hour | K5: =Inputs!$B$26*60 -> 600
A6: 18 | B6: 24 | C6: =A6/B6 -> 0.75 | D6: =A6/(B6*(B6-A6)) -> 0.125 | E6: =D6*60 -> 7.5 | F6: =60/(B6-A6) -> 10 | G6: =A6*D6 -> 2.25 | H6: =A6*F6/60 -> 3 | J6: ρ | K6: λ /hour | L6: Wq (min) | M6: Lq
A7: Lecture answers: ρ = 75%, Wq = 7.5 min, W = 10 min, Lq = 2.25. If these match, the formulas below are right. | J7: 0.5 | K7: =J7*$K$5 -> 300 | L7: =K7/($K$5*($K$5-K7))*60 -> 0.1 | M7: =K7*L7/60 -> 0.5
J8: 0.6 | K8: =J8*$K$5 -> 360 | L8: =K8/($K$5*($K$5-K8))*60 -> 0.15 | M8: =K8*L8/60 -> 0.9
J9: 0.7 | K9: =J9*$K$5 -> 420 | L9: =K9/($K$5*($K$5-K9))*60 -> 0.23333333 | M9: =K9*L9/60 -> 1.6333333
J10: 0.75 | K10: =J10*$K$5 -> 450 | L10: =K10/($K$5*($K$5-K10))*60 -> 0.3 | M10: =K10*L10/60 -> 2.25
J11: 0.8 | K11: =J11*$K$5 -> 480 | L11: =K11/($K$5*($K$5-K11))*60 -> 0.4 | M11: =K11*L11/60 -> 3.2
J12: 0.85 | K12: =J12*$K$5 -> 510 | L12: =K12/($K$5*($K$5-K12))*60 -> 0.56666667 | M12: =K12*L12/60 -> 4.8166667
J13: 0.9 | K13: =J13*$K$5 -> 540 | L13: =K13/($K$5*($K$5-K13))*60 -> 0.9 | M13: =K13*L13/60 -> 8.1
J14: 0.93 | K14: =J14*$K$5 -> 558 | L14: =K14/($K$5*($K$5-K14))*60 -> 1.3285714 | M14: =K14*L14/60 -> 12.355714
J15: 0.95 | K15: =J15*$K$5 -> 570 | L15: =K15/($K$5*($K$5-K15))*60 -> 1.9 | M15: =K15*L15/60 -> 18.05
J16: 0.96 | K16: =J16*$K$5 -> 576 | L16: =K16/($K$5*($K$5-K16))*60 -> 2.4 | M16: =K16*L16/60 -> 23.04
J17: 0.97 | K17: =J17*$K$5 -> 582 | L17: =K17/($K$5*($K$5-K17))*60 -> 3.2333333 | M17: =K17*L17/60 -> 31.363333
J18: 0.98 | K18: =J18*$K$5 -> 588 | L18: =K18/($K$5*($K$5-K18))*60 -> 4.9 | M18: =K18*L18/60 -> 48.02
A22: 3. Lunch by 10-minute slot: without vs with the door screens (M/M/c, plus a fluid queue for overload)
A23: Arrivals = the department lunch breaks added up (Arrival Curve tab; shape ASSUMED until the biometric logs replace column C). Backlog (end of slot) = max(0, backlog at the start + arrivals − capacity × 10): the line carried from slot to slot. Queue wait = (backlog at the start + backlog at the end) ÷ 2 ÷ capacity (the line a student meets half-way through the slot) + the M/M/c wait with ρ capped at 95% for the randomness a smooth average misses (P(wait) and Wq random use the capped rate; the live engine uses the same rule). Throughput = stage 1 + queue wait + serving + food line + eating + disposal. 'With screens' moves the share who comply toward equal utilisation in every slot, with perfect knowledge (see Reconciliation).
A25: Equal-utilisation share for Central | E25: =Inputs!$B$82/(Inputs!$B$82+Inputs!$B$83) -> 0.5 | F25: Formula: capacity of Central ÷ (capacity of Central + capacity of Munch)
A26: Realised share for Central with screens | E26: =Inputs!$B$35+Inputs!$B$36*(E25-Inputs!$B$35) -> 0.6188 | F26: Formula: habit + compliance × (target − habit). Only students who follow the screen move
E28: Without screens — Central CT | N28: Without screens — Munch | W28: With screens — Central CT | AF28: With screens — Munch
A29: Slot start | B29: Curve share | C29: Arrivals (both messes) | D29: λ total /min | E29: λ /min | F29: Scanner ρ | G29: ρ | H29: P(wait) | I29: Wq random (min) | J29: Backlog end | K29: Queue wait (min) | L29: Throughput (min) | M29: People inside | N29: λ /min | O29: Scanner ρ | P29: ρ | Q29: P(wait) | R29: Wq random (min) | S29: Backlog end | T29: Queue wait (min) | U29: Throughput (min) | V29: People inside | W29: λ /min | X29: Scanner ρ | Y29: ρ | Z29: P(wait) | AA29: Wq random (min) | AB29: Backlog end | AC29: Queue wait (min) | AD29: Throughput (min) | AE29: People inside | AF29: λ /min | AG29: Scanner ρ | AH29: ρ | AI29: P(wait) | AJ29: Wq random (min) | AK29: Backlog end | AL29: Queue wait (min) | AM29: Throughput (min) | AN29: People inside
A30: 11:30 | B30: ='Arrival Curve'!$L$19 -> 0 | C30: ='Arrival Curve'!$K$19 -> 0 | D30: =C30/10 -> 0 | E30: =$D30*Inputs!$B$35 -> 0 | F30: =E30/Inputs!$B$84 -> 0 | G30: =E30/(Inputs!$B$11*Inputs!$B$26) -> 0 | H30: =IF(E30>0,((MIN(E30,0.95*Inputs!$B$11*Inputs!$B$26)/Inputs!$B$26)^Inputs!$B$11/FACT(Inputs!$B$11)*Inputs!$B$11/(Inputs!$B$11-(MIN(E30,0.95*Inputs!$B$11*Inputs!$B$26)/Inputs!$B$26)))/(SUMPRODUCT(--({0,1,2,3,4,5,6,7,8,9}<Inputs!$B$11),(MIN(E30,0.95*Inputs!$B$11*Inputs!$B$26)/Inputs!$B$26)^{0,1,2,3,4,5,6,7,8,9}/FACT({0,1,2,3,4,5,6,7,8,9}))+((MIN(E30,0.95*Inputs!$B$11*Inputs!$B$26)/Inputs!$B$26)^Inputs!$B$11/FACT(Inputs!$B$11)*Inputs!$B$11/(Inputs!$B$11-(MIN(E30,0.95*Inputs!$B$11*Inputs!$B$26)/Inputs!$B$26)))),0) -> 0 | I30: =IF(E30>0,H30/(Inputs!$B$11*Inputs!$B$26-MIN(E30,0.95*Inputs!$B$11*Inputs!$B$26)),0) -> 0 | J30: =MAX(0,0+(E30-Inputs!$B$11*Inputs!$B$26)*10) -> 0 | K30: =(0+J30)/2/(Inputs!$B$11*Inputs!$B$26)+I30 -> 0 | L30: =Inputs!$B$86+K30+1/Inputs!$B$26+Inputs!$B$87+Inputs!$B$88+Inputs!$B$89 -> 28.625 | M30: =E30*L30 -> 0 | N30: =$D30*(1-Inputs!$B$35) -> 0 | O30: =N30/Inputs!$B$85 -> 0 | P30: =N30/(Inputs!$B$12*Inputs!$B$26) -> 0 | Q30: =IF(N30>0,((MIN(N30,0.95*Inputs!$B$12*Inputs!$B$26)/Inputs!$B$26)^Inputs!$B$12/FACT(Inputs!$B$12)*Inputs!$B$12/(Inputs!$B$12-(MIN(N30,0.95*Inputs!$B$12*Inputs!$B$26)/Inputs!$B$26)))/(SUMPRODUCT(--({0,1,2,3,4,5,6,7,8,9}<Inputs!$B$12),(MIN(N30,0.95*Inputs!$B$12*Inputs!$B$26)/Inputs!$B$26)^{0,1,2,3,4,5,6,7,8,9}/FACT({0,1,2,3,4,5,6,7,8,9}))+((MIN(N30,0.95*Inputs!$B$12*Inputs!$B$26)/Inputs!$B$26)^Inputs!$B$12/FACT(Inputs!$B$12)*Inputs!$B$12/(Inputs!$B$12-(MIN(N30,0.95*Inputs!$B$12*Inputs!$B$26)/Inputs!$B$26)))),0) -> 0 | R30: =IF(N30>0,Q30/(Inputs!$B$12*Inputs!$B$26-MIN(N30,0.95*Inputs!$B$12*Inputs!$B$26)),0) -> 0 | S30: =MAX(0,0+(N30-Inputs!$B$12*Inputs!$B$26)*10) -> 0 | T30: =(0+S30)/2/(Inputs!$B$12*Inputs!$B$26)+R30 -> 0 | U30: =Inputs!$B$86+T30+1/Inputs!$B$26+Inputs!$B$87+Inputs!$B$88+Inputs!$B$89 -> 28.625 | V30: =N30*U30 -> 0 | W30: =$D30*$E$26 -> 0 | X30: =W30/Inputs!$B$84 -> 0 | Y30: =W30/(Inputs!$B$11*Inputs!$B$26) -> 0 | Z30: =IF(W30>0,((MIN(W30,0.95*Inputs!$B$11*Inputs!$B$26)/Inputs!$B$26)^Inputs!$B$11/FACT(Inputs!$B$11)*Inputs!$B$11/(Inputs!$B$11-(MIN(W30,0.95*Inputs!$B$11*Inputs!$B$26)/Inputs!$B$26)))/(SUMPRODUCT(--({0,1,2,3,4,5,6,7,8,9}<Inputs!$B$11),(MIN(W30,0.95*Inputs!$B$11*Inputs!$B$26)/Inputs!$B$26)^{0,1,2,3,4,5,6,7,8,9}/FACT({0,1,2,3,4,5,6,7,8,9}))+((MIN(W30,0.95*Inputs!$B$11*Inputs!$B$26)/Inputs!$B$26)^Inputs!$B$11/FACT(Inputs!$B$11)*Inputs!$B$11/(Inputs!$B$11-(MIN(W30,0.95*Inputs!$B$11*Inputs!$B$26)/Inputs!$B$26)))),0) -> 0 | AA30: =IF(W30>0,Z30/(Inputs!$B$11*Inputs!$B$26-MIN(W30,0.95*Inputs!$B$11*Inputs!$B$26)),0) -> 0 | AB30: =MAX(0,0+(W30-Inputs!$B$11*Inputs!$B$26)*10) -> 0 | AC30: =(0+AB30)/2/(Inputs!$B$11*Inputs!$B$26)+AA30 -> 0 | AD30: =Inputs!$B$86+AC30+1/Inputs!$B$26+Inputs!$B$87+Inputs!$B$88+Inputs!$B$89 -> 28.625 | AE30: =W30*AD30 -> 0 | AF30: =$D30*(1-$E$26) -> 0 | AG30: =AF30/Inputs!$B$85 -> 0 | AH30: =AF30/(Inputs!$B$12*Inputs!$B$26) -> 0 | AI30: =IF(AF30>0,((MIN(AF30,0.95*Inputs!$B$12*Inputs!$B$26)/Inputs!$B$26)^Inputs!$B$12/FACT(Inputs!$B$12)*Inputs!$B$12/(Inputs!$B$12-(MIN(AF30,0.95*Inputs!$B$12*Inputs!$B$26)/Inputs!$B$26)))/(SUMPRODUCT(--({0,1,2,3,4,5,6,7,8,9}<Inputs!$B$12),(MIN(AF30,0.95*Inputs!$B$12*Inputs!$B$26)/Inputs!$B$26)^{0,1,2,3,4,5,6,7,8,9}/FACT({0,1,2,3,4,5,6,7,8,9}))+((MIN(AF30,0.95*Inputs!$B$12*Inputs!$B$26)/Inputs!$B$26)^Inputs!$B$12/FACT(Inputs!$B$12)*Inputs!$B$12/(Inputs!$B$12-(MIN(AF30,0.95*Inputs!$B$12*Inputs!$B$26)/Inputs!$B$26)))),0) -> 0 | AJ30: =IF(AF30>0,AI30/(Inputs!$B$12*Inputs!$B$26-MIN(AF30,0.95*Inputs!$B$12*Inputs!$B$26)),0) -> 0 | AK30: =MAX(0,0+(AF30-Inputs!$B$12*Inputs!$B$26)*10) -> 0 | AL30: =(0+AK30)/2/(Inputs!$B$12*Inputs!$B$26)+AJ30 -> 0 | AM30: =Inputs!$B$86+AL30+1/Inputs!$B$26+Inputs!$B$87+Inputs!$B$88+Inputs!$B$89 -> 28.625 | AN30: =AF30*AM30 -> 0
A31: 11:40 | B31: ='Arrival Curve'!$L$20 -> 0 | C31: ='Arrival Curve'!$K$20 -> 0 | D31: =C31/10 -> 0 | E31: =$D31*Inputs!$B$35 -> 0 | F31: =E31/Inputs!$B$84 -> 0 | G31: =E31/(Inputs!$B$11*Inputs!$B$26) -> 0 | H31: =IF(E31>0,((MIN(E31,0.95*Inputs!$B$11*Inputs!$B$26)/Inputs!$B$26)^Inputs!$B$11/FACT(Inputs!$B$11)*Inputs!$B$11/(Inputs!$B$11-(MIN(E31,0.95*Inputs!$B$11*Inputs!$B$26)/Inputs!$B$26)))/(SUMPRODUCT(--({0,1,2,3,4,5,6,7,8,9}<Inputs!$B$11),(MIN(E31,0.95*Inputs!$B$11*Inputs!$B$26)/Inputs!$B$26)^{0,1,2,3,4,5,6,7,8,9}/FACT({0,1,2,3,4,5,6,7,8,9}))+((MIN(E31,0.95*Inputs!$B$11*Inputs!$B$26)/Inputs!$B$26)^Inputs!$B$11/FACT(Inputs!$B$11)*Inputs!$B$11/(Inputs!$B$11-(MIN(E31,0.95*Inputs!$B$11*Inputs!$B$26)/Inputs!$B$26)))),0) -> 0 | I31: =IF(E31>0,H31/(Inputs!$B$11*Inputs!$B$26-MIN(E31,0.95*Inputs!$B$11*Inputs!$B$26)),0) -> 0 | J31: =MAX(0,J30+(E31-Inputs!$B$11*Inputs!$B$26)*10) -> 0 | K31: =(J30+J31)/2/(Inputs!$B$11*Inputs!$B$26)+I31 -> 0 | L31: =Inputs!$B$86+K31+1/Inputs!$B$26+Inputs!$B$87+Inputs!$B$88+Inputs!$B$89 -> 28.625 | M31: =E31*L31 -> 0 | N31: =$D31*(1-Inputs!$B$35) -> 0 | O31: =N31/Inputs!$B$85 -> 0 | P31: =N31/(Inputs!$B$12*Inputs!$B$26) -> 0 | Q31: =IF(N31>0,((MIN(N31,0.95*Inputs!$B$12*Inputs!$B$26)/Inputs!$B$26)^Inputs!$B$12/FACT(Inputs!$B$12)*Inputs!$B$12/(Inputs!$B$12-(MIN(N31,0.95*Inputs!$B$12*Inputs!$B$26)/Inputs!$B$26)))/(SUMPRODUCT(--({0,1,2,3,4,5,6,7,8,9}<Inputs!$B$12),(MIN(N31,0.95*Inputs!$B$12*Inputs!$B$26)/Inputs!$B$26)^{0,1,2,3,4,5,6,7,8,9}/FACT({0,1,2,3,4,5,6,7,8,9}))+((MIN(N31,0.95*Inputs!$B$12*Inputs!$B$26)/Inputs!$B$26)^Inputs!$B$12/FACT(Inputs!$B$12)*Inputs!$B$12/(Inputs!$B$12-(MIN(N31,0.95*Inputs!$B$12*Inputs!$B$26)/Inputs!$B$26)))),0) -> 0 | R31: =IF(N31>0,Q31/(Inputs!$B$12*Inputs!$B$26-MIN(N31,0.95*Inputs!$B$12*Inputs!$B$26)),0) -> 0 | S31: =MAX(0,S30+(N31-Inputs!$B$12*Inputs!$B$26)*10) -> 0 | T31: =(S30+S31)/2/(Inputs!$B$12*Inputs!$B$26)+R31 -> 0 | U31: =Inputs!$B$86+T31+1/Inputs!$B$26+Inputs!$B$87+Inputs!$B$88+Inputs!$B$89 -> 28.625 | V31: =N31*U31 -> 0 | W31: =$D31*$E$26 -> 0 | X31: =W31/Inputs!$B$84 -> 0 | Y31: =W31/(Inputs!$B$11*Inputs!$B$26) -> 0 | Z31: =IF(W31>0,((MIN(W31,0.95*Inputs!$B$11*Inputs!$B$26)/Inputs!$B$26)^Inputs!$B$11/FACT(Inputs!$B$11)*Inputs!$B$11/(Inputs!$B$11-(MIN(W31,0.95*Inputs!$B$11*Inputs!$B$26)/Inputs!$B$26)))/(SUMPRODUCT(--({0,1,2,3,4,5,6,7,8,9}<Inputs!$B$11),(MIN(W31,0.95*Inputs!$B$11*Inputs!$B$26)/Inputs!$B$26)^{0,1,2,3,4,5,6,7,8,9}/FACT({0,1,2,3,4,5,6,7,8,9}))+((MIN(W31,0.95*Inputs!$B$11*Inputs!$B$26)/Inputs!$B$26)^Inputs!$B$11/FACT(Inputs!$B$11)*Inputs!$B$11/(Inputs!$B$11-(MIN(W31,0.95*Inputs!$B$11*Inputs!$B$26)/Inputs!$B$26)))),0) -> 0 | AA31: =IF(W31>0,Z31/(Inputs!$B$11*Inputs!$B$26-MIN(W31,0.95*Inputs!$B$11*Inputs!$B$26)),0) -> 0 | AB31: =MAX(0,AB30+(W31-Inputs!$B$11*Inputs!$B$26)*10) -> 0 | AC31: =(AB30+AB31)/2/(Inputs!$B$11*Inputs!$B$26)+AA31 -> 0 | AD31: =Inputs!$B$86+AC31+1/Inputs!$B$26+Inputs!$B$87+Inputs!$B$88+Inputs!$B$89 -> 28.625 | AE31: =W31*AD31 -> 0 | AF31: =$D31*(1-$E$26) -> 0 | AG31: =AF31/Inputs!$B$85 -> 0 | AH31: =AF31/(Inputs!$B$12*Inputs!$B$26) -> 0 | AI31: =IF(AF31>0,((MIN(AF31,0.95*Inputs!$B$12*Inputs!$B$26)/Inputs!$B$26)^Inputs!$B$12/FACT(Inputs!$B$12)*Inputs!$B$12/(Inputs!$B$12-(MIN(AF31,0.95*Inputs!$B$12*Inputs!$B$26)/Inputs!$B$26)))/(SUMPRODUCT(--({0,1,2,3,4,5,6,7,8,9}<Inputs!$B$12),(MIN(AF31,0.95*Inputs!$B$12*Inputs!$B$26)/Inputs!$B$26)^{0,1,2,3,4,5,6,7,8,9}/FACT({0,1,2,3,4,5,6,7,8,9}))+((MIN(AF31,0.95*Inputs!$B$12*Inputs!$B$26)/Inputs!$B$26)^Inputs!$B$12/FACT(Inputs!$B$12)*Inputs!$B$12/(Inputs!$B$12-(MIN(AF31,0.95*Inputs!$B$12*Inputs!$B$26)/Inputs!$B$26)))),0) -> 0 | AJ31: =IF(AF31>0,AI31/(Inputs!$B$12*Inputs!$B$26-MIN(AF31,0.95*Inputs!$B$12*Inputs!$B$26)),0) -> 0 | AK31: =MAX(0,AK30+(AF31-Inputs!$B$12*Inputs!$B$26)*10) -> 0 | AL31: =(AK30+AK31)/2/(Inputs!$B$12*Inputs!$B$26)+AJ31 -> 0 | AM31: =Inputs!$B$86+AL31+1/Inputs!$B$26+Inputs!$B$87+Inputs!$B$88+Inputs!$B$89 -> 28.625 | AN31: =AF31*AM31 -> 0
A32: 11:50 | B32: ='Arrival Curve'!$L$21 -> 0 | C32: ='Arrival Curve'!$K$21 -> 0 | D32: =C32/10 -> 0 | E32: =$D32*Inputs!$B$35 -> 0 | F32: =E32/Inputs!$B$84 -> 0 | G32: =E32/(Inputs!$B$11*Inputs!$B$26) -> 0 | H32: =IF(E32>0,((MIN(E32,0.95*Inputs!$B$11*Inputs!$B$26)/Inputs!$B$26)^Inputs!$B$11/FACT(Inputs!$B$11)*Inputs!$B$11/(Inputs!$B$11-(MIN(E32,0.95*Inputs!$B$11*Inputs!$B$26)/Inputs!$B$26)))/(SUMPRODUCT(--({0,1,2,3,4,5,6,7,8,9}<Inputs!$B$11),(MIN(E32,0.95*Inputs!$B$11*Inputs!$B$26)/Inputs!$B$26)^{0,1,2,3,4,5,6,7,8,9}/FACT({0,1,2,3,4,5,6,7,8,9}))+((MIN(E32,0.95*Inputs!$B$11*Inputs!$B$26)/Inputs!$B$26)^Inputs!$B$11/FACT(Inputs!$B$11)*Inputs!$B$11/(Inputs!$B$11-(MIN(E32,0.95*Inputs!$B$11*Inputs!$B$26)/Inputs!$B$26)))),0) -> 0 | I32: =IF(E32>0,H32/(Inputs!$B$11*Inputs!$B$26-MIN(E32,0.95*Inputs!$B$11*Inputs!$B$26)),0) -> 0 | J32: =MAX(0,J31+(E32-Inputs!$B$11*Inputs!$B$26)*10) -> 0 | K32: =(J31+J32)/2/(Inputs!$B$11*Inputs!$B$26)+I32 -> 0 | L32: =Inputs!$B$86+K32+1/Inputs!$B$26+Inputs!$B$87+Inputs!$B$88+Inputs!$B$89 -> 28.625 | M32: =E32*L32 -> 0 | N32: =$D32*(1-Inputs!$B$35) -> 0 | O32: =N32/Inputs!$B$85 -> 0 | P32: =N32/(Inputs!$B$12*Inputs!$B$26) -> 0 | Q32: =IF(N32>0,((MIN(N32,0.95*Inputs!$B$12*Inputs!$B$26)/Inputs!$B$26)^Inputs!$B$12/FACT(Inputs!$B$12)*Inputs!$B$12/(Inputs!$B$12-(MIN(N32,0.95*Inputs!$B$12*Inputs!$B$26)/Inputs!$B$26)))/(SUMPRODUCT(--({0,1,2,3,4,5,6,7,8,9}<Inputs!$B$12),(MIN(N32,0.95*Inputs!$B$12*Inputs!$B$26)/Inputs!$B$26)^{0,1,2,3,4,5,6,7,8,9}/FACT({0,1,2,3,4,5,6,7,8,9}))+((MIN(N32,0.95*Inputs!$B$12*Inputs!$B$26)/Inputs!$B$26)^Inputs!$B$12/FACT(Inputs!$B$12)*Inputs!$B$12/(Inputs!$B$12-(MIN(N32,0.95*Inputs!$B$12*Inputs!$B$26)/Inputs!$B$26)))),0) -> 0 | R32: =IF(N32>0,Q32/(Inputs!$B$12*Inputs!$B$26-MIN(N32,0.95*Inputs!$B$12*Inputs!$B$26)),0) -> 0 | S32: =MAX(0,S31+(N32-Inputs!$B$12*Inputs!$B$26)*10) -> 0 | T32: =(S31+S32)/2/(Inputs!$B$12*Inputs!$B$26)+R32 -> 0 | U32: =Inputs!$B$86+T32+1/Inputs!$B$26+Inputs!$B$87+Inputs!$B$88+Inputs!$B$89 -> 28.625 | V32: =N32*U32 -> 0 | W32: =$D32*$E$26 -> 0 | X32: =W32/Inputs!$B$84 -> 0 | Y32: =W32/(Inputs!$B$11*Inputs!$B$26) -> 0 | Z32: =IF(W32>0,((MIN(W32,0.95*Inputs!$B$11*Inputs!$B$26)/Inputs!$B$26)^Inputs!$B$11/FACT(Inputs!$B$11)*Inputs!$B$11/(Inputs!$B$11-(MIN(W32,0.95*Inputs!$B$11*Inputs!$B$26)/Inputs!$B$26)))/(SUMPRODUCT(--({0,1,2,3,4,5,6,7,8,9}<Inputs!$B$11),(MIN(W32,0.95*Inputs!$B$11*Inputs!$B$26)/Inputs!$B$26)^{0,1,2,3,4,5,6,7,8,9}/FACT({0,1,2,3,4,5,6,7,8,9}))+((MIN(W32,0.95*Inputs!$B$11*Inputs!$B$26)/Inputs!$B$26)^Inputs!$B$11/FACT(Inputs!$B$11)*Inputs!$B$11/(Inputs!$B$11-(MIN(W32,0.95*Inputs!$B$11*Inputs!$B$26)/Inputs!$B$26)))),0) -> 0 | AA32: =IF(W32>0,Z32/(Inputs!$B$11*Inputs!$B$26-MIN(W32,0.95*Inputs!$B$11*Inputs!$B$26)),0) -> 0 | AB32: =MAX(0,AB31+(W32-Inputs!$B$11*Inputs!$B$26)*10) -> 0 | AC32: =(AB31+AB32)/2/(Inputs!$B$11*Inputs!$B$26)+AA32 -> 0 | AD32: =Inputs!$B$86+AC32+1/Inputs!$B$26+Inputs!$B$87+Inputs!$B$88+Inputs!$B$89 -> 28.625 | AE32: =W32*AD32 -> 0 | AF32: =$D32*(1-$E$26) -> 0 | AG32: =AF32/Inputs!$B$85 -> 0 | AH32: =AF32/(Inputs!$B$12*Inputs!$B$26) -> 0 | AI32: =IF(AF32>0,((MIN(AF32,0.95*Inputs!$B$12*Inputs!$B$26)/Inputs!$B$26)^Inputs!$B$12/FACT(Inputs!$B$12)*Inputs!$B$12/(Inputs!$B$12-(MIN(AF32,0.95*Inputs!$B$12*Inputs!$B$26)/Inputs!$B$26)))/(SUMPRODUCT(--({0,1,2,3,4,5,6,7,8,9}<Inputs!$B$12),(MIN(AF32,0.95*Inputs!$B$12*Inputs!$B$26)/Inputs!$B$26)^{0,1,2,3,4,5,6,7,8,9}/FACT({0,1,2,3,4,5,6,7,8,9}))+((MIN(AF32,0.95*Inputs!$B$12*Inputs!$B$26)/Inputs!$B$26)^Inputs!$B$12/FACT(Inputs!$B$12)*Inputs!$B$12/(Inputs!$B$12-(MIN(AF32,0.95*Inputs!$B$12*Inputs!$B$26)/Inputs!$B$26)))),0) -> 0 | AJ32: =IF(AF32>0,AI32/(Inputs!$B$12*Inputs!$B$26-MIN(AF32,0.95*Inputs!$B$12*Inputs!$B$26)),0) -> 0 | AK32: =MAX(0,AK31+(AF32-Inputs!$B$12*Inputs!$B$26)*10) -> 0 | AL32: =(AK31+AK32)/2/(Inputs!$B$12*Inputs!$B$26)+AJ32 -> 0 | AM32: =Inputs!$B$86+AL32+1/Inputs!$B$26+Inputs!$B$87+Inputs!$B$88+Inputs!$B$89 -> 28.625 | AN32: =AF32*AM32 -> 0
A33: 12:00 | B33: ='Arrival Curve'!$L$22 -> 0.061322991 | C33: ='Arrival Curve'!$K$22 -> 181.51605 | D33: =C33/10 -> 18.151605 | E33: =$D33*Inputs!$B$35 -> 14.466829 | F33: =E33/Inputs!$B$84 -> 0.48222765 | G33: =E33/(Inputs!$B$11*Inputs!$B$26) -> 0.72334147 | H33: =IF(E33>0,((MIN(E33,0.95*Inputs!$B$11*Inputs!$B$26)/Inputs!$B$26)^Inputs!$B$11/FACT(Inputs!$B$11)*Inputs!$B$11/(Inputs!$B$11-(MIN(E33,0.95*Inputs!$B$11*Inputs!$B$26)/Inputs!$B$26)))/(SUMPRODUCT(--({0,1,2,3,4,5,6,7,8,9}<Inputs!$B$11),(MIN(E33,0.95*Inputs!$B$11*Inputs!$B$26)/Inputs!$B$26)^{0,1,2,3,4,5,6,7,8,9}/FACT({0,1,2,3,4,5,6,7,8,9}))+((MIN(E33,0.95*Inputs!$B$11*Inputs!$B$26)/Inputs!$B$26)^Inputs!$B$11/FACT(Inputs!$B$11)*Inputs!$B$11/(Inputs!$B$11-(MIN(E33,0.95*Inputs!$B$11*Inputs!$B$26)/Inputs!$B$26)))),0) -> 0.60721905 | I33: =IF(E33>0,H33/(Inputs!$B$11*Inputs!$B$26-MIN(E33,0.95*Inputs!$B$11*Inputs!$B$26)),0) -> 0.10974161 | J33: =MAX(0,J32+(E33-Inputs!$B$11*Inputs!$B$26)*10) -> 0 | K33: =(J32+J33)/2/(Inputs!$B$11*Inputs!$B$26)+I33 -> 0.10974161 | L33: =Inputs!$B$86+K33+1/Inputs!$B$26+Inputs!$B$87+Inputs!$B$88+Inputs!$B$89 -> 28.734742 | M33: =E33*L33 -> 415.7006 | N33: =$D33*(1-Inputs!$B$35) -> 3.6847759 | O33: =N33/Inputs!$B$85 -> 0.12282586 | P33: =N33/(Inputs!$B$12*Inputs!$B$26) -> 0.18423879 | Q33: =IF(N33>0,((MIN(N33,0.95*Inputs!$B$12*Inputs!$B$26)/Inputs!$B$26)^Inputs!$B$12/FACT(Inputs!$B$12)*Inputs!$B$12/(Inputs!$B$12-(MIN(N33,0.95*Inputs!$B$12*Inputs!$B$26)/Inputs!$B$26)))/(SUMPRODUCT(--({0,1,2,3,4,5,6,7,8,9}<Inputs!$B$12),(MIN(N33,0.95*Inputs!$B$12*Inputs!$B$26)/Inputs!$B$26)^{0,1,2,3,4,5,6,7,8,9}/FACT({0,1,2,3,4,5,6,7,8,9}))+((MIN(N33,0.95*Inputs!$B$12*Inputs!$B$26)/Inputs!$B$26)^Inputs!$B$12/FACT(Inputs!$B$12)*Inputs!$B$12/(Inputs!$B$12-(MIN(N33,0.95*Inputs!$B$12*Inputs!$B$26)/Inputs!$B$26)))),0) -> 0.057326163 | R33: =IF(N33>0,Q33/(Inputs!$B$12*Inputs!$B$26-MIN(N33,0.95*Inputs!$B$12*Inputs!$B$26)),0) -> 0.0035136608 | S33: =MAX(0,S32+(N33-Inputs!$B$12*Inputs!$B$26)*10) -> 0 | T33: =(S32+S33)/2/(Inputs!$B$12*Inputs!$B$26)+R33 -> 0.0035136608 | U33: =Inputs!$B$86+T33+1/Inputs!$B$26+Inputs!$B$87+Inputs!$B$88+Inputs!$B$89 -> 28.628514 | V33: =N33*U33 -> 105.48966 | W33: =$D33*$E$26 -> 11.232213 | X33: =W33/Inputs!$B$84 -> 0.37440711 | Y33: =W33/(Inputs!$B$11*Inputs!$B$26) -> 0.56161067 | Z33: =IF(W33>0,((MIN(W33,0.95*Inputs!$B$11*Inputs!$B$26)/Inputs!$B$26)^Inputs!$B$11/FACT(Inputs!$B$11)*Inputs!$B$11/(Inputs!$B$11-(MIN(W33,0.95*Inputs!$B$11*Inputs!$B$26)/Inputs!$B$26)))/(SUMPRODUCT(--({0,1,2,3,4,5,6,7,8,9}<Inputs!$B$11),(MIN(W33,0.95*Inputs!$B$11*Inputs!$B$26)/Inputs!$B$26)^{0,1,2,3,4,5,6,7,8,9}/FACT({0,1,2,3,4,5,6,7,8,9}))+((MIN(W33,0.95*Inputs!$B$11*Inputs!$B$26)/Inputs!$B$26)^Inputs!$B$11/FACT(Inputs!$B$11)*Inputs!$B$11/(Inputs!$B$11-(MIN(W33,0.95*Inputs!$B$11*Inputs!$B$26)/Inputs!$B$26)))),0) -> 0.40395029 | AA33: =IF(W33>0,Z33/(Inputs!$B$11*Inputs!$B$26-MIN(W33,0.95*Inputs!$B$11*Inputs!$B$26)),0) -> 0.046072094 | AB33: =MAX(0,AB32+(W33-Inputs!$B$11*Inputs!$B$26)*10) -> 0 | AC33: =(AB32+AB33)/2/(Inputs!$B$11*Inputs!$B$26)+AA33 -> 0.046072094 | AD33: =Inputs!$B$86+AC33+1/Inputs!$B$26+Inputs!$B$87+Inputs!$B$88+Inputs!$B$89 -> 28.671072 | AE33: =W33*AD33 -> 322.0396 | AF33: =$D33*(1-$E$26) -> 6.9193919 | AG33: =AF33/Inputs!$B$85 -> 0.2306464 | AH33: =AF33/(Inputs!$B$12*Inputs!$B$26) -> 0.3459696 | AI33: =IF(AF33>0,((MIN(AF33,0.95*Inputs!$B$12*Inputs!$B$26)/Inputs!$B$26)^Inputs!$B$12/FACT(Inputs!$B$12)*Inputs!$B$12/(Inputs!$B$12-(MIN(AF33,0.95*Inputs!$B$12*Inputs!$B$26)/Inputs!$B$26)))/(SUMPRODUCT(--({0,1,2,3,4,5,6,7,8,9}<Inputs!$B$12),(MIN(AF33,0.95*Inputs!$B$12*Inputs!$B$26)/Inputs!$B$26)^{0,1,2,3,4,5,6,7,8,9}/FACT({0,1,2,3,4,5,6,7,8,9}))+((MIN(AF33,0.95*Inputs!$B$12*Inputs!$B$26)/Inputs!$B$26)^Inputs!$B$12/FACT(Inputs!$B$12)*Inputs!$B$12/(Inputs!$B$12-(MIN(AF33,0.95*Inputs!$B$12*Inputs!$B$26)/Inputs!$B$26)))),0) -> 0.17785686 | AJ33: =IF(AF33>0,AI33/(Inputs!$B$12*Inputs!$B$26-MIN(AF33,0.95*Inputs!$B$12*Inputs!$B$26)),0) -> 0.013596987 | AK33: =MAX(0,AK32+(AF33-Inputs!$B$12*Inputs!$B$26)*10) -> 0 | AL33: =(AK32+AK33)/2/(Inputs!$B$12*Inputs!$B$26)+AJ33 -> 0.013596987 | AM33: =Inputs!$B$86+AL33+1/Inputs!$B$26+Inputs!$B$87+Inputs!$B$88+Inputs!$B$89 -> 28.638597 | AN33: =AF33*AM33 -> 198.16168
A34: 12:10 | B34: ='Arrival Curve'!$L$23 -> 0.078335147 | C34: ='Arrival Curve'!$K$23 -> 231.87203 | D34: =C34/10 -> 23.187203 | E34: =$D34*Inputs!$B$35 -> 18.480201 | F34: =E34/Inputs!$B$84 -> 0.6160067 | G34: =E34/(Inputs!$B$11*Inputs!$B$26) -> 0.92401006 | H34: =IF(E34>0,((MIN(E34,0.95*Inputs!$B$11*Inputs!$B$26)/Inputs!$B$26)^Inputs!$B$11/FACT(Inputs!$B$11)*Inputs!$B$11/(Inputs!$B$11-(MIN(E34,0.95*Inputs!$B$11*Inputs!$B$26)/Inputs!$B$26)))/(SUMPRODUCT(--({0,1,2,3,4,5,6,7,8,9}<Inputs!$B$11),(MIN(E34,0.95*Inputs!$B$11*Inputs!$B$26)/Inputs!$B$26)^{0,1,2,3,4,5,6,7,8,9}/FACT({0,1,2,3,4,5,6,7,8,9}))+((MIN(E34,0.95*Inputs!$B$11*Inputs!$B$26)/Inputs!$B$26)^Inputs!$B$11/FACT(Inputs!$B$11)*Inputs!$B$11/(Inputs!$B$11-(MIN(E34,0.95*Inputs!$B$11*Inputs!$B$26)/Inputs!$B$26)))),0) -> 0.88751572 | I34: =IF(E34>0,H34/(Inputs!$B$11*Inputs!$B$26-MIN(E34,0.95*Inputs!$B$11*Inputs!$B$26)),0) -> 0.58396918 | J34: =MAX(0,J33+(E34-Inputs!$B$11*Inputs!$B$26)*10) -> 0 | K34: =(J33+J34)/2/(Inputs!$B$11*Inputs!$B$26)+I34 -> 0.58396918 | L34: =Inputs!$B$86+K34+1/Inputs!$B$26+Inputs!$B$87+Inputs!$B$88+Inputs!$B$89 -> 29.208969 | M34: =E34*L34 -> 539.78762 | N34: =$D34*(1-Inputs!$B$35) -> 4.7070023 | O34: =N34/Inputs!$B$85 -> 0.15690008 | P34: =N34/(Inputs!$B$12*Inputs!$B$26) -> 0.23535011 | Q34: =IF(N34>0,((MIN(N34,0.95*Inputs!$B$12*Inputs!$B$26)/Inputs!$B$26)^Inputs!$B$12/FACT(Inputs!$B$12)*Inputs!$B$12/(Inputs!$B$12-(MIN(N34,0.95*Inputs!$B$12*Inputs!$B$26)/Inputs!$B$26)))/(SUMPRODUCT(--({0,1,2,3,4,5,6,7,8,9}<Inputs!$B$12),(MIN(N34,0.95*Inputs!$B$12*Inputs!$B$26)/Inputs!$B$26)^{0,1,2,3,4,5,6,7,8,9}/FACT({0,1,2,3,4,5,6,7,8,9}))+((MIN(N34,0.95*Inputs!$B$12*Inputs!$B$26)/Inputs!$B$26)^Inputs!$B$12/FACT(Inputs!$B$12)*Inputs!$B$12/(Inputs!$B$12-(MIN(N34,0.95*Inputs!$B$12*Inputs!$B$26)/Inputs!$B$26)))),0) -> 0.089674459 | R34: =IF(N34>0,Q34/(Inputs!$B$12*Inputs!$B$26-MIN(N34,0.95*Inputs!$B$12*Inputs!$B$26)),0) -> 0.0058637594 | S34: =MAX(0,S33+(N34-Inputs!$B$12*Inputs!$B$26)*10) -> 0 | T34: =(S33+S34)/2/(Inputs!$B$12*Inputs!$B$26)+R34 -> 0.0058637594 | U34: =Inputs!$B$86+T34+1/Inputs!$B$26+Inputs!$B$87+Inputs!$B$88+Inputs!$B$89 -> 28.630864 | V34: =N34*U34 -> 134.76554 | W34: =$D34*$E$26 -> 14.348241 | X34: =W34/Inputs!$B$84 -> 0.47827472 | Y34: =W34/(Inputs!$B$11*Inputs!$B$26) -> 0.71741207 | Z34: =IF(W34>0,((MIN(W34,0.95*Inputs!$B$11*Inputs!$B$26)/Inputs!$B$26)^Inputs!$B$11/FACT(Inputs!$B$11)*Inputs!$B$11/(Inputs!$B$11-(MIN(W34,0.95*Inputs!$B$11*Inputs!$B$26)/Inputs!$B$26)))/(SUMPRODUCT(--({0,1,2,3,4,5,6,7,8,9}<Inputs!$B$11),(MIN(W34,0.95*Inputs!$B$11*Inputs!$B$26)/Inputs!$B$26)^{0,1,2,3,4,5,6,7,8,9}/FACT({0,1,2,3,4,5,6,7,8,9}))+((MIN(W34,0.95*Inputs!$B$11*Inputs!$B$26)/Inputs!$B$26)^Inputs!$B$11/FACT(Inputs!$B$11)*Inputs!$B$11/(Inputs!$B$11-(MIN(W34,0.95*Inputs!$B$11*Inputs!$B$26)/Inputs!$B$26)))),0) -> 0.59936702 | AA34: =IF(W34>0,Z34/(Inputs!$B$11*Inputs!$B$26-MIN(W34,0.95*Inputs!$B$11*Inputs!$B$26)),0) -> 0.10604965 | AB34: =MAX(0,AB33+(W34-Inputs!$B$11*Inputs!$B$26)*10) -> 0 | AC34: =(AB33+AB34)/2/(Inputs!$B$11*Inputs!$B$26)+AA34 -> 0.10604965 | AD34: =Inputs!$B$86+AC34+1/Inputs!$B$26+Inputs!$B$87+Inputs!$B$88+Inputs!$B$89 -> 28.73105 | AE34: =W34*AD34 -> 412.24004 | AF34: =$D34*(1-$E$26) -> 8.8389619 | AG34: =AF34/Inputs!$B$85 -> 0.29463206 | AH34: =AF34/(Inputs!$B$12*Inputs!$B$26) -> 0.4419481 | AI34: =IF(AF34>0,((MIN(AF34,0.95*Inputs!$B$12*Inputs!$B$26)/Inputs!$B$26)^Inputs!$B$12/FACT(Inputs!$B$12)*Inputs!$B$12/(Inputs!$B$12-(MIN(AF34,0.95*Inputs!$B$12*Inputs!$B$26)/Inputs!$B$26)))/(SUMPRODUCT(--({0,1,2,3,4,5,6,7,8,9}<Inputs!$B$12),(MIN(AF34,0.95*Inputs!$B$12*Inputs!$B$26)/Inputs!$B$26)^{0,1,2,3,4,5,6,7,8,9}/FACT({0,1,2,3,4,5,6,7,8,9}))+((MIN(AF34,0.95*Inputs!$B$12*Inputs!$B$26)/Inputs!$B$26)^Inputs!$B$12/FACT(Inputs!$B$12)*Inputs!$B$12/(Inputs!$B$12-(MIN(AF34,0.95*Inputs!$B$12*Inputs!$B$26)/Inputs!$B$26)))),0) -> 0.27090867 | AJ34: =IF(AF34>0,AI34/(Inputs!$B$12*Inputs!$B$26-MIN(AF34,0.95*Inputs!$B$12*Inputs!$B$26)),0) -> 0.024272713 | AK34: =MAX(0,AK33+(AF34-Inputs!$B$12*Inputs!$B$26)*10) -> 0 | AL34: =(AK33+AK34)/2/(Inputs!$B$12*Inputs!$B$26)+AJ34 -> 0.024272713 | AM34: =Inputs!$B$86+AL34+1/Inputs!$B$26+Inputs!$B$87+Inputs!$B$88+Inputs!$B$89 -> 28.649273 | AN34: =AF34*AM34 -> 253.22983
A35: 12:20 | B35: ='Arrival Curve'!$L$24 -> 0.078335147 | C35: ='Arrival Curve'!$K$24 -> 231.87203 | D35: =C35/10 -> 23.187203 | E35: =$D35*Inputs!$B$35 -> 18.480201 | F35: =E35/Inputs!$B$84 -> 0.6160067 | G35: =E35/(Inputs!$B$11*Inputs!$B$26) -> 0.92401006 | H35: =IF(E35>0,((MIN(E35,0.95*Inputs!$B$11*Inputs!$B$26)/Inputs!$B$26)^Inputs!$B$11/FACT(Inputs!$B$11)*Inputs!$B$11/(Inputs!$B$11-(MIN(E35,0.95*Inputs!$B$11*Inputs!$B$26)/Inputs!$B$26)))/(SUMPRODUCT(--({0,1,2,3,4,5,6,7,8,9}<Inputs!$B$11),(MIN(E35,0.95*Inputs!$B$11*Inputs!$B$26)/Inputs!$B$26)^{0,1,2,3,4,5,6,7,8,9}/FACT({0,1,2,3,4,5,6,7,8,9}))+((MIN(E35,0.95*Inputs!$B$11*Inputs!$B$26)/Inputs!$B$26)^Inputs!$B$11/FACT(Inputs!$B$11)*Inputs!$B$11/(Inputs!$B$11-(MIN(E35,0.95*Inputs!$B$11*Inputs!$B$26)/Inputs!$B$26)))),0) -> 0.88751572 | I35: =IF(E35>0,H35/(Inputs!$B$11*Inputs!$B$26-MIN(E35,0.95*Inputs!$B$11*Inputs!$B$26)),0) -> 0.58396918 | J35: =MAX(0,J34+(E35-Inputs!$B$11*Inputs!$B$26)*10) -> 0 | K35: =(J34+J35)/2/(Inputs!$B$11*Inputs!$B$26)+I35 -> 0.58396918 | L35: =Inputs!$B$86+K35+1/Inputs!$B$26+Inputs!$B$87+Inputs!$B$88+Inputs!$B$89 -> 29.208969 | M35: =E35*L35 -> 539.78762 | N35: =$D35*(1-Inputs!$B$35) -> 4.7070023 | O35: =N35/Inputs!$B$85 -> 0.15690008 | P35: =N35/(Inputs!$B$12*Inputs!$B$26) -> 0.23535011 | Q35: =IF(N35>0,((MIN(N35,0.95*Inputs!$B$12*Inputs!$B$26)/Inputs!$B$26)^Inputs!$B$12/FACT(Inputs!$B$12)*Inputs!$B$12/(Inputs!$B$12-(MIN(N35,0.95*Inputs!$B$12*Inputs!$B$26)/Inputs!$B$26)))/(SUMPRODUCT(--({0,1,2,3,4,5,6,7,8,9}<Inputs!$B$12),(MIN(N35,0.95*Inputs!$B$12*Inputs!$B$26)/Inputs!$B$26)^{0,1,2,3,4,5,6,7,8,9}/FACT({0,1,2,3,4,5,6,7,8,9}))+((MIN(N35,0.95*Inputs!$B$12*Inputs!$B$26)/Inputs!$B$26)^Inputs!$B$12/FACT(Inputs!$B$12)*Inputs!$B$12/(Inputs!$B$12-(MIN(N35,0.95*Inputs!$B$12*Inputs!$B$26)/Inputs!$B$26)))),0) -> 0.089674459 | R35: =IF(N35>0,Q35/(Inputs!$B$12*Inputs!$B$26-MIN(N35,0.95*Inputs!$B$12*Inputs!$B$26)),0) -> 0.0058637594 | S35: =MAX(0,S34+(N35-Inputs!$B$12*Inputs!$B$26)*10) -> 0 | T35: =(S34+S35)/2/(Inputs!$B$12*Inputs!$B$26)+R35 -> 0.0058637594 | U35: =Inputs!$B$86+T35+1/Inputs!$B$26+Inputs!$B$87+Inputs!$B$88+Inputs!$B$89 -> 28.630864 | V35: =N35*U35 -> 134.76554 | W35: =$D35*$E$26 -> 14.348241 | X35: =W35/Inputs!$B$84 -> 0.47827472 | Y35: =W35/(Inputs!$B$11*Inputs!$B$26) -> 0.71741207 | Z35: =IF(W35>0,((MIN(W35,0.95*Inputs!$B$11*Inputs!$B$26)/Inputs!$B$26)^Inputs!$B$11/FACT(Inputs!$B$11)*Inputs!$B$11/(Inputs!$B$11-(MIN(W35,0.95*Inputs!$B$11*Inputs!$B$26)/Inputs!$B$26)))/(SUMPRODUCT(--({0,1,2,3,4,5,6,7,8,9}<Inputs!$B$11),(MIN(W35,0.95*Inputs!$B$11*Inputs!$B$26)/Inputs!$B$26)^{0,1,2,3,4,5,6,7,8,9}/FACT({0,1,2,3,4,5,6,7,8,9}))+((MIN(W35,0.95*Inputs!$B$11*Inputs!$B$26)/Inputs!$B$26)^Inputs!$B$11/FACT(Inputs!$B$11)*Inputs!$B$11/(Inputs!$B$11-(MIN(W35,0.95*Inputs!$B$11*Inputs!$B$26)/Inputs!$B$26)))),0) -> 0.59936702 | AA35: =IF(W35>0,Z35/(Inputs!$B$11*Inputs!$B$26-MIN(W35,0.95*Inputs!$B$11*Inputs!$B$26)),0) -> 0.10604965 | AB35: =MAX(0,AB34+(W35-Inputs!$B$11*Inputs!$B$26)*10) -> 0 | AC35: =(AB34+AB35)/2/(Inputs!$B$11*Inputs!$B$26)+AA35 -> 0.10604965 | AD35: =Inputs!$B$86+AC35+1/Inputs!$B$26+Inputs!$B$87+Inputs!$B$88+Inputs!$B$89 -> 28.73105 | AE35: =W35*AD35 -> 412.24004 | AF35: =$D35*(1-$E$26) -> 8.8389619 | AG35: =AF35/Inputs!$B$85 -> 0.29463206 | AH35: =AF35/(Inputs!$B$12*Inputs!$B$26) -> 0.4419481 | AI35: =IF(AF35>0,((MIN(AF35,0.95*Inputs!$B$12*Inputs!$B$26)/Inputs!$B$26)^Inputs!$B$12/FACT(Inputs!$B$12)*Inputs!$B$12/(Inputs!$B$12-(MIN(AF35,0.95*Inputs!$B$12*Inputs!$B$26)/Inputs!$B$26)))/(SUMPRODUCT(--({0,1,2,3,4,5,6,7,8,9}<Inputs!$B$12),(MIN(AF35,0.95*Inputs!$B$12*Inputs!$B$26)/Inputs!$B$26)^{0,1,2,3,4,5,6,7,8,9}/FACT({0,1,2,3,4,5,6,7,8,9}))+((MIN(AF35,0.95*Inputs!$B$12*Inputs!$B$26)/Inputs!$B$26)^Inputs!$B$12/FACT(Inputs!$B$12)*Inputs!$B$12/(Inputs!$B$12-(MIN(AF35,0.95*Inputs!$B$12*Inputs!$B$26)/Inputs!$B$26)))),0) -> 0.27090867 | AJ35: =IF(AF35>0,AI35/(Inputs!$B$12*Inputs!$B$26-MIN(AF35,0.95*Inputs!$B$12*Inputs!$B$26)),0) -> 0.024272713 | AK35: =MAX(0,AK34+(AF35-Inputs!$B$12*Inputs!$B$26)*10) -> 0 | AL35: =(AK34+AK35)/2/(Inputs!$B$12*Inputs!$B$26)+AJ35 -> 0.024272713 | AM35: =Inputs!$B$86+AL35+1/Inputs!$B$26+Inputs!$B$87+Inputs!$B$88+Inputs!$B$89 -> 28.649273 | AN35: =AF35*AM35 -> 253.22983
A36: 12:30 | B36: ='Arrival Curve'!$L$25 -> 0.096198625 | C36: ='Arrival Curve'!$K$25 -> 284.74793 | D36: =C36/10 -> 28.474793 | E36: =$D36*Inputs!$B$35 -> 22.69441 | F36: =E36/Inputs!$B$84 -> 0.75648034 | G36: =E36/(Inputs!$B$11*Inputs!$B$26) -> 1.1347205 | H36: =IF(E36>0,((MIN(E36,0.95*Inputs!$B$11*Inputs!$B$26)/Inputs!$B$26)^Inputs!$B$11/FACT(Inputs!$B$11)*Inputs!$B$11/(Inputs!$B$11-(MIN(E36,0.95*Inputs!$B$11*Inputs!$B$26)/Inputs!$B$26)))/(SUMPRODUCT(--({0,1,2,3,4,5,6,7,8,9}<Inputs!$B$11),(MIN(E36,0.95*Inputs!$B$11*Inputs!$B$26)/Inputs!$B$26)^{0,1,2,3,4,5,6,7,8,9}/FACT({0,1,2,3,4,5,6,7,8,9}))+((MIN(E36,0.95*Inputs!$B$11*Inputs!$B$26)/Inputs!$B$26)^Inputs!$B$11/FACT(Inputs!$B$11)*Inputs!$B$11/(Inputs!$B$11-(MIN(E36,0.95*Inputs!$B$11*Inputs!$B$26)/Inputs!$B$26)))),0) -> 0.92564103 | I36: =IF(E36>0,H36/(Inputs!$B$11*Inputs!$B$26-MIN(E36,0.95*Inputs!$B$11*Inputs!$B$26)),0) -> 0.92564103 | J36: =MAX(0,J35+(E36-Inputs!$B$11*Inputs!$B$26)*10) -> 26.944101 | K36: =(J35+J36)/2/(Inputs!$B$11*Inputs!$B$26)+I36 -> 1.5992436 | L36: =Inputs!$B$86+K36+1/Inputs!$B$26+Inputs!$B$87+Inputs!$B$88+Inputs!$B$89 -> 30.224244 | M36: =E36*L36 -> 685.92138 | N36: =$D36*(1-Inputs!$B$35) -> 5.780383 | O36: =N36/Inputs!$B$85 -> 0.19267943 | P36: =N36/(Inputs!$B$12*Inputs!$B$26) -> 0.28901915 | Q36: =IF(N36>0,((MIN(N36,0.95*Inputs!$B$12*Inputs!$B$26)/Inputs!$B$26)^Inputs!$B$12/FACT(Inputs!$B$12)*Inputs!$B$12/(Inputs!$B$12-(MIN(N36,0.95*Inputs!$B$12*Inputs!$B$26)/Inputs!$B$26)))/(SUMPRODUCT(--({0,1,2,3,4,5,6,7,8,9}<Inputs!$B$12),(MIN(N36,0.95*Inputs!$B$12*Inputs!$B$26)/Inputs!$B$26)^{0,1,2,3,4,5,6,7,8,9}/FACT({0,1,2,3,4,5,6,7,8,9}))+((MIN(N36,0.95*Inputs!$B$12*Inputs!$B$26)/Inputs!$B$26)^Inputs!$B$12/FACT(Inputs!$B$12)*Inputs!$B$12/(Inputs!$B$12-(MIN(N36,0.95*Inputs!$B$12*Inputs!$B$26)/Inputs!$B$26)))),0) -> 0.12960563 | R36: =IF(N36>0,Q36/(Inputs!$B$12*Inputs!$B$26-MIN(N36,0.95*Inputs!$B$12*Inputs!$B$26)),0) -> 0.0091145654 | S36: =MAX(0,S35+(N36-Inputs!$B$12*Inputs!$B$26)*10) -> 0 | T36: =(S35+S36)/2/(Inputs!$B$12*Inputs!$B$26)+R36 -> 0.0091145654 | U36: =Inputs!$B$86+T36+1/Inputs!$B$26+Inputs!$B$87+Inputs!$B$88+Inputs!$B$89 -> 28.634115 | V36: =N36*U36 -> 165.51615 | W36: =$D36*$E$26 -> 17.620202 | X36: =W36/Inputs!$B$84 -> 0.58734007 | Y36: =W36/(Inputs!$B$11*Inputs!$B$26) -> 0.8810101 | Z36: =IF(W36>0,((MIN(W36,0.95*Inputs!$B$11*Inputs!$B$26)/Inputs!$B$26)^Inputs!$B$11/FACT(Inputs!$B$11)*Inputs!$B$11/(Inputs!$B$11-(MIN(W36,0.95*Inputs!$B$11*Inputs!$B$26)/Inputs!$B$26)))/(SUMPRODUCT(--({0,1,2,3,4,5,6,7,8,9}<Inputs!$B$11),(MIN(W36,0.95*Inputs!$B$11*Inputs!$B$26)/Inputs!$B$26)^{0,1,2,3,4,5,6,7,8,9}/FACT({0,1,2,3,4,5,6,7,8,9}))+((MIN(W36,0.95*Inputs!$B$11*Inputs!$B$26)/Inputs!$B$26)^Inputs!$B$11/FACT(Inputs!$B$11)*Inputs!$B$11/(Inputs!$B$11-(MIN(W36,0.95*Inputs!$B$11*Inputs!$B$26)/Inputs!$B$26)))),0) -> 0.82527871 | AA36: =IF(W36>0,Z36/(Inputs!$B$11*Inputs!$B$26-MIN(W36,0.95*Inputs!$B$11*Inputs!$B$26)),0) -> 0.34678519 | AB36: =MAX(0,AB35+(W36-Inputs!$B$11*Inputs!$B$26)*10) -> 0 | AC36: =(AB35+AB36)/2/(Inputs!$B$11*Inputs!$B$26)+AA36 -> 0.34678519 | AD36: =Inputs!$B$86+AC36+1/Inputs!$B$26+Inputs!$B$87+Inputs!$B$88+Inputs!$B$89 -> 28.971785 | AE36: =W36*AD36 -> 510.48871 | AF36: =$D36*(1-$E$26) -> 10.854591 | AG36: =AF36/Inputs!$B$85 -> 0.3618197 | AH36: =AF36/(Inputs!$B$12*Inputs!$B$26) -> 0.54272956 | AI36: =IF(AF36>0,((MIN(AF36,0.95*Inputs!$B$12*Inputs!$B$26)/Inputs!$B$26)^Inputs!$B$12/FACT(Inputs!$B$12)*Inputs!$B$12/(Inputs!$B$12-(MIN(AF36,0.95*Inputs!$B$12*Inputs!$B$26)/Inputs!$B$26)))/(SUMPRODUCT(--({0,1,2,3,4,5,6,7,8,9}<Inputs!$B$12),(MIN(AF36,0.95*Inputs!$B$12*Inputs!$B$26)/Inputs!$B$26)^{0,1,2,3,4,5,6,7,8,9}/FACT({0,1,2,3,4,5,6,7,8,9}))+((MIN(AF36,0.95*Inputs!$B$12*Inputs!$B$26)/Inputs!$B$26)^Inputs!$B$12/FACT(Inputs!$B$12)*Inputs!$B$12/(Inputs!$B$12-(MIN(AF36,0.95*Inputs!$B$12*Inputs!$B$26)/Inputs!$B$26)))),0) -> 0.38186262 | AJ36: =IF(AF36>0,AI36/(Inputs!$B$12*Inputs!$B$26-MIN(AF36,0.95*Inputs!$B$12*Inputs!$B$26)),0) -> 0.04175457 | AK36: =MAX(0,AK35+(AF36-Inputs!$B$12*Inputs!$B$26)*10) -> 0 | AL36: =(AK35+AK36)/2/(Inputs!$B$12*Inputs!$B$26)+AJ36 -> 0.04175457 | AM36: =Inputs!$B$86+AL36+1/Inputs!$B$26+Inputs!$B$87+Inputs!$B$88+Inputs!$B$89 -> 28.666755 | AN36: =AF36*AM36 -> 311.1659
A37: 12:40 | B37: ='Arrival Curve'!$L$26 -> 0.087942206 | C37: ='Arrival Curve'!$K$26 -> 260.30893 | D37: =C37/10 -> 26.030893 | E37: =$D37*Inputs!$B$35 -> 20.746622 | F37: =E37/Inputs!$B$84 -> 0.69155406 | G37: =E37/(Inputs!$B$11*Inputs!$B$26) -> 1.0373311 | H37: =IF(E37>0,((MIN(E37,0.95*Inputs!$B$11*Inputs!$B$26)/Inputs!$B$26)^Inputs!$B$11/FACT(Inputs!$B$11)*Inputs!$B$11/(Inputs!$B$11-(MIN(E37,0.95*Inputs!$B$11*Inputs!$B$26)/Inputs!$B$26)))/(SUMPRODUCT(--({0,1,2,3,4,5,6,7,8,9}<Inputs!$B$11),(MIN(E37,0.95*Inputs!$B$11*Inputs!$B$26)/Inputs!$B$26)^{0,1,2,3,4,5,6,7,8,9}/FACT({0,1,2,3,4,5,6,7,8,9}))+((MIN(E37,0.95*Inputs!$B$11*Inputs!$B$26)/Inputs!$B$26)^Inputs!$B$11/FACT(Inputs!$B$11)*Inputs!$B$11/(Inputs!$B$11-(MIN(E37,0.95*Inputs!$B$11*Inputs!$B$26)/Inputs!$B$26)))),0) -> 0.92564103 | I37: =IF(E37>0,H37/(Inputs!$B$11*Inputs!$B$26-MIN(E37,0.95*Inputs!$B$11*Inputs!$B$26)),0) -> 0.92564103 | J37: =MAX(0,J36+(E37-Inputs!$B$11*Inputs!$B$26)*10) -> 34.410318 | K37: =(J36+J37)/2/(Inputs!$B$11*Inputs!$B$26)+I37 -> 2.4595015 | L37: =Inputs!$B$86+K37+1/Inputs!$B$26+Inputs!$B$87+Inputs!$B$88+Inputs!$B$89 -> 31.084502 | M37: =E37*L37 -> 644.89839 | N37: =$D37*(1-Inputs!$B$35) -> 5.2842713 | O37: =N37/Inputs!$B$85 -> 0.17614238 | P37: =N37/(Inputs!$B$12*Inputs!$B$26) -> 0.26421356 | Q37: =IF(N37>0,((MIN(N37,0.95*Inputs!$B$12*Inputs!$B$26)/Inputs!$B$26)^Inputs!$B$12/FACT(Inputs!$B$12)*Inputs!$B$12/(Inputs!$B$12-(MIN(N37,0.95*Inputs!$B$12*Inputs!$B$26)/Inputs!$B$26)))/(SUMPRODUCT(--({0,1,2,3,4,5,6,7,8,9}<Inputs!$B$12),(MIN(N37,0.95*Inputs!$B$12*Inputs!$B$26)/Inputs!$B$26)^{0,1,2,3,4,5,6,7,8,9}/FACT({0,1,2,3,4,5,6,7,8,9}))+((MIN(N37,0.95*Inputs!$B$12*Inputs!$B$26)/Inputs!$B$26)^Inputs!$B$12/FACT(Inputs!$B$12)*Inputs!$B$12/(Inputs!$B$12-(MIN(N37,0.95*Inputs!$B$12*Inputs!$B$26)/Inputs!$B$26)))),0) -> 0.11043831 | R37: =IF(N37>0,Q37/(Inputs!$B$12*Inputs!$B$26-MIN(N37,0.95*Inputs!$B$12*Inputs!$B$26)),0) -> 0.0075047805 | S37: =MAX(0,S36+(N37-Inputs!$B$12*Inputs!$B$26)*10) -> 0 | T37: =(S36+S37)/2/(Inputs!$B$12*Inputs!$B$26)+R37 -> 0.0075047805 | U37: =Inputs!$B$86+T37+1/Inputs!$B$26+Inputs!$B$87+Inputs!$B$88+Inputs!$B$89 -> 28.632505 | V37: =N37*U37 -> 151.30192 | W37: =$D37*$E$26 -> 16.107917 | X37: =W37/Inputs!$B$84 -> 0.53693055 | Y37: =W37/(Inputs!$B$11*Inputs!$B$26) -> 0.80539583 | Z37: =IF(W37>0,((MIN(W37,0.95*Inputs!$B$11*Inputs!$B$26)/Inputs!$B$26)^Inputs!$B$11/FACT(Inputs!$B$11)*Inputs!$B$11/(Inputs!$B$11-(MIN(W37,0.95*Inputs!$B$11*Inputs!$B$26)/Inputs!$B$26)))/(SUMPRODUCT(--({0,1,2,3,4,5,6,7,8,9}<Inputs!$B$11),(MIN(W37,0.95*Inputs!$B$11*Inputs!$B$26)/Inputs!$B$26)^{0,1,2,3,4,5,6,7,8,9}/FACT({0,1,2,3,4,5,6,7,8,9}))+((MIN(W37,0.95*Inputs!$B$11*Inputs!$B$26)/Inputs!$B$26)^Inputs!$B$11/FACT(Inputs!$B$11)*Inputs!$B$11/(Inputs!$B$11-(MIN(W37,0.95*Inputs!$B$11*Inputs!$B$26)/Inputs!$B$26)))),0) -> 0.71858196 | AA37: =IF(W37>0,Z37/(Inputs!$B$11*Inputs!$B$26-MIN(W37,0.95*Inputs!$B$11*Inputs!$B$26)),0) -> 0.18462656 | AB37: =MAX(0,AB36+(W37-Inputs!$B$11*Inputs!$B$26)*10) -> 0 | AC37: =(AB36+AB37)/2/(Inputs!$B$11*Inputs!$B$26)+AA37 -> 0.18462656 | AD37: =Inputs!$B$86+AC37+1/Inputs!$B$26+Inputs!$B$87+Inputs!$B$88+Inputs!$B$89 -> 28.809627 | AE37: =W37*AD37 -> 464.06306 | AF37: =$D37*(1-$E$26) -> 9.9229764 | AG37: =AF37/Inputs!$B$85 -> 0.33076588 | AH37: =AF37/(Inputs!$B$12*Inputs!$B$26) -> 0.49614882 | AI37: =IF(AF37>0,((MIN(AF37,0.95*Inputs!$B$12*Inputs!$B$26)/Inputs!$B$26)^Inputs!$B$12/FACT(Inputs!$B$12)*Inputs!$B$12/(Inputs!$B$12-(MIN(AF37,0.95*Inputs!$B$12*Inputs!$B$26)/Inputs!$B$26)))/(SUMPRODUCT(--({0,1,2,3,4,5,6,7,8,9}<Inputs!$B$12),(MIN(AF37,0.95*Inputs!$B$12*Inputs!$B$26)/Inputs!$B$26)^{0,1,2,3,4,5,6,7,8,9}/FACT({0,1,2,3,4,5,6,7,8,9}))+((MIN(AF37,0.95*Inputs!$B$12*Inputs!$B$26)/Inputs!$B$26)^Inputs!$B$12/FACT(Inputs!$B$12)*Inputs!$B$12/(Inputs!$B$12-(MIN(AF37,0.95*Inputs!$B$12*Inputs!$B$26)/Inputs!$B$26)))),0) -> 0.32906306 | AJ37: =IF(AF37>0,AI37/(Inputs!$B$12*Inputs!$B$26-MIN(AF37,0.95*Inputs!$B$12*Inputs!$B$26)),0) -> 0.032654787 | AK37: =MAX(0,AK36+(AF37-Inputs!$B$12*Inputs!$B$26)*10) -> 0 | AL37: =(AK36+AK37)/2/(Inputs!$B$12*Inputs!$B$26)+AJ37 -> 0.032654787 | AM37: =Inputs!$B$86+AL37+1/Inputs!$B$26+Inputs!$B$87+Inputs!$B$88+Inputs!$B$89 -> 28.657655 | AN37: =AF37*AM37 -> 284.36923
A38: 12:50 | B38: ='Arrival Curve'!$L$27 -> 0.072907784 | C38: ='Arrival Curve'!$K$27 -> 215.80704 | D38: =C38/10 -> 21.580704 | E38: =$D38*Inputs!$B$35 -> 17.199821 | F38: =E38/Inputs!$B$84 -> 0.57332737 | G38: =E38/(Inputs!$B$11*Inputs!$B$26) -> 0.85999105 | H38: =IF(E38>0,((MIN(E38,0.95*Inputs!$B$11*Inputs!$B$26)/Inputs!$B$26)^Inputs!$B$11/FACT(Inputs!$B$11)*Inputs!$B$11/(Inputs!$B$11-(MIN(E38,0.95*Inputs!$B$11*Inputs!$B$26)/Inputs!$B$26)))/(SUMPRODUCT(--({0,1,2,3,4,5,6,7,8,9}<Inputs!$B$11),(MIN(E38,0.95*Inputs!$B$11*Inputs!$B$26)/Inputs!$B$26)^{0,1,2,3,4,5,6,7,8,9}/FACT({0,1,2,3,4,5,6,7,8,9}))+((MIN(E38,0.95*Inputs!$B$11*Inputs!$B$26)/Inputs!$B$26)^Inputs!$B$11/FACT(Inputs!$B$11)*Inputs!$B$11/(Inputs!$B$11-(MIN(E38,0.95*Inputs!$B$11*Inputs!$B$26)/Inputs!$B$26)))),0) -> 0.7952561 | I38: =IF(E38>0,H38/(Inputs!$B$11*Inputs!$B$26-MIN(E38,0.95*Inputs!$B$11*Inputs!$B$26)),0) -> 0.28400189 | J38: =MAX(0,J37+(E38-Inputs!$B$11*Inputs!$B$26)*10) -> 6.4085288 | K38: =(J37+J38)/2/(Inputs!$B$11*Inputs!$B$26)+I38 -> 1.3044731 | L38: =Inputs!$B$86+K38+1/Inputs!$B$26+Inputs!$B$87+Inputs!$B$88+Inputs!$B$89 -> 29.929473 | M38: =E38*L38 -> 514.78158 | N38: =$D38*(1-Inputs!$B$35) -> 4.3808829 | O38: =N38/Inputs!$B$85 -> 0.14602943 | P38: =N38/(Inputs!$B$12*Inputs!$B$26) -> 0.21904415 | Q38: =IF(N38>0,((MIN(N38,0.95*Inputs!$B$12*Inputs!$B$26)/Inputs!$B$26)^Inputs!$B$12/FACT(Inputs!$B$12)*Inputs!$B$12/(Inputs!$B$12-(MIN(N38,0.95*Inputs!$B$12*Inputs!$B$26)/Inputs!$B$26)))/(SUMPRODUCT(--({0,1,2,3,4,5,6,7,8,9}<Inputs!$B$12),(MIN(N38,0.95*Inputs!$B$12*Inputs!$B$26)/Inputs!$B$26)^{0,1,2,3,4,5,6,7,8,9}/FACT({0,1,2,3,4,5,6,7,8,9}))+((MIN(N38,0.95*Inputs!$B$12*Inputs!$B$26)/Inputs!$B$26)^Inputs!$B$12/FACT(Inputs!$B$12)*Inputs!$B$12/(Inputs!$B$12-(MIN(N38,0.95*Inputs!$B$12*Inputs!$B$26)/Inputs!$B$26)))),0) -> 0.078717966 | R38: =IF(N38>0,Q38/(Inputs!$B$12*Inputs!$B$26-MIN(N38,0.95*Inputs!$B$12*Inputs!$B$26)),0) -> 0.0050398473 | S38: =MAX(0,S37+(N38-Inputs!$B$12*Inputs!$B$26)*10) -> 0 | T38: =(S37+S38)/2/(Inputs!$B$12*Inputs!$B$26)+R38 -> 0.0050398473 | U38: =Inputs!$B$86+T38+1/Inputs!$B$26+Inputs!$B$87+Inputs!$B$88+Inputs!$B$89 -> 28.63004 | V38: =N38*U38 -> 125.42485 | W38: =$D38*$E$26 -> 13.35414 | X38: =W38/Inputs!$B$84 -> 0.44513799 | Y38: =W38/(Inputs!$B$11*Inputs!$B$26) -> 0.66770698 | Z38: =IF(W38>0,((MIN(W38,0.95*Inputs!$B$11*Inputs!$B$26)/Inputs!$B$26)^Inputs!$B$11/FACT(Inputs!$B$11)*Inputs!$B$11/(Inputs!$B$11-(MIN(W38,0.95*Inputs!$B$11*Inputs!$B$26)/Inputs!$B$26)))/(SUMPRODUCT(--({0,1,2,3,4,5,6,7,8,9}<Inputs!$B$11),(MIN(W38,0.95*Inputs!$B$11*Inputs!$B$26)/Inputs!$B$26)^{0,1,2,3,4,5,6,7,8,9}/FACT({0,1,2,3,4,5,6,7,8,9}))+((MIN(W38,0.95*Inputs!$B$11*Inputs!$B$26)/Inputs!$B$26)^Inputs!$B$11/FACT(Inputs!$B$11)*Inputs!$B$11/(Inputs!$B$11-(MIN(W38,0.95*Inputs!$B$11*Inputs!$B$26)/Inputs!$B$26)))),0) -> 0.5346654 | AA38: =IF(W38>0,Z38/(Inputs!$B$11*Inputs!$B$26-MIN(W38,0.95*Inputs!$B$11*Inputs!$B$26)),0) -> 0.080450893 | AB38: =MAX(0,AB37+(W38-Inputs!$B$11*Inputs!$B$26)*10) -> 0 | AC38: =(AB37+AB38)/2/(Inputs!$B$11*Inputs!$B$26)+AA38 -> 0.080450893 | AD38: =Inputs!$B$86+AC38+1/Inputs!$B$26+Inputs!$B$87+Inputs!$B$88+Inputs!$B$89 -> 28.705451 | AE38: =W38*AD38 -> 383.3366 | AF38: =$D38*(1-$E$26) -> 8.2265644 | AG38: =AF38/Inputs!$B$85 -> 0.27421881 | AH38: =AF38/(Inputs!$B$12*Inputs!$B$26) -> 0.41132822 | AI38: =IF(AF38>0,((MIN(AF38,0.95*Inputs!$B$12*Inputs!$B$26)/Inputs!$B$26)^Inputs!$B$12/FACT(Inputs!$B$12)*Inputs!$B$12/(Inputs!$B$12-(MIN(AF38,0.95*Inputs!$B$12*Inputs!$B$26)/Inputs!$B$26)))/(SUMPRODUCT(--({0,1,2,3,4,5,6,7,8,9}<Inputs!$B$12),(MIN(AF38,0.95*Inputs!$B$12*Inputs!$B$26)/Inputs!$B$26)^{0,1,2,3,4,5,6,7,8,9}/FACT({0,1,2,3,4,5,6,7,8,9}))+((MIN(AF38,0.95*Inputs!$B$12*Inputs!$B$26)/Inputs!$B$26)^Inputs!$B$12/FACT(Inputs!$B$12)*Inputs!$B$12/(Inputs!$B$12-(MIN(AF38,0.95*Inputs!$B$12*Inputs!$B$26)/Inputs!$B$26)))),0) -> 0.23976124 | AJ38: =IF(AF38>0,AI38/(Inputs!$B$12*Inputs!$B$26-MIN(AF38,0.95*Inputs!$B$12*Inputs!$B$26)),0) -> 0.020364594 | AK38: =MAX(0,AK37+(AF38-Inputs!$B$12*Inputs!$B$26)*10) -> 0 | AL38: =(AK37+AK38)/2/(Inputs!$B$12*Inputs!$B$26)+AJ38 -> 0.020364594 | AM38: =Inputs!$B$86+AL38+1/Inputs!$B$26+Inputs!$B$87+Inputs!$B$88+Inputs!$B$89 -> 28.645365 | AN38: =AF38*AM38 -> 235.65294
A39: 13:00 | B39: ='Arrival Curve'!$L$28 -> 0.097676044 | C39: ='Arrival Curve'!$K$28 -> 289.12109 | D39: =C39/10 -> 28.912109 | E39: =$D39*Inputs!$B$35 -> 23.042951 | F39: =E39/Inputs!$B$84 -> 0.76809836 | G39: =E39/(Inputs!$B$11*Inputs!$B$26) -> 1.1521475 | H39: =IF(E39>0,((MIN(E39,0.95*Inputs!$B$11*Inputs!$B$26)/Inputs!$B$26)^Inputs!$B$11/FACT(Inputs!$B$11)*Inputs!$B$11/(Inputs!$B$11-(MIN(E39,0.95*Inputs!$B$11*Inputs!$B$26)/Inputs!$B$26)))/(SUMPRODUCT(--({0,1,2,3,4,5,6,7,8,9}<Inputs!$B$11),(MIN(E39,0.95*Inputs!$B$11*Inputs!$B$26)/Inputs!$B$26)^{0,1,2,3,4,5,6,7,8,9}/FACT({0,1,2,3,4,5,6,7,8,9}))+((MIN(E39,0.95*Inputs!$B$11*Inputs!$B$26)/Inputs!$B$26)^Inputs!$B$11/FACT(Inputs!$B$11)*Inputs!$B$11/(Inputs!$B$11-(MIN(E39,0.95*Inputs!$B$11*Inputs!$B$26)/Inputs!$B$26)))),0) -> 0.92564103 | I39: =IF(E39>0,H39/(Inputs!$B$11*Inputs!$B$26-MIN(E39,0.95*Inputs!$B$11*Inputs!$B$26)),0) -> 0.92564103 | J39: =MAX(0,J38+(E39-Inputs!$B$11*Inputs!$B$26)*10) -> 36.838038 | K39: =(J38+J39)/2/(Inputs!$B$11*Inputs!$B$26)+I39 -> 2.0068052 | L39: =Inputs!$B$86+K39+1/Inputs!$B$26+Inputs!$B$87+Inputs!$B$88+Inputs!$B$89 -> 30.631805 | M39: =E39*L39 -> 705.84718 | N39: =$D39*(1-Inputs!$B$35) -> 5.8691581 | O39: =N39/Inputs!$B$85 -> 0.1956386 | P39: =N39/(Inputs!$B$12*Inputs!$B$26) -> 0.29345791 | Q39: =IF(N39>0,((MIN(N39,0.95*Inputs!$B$12*Inputs!$B$26)/Inputs!$B$26)^Inputs!$B$12/FACT(Inputs!$B$12)*Inputs!$B$12/(Inputs!$B$12-(MIN(N39,0.95*Inputs!$B$12*Inputs!$B$26)/Inputs!$B$26)))/(SUMPRODUCT(--({0,1,2,3,4,5,6,7,8,9}<Inputs!$B$12),(MIN(N39,0.95*Inputs!$B$12*Inputs!$B$26)/Inputs!$B$26)^{0,1,2,3,4,5,6,7,8,9}/FACT({0,1,2,3,4,5,6,7,8,9}))+((MIN(N39,0.95*Inputs!$B$12*Inputs!$B$26)/Inputs!$B$26)^Inputs!$B$12/FACT(Inputs!$B$12)*Inputs!$B$12/(Inputs!$B$12-(MIN(N39,0.95*Inputs!$B$12*Inputs!$B$26)/Inputs!$B$26)))),0) -> 0.13315863 | R39: =IF(N39>0,Q39/(Inputs!$B$12*Inputs!$B$26-MIN(N39,0.95*Inputs!$B$12*Inputs!$B$26)),0) -> 0.0094232625 | S39: =MAX(0,S38+(N39-Inputs!$B$12*Inputs!$B$26)*10) -> 0 | T39: =(S38+S39)/2/(Inputs!$B$12*Inputs!$B$26)+R39 -> 0.0094232625 | U39: =Inputs!$B$86+T39+1/Inputs!$B$26+Inputs!$B$87+Inputs!$B$88+Inputs!$B$89 -> 28.634423 | V39: =N39*U39 -> 168.05996 | W39: =$D39*$E$26 -> 17.890813 | X39: =W39/Inputs!$B$84 -> 0.59636044 | Y39: =W39/(Inputs!$B$11*Inputs!$B$26) -> 0.89454065 | Z39: =IF(W39>0,((MIN(W39,0.95*Inputs!$B$11*Inputs!$B$26)/Inputs!$B$26)^Inputs!$B$11/FACT(Inputs!$B$11)*Inputs!$B$11/(Inputs!$B$11-(MIN(W39,0.95*Inputs!$B$11*Inputs!$B$26)/Inputs!$B$26)))/(SUMPRODUCT(--({0,1,2,3,4,5,6,7,8,9}<Inputs!$B$11),(MIN(W39,0.95*Inputs!$B$11*Inputs!$B$26)/Inputs!$B$26)^{0,1,2,3,4,5,6,7,8,9}/FACT({0,1,2,3,4,5,6,7,8,9}))+((MIN(W39,0.95*Inputs!$B$11*Inputs!$B$26)/Inputs!$B$26)^Inputs!$B$11/FACT(Inputs!$B$11)*Inputs!$B$11/(Inputs!$B$11-(MIN(W39,0.95*Inputs!$B$11*Inputs!$B$26)/Inputs!$B$26)))),0) -> 0.84474617 | AA39: =IF(W39>0,Z39/(Inputs!$B$11*Inputs!$B$26-MIN(W39,0.95*Inputs!$B$11*Inputs!$B$26)),0) -> 0.40050796 | AB39: =MAX(0,AB38+(W39-Inputs!$B$11*Inputs!$B$26)*10) -> 0 | AC39: =(AB38+AB39)/2/(Inputs!$B$11*Inputs!$B$26)+AA39 -> 0.40050796 | AD39: =Inputs!$B$86+AC39+1/Inputs!$B$26+Inputs!$B$87+Inputs!$B$88+Inputs!$B$89 -> 29.025508 | AE39: =W39*AD39 -> 519.28994 | AF39: =$D39*(1-$E$26) -> 11.021296 | AG39: =AF39/Inputs!$B$85 -> 0.36737653 | AH39: =AF39/(Inputs!$B$12*Inputs!$B$26) -> 0.5510648 | AI39: =IF(AF39>0,((MIN(AF39,0.95*Inputs!$B$12*Inputs!$B$26)/Inputs!$B$26)^Inputs!$B$12/FACT(Inputs!$B$12)*Inputs!$B$12/(Inputs!$B$12-(MIN(AF39,0.95*Inputs!$B$12*Inputs!$B$26)/Inputs!$B$26)))/(SUMPRODUCT(--({0,1,2,3,4,5,6,7,8,9}<Inputs!$B$12),(MIN(AF39,0.95*Inputs!$B$12*Inputs!$B$26)/Inputs!$B$26)^{0,1,2,3,4,5,6,7,8,9}/FACT({0,1,2,3,4,5,6,7,8,9}))+((MIN(AF39,0.95*Inputs!$B$12*Inputs!$B$26)/Inputs!$B$26)^Inputs!$B$12/FACT(Inputs!$B$12)*Inputs!$B$12/(Inputs!$B$12-(MIN(AF39,0.95*Inputs!$B$12*Inputs!$B$26)/Inputs!$B$26)))),0) -> 0.39156638 | AJ39: =IF(AF39>0,AI39/(Inputs!$B$12*Inputs!$B$26-MIN(AF39,0.95*Inputs!$B$12*Inputs!$B$26)),0) -> 0.043610567 | AK39: =MAX(0,AK38+(AF39-Inputs!$B$12*Inputs!$B$26)*10) -> 0 | AL39: =(AK38+AK39)/2/(Inputs!$B$12*Inputs!$B$26)+AJ39 -> 0.043610567 | AM39: =Inputs!$B$86+AL39+1/Inputs!$B$26+Inputs!$B$87+Inputs!$B$88+Inputs!$B$89 -> 28.668611 | AN39: =AF39*AM39 -> 315.96524
A40: 13:10 | B40: ='Arrival Curve'!$L$29 -> 0.12647211 | C40: ='Arrival Curve'!$K$29 -> 374.35746 | D40: =C40/10 -> 37.435746 | E40: =$D40*Inputs!$B$35 -> 29.836289 | F40: =E40/Inputs!$B$84 -> 0.99454297 | G40: =E40/(Inputs!$B$11*Inputs!$B$26) -> 1.4918145 | H40: =IF(E40>0,((MIN(E40,0.95*Inputs!$B$11*Inputs!$B$26)/Inputs!$B$26)^Inputs!$B$11/FACT(Inputs!$B$11)*Inputs!$B$11/(Inputs!$B$11-(MIN(E40,0.95*Inputs!$B$11*Inputs!$B$26)/Inputs!$B$26)))/(SUMPRODUCT(--({0,1,2,3,4,5,6,7,8,9}<Inputs!$B$11),(MIN(E40,0.95*Inputs!$B$11*Inputs!$B$26)/Inputs!$B$26)^{0,1,2,3,4,5,6,7,8,9}/FACT({0,1,2,3,4,5,6,7,8,9}))+((MIN(E40,0.95*Inputs!$B$11*Inputs!$B$26)/Inputs!$B$26)^Inputs!$B$11/FACT(Inputs!$B$11)*Inputs!$B$11/(Inputs!$B$11-(MIN(E40,0.95*Inputs!$B$11*Inputs!$B$26)/Inputs!$B$26)))),0) -> 0.92564103 | I40: =IF(E40>0,H40/(Inputs!$B$11*Inputs!$B$26-MIN(E40,0.95*Inputs!$B$11*Inputs!$B$26)),0) -> 0.92564103 | J40: =MAX(0,J39+(E40-Inputs!$B$11*Inputs!$B$26)*10) -> 135.20093 | K40: =(J39+J40)/2/(Inputs!$B$11*Inputs!$B$26)+I40 -> 5.2266152 | L40: =Inputs!$B$86+K40+1/Inputs!$B$26+Inputs!$B$87+Inputs!$B$88+Inputs!$B$89 -> 33.851615 | M40: =E40*L40 -> 1010.0066 | N40: =$D40*(1-Inputs!$B$35) -> 7.5994564 | O40: =N40/Inputs!$B$85 -> 0.25331521 | P40: =N40/(Inputs!$B$12*Inputs!$B$26) -> 0.37997282 | Q40: =IF(N40>0,((MIN(N40,0.95*Inputs!$B$12*Inputs!$B$26)/Inputs!$B$26)^Inputs!$B$12/FACT(Inputs!$B$12)*Inputs!$B$12/(Inputs!$B$12-(MIN(N40,0.95*Inputs!$B$12*Inputs!$B$26)/Inputs!$B$26)))/(SUMPRODUCT(--({0,1,2,3,4,5,6,7,8,9}<Inputs!$B$12),(MIN(N40,0.95*Inputs!$B$12*Inputs!$B$26)/Inputs!$B$26)^{0,1,2,3,4,5,6,7,8,9}/FACT({0,1,2,3,4,5,6,7,8,9}))+((MIN(N40,0.95*Inputs!$B$12*Inputs!$B$26)/Inputs!$B$26)^Inputs!$B$12/FACT(Inputs!$B$12)*Inputs!$B$12/(Inputs!$B$12-(MIN(N40,0.95*Inputs!$B$12*Inputs!$B$26)/Inputs!$B$26)))),0) -> 0.20924955 | R40: =IF(N40>0,Q40/(Inputs!$B$12*Inputs!$B$26-MIN(N40,0.95*Inputs!$B$12*Inputs!$B$26)),0) -> 0.016874224 | S40: =MAX(0,S39+(N40-Inputs!$B$12*Inputs!$B$26)*10) -> 0 | T40: =(S39+S40)/2/(Inputs!$B$12*Inputs!$B$26)+R40 -> 0.016874224 | U40: =Inputs!$B$86+T40+1/Inputs!$B$26+Inputs!$B$87+Inputs!$B$88+Inputs!$B$89 -> 28.641874 | V40: =N40*U40 -> 217.66267 | W40: =$D40*$E$26 -> 23.165239 | X40: =W40/Inputs!$B$84 -> 0.77217465 | Y40: =W40/(Inputs!$B$11*Inputs!$B$26) -> 1.158262 | Z40: =IF(W40>0,((MIN(W40,0.95*Inputs!$B$11*Inputs!$B$26)/Inputs!$B$26)^Inputs!$B$11/FACT(Inputs!$B$11)*Inputs!$B$11/(Inputs!$B$11-(MIN(W40,0.95*Inputs!$B$11*Inputs!$B$26)/Inputs!$B$26)))/(SUMPRODUCT(--({0,1,2,3,4,5,6,7,8,9}<Inputs!$B$11),(MIN(W40,0.95*Inputs!$B$11*Inputs!$B$26)/Inputs!$B$26)^{0,1,2,3,4,5,6,7,8,9}/FACT({0,1,2,3,4,5,6,7,8,9}))+((MIN(W40,0.95*Inputs!$B$11*Inputs!$B$26)/Inputs!$B$26)^Inputs!$B$11/FACT(Inputs!$B$11)*Inputs!$B$11/(Inputs!$B$11-(MIN(W40,0.95*Inputs!$B$11*Inputs!$B$26)/Inputs!$B$26)))),0) -> 0.92564103 | AA40: =IF(W40>0,Z40/(Inputs!$B$11*Inputs!$B$26-MIN(W40,0.95*Inputs!$B$11*Inputs!$B$26)),0) -> 0.92564103 | AB40: =MAX(0,AB39+(W40-Inputs!$B$11*Inputs!$B$26)*10) -> 31.652394 | AC40: =(AB39+AB40)/2/(Inputs!$B$11*Inputs!$B$26)+AA40 -> 1.7169509 | AD40: =Inputs!$B$86+AC40+1/Inputs!$B$26+Inputs!$B$87+Inputs!$B$88+Inputs!$B$89 -> 30.341951 | AE40: =W40*AD40 -> 702.87856 | AF40: =$D40*(1-$E$26) -> 14.270506 | AG40: =AF40/Inputs!$B$85 -> 0.47568354 | AH40: =AF40/(Inputs!$B$12*Inputs!$B$26) -> 0.71352531 | AI40: =IF(AF40>0,((MIN(AF40,0.95*Inputs!$B$12*Inputs!$B$26)/Inputs!$B$26)^Inputs!$B$12/FACT(Inputs!$B$12)*Inputs!$B$12/(Inputs!$B$12-(MIN(AF40,0.95*Inputs!$B$12*Inputs!$B$26)/Inputs!$B$26)))/(SUMPRODUCT(--({0,1,2,3,4,5,6,7,8,9}<Inputs!$B$12),(MIN(AF40,0.95*Inputs!$B$12*Inputs!$B$26)/Inputs!$B$26)^{0,1,2,3,4,5,6,7,8,9}/FACT({0,1,2,3,4,5,6,7,8,9}))+((MIN(AF40,0.95*Inputs!$B$12*Inputs!$B$26)/Inputs!$B$26)^Inputs!$B$12/FACT(Inputs!$B$12)*Inputs!$B$12/(Inputs!$B$12-(MIN(AF40,0.95*Inputs!$B$12*Inputs!$B$26)/Inputs!$B$26)))),0) -> 0.59423502 | AJ40: =IF(AF40>0,AI40/(Inputs!$B$12*Inputs!$B$26-MIN(AF40,0.95*Inputs!$B$12*Inputs!$B$26)),0) -> 0.1037151 | AK40: =MAX(0,AK39+(AF40-Inputs!$B$12*Inputs!$B$26)*10) -> 0 | AL40: =(AK39+AK40)/2/(Inputs!$B$12*Inputs!$B$26)+AJ40 -> 0.1037151 | AM40: =Inputs!$B$86+AL40+1/Inputs!$B$26+Inputs!$B$87+Inputs!$B$88+Inputs!$B$89 -> 28.728715 | AN40: =AF40*AM40 -> 409.97331
A41: 13:20 | B41: ='Arrival Curve'!$L$30 -> 0.11995495 | C41: ='Arrival Curve'!$K$30 -> 355.06664 | D41: =C41/10 -> 35.506664 | E41: =$D41*Inputs!$B$35 -> 28.298812 | F41: =E41/Inputs!$B$84 -> 0.94329372 | G41: =E41/(Inputs!$B$11*Inputs!$B$26) -> 1.4149406 | H41: =IF(E41>0,((MIN(E41,0.95*Inputs!$B$11*Inputs!$B$26)/Inputs!$B$26)^Inputs!$B$11/FACT(Inputs!$B$11)*Inputs!$B$11/(Inputs!$B$11-(MIN(E41,0.95*Inputs!$B$11*Inputs!$B$26)/Inputs!$B$26)))/(SUMPRODUCT(--({0,1,2,3,4,5,6,7,8,9}<Inputs!$B$11),(MIN(E41,0.95*Inputs!$B$11*Inputs!$B$26)/Inputs!$B$26)^{0,1,2,3,4,5,6,7,8,9}/FACT({0,1,2,3,4,5,6,7,8,9}))+((MIN(E41,0.95*Inputs!$B$11*Inputs!$B$26)/Inputs!$B$26)^Inputs!$B$11/FACT(Inputs!$B$11)*Inputs!$B$11/(Inputs!$B$11-(MIN(E41,0.95*Inputs!$B$11*Inputs!$B$26)/Inputs!$B$26)))),0) -> 0.92564103 | I41: =IF(E41>0,H41/(Inputs!$B$11*Inputs!$B$26-MIN(E41,0.95*Inputs!$B$11*Inputs!$B$26)),0) -> 0.92564103 | J41: =MAX(0,J40+(E41-Inputs!$B$11*Inputs!$B$26)*10) -> 218.18905 | K41: =(J40+J41)/2/(Inputs!$B$11*Inputs!$B$26)+I41 -> 9.7603904 | L41: =Inputs!$B$86+K41+1/Inputs!$B$26+Inputs!$B$87+Inputs!$B$88+Inputs!$B$89 -> 38.38539 | M41: =E41*L41 -> 1086.2609 | N41: =$D41*(1-Inputs!$B$35) -> 7.2078529 | O41: =N41/Inputs!$B$85 -> 0.24026176 | P41: =N41/(Inputs!$B$12*Inputs!$B$26) -> 0.36039264 | Q41: =IF(N41>0,((MIN(N41,0.95*Inputs!$B$12*Inputs!$B$26)/Inputs!$B$26)^Inputs!$B$12/FACT(Inputs!$B$12)*Inputs!$B$12/(Inputs!$B$12-(MIN(N41,0.95*Inputs!$B$12*Inputs!$B$26)/Inputs!$B$26)))/(SUMPRODUCT(--({0,1,2,3,4,5,6,7,8,9}<Inputs!$B$12),(MIN(N41,0.95*Inputs!$B$12*Inputs!$B$26)/Inputs!$B$26)^{0,1,2,3,4,5,6,7,8,9}/FACT({0,1,2,3,4,5,6,7,8,9}))+((MIN(N41,0.95*Inputs!$B$12*Inputs!$B$26)/Inputs!$B$26)^Inputs!$B$12/FACT(Inputs!$B$12)*Inputs!$B$12/(Inputs!$B$12-(MIN(N41,0.95*Inputs!$B$12*Inputs!$B$26)/Inputs!$B$26)))),0) -> 0.19094907 | R41: =IF(N41>0,Q41/(Inputs!$B$12*Inputs!$B$26-MIN(N41,0.95*Inputs!$B$12*Inputs!$B$26)),0) -> 0.014927054 | S41: =MAX(0,S40+(N41-Inputs!$B$12*Inputs!$B$26)*10) -> 0 | T41: =(S40+S41)/2/(Inputs!$B$12*Inputs!$B$26)+R41 -> 0.014927054 | U41: =Inputs!$B$86+T41+1/Inputs!$B$26+Inputs!$B$87+Inputs!$B$88+Inputs!$B$89 -> 28.639927 | V41: =N41*U41 -> 206.43238 | W41: =$D41*$E$26 -> 21.971524 | X41: =W41/Inputs!$B$84 -> 0.73238413 | Y41: =W41/(Inputs!$B$11*Inputs!$B$26) -> 1.0985762 | Z41: =IF(W41>0,((MIN(W41,0.95*Inputs!$B$11*Inputs!$B$26)/Inputs!$B$26)^Inputs!$B$11/FACT(Inputs!$B$11)*Inputs!$B$11/(Inputs!$B$11-(MIN(W41,0.95*Inputs!$B$11*Inputs!$B$26)/Inputs!$B$26)))/(SUMPRODUCT(--({0,1,2,3,4,5,6,7,8,9}<Inputs!$B$11),(MIN(W41,0.95*Inputs!$B$11*Inputs!$B$26)/Inputs!$B$26)^{0,1,2,3,4,5,6,7,8,9}/FACT({0,1,2,3,4,5,6,7,8,9}))+((MIN(W41,0.95*Inputs!$B$11*Inputs!$B$26)/Inputs!$B$26)^Inputs!$B$11/FACT(Inputs!$B$11)*Inputs!$B$11/(Inputs!$B$11-(MIN(W41,0.95*Inputs!$B$11*Inputs!$B$26)/Inputs!$B$26)))),0) -> 0.92564103 | AA41: =IF(W41>0,Z41/(Inputs!$B$11*Inputs!$B$26-MIN(W41,0.95*Inputs!$B$11*Inputs!$B$26)),0) -> 0.92564103 | AB41: =MAX(0,AB40+(W41-Inputs!$B$11*Inputs!$B$26)*10) -> 51.367633 | AC41: =(AB40+AB41)/2/(Inputs!$B$11*Inputs!$B$26)+AA41 -> 3.0011417 | AD41: =Inputs!$B$86+AC41+1/Inputs!$B$26+Inputs!$B$87+Inputs!$B$88+Inputs!$B$89 -> 31.626142 | AE41: =W41*AD41 -> 694.87453 | AF41: =$D41*(1-$E$26) -> 13.53514 | AG41: =AF41/Inputs!$B$85 -> 0.45117135 | AH41: =AF41/(Inputs!$B$12*Inputs!$B$26) -> 0.67675702 | AI41: =IF(AF41>0,((MIN(AF41,0.95*Inputs!$B$12*Inputs!$B$26)/Inputs!$B$26)^Inputs!$B$12/FACT(Inputs!$B$12)*Inputs!$B$12/(Inputs!$B$12-(MIN(AF41,0.95*Inputs!$B$12*Inputs!$B$26)/Inputs!$B$26)))/(SUMPRODUCT(--({0,1,2,3,4,5,6,7,8,9}<Inputs!$B$12),(MIN(AF41,0.95*Inputs!$B$12*Inputs!$B$26)/Inputs!$B$26)^{0,1,2,3,4,5,6,7,8,9}/FACT({0,1,2,3,4,5,6,7,8,9}))+((MIN(AF41,0.95*Inputs!$B$12*Inputs!$B$26)/Inputs!$B$26)^Inputs!$B$12/FACT(Inputs!$B$12)*Inputs!$B$12/(Inputs!$B$12-(MIN(AF41,0.95*Inputs!$B$12*Inputs!$B$26)/Inputs!$B$26)))),0) -> 0.54629271 | AJ41: =IF(AF41>0,AI41/(Inputs!$B$12*Inputs!$B$26-MIN(AF41,0.95*Inputs!$B$12*Inputs!$B$26)),0) -> 0.084501868 | AK41: =MAX(0,AK40+(AF41-Inputs!$B$12*Inputs!$B$26)*10) -> 0 | AL41: =(AK40+AK41)/2/(Inputs!$B$12*Inputs!$B$26)+AJ41 -> 0.084501868 | AM41: =Inputs!$B$86+AL41+1/Inputs!$B$26+Inputs!$B$87+Inputs!$B$88+Inputs!$B$89 -> 28.709502 | AN41: =AF41*AM41 -> 388.58714
A42: 13:30 | B42: ='Arrival Curve'!$L$31 -> 0.091082671 | C42: ='Arrival Curve'!$K$31 -> 269.60471 | D42: =C42/10 -> 26.960471 | E42: =$D42*Inputs!$B$35 -> 21.487495 | F42: =E42/Inputs!$B$84 -> 0.71624984 | G42: =E42/(Inputs!$B$11*Inputs!$B$26) -> 1.0743748 | H42: =IF(E42>0,((MIN(E42,0.95*Inputs!$B$11*Inputs!$B$26)/Inputs!$B$26)^Inputs!$B$11/FACT(Inputs!$B$11)*Inputs!$B$11/(Inputs!$B$11-(MIN(E42,0.95*Inputs!$B$11*Inputs!$B$26)/Inputs!$B$26)))/(SUMPRODUCT(--({0,1,2,3,4,5,6,7,8,9}<Inputs!$B$11),(MIN(E42,0.95*Inputs!$B$11*Inputs!$B$26)/Inputs!$B$26)^{0,1,2,3,4,5,6,7,8,9}/FACT({0,1,2,3,4,5,6,7,8,9}))+((MIN(E42,0.95*Inputs!$B$11*Inputs!$B$26)/Inputs!$B$26)^Inputs!$B$11/FACT(Inputs!$B$11)*Inputs!$B$11/(Inputs!$B$11-(MIN(E42,0.95*Inputs!$B$11*Inputs!$B$26)/Inputs!$B$26)))),0) -> 0.92564103 | I42: =IF(E42>0,H42/(Inputs!$B$11*Inputs!$B$26-MIN(E42,0.95*Inputs!$B$11*Inputs!$B$26)),0) -> 0.92564103 | J42: =MAX(0,J41+(E42-Inputs!$B$11*Inputs!$B$26)*10) -> 233.064 | K42: =(J41+J42)/2/(Inputs!$B$11*Inputs!$B$26)+I42 -> 12.206967 | L42: =Inputs!$B$86+K42+1/Inputs!$B$26+Inputs!$B$87+Inputs!$B$88+Inputs!$B$89 -> 40.831967 | M42: =E42*L42 -> 877.3767 | N42: =$D42*(1-Inputs!$B$35) -> 5.4729756 | O42: =N42/Inputs!$B$85 -> 0.18243252 | P42: =N42/(Inputs!$B$12*Inputs!$B$26) -> 0.27364878 | Q42: =IF(N42>0,((MIN(N42,0.95*Inputs!$B$12*Inputs!$B$26)/Inputs!$B$26)^Inputs!$B$12/FACT(Inputs!$B$12)*Inputs!$B$12/(Inputs!$B$12-(MIN(N42,0.95*Inputs!$B$12*Inputs!$B$26)/Inputs!$B$26)))/(SUMPRODUCT(--({0,1,2,3,4,5,6,7,8,9}<Inputs!$B$12),(MIN(N42,0.95*Inputs!$B$12*Inputs!$B$26)/Inputs!$B$26)^{0,1,2,3,4,5,6,7,8,9}/FACT({0,1,2,3,4,5,6,7,8,9}))+((MIN(N42,0.95*Inputs!$B$12*Inputs!$B$26)/Inputs!$B$26)^Inputs!$B$12/FACT(Inputs!$B$12)*Inputs!$B$12/(Inputs!$B$12-(MIN(N42,0.95*Inputs!$B$12*Inputs!$B$26)/Inputs!$B$26)))),0) -> 0.11758917 | R42: =IF(N42>0,Q42/(Inputs!$B$12*Inputs!$B$26-MIN(N42,0.95*Inputs!$B$12*Inputs!$B$26)),0) -> 0.008094512 | S42: =MAX(0,S41+(N42-Inputs!$B$12*Inputs!$B$26)*10) -> 0 | T42: =(S41+S42)/2/(Inputs!$B$12*Inputs!$B$26)+R42 -> 0.008094512 | U42: =Inputs!$B$86+T42+1/Inputs!$B$26+Inputs!$B$87+Inputs!$B$88+Inputs!$B$89 -> 28.633095 | V42: =N42*U42 -> 156.70823 | W42: =$D42*$E$26 -> 16.683139 | X42: =W42/Inputs!$B$84 -> 0.55610464 | Y42: =W42/(Inputs!$B$11*Inputs!$B$26) -> 0.83415697 | Z42: =IF(W42>0,((MIN(W42,0.95*Inputs!$B$11*Inputs!$B$26)/Inputs!$B$26)^Inputs!$B$11/FACT(Inputs!$B$11)*Inputs!$B$11/(Inputs!$B$11-(MIN(W42,0.95*Inputs!$B$11*Inputs!$B$26)/Inputs!$B$26)))/(SUMPRODUCT(--({0,1,2,3,4,5,6,7,8,9}<Inputs!$B$11),(MIN(W42,0.95*Inputs!$B$11*Inputs!$B$26)/Inputs!$B$26)^{0,1,2,3,4,5,6,7,8,9}/FACT({0,1,2,3,4,5,6,7,8,9}))+((MIN(W42,0.95*Inputs!$B$11*Inputs!$B$26)/Inputs!$B$26)^Inputs!$B$11/FACT(Inputs!$B$11)*Inputs!$B$11/(Inputs!$B$11-(MIN(W42,0.95*Inputs!$B$11*Inputs!$B$26)/Inputs!$B$26)))),0) -> 0.75873315 | AA42: =IF(W42>0,Z42/(Inputs!$B$11*Inputs!$B$26-MIN(W42,0.95*Inputs!$B$11*Inputs!$B$26)),0) -> 0.22875038 | AB42: =MAX(0,AB41+(W42-Inputs!$B$11*Inputs!$B$26)*10) -> 18.199026 | AC42: =(AB41+AB42)/2/(Inputs!$B$11*Inputs!$B$26)+AA42 -> 1.9679169 | AD42: =Inputs!$B$86+AC42+1/Inputs!$B$26+Inputs!$B$87+Inputs!$B$88+Inputs!$B$89 -> 30.592917 | AE42: =W42*AD42 -> 510.38589 | AF42: =$D42*(1-$E$26) -> 10.277331 | AG42: =AF42/Inputs!$B$85 -> 0.34257772 | AH42: =AF42/(Inputs!$B$12*Inputs!$B$26) -> 0.51386657 | AI42: =IF(AF42>0,((MIN(AF42,0.95*Inputs!$B$12*Inputs!$B$26)/Inputs!$B$26)^Inputs!$B$12/FACT(Inputs!$B$12)*Inputs!$B$12/(Inputs!$B$12-(MIN(AF42,0.95*Inputs!$B$12*Inputs!$B$26)/Inputs!$B$26)))/(SUMPRODUCT(--({0,1,2,3,4,5,6,7,8,9}<Inputs!$B$12),(MIN(AF42,0.95*Inputs!$B$12*Inputs!$B$26)/Inputs!$B$26)^{0,1,2,3,4,5,6,7,8,9}/FACT({0,1,2,3,4,5,6,7,8,9}))+((MIN(AF42,0.95*Inputs!$B$12*Inputs!$B$26)/Inputs!$B$26)^Inputs!$B$12/FACT(Inputs!$B$12)*Inputs!$B$12/(Inputs!$B$12-(MIN(AF42,0.95*Inputs!$B$12*Inputs!$B$26)/Inputs!$B$26)))),0) -> 0.34885354 | AJ42: =IF(AF42>0,AI42/(Inputs!$B$12*Inputs!$B$26-MIN(AF42,0.95*Inputs!$B$12*Inputs!$B$26)),0) -> 0.035880431 | AK42: =MAX(0,AK41+(AF42-Inputs!$B$12*Inputs!$B$26)*10) -> 0 | AL42: =(AK41+AK42)/2/(Inputs!$B$12*Inputs!$B$26)+AJ42 -> 0.035880431 | AM42: =Inputs!$B$86+AL42+1/Inputs!$B$26+Inputs!$B$87+Inputs!$B$88+Inputs!$B$89 -> 28.66088 | AN42: =AF42*AM42 -> 294.55737
A43: 13:40 | B43: ='Arrival Curve'!$L$32 -> 0.059226514 | C43: ='Arrival Curve'!$K$32 -> 175.31048 | D43: =C43/10 -> 17.531048 | E43: =$D43*Inputs!$B$35 -> 13.972245 | F43: =E43/Inputs!$B$84 -> 0.46574151 | G43: =E43/(Inputs!$B$11*Inputs!$B$26) -> 0.69861226 | H43: =IF(E43>0,((MIN(E43,0.95*Inputs!$B$11*Inputs!$B$26)/Inputs!$B$26)^Inputs!$B$11/FACT(Inputs!$B$11)*Inputs!$B$11/(Inputs!$B$11-(MIN(E43,0.95*Inputs!$B$11*Inputs!$B$26)/Inputs!$B$26)))/(SUMPRODUCT(--({0,1,2,3,4,5,6,7,8,9}<Inputs!$B$11),(MIN(E43,0.95*Inputs!$B$11*Inputs!$B$26)/Inputs!$B$26)^{0,1,2,3,4,5,6,7,8,9}/FACT({0,1,2,3,4,5,6,7,8,9}))+((MIN(E43,0.95*Inputs!$B$11*Inputs!$B$26)/Inputs!$B$26)^Inputs!$B$11/FACT(Inputs!$B$11)*Inputs!$B$11/(Inputs!$B$11-(MIN(E43,0.95*Inputs!$B$11*Inputs!$B$26)/Inputs!$B$26)))),0) -> 0.57465627 | I43: =IF(E43>0,H43/(Inputs!$B$11*Inputs!$B$26-MIN(E43,0.95*Inputs!$B$11*Inputs!$B$26)),0) -> 0.095335046 | J43: =MAX(0,J42+(E43-Inputs!$B$11*Inputs!$B$26)*10) -> 172.78645 | K43: =(J42+J43)/2/(Inputs!$B$11*Inputs!$B$26)+I43 -> 10.241596 | L43: =Inputs!$B$86+K43+1/Inputs!$B$26+Inputs!$B$87+Inputs!$B$88+Inputs!$B$89 -> 38.866596 | M43: =E43*L43 -> 543.05362 | N43: =$D43*(1-Inputs!$B$35) -> 3.5588028 | O43: =N43/Inputs!$B$85 -> 0.11862676 | P43: =N43/(Inputs!$B$12*Inputs!$B$26) -> 0.17794014 | Q43: =IF(N43>0,((MIN(N43,0.95*Inputs!$B$12*Inputs!$B$26)/Inputs!$B$26)^Inputs!$B$12/FACT(Inputs!$B$12)*Inputs!$B$12/(Inputs!$B$12-(MIN(N43,0.95*Inputs!$B$12*Inputs!$B$26)/Inputs!$B$26)))/(SUMPRODUCT(--({0,1,2,3,4,5,6,7,8,9}<Inputs!$B$12),(MIN(N43,0.95*Inputs!$B$12*Inputs!$B$26)/Inputs!$B$26)^{0,1,2,3,4,5,6,7,8,9}/FACT({0,1,2,3,4,5,6,7,8,9}))+((MIN(N43,0.95*Inputs!$B$12*Inputs!$B$26)/Inputs!$B$26)^Inputs!$B$12/FACT(Inputs!$B$12)*Inputs!$B$12/(Inputs!$B$12-(MIN(N43,0.95*Inputs!$B$12*Inputs!$B$26)/Inputs!$B$26)))),0) -> 0.053759426 | R43: =IF(N43>0,Q43/(Inputs!$B$12*Inputs!$B$26-MIN(N43,0.95*Inputs!$B$12*Inputs!$B$26)),0) -> 0.0032697999 | S43: =MAX(0,S42+(N43-Inputs!$B$12*Inputs!$B$26)*10) -> 0 | T43: =(S42+S43)/2/(Inputs!$B$12*Inputs!$B$26)+R43 -> 0.0032697999 | U43: =Inputs!$B$86+T43+1/Inputs!$B$26+Inputs!$B$87+Inputs!$B$88+Inputs!$B$89 -> 28.62827 | V43: =N43*U43 -> 101.88237 | W43: =$D43*$E$26 -> 10.848213 | X43: =W43/Inputs!$B$84 -> 0.36160708 | Y43: =W43/(Inputs!$B$11*Inputs!$B$26) -> 0.54241063 | Z43: =IF(W43>0,((MIN(W43,0.95*Inputs!$B$11*Inputs!$B$26)/Inputs!$B$26)^Inputs!$B$11/FACT(Inputs!$B$11)*Inputs!$B$11/(Inputs!$B$11-(MIN(W43,0.95*Inputs!$B$11*Inputs!$B$26)/Inputs!$B$26)))/(SUMPRODUCT(--({0,1,2,3,4,5,6,7,8,9}<Inputs!$B$11),(MIN(W43,0.95*Inputs!$B$11*Inputs!$B$26)/Inputs!$B$26)^{0,1,2,3,4,5,6,7,8,9}/FACT({0,1,2,3,4,5,6,7,8,9}))+((MIN(W43,0.95*Inputs!$B$11*Inputs!$B$26)/Inputs!$B$26)^Inputs!$B$11/FACT(Inputs!$B$11)*Inputs!$B$11/(Inputs!$B$11-(MIN(W43,0.95*Inputs!$B$11*Inputs!$B$26)/Inputs!$B$26)))),0) -> 0.38149282 | AA43: =IF(W43>0,Z43/(Inputs!$B$11*Inputs!$B$26-MIN(W43,0.95*Inputs!$B$11*Inputs!$B$26)),0) -> 0.041685061 | AB43: =MAX(0,AB42+(W43-Inputs!$B$11*Inputs!$B$26)*10) -> 0 | AC43: =(AB42+AB43)/2/(Inputs!$B$11*Inputs!$B$26)+AA43 -> 0.49666071 | AD43: =Inputs!$B$86+AC43+1/Inputs!$B$26+Inputs!$B$87+Inputs!$B$88+Inputs!$B$89 -> 29.121661 | AE43: =W43*AD43 -> 315.91796 | AF43: =$D43*(1-$E$26) -> 6.6828355 | AG43: =AF43/Inputs!$B$85 -> 0.22276118 | AH43: =AF43/(Inputs!$B$12*Inputs!$B$26) -> 0.33414178 | AI43: =IF(AF43>0,((MIN(AF43,0.95*Inputs!$B$12*Inputs!$B$26)/Inputs!$B$26)^Inputs!$B$12/FACT(Inputs!$B$12)*Inputs!$B$12/(Inputs!$B$12-(MIN(AF43,0.95*Inputs!$B$12*Inputs!$B$26)/Inputs!$B$26)))/(SUMPRODUCT(--({0,1,2,3,4,5,6,7,8,9}<Inputs!$B$12),(MIN(AF43,0.95*Inputs!$B$12*Inputs!$B$26)/Inputs!$B$26)^{0,1,2,3,4,5,6,7,8,9}/FACT({0,1,2,3,4,5,6,7,8,9}))+((MIN(AF43,0.95*Inputs!$B$12*Inputs!$B$26)/Inputs!$B$26)^Inputs!$B$12/FACT(Inputs!$B$12)*Inputs!$B$12/(Inputs!$B$12-(MIN(AF43,0.95*Inputs!$B$12*Inputs!$B$26)/Inputs!$B$26)))),0) -> 0.1673746 | AJ43: =IF(AF43>0,AI43/(Inputs!$B$12*Inputs!$B$26-MIN(AF43,0.95*Inputs!$B$12*Inputs!$B$26)),0) -> 0.012568337 | AK43: =MAX(0,AK42+(AF43-Inputs!$B$12*Inputs!$B$26)*10) -> 0 | AL43: =(AK42+AK43)/2/(Inputs!$B$12*Inputs!$B$26)+AJ43 -> 0.012568337 | AM43: =Inputs!$B$86+AL43+1/Inputs!$B$26+Inputs!$B$87+Inputs!$B$88+Inputs!$B$89 -> 28.637568 | AN43: =AF43*AM43 -> 191.38016
A44: 13:50 | B44: ='Arrival Curve'!$L$33 -> 0.030545811 | C44: ='Arrival Curve'!$K$33 -> 90.415601 | D44: =C44/10 -> 9.0415601 | E44: =$D44*Inputs!$B$35 -> 7.2061234 | F44: =E44/Inputs!$B$84 -> 0.24020411 | G44: =E44/(Inputs!$B$11*Inputs!$B$26) -> 0.36030617 | H44: =IF(E44>0,((MIN(E44,0.95*Inputs!$B$11*Inputs!$B$26)/Inputs!$B$26)^Inputs!$B$11/FACT(Inputs!$B$11)*Inputs!$B$11/(Inputs!$B$11-(MIN(E44,0.95*Inputs!$B$11*Inputs!$B$26)/Inputs!$B$26)))/(SUMPRODUCT(--({0,1,2,3,4,5,6,7,8,9}<Inputs!$B$11),(MIN(E44,0.95*Inputs!$B$11*Inputs!$B$26)/Inputs!$B$26)^{0,1,2,3,4,5,6,7,8,9}/FACT({0,1,2,3,4,5,6,7,8,9}))+((MIN(E44,0.95*Inputs!$B$11*Inputs!$B$26)/Inputs!$B$26)^Inputs!$B$11/FACT(Inputs!$B$11)*Inputs!$B$11/(Inputs!$B$11-(MIN(E44,0.95*Inputs!$B$11*Inputs!$B$26)/Inputs!$B$26)))),0) -> 0.19086958 | I44: =IF(E44>0,H44/(Inputs!$B$11*Inputs!$B$26-MIN(E44,0.95*Inputs!$B$11*Inputs!$B$26)),0) -> 0.014918823 | J44: =MAX(0,J43+(E44-Inputs!$B$11*Inputs!$B$26)*10) -> 44.847684 | K44: =(J43+J44)/2/(Inputs!$B$11*Inputs!$B$26)+I44 -> 5.4557722 | L44: =Inputs!$B$86+K44+1/Inputs!$B$26+Inputs!$B$87+Inputs!$B$88+Inputs!$B$89 -> 34.080772 | M44: =E44*L44 -> 245.59025 | N44: =$D44*(1-Inputs!$B$35) -> 1.8354367 | O44: =N44/Inputs!$B$85 -> 0.061181223 | P44: =N44/(Inputs!$B$12*Inputs!$B$26) -> 0.091771835 | Q44: =IF(N44>0,((MIN(N44,0.95*Inputs!$B$12*Inputs!$B$26)/Inputs!$B$26)^Inputs!$B$12/FACT(Inputs!$B$12)*Inputs!$B$12/(Inputs!$B$12-(MIN(N44,0.95*Inputs!$B$12*Inputs!$B$26)/Inputs!$B$26)))/(SUMPRODUCT(--({0,1,2,3,4,5,6,7,8,9}<Inputs!$B$12),(MIN(N44,0.95*Inputs!$B$12*Inputs!$B$26)/Inputs!$B$26)^{0,1,2,3,4,5,6,7,8,9}/FACT({0,1,2,3,4,5,6,7,8,9}))+((MIN(N44,0.95*Inputs!$B$12*Inputs!$B$26)/Inputs!$B$26)^Inputs!$B$12/FACT(Inputs!$B$12)*Inputs!$B$12/(Inputs!$B$12-(MIN(N44,0.95*Inputs!$B$12*Inputs!$B$26)/Inputs!$B$26)))),0) -> 0.01542826 | R44: =IF(N44>0,Q44/(Inputs!$B$12*Inputs!$B$26-MIN(N44,0.95*Inputs!$B$12*Inputs!$B$26)),0) -> 0.00084936034 | S44: =MAX(0,S43+(N44-Inputs!$B$12*Inputs!$B$26)*10) -> 0 | T44: =(S43+S44)/2/(Inputs!$B$12*Inputs!$B$26)+R44 -> 0.00084936034 | U44: =Inputs!$B$86+T44+1/Inputs!$B$26+Inputs!$B$87+Inputs!$B$88+Inputs!$B$89 -> 28.625849 | V44: =N44*U44 -> 52.540934 | W44: =$D44*$E$26 -> 5.5949174 | X44: =W44/Inputs!$B$84 -> 0.18649725 | Y44: =W44/(Inputs!$B$11*Inputs!$B$26) -> 0.27974587 | Z44: =IF(W44>0,((MIN(W44,0.95*Inputs!$B$11*Inputs!$B$26)/Inputs!$B$26)^Inputs!$B$11/FACT(Inputs!$B$11)*Inputs!$B$11/(Inputs!$B$11-(MIN(W44,0.95*Inputs!$B$11*Inputs!$B$26)/Inputs!$B$26)))/(SUMPRODUCT(--({0,1,2,3,4,5,6,7,8,9}<Inputs!$B$11),(MIN(W44,0.95*Inputs!$B$11*Inputs!$B$26)/Inputs!$B$26)^{0,1,2,3,4,5,6,7,8,9}/FACT({0,1,2,3,4,5,6,7,8,9}))+((MIN(W44,0.95*Inputs!$B$11*Inputs!$B$26)/Inputs!$B$26)^Inputs!$B$11/FACT(Inputs!$B$11)*Inputs!$B$11/(Inputs!$B$11-(MIN(W44,0.95*Inputs!$B$11*Inputs!$B$26)/Inputs!$B$26)))),0) -> 0.12230202 | AA44: =IF(W44>0,Z44/(Inputs!$B$11*Inputs!$B$26-MIN(W44,0.95*Inputs!$B$11*Inputs!$B$26)),0) -> 0.008490199 | AB44: =MAX(0,AB43+(W44-Inputs!$B$11*Inputs!$B$26)*10) -> 0 | AC44: =(AB43+AB44)/2/(Inputs!$B$11*Inputs!$B$26)+AA44 -> 0.008490199 | AD44: =Inputs!$B$86+AC44+1/Inputs!$B$26+Inputs!$B$87+Inputs!$B$88+Inputs!$B$89 -> 28.63349 | AE44: =W44*AD44 -> 160.20201 | AF44: =$D44*(1-$E$26) -> 3.4466427 | AG44: =AF44/Inputs!$B$85 -> 0.11488809 | AH44: =AF44/(Inputs!$B$12*Inputs!$B$26) -> 0.17233214 | AI44: =IF(AF44>0,((MIN(AF44,0.95*Inputs!$B$12*Inputs!$B$26)/Inputs!$B$26)^Inputs!$B$12/FACT(Inputs!$B$12)*Inputs!$B$12/(Inputs!$B$12-(MIN(AF44,0.95*Inputs!$B$12*Inputs!$B$26)/Inputs!$B$26)))/(SUMPRODUCT(--({0,1,2,3,4,5,6,7,8,9}<Inputs!$B$12),(MIN(AF44,0.95*Inputs!$B$12*Inputs!$B$26)/Inputs!$B$26)^{0,1,2,3,4,5,6,7,8,9}/FACT({0,1,2,3,4,5,6,7,8,9}))+((MIN(AF44,0.95*Inputs!$B$12*Inputs!$B$26)/Inputs!$B$26)^Inputs!$B$12/FACT(Inputs!$B$12)*Inputs!$B$12/(Inputs!$B$12-(MIN(AF44,0.95*Inputs!$B$12*Inputs!$B$26)/Inputs!$B$26)))),0) -> 0.050665445 | AJ44: =IF(AF44>0,AI44/(Inputs!$B$12*Inputs!$B$26-MIN(AF44,0.95*Inputs!$B$12*Inputs!$B$26)),0) -> 0.0030607353 | AK44: =MAX(0,AK43+(AF44-Inputs!$B$12*Inputs!$B$26)*10) -> 0 | AL44: =(AK43+AK44)/2/(Inputs!$B$12*Inputs!$B$26)+AJ44 -> 0.0030607353 | AM44: =Inputs!$B$86+AL44+1/Inputs!$B$26+Inputs!$B$87+Inputs!$B$88+Inputs!$B$89 -> 28.628061 | AN44: =AF44*AM44 -> 98.670697
A45: 14:00 | B45: ='Arrival Curve'!$L$34 -> 0 | C45: ='Arrival Curve'!$K$34 -> 0 | D45: =C45/10 -> 0 | E45: =$D45*Inputs!$B$35 -> 0 | F45: =E45/Inputs!$B$84 -> 0 | G45: =E45/(Inputs!$B$11*Inputs!$B$26) -> 0 | H45: =IF(E45>0,((MIN(E45,0.95*Inputs!$B$11*Inputs!$B$26)/Inputs!$B$26)^Inputs!$B$11/FACT(Inputs!$B$11)*Inputs!$B$11/(Inputs!$B$11-(MIN(E45,0.95*Inputs!$B$11*Inputs!$B$26)/Inputs!$B$26)))/(SUMPRODUCT(--({0,1,2,3,4,5,6,7,8,9}<Inputs!$B$11),(MIN(E45,0.95*Inputs!$B$11*Inputs!$B$26)/Inputs!$B$26)^{0,1,2,3,4,5,6,7,8,9}/FACT({0,1,2,3,4,5,6,7,8,9}))+((MIN(E45,0.95*Inputs!$B$11*Inputs!$B$26)/Inputs!$B$26)^Inputs!$B$11/FACT(Inputs!$B$11)*Inputs!$B$11/(Inputs!$B$11-(MIN(E45,0.95*Inputs!$B$11*Inputs!$B$26)/Inputs!$B$26)))),0) -> 0 | I45: =IF(E45>0,H45/(Inputs!$B$11*Inputs!$B$26-MIN(E45,0.95*Inputs!$B$11*Inputs!$B$26)),0) -> 0 | J45: =MAX(0,J44+(E45-Inputs!$B$11*Inputs!$B$26)*10) -> 0 | K45: =(J44+J45)/2/(Inputs!$B$11*Inputs!$B$26)+I45 -> 1.1211921 | L45: =Inputs!$B$86+K45+1/Inputs!$B$26+Inputs!$B$87+Inputs!$B$88+Inputs!$B$89 -> 29.746192 | M45: =E45*L45 -> 0 | N45: =$D45*(1-Inputs!$B$35) -> 0 | O45: =N45/Inputs!$B$85 -> 0 | P45: =N45/(Inputs!$B$12*Inputs!$B$26) -> 0 | Q45: =IF(N45>0,((MIN(N45,0.95*Inputs!$B$12*Inputs!$B$26)/Inputs!$B$26)^Inputs!$B$12/FACT(Inputs!$B$12)*Inputs!$B$12/(Inputs!$B$12-(MIN(N45,0.95*Inputs!$B$12*Inputs!$B$26)/Inputs!$B$26)))/(SUMPRODUCT(--({0,1,2,3,4,5,6,7,8,9}<Inputs!$B$12),(MIN(N45,0.95*Inputs!$B$12*Inputs!$B$26)/Inputs!$B$26)^{0,1,2,3,4,5,6,7,8,9}/FACT({0,1,2,3,4,5,6,7,8,9}))+((MIN(N45,0.95*Inputs!$B$12*Inputs!$B$26)/Inputs!$B$26)^Inputs!$B$12/FACT(Inputs!$B$12)*Inputs!$B$12/(Inputs!$B$12-(MIN(N45,0.95*Inputs!$B$12*Inputs!$B$26)/Inputs!$B$26)))),0) -> 0 | R45: =IF(N45>0,Q45/(Inputs!$B$12*Inputs!$B$26-MIN(N45,0.95*Inputs!$B$12*Inputs!$B$26)),0) -> 0 | S45: =MAX(0,S44+(N45-Inputs!$B$12*Inputs!$B$26)*10) -> 0 | T45: =(S44+S45)/2/(Inputs!$B$12*Inputs!$B$26)+R45 -> 0 | U45: =Inputs!$B$86+T45+1/Inputs!$B$26+Inputs!$B$87+Inputs!$B$88+Inputs!$B$89 -> 28.625 | V45: =N45*U45 -> 0 | W45: =$D45*$E$26 -> 0 | X45: =W45/Inputs!$B$84 -> 0 | Y45: =W45/(Inputs!$B$11*Inputs!$B$26) -> 0 | Z45: =IF(W45>0,((MIN(W45,0.95*Inputs!$B$11*Inputs!$B$26)/Inputs!$B$26)^Inputs!$B$11/FACT(Inputs!$B$11)*Inputs!$B$11/(Inputs!$B$11-(MIN(W45,0.95*Inputs!$B$11*Inputs!$B$26)/Inputs!$B$26)))/(SUMPRODUCT(--({0,1,2,3,4,5,6,7,8,9}<Inputs!$B$11),(MIN(W45,0.95*Inputs!$B$11*Inputs!$B$26)/Inputs!$B$26)^{0,1,2,3,4,5,6,7,8,9}/FACT({0,1,2,3,4,5,6,7,8,9}))+((MIN(W45,0.95*Inputs!$B$11*Inputs!$B$26)/Inputs!$B$26)^Inputs!$B$11/FACT(Inputs!$B$11)*Inputs!$B$11/(Inputs!$B$11-(MIN(W45,0.95*Inputs!$B$11*Inputs!$B$26)/Inputs!$B$26)))),0) -> 0 | AA45: =IF(W45>0,Z45/(Inputs!$B$11*Inputs!$B$26-MIN(W45,0.95*Inputs!$B$11*Inputs!$B$26)),0) -> 0 | AB45: =MAX(0,AB44+(W45-Inputs!$B$11*Inputs!$B$26)*10) -> 0 | AC45: =(AB44+AB45)/2/(Inputs!$B$11*Inputs!$B$26)+AA45 -> 0 | AD45: =Inputs!$B$86+AC45+1/Inputs!$B$26+Inputs!$B$87+Inputs!$B$88+Inputs!$B$89 -> 28.625 | AE45: =W45*AD45 -> 0 | AF45: =$D45*(1-$E$26) -> 0 | AG45: =AF45/Inputs!$B$85 -> 0 | AH45: =AF45/(Inputs!$B$12*Inputs!$B$26) -> 0 | AI45: =IF(AF45>0,((MIN(AF45,0.95*Inputs!$B$12*Inputs!$B$26)/Inputs!$B$26)^Inputs!$B$12/FACT(Inputs!$B$12)*Inputs!$B$12/(Inputs!$B$12-(MIN(AF45,0.95*Inputs!$B$12*Inputs!$B$26)/Inputs!$B$26)))/(SUMPRODUCT(--({0,1,2,3,4,5,6,7,8,9}<Inputs!$B$12),(MIN(AF45,0.95*Inputs!$B$12*Inputs!$B$26)/Inputs!$B$26)^{0,1,2,3,4,5,6,7,8,9}/FACT({0,1,2,3,4,5,6,7,8,9}))+((MIN(AF45,0.95*Inputs!$B$12*Inputs!$B$26)/Inputs!$B$26)^Inputs!$B$12/FACT(Inputs!$B$12)*Inputs!$B$12/(Inputs!$B$12-(MIN(AF45,0.95*Inputs!$B$12*Inputs!$B$26)/Inputs!$B$26)))),0) -> 0 | AJ45: =IF(AF45>0,AI45/(Inputs!$B$12*Inputs!$B$26-MIN(AF45,0.95*Inputs!$B$12*Inputs!$B$26)),0) -> 0 | AK45: =MAX(0,AK44+(AF45-Inputs!$B$12*Inputs!$B$26)*10) -> 0 | AL45: =(AK44+AK45)/2/(Inputs!$B$12*Inputs!$B$26)+AJ45 -> 0 | AM45: =Inputs!$B$86+AL45+1/Inputs!$B$26+Inputs!$B$87+Inputs!$B$88+Inputs!$B$89 -> 28.625 | AN45: =AF45*AM45 -> 0
A46: 14:10 | B46: ='Arrival Curve'!$L$35 -> 0 | C46: ='Arrival Curve'!$K$35 -> 0 | D46: =C46/10 -> 0 | E46: =$D46*Inputs!$B$35 -> 0 | F46: =E46/Inputs!$B$84 -> 0 | G46: =E46/(Inputs!$B$11*Inputs!$B$26) -> 0 | H46: =IF(E46>0,((MIN(E46,0.95*Inputs!$B$11*Inputs!$B$26)/Inputs!$B$26)^Inputs!$B$11/FACT(Inputs!$B$11)*Inputs!$B$11/(Inputs!$B$11-(MIN(E46,0.95*Inputs!$B$11*Inputs!$B$26)/Inputs!$B$26)))/(SUMPRODUCT(--({0,1,2,3,4,5,6,7,8,9}<Inputs!$B$11),(MIN(E46,0.95*Inputs!$B$11*Inputs!$B$26)/Inputs!$B$26)^{0,1,2,3,4,5,6,7,8,9}/FACT({0,1,2,3,4,5,6,7,8,9}))+((MIN(E46,0.95*Inputs!$B$11*Inputs!$B$26)/Inputs!$B$26)^Inputs!$B$11/FACT(Inputs!$B$11)*Inputs!$B$11/(Inputs!$B$11-(MIN(E46,0.95*Inputs!$B$11*Inputs!$B$26)/Inputs!$B$26)))),0) -> 0 | I46: =IF(E46>0,H46/(Inputs!$B$11*Inputs!$B$26-MIN(E46,0.95*Inputs!$B$11*Inputs!$B$26)),0) -> 0 | J46: =MAX(0,J45+(E46-Inputs!$B$11*Inputs!$B$26)*10) -> 0 | K46: =(J45+J46)/2/(Inputs!$B$11*Inputs!$B$26)+I46 -> 0 | L46: =Inputs!$B$86+K46+1/Inputs!$B$26+Inputs!$B$87+Inputs!$B$88+Inputs!$B$89 -> 28.625 | M46: =E46*L46 -> 0 | N46: =$D46*(1-Inputs!$B$35) -> 0 | O46: =N46/Inputs!$B$85 -> 0 | P46: =N46/(Inputs!$B$12*Inputs!$B$26) -> 0 | Q46: =IF(N46>0,((MIN(N46,0.95*Inputs!$B$12*Inputs!$B$26)/Inputs!$B$26)^Inputs!$B$12/FACT(Inputs!$B$12)*Inputs!$B$12/(Inputs!$B$12-(MIN(N46,0.95*Inputs!$B$12*Inputs!$B$26)/Inputs!$B$26)))/(SUMPRODUCT(--({0,1,2,3,4,5,6,7,8,9}<Inputs!$B$12),(MIN(N46,0.95*Inputs!$B$12*Inputs!$B$26)/Inputs!$B$26)^{0,1,2,3,4,5,6,7,8,9}/FACT({0,1,2,3,4,5,6,7,8,9}))+((MIN(N46,0.95*Inputs!$B$12*Inputs!$B$26)/Inputs!$B$26)^Inputs!$B$12/FACT(Inputs!$B$12)*Inputs!$B$12/(Inputs!$B$12-(MIN(N46,0.95*Inputs!$B$12*Inputs!$B$26)/Inputs!$B$26)))),0) -> 0 | R46: =IF(N46>0,Q46/(Inputs!$B$12*Inputs!$B$26-MIN(N46,0.95*Inputs!$B$12*Inputs!$B$26)),0) -> 0 | S46: =MAX(0,S45+(N46-Inputs!$B$12*Inputs!$B$26)*10) -> 0 | T46: =(S45+S46)/2/(Inputs!$B$12*Inputs!$B$26)+R46 -> 0 | U46: =Inputs!$B$86+T46+1/Inputs!$B$26+Inputs!$B$87+Inputs!$B$88+Inputs!$B$89 -> 28.625 | V46: =N46*U46 -> 0 | W46: =$D46*$E$26 -> 0 | X46: =W46/Inputs!$B$84 -> 0 | Y46: =W46/(Inputs!$B$11*Inputs!$B$26) -> 0 | Z46: =IF(W46>0,((MIN(W46,0.95*Inputs!$B$11*Inputs!$B$26)/Inputs!$B$26)^Inputs!$B$11/FACT(Inputs!$B$11)*Inputs!$B$11/(Inputs!$B$11-(MIN(W46,0.95*Inputs!$B$11*Inputs!$B$26)/Inputs!$B$26)))/(SUMPRODUCT(--({0,1,2,3,4,5,6,7,8,9}<Inputs!$B$11),(MIN(W46,0.95*Inputs!$B$11*Inputs!$B$26)/Inputs!$B$26)^{0,1,2,3,4,5,6,7,8,9}/FACT({0,1,2,3,4,5,6,7,8,9}))+((MIN(W46,0.95*Inputs!$B$11*Inputs!$B$26)/Inputs!$B$26)^Inputs!$B$11/FACT(Inputs!$B$11)*Inputs!$B$11/(Inputs!$B$11-(MIN(W46,0.95*Inputs!$B$11*Inputs!$B$26)/Inputs!$B$26)))),0) -> 0 | AA46: =IF(W46>0,Z46/(Inputs!$B$11*Inputs!$B$26-MIN(W46,0.95*Inputs!$B$11*Inputs!$B$26)),0) -> 0 | AB46: =MAX(0,AB45+(W46-Inputs!$B$11*Inputs!$B$26)*10) -> 0 | AC46: =(AB45+AB46)/2/(Inputs!$B$11*Inputs!$B$26)+AA46 -> 0 | AD46: =Inputs!$B$86+AC46+1/Inputs!$B$26+Inputs!$B$87+Inputs!$B$88+Inputs!$B$89 -> 28.625 | AE46: =W46*AD46 -> 0 | AF46: =$D46*(1-$E$26) -> 0 | AG46: =AF46/Inputs!$B$85 -> 0 | AH46: =AF46/(Inputs!$B$12*Inputs!$B$26) -> 0 | AI46: =IF(AF46>0,((MIN(AF46,0.95*Inputs!$B$12*Inputs!$B$26)/Inputs!$B$26)^Inputs!$B$12/FACT(Inputs!$B$12)*Inputs!$B$12/(Inputs!$B$12-(MIN(AF46,0.95*Inputs!$B$12*Inputs!$B$26)/Inputs!$B$26)))/(SUMPRODUCT(--({0,1,2,3,4,5,6,7,8,9}<Inputs!$B$12),(MIN(AF46,0.95*Inputs!$B$12*Inputs!$B$26)/Inputs!$B$26)^{0,1,2,3,4,5,6,7,8,9}/FACT({0,1,2,3,4,5,6,7,8,9}))+((MIN(AF46,0.95*Inputs!$B$12*Inputs!$B$26)/Inputs!$B$26)^Inputs!$B$12/FACT(Inputs!$B$12)*Inputs!$B$12/(Inputs!$B$12-(MIN(AF46,0.95*Inputs!$B$12*Inputs!$B$26)/Inputs!$B$26)))),0) -> 0 | AJ46: =IF(AF46>0,AI46/(Inputs!$B$12*Inputs!$B$26-MIN(AF46,0.95*Inputs!$B$12*Inputs!$B$26)),0) -> 0 | AK46: =MAX(0,AK45+(AF46-Inputs!$B$12*Inputs!$B$26)*10) -> 0 | AL46: =(AK45+AK46)/2/(Inputs!$B$12*Inputs!$B$26)+AJ46 -> 0 | AM46: =Inputs!$B$86+AL46+1/Inputs!$B$26+Inputs!$B$87+Inputs!$B$88+Inputs!$B$89 -> 28.625 | AN46: =AF46*AM46 -> 0
A47: 14:20 | B47: ='Arrival Curve'!$L$36 -> 0 | C47: ='Arrival Curve'!$K$36 -> 0 | D47: =C47/10 -> 0 | E47: =$D47*Inputs!$B$35 -> 0 | F47: =E47/Inputs!$B$84 -> 0 | G47: =E47/(Inputs!$B$11*Inputs!$B$26) -> 0 | H47: =IF(E47>0,((MIN(E47,0.95*Inputs!$B$11*Inputs!$B$26)/Inputs!$B$26)^Inputs!$B$11/FACT(Inputs!$B$11)*Inputs!$B$11/(Inputs!$B$11-(MIN(E47,0.95*Inputs!$B$11*Inputs!$B$26)/Inputs!$B$26)))/(SUMPRODUCT(--({0,1,2,3,4,5,6,7,8,9}<Inputs!$B$11),(MIN(E47,0.95*Inputs!$B$11*Inputs!$B$26)/Inputs!$B$26)^{0,1,2,3,4,5,6,7,8,9}/FACT({0,1,2,3,4,5,6,7,8,9}))+((MIN(E47,0.95*Inputs!$B$11*Inputs!$B$26)/Inputs!$B$26)^Inputs!$B$11/FACT(Inputs!$B$11)*Inputs!$B$11/(Inputs!$B$11-(MIN(E47,0.95*Inputs!$B$11*Inputs!$B$26)/Inputs!$B$26)))),0) -> 0 | I47: =IF(E47>0,H47/(Inputs!$B$11*Inputs!$B$26-MIN(E47,0.95*Inputs!$B$11*Inputs!$B$26)),0) -> 0 | J47: =MAX(0,J46+(E47-Inputs!$B$11*Inputs!$B$26)*10) -> 0 | K47: =(J46+J47)/2/(Inputs!$B$11*Inputs!$B$26)+I47 -> 0 | L47: =Inputs!$B$86+K47+1/Inputs!$B$26+Inputs!$B$87+Inputs!$B$88+Inputs!$B$89 -> 28.625 | M47: =E47*L47 -> 0 | N47: =$D47*(1-Inputs!$B$35) -> 0 | O47: =N47/Inputs!$B$85 -> 0 | P47: =N47/(Inputs!$B$12*Inputs!$B$26) -> 0 | Q47: =IF(N47>0,((MIN(N47,0.95*Inputs!$B$12*Inputs!$B$26)/Inputs!$B$26)^Inputs!$B$12/FACT(Inputs!$B$12)*Inputs!$B$12/(Inputs!$B$12-(MIN(N47,0.95*Inputs!$B$12*Inputs!$B$26)/Inputs!$B$26)))/(SUMPRODUCT(--({0,1,2,3,4,5,6,7,8,9}<Inputs!$B$12),(MIN(N47,0.95*Inputs!$B$12*Inputs!$B$26)/Inputs!$B$26)^{0,1,2,3,4,5,6,7,8,9}/FACT({0,1,2,3,4,5,6,7,8,9}))+((MIN(N47,0.95*Inputs!$B$12*Inputs!$B$26)/Inputs!$B$26)^Inputs!$B$12/FACT(Inputs!$B$12)*Inputs!$B$12/(Inputs!$B$12-(MIN(N47,0.95*Inputs!$B$12*Inputs!$B$26)/Inputs!$B$26)))),0) -> 0 | R47: =IF(N47>0,Q47/(Inputs!$B$12*Inputs!$B$26-MIN(N47,0.95*Inputs!$B$12*Inputs!$B$26)),0) -> 0 | S47: =MAX(0,S46+(N47-Inputs!$B$12*Inputs!$B$26)*10) -> 0 | T47: =(S46+S47)/2/(Inputs!$B$12*Inputs!$B$26)+R47 -> 0 | U47: =Inputs!$B$86+T47+1/Inputs!$B$26+Inputs!$B$87+Inputs!$B$88+Inputs!$B$89 -> 28.625 | V47: =N47*U47 -> 0 | W47: =$D47*$E$26 -> 0 | X47: =W47/Inputs!$B$84 -> 0 | Y47: =W47/(Inputs!$B$11*Inputs!$B$26) -> 0 | Z47: =IF(W47>0,((MIN(W47,0.95*Inputs!$B$11*Inputs!$B$26)/Inputs!$B$26)^Inputs!$B$11/FACT(Inputs!$B$11)*Inputs!$B$11/(Inputs!$B$11-(MIN(W47,0.95*Inputs!$B$11*Inputs!$B$26)/Inputs!$B$26)))/(SUMPRODUCT(--({0,1,2,3,4,5,6,7,8,9}<Inputs!$B$11),(MIN(W47,0.95*Inputs!$B$11*Inputs!$B$26)/Inputs!$B$26)^{0,1,2,3,4,5,6,7,8,9}/FACT({0,1,2,3,4,5,6,7,8,9}))+((MIN(W47,0.95*Inputs!$B$11*Inputs!$B$26)/Inputs!$B$26)^Inputs!$B$11/FACT(Inputs!$B$11)*Inputs!$B$11/(Inputs!$B$11-(MIN(W47,0.95*Inputs!$B$11*Inputs!$B$26)/Inputs!$B$26)))),0) -> 0 | AA47: =IF(W47>0,Z47/(Inputs!$B$11*Inputs!$B$26-MIN(W47,0.95*Inputs!$B$11*Inputs!$B$26)),0) -> 0 | AB47: =MAX(0,AB46+(W47-Inputs!$B$11*Inputs!$B$26)*10) -> 0 | AC47: =(AB46+AB47)/2/(Inputs!$B$11*Inputs!$B$26)+AA47 -> 0 | AD47: =Inputs!$B$86+AC47+1/Inputs!$B$26+Inputs!$B$87+Inputs!$B$88+Inputs!$B$89 -> 28.625 | AE47: =W47*AD47 -> 0 | AF47: =$D47*(1-$E$26) -> 0 | AG47: =AF47/Inputs!$B$85 -> 0 | AH47: =AF47/(Inputs!$B$12*Inputs!$B$26) -> 0 | AI47: =IF(AF47>0,((MIN(AF47,0.95*Inputs!$B$12*Inputs!$B$26)/Inputs!$B$26)^Inputs!$B$12/FACT(Inputs!$B$12)*Inputs!$B$12/(Inputs!$B$12-(MIN(AF47,0.95*Inputs!$B$12*Inputs!$B$26)/Inputs!$B$26)))/(SUMPRODUCT(--({0,1,2,3,4,5,6,7,8,9}<Inputs!$B$12),(MIN(AF47,0.95*Inputs!$B$12*Inputs!$B$26)/Inputs!$B$26)^{0,1,2,3,4,5,6,7,8,9}/FACT({0,1,2,3,4,5,6,7,8,9}))+((MIN(AF47,0.95*Inputs!$B$12*Inputs!$B$26)/Inputs!$B$26)^Inputs!$B$12/FACT(Inputs!$B$12)*Inputs!$B$12/(Inputs!$B$12-(MIN(AF47,0.95*Inputs!$B$12*Inputs!$B$26)/Inputs!$B$26)))),0) -> 0 | AJ47: =IF(AF47>0,AI47/(Inputs!$B$12*Inputs!$B$26-MIN(AF47,0.95*Inputs!$B$12*Inputs!$B$26)),0) -> 0 | AK47: =MAX(0,AK46+(AF47-Inputs!$B$12*Inputs!$B$26)*10) -> 0 | AL47: =(AK46+AK47)/2/(Inputs!$B$12*Inputs!$B$26)+AJ47 -> 0 | AM47: =Inputs!$B$86+AL47+1/Inputs!$B$26+Inputs!$B$87+Inputs!$B$88+Inputs!$B$89 -> 28.625 | AN47: =AF47*AM47 -> 0
A49: Summary
A50: Measure | E50: Without: Central | F50: Without: Munch | G50: With: Central | H50: With: Munch | I50: Without: both | J50: With: both
A51: Average queue wait per student (min) | E51: =SUMPRODUCT(K30:K47,E30:E47)/SUM(E30:E47) -> 4.4763787 | F51: =SUMPRODUCT(T30:T47,N30:N47)/SUM(N30:N47) -> 0.0088403775 | G51: =SUMPRODUCT(AC30:AC47,W30:W47)/SUM(W30:W47) -> 0.90008851 | H51: =SUMPRODUCT(AL30:AL47,AF30:AF47)/SUM(AF30:AF47) -> 0.044628974 | I51: =(E51*SUM(E30:E47)+F51*SUM(N30:N47))/SUM(D30:D47) -> 3.5694685 | J51: =(G51*SUM(W30:W47)+H51*SUM(AF30:AF47))/SUM(D30:D47) -> 0.57398734
A52: Average throughput, door to leaving (min) | E52: =SUMPRODUCT(L30:L47,E30:E47)/SUM(E30:E47) -> 33.101379 | F52: =SUMPRODUCT(U30:U47,N30:N47)/SUM(N30:N47) -> 28.63384 | G52: =SUMPRODUCT(AD30:AD47,W30:W47)/SUM(W30:W47) -> 29.525089 | H52: =SUMPRODUCT(AM30:AM47,AF30:AF47)/SUM(AF30:AF47) -> 28.669629 | I52: =(E52*SUM(E30:E47)+F52*SUM(N30:N47))/SUM(D30:D47) -> 32.194468 | J52: =(G52*SUM(W30:W47)+H52*SUM(AF30:AF47))/SUM(D30:D47) -> 29.198987
A53: Peak utilisation ρ (serving) | E53: =MAX(G30:G47) -> 1.4918145 | F53: =MAX(P30:P47) -> 0.37997282 | G53: =MAX(Y30:Y47) -> 1.158262 | H53: =MAX(AH30:AH47) -> 0.71352531
A54: Peak scanner utilisation | E54: =MAX(F30:F47) -> 0.99454297 | F54: =MAX(O30:O47) -> 0.25331521 | G54: =MAX(X30:X47) -> 0.77217465 | H54: =MAX(AG30:AG47) -> 0.47568354
A55: Largest queue (students) | E55: =MAX(J30:J47) -> 233.064 | F55: =MAX(S30:S47) -> 0 | G55: =MAX(AB30:AB47) -> 51.367633 | H55: =MAX(AK30:AK47) -> 0
A56: Longest queue wait (min) | E56: =MAX(K30:K47) -> 12.206967 | F56: =MAX(T30:T47) -> 0.016874224 | G56: =MAX(AC30:AC47) -> 3.0011417 | H56: =MAX(AL30:AL47) -> 0.1037151
A57: Peak people inside (Little's Law L = λW, includes the queue) | E57: =MAX(M30:M47) -> 1086.2609 | F57: =MAX(V30:V47) -> 217.66267 | G57: =MAX(AE30:AE47) -> 702.87856 | H57: =MAX(AN30:AN47) -> 409.97331
A58: Peak seats needed (served per min × seat time; the stations cap the served rate) | E58: =MIN(MAX(E30:E47),Inputs!$B$11*Inputs!$B$26)*Inputs!$B$88 -> 500 | F58: =MIN(MAX(N30:N47),Inputs!$B$12*Inputs!$B$26)*Inputs!$B$88 -> 189.98641 | G58: =MIN(MAX(W30:W47),Inputs!$B$11*Inputs!$B$26)*Inputs!$B$88 -> 500 | H58: =MIN(MAX(AF30:AF47),Inputs!$B$12*Inputs!$B$26)*Inputs!$B$88 -> 356.76266
A59: Seats | E59: =Inputs!$B$9 -> 900 | F59: =Inputs!$B$10 -> 492 | G59: =Inputs!$B$9 -> 900 | H59: =Inputs!$B$10 -> 492
A61: Reading it: above ~85–90% utilisation waits climb steeply; above 100% the queue grows every minute (backlog column). The screens lower the peak utilisation of Central by moving some students to Munch. This spreadsheet measures the queue at the serving stations only; the simulator also counts the scanner queue and any wait for a seat, and adds run-outs (Reconciliation tab).

Sheet LP Student Flow
A1: Linear programming (primary model): how many students to direct to each mess in each 10-minute slot
A2: Sessions 10–11: LP formulation, constraints, Solver/simplex, shadow prices · solved with SciPy (HiGHS); re-solve in Excel with Solver
A4: Formulation (a fluid queue: each slot's queue = last slot's queue + arrivals − what the stations serve)
A5: Decision variables: y(t) = students redirected from Central to Munch in slot t; QA(t), QB(t) = students still queueing at Central / Munch at the end of slot t
A6: Objective: minimise total student-minutes of waiting = 10 × Σ [QA(t) + QB(t)] + walk × Σ y(t) (queue × 10-minute slot, plus 0.5 min per redirected student)
A7: Subject to: QA(t) ≥ QA(t−1) + h·D(t) − y(t) − 10·capA; QB(t) ≥ QB(t−1) + (1−h)·D(t) + y(t) − 10·capB (queues carry over; capacity per slot = 10 min × students/min)
A8: 0 ≤ y(t) ≤ κ·h·D(t) (only students at Central's door who follow the screen can move); Σ [(1−h)·D(t) + y(t)] ≤ F_B (Munch's star-dish portions)
A9: QA, QB ≥ 0. Data: D(t) arrivals (S15), h habit share, κ compliance, cap = stations × service rate (Inputs). Food is the operational constraint.
A11: Parameters (from Inputs)
A12: h: share heading to Central by habit | D12: =Inputs!$B$35 -> 0.797
A13: κ: share who follow the screen | D13: =Inputs!$B$36 -> 0.6
A14: capA: Central serving capacity (/min) | D14: =Inputs!$B$82 -> 20
A15: capB: Munch serving capacity (/min) | D15: =Inputs!$B$83 -> 20
A16: Walk between doors (min) | D16: =Inputs!$B$37 -> 0.5
A17: F_B: Munch star-dish portions | D17: =Inputs!$B$69 -> 1000
A19: Slot | B19: Arrivals D(t) | C19: At Central by habit h·D | D19: At Munch by habit | E19: Max redirect κ·h·D | F19: y(t) redirect (decision) | G19: QA(t) (decision) | H19: QB(t) (decision) | I19: Central constraint slack ≥ 0 | J19: Munch constraint slack ≥ 0 | K19: Today: QA (no redirect) | L19: Today: QB | M19: Central arrivals after | N19: Munch arrivals after
A20: 11:30 | B20: ='S15 Queuing'!$C$30 -> 0 | C20: =B20*$D$12 -> 0 | D20: =B20*(1-$D$12) -> 0 | E20: =$D$13*C20 -> 0 | F20: 0 | G20: 0 | H20: 0 | I20: =G20-(0+C20-F20-10*$D$14) -> 200 | J20: =H20-(0+D20+F20-10*$D$15) -> 200 | K20: =MAX(0,0+C20-10*$D$14) -> 0 | L20: =MAX(0,0+D20-10*$D$15) -> 0 | M20: =C20-F20 -> 0 | N20: =D20+F20 -> 0
A21: 11:40 | B21: ='S15 Queuing'!$C$31 -> 0 | C21: =B21*$D$12 -> 0 | D21: =B21*(1-$D$12) -> 0 | E21: =$D$13*C21 -> 0 | F21: 0 | G21: 0 | H21: 0 | I21: =G21-(G20+C21-F21-10*$D$14) -> 200 | J21: =H21-(H20+D21+F21-10*$D$15) -> 200 | K21: =MAX(0,K20+C21-10*$D$14) -> 0 | L21: =MAX(0,L20+D21-10*$D$15) -> 0 | M21: =C21-F21 -> 0 | N21: =D21+F21 -> 0
A22: 11:50 | B22: ='S15 Queuing'!$C$32 -> 0 | C22: =B22*$D$12 -> 0 | D22: =B22*(1-$D$12) -> 0 | E22: =$D$13*C22 -> 0 | F22: 0 | G22: 0 | H22: 0 | I22: =G22-(G21+C22-F22-10*$D$14) -> 200 | J22: =H22-(H21+D22+F22-10*$D$15) -> 200 | K22: =MAX(0,K21+C22-10*$D$14) -> 0 | L22: =MAX(0,L21+D22-10*$D$15) -> 0 | M22: =C22-F22 -> 0 | N22: =D22+F22 -> 0
A23: 12:00 | B23: ='S15 Queuing'!$C$33 -> 181.51605 | C23: =B23*$D$12 -> 144.66829 | D23: =B23*(1-$D$12) -> 36.847759 | E23: =$D$13*C23 -> 86.800976 | F23: 0 | G23: 0 | H23: 0 | I23: =G23-(G22+C23-F23-10*$D$14) -> 55.331706 | J23: =H23-(H22+D23+F23-10*$D$15) -> 163.15224 | K23: =MAX(0,K22+C23-10*$D$14) -> 0 | L23: =MAX(0,L22+D23-10*$D$15) -> 0 | M23: =C23-F23 -> 144.66829 | N23: =D23+F23 -> 36.847759
A24: 12:10 | B24: ='S15 Queuing'!$C$34 -> 231.87203 | C24: =B24*$D$12 -> 184.80201 | D24: =B24*(1-$D$12) -> 47.070023 | E24: =$D$13*C24 -> 110.88121 | F24: 0 | G24: 0 | H24: 0 | I24: =G24-(G23+C24-F24-10*$D$14) -> 15.197989 | J24: =H24-(H23+D24+F24-10*$D$15) -> 152.92998 | K24: =MAX(0,K23+C24-10*$D$14) -> 0 | L24: =MAX(0,L23+D24-10*$D$15) -> 0 | M24: =C24-F24 -> 184.80201 | N24: =D24+F24 -> 47.070023
A25: 12:20 | B25: ='S15 Queuing'!$C$35 -> 231.87203 | C25: =B25*$D$12 -> 184.80201 | D25: =B25*(1-$D$12) -> 47.070023 | E25: =$D$13*C25 -> 110.88121 | F25: 0 | G25: 0 | H25: 0 | I25: =G25-(G24+C25-F25-10*$D$14) -> 15.197989 | J25: =H25-(H24+D25+F25-10*$D$15) -> 152.92998 | K25: =MAX(0,K24+C25-10*$D$14) -> 0 | L25: =MAX(0,L24+D25-10*$D$15) -> 0 | M25: =C25-F25 -> 184.80201 | N25: =D25+F25 -> 47.070023
A26: 12:30 | B26: ='S15 Queuing'!$C$36 -> 284.74793 | C26: =B26*$D$12 -> 226.9441 | D26: =B26*(1-$D$12) -> 57.80383 | E26: =$D$13*C26 -> 136.16646 | F26: 26.944101 | G26: 0 | H26: 0 | I26: =G26-(G25+C26-F26-10*$D$14) -> -8.4615948e-08 | J26: =H26-(H25+D26+F26-10*$D$15) -> 115.25207 | K26: =MAX(0,K25+C26-10*$D$14) -> 26.944101 | L26: =MAX(0,L25+D26-10*$D$15) -> 0 | M26: =C26-F26 -> 200 | N26: =D26+F26 -> 84.747931
A27: 12:40 | B27: ='S15 Queuing'!$C$37 -> 260.30893 | C27: =B27*$D$12 -> 207.46622 | D27: =B27*(1-$D$12) -> 52.842713 | E27: =$D$13*C27 -> 124.47973 | F27: 7.466217 | G27: 0 | H27: 0 | I27: =G27-(G26+C27-F27-10*$D$14) -> 1.4715701e-07 | J27: =H27-(H26+D27+F27-10*$D$15) -> 139.69107 | K27: =MAX(0,K26+C27-10*$D$14) -> 34.410318 | L27: =MAX(0,L26+D27-10*$D$15) -> 0 | M27: =C27-F27 -> 200 | N27: =D27+F27 -> 60.30893
A28: 12:50 | B28: ='S15 Queuing'!$C$38 -> 215.80704 | C28: =B28*$D$12 -> 171.99821 | D28: =B28*(1-$D$12) -> 43.808829 | E28: =$D$13*C28 -> 103.19893 | F28: 0 | G28: 0 | H28: 0 | I28: =G28-(G27+C28-F28-10*$D$14) -> 28.001789 | J28: =H28-(H27+D28+F28-10*$D$15) -> 156.19117 | K28: =MAX(0,K27+C28-10*$D$14) -> 6.4085288 | L28: =MAX(0,L27+D28-10*$D$15) -> 0 | M28: =C28-F28 -> 171.99821 | N28: =D28+F28 -> 43.808829
A29: 13:00 | B29: ='S15 Queuing'!$C$39 -> 289.12109 | C29: =B29*$D$12 -> 230.42951 | D29: =B29*(1-$D$12) -> 58.691581 | E29: =$D$13*C29 -> 138.25771 | F29: 30.429509 | G29: 0 | H29: 0 | I29: =G29-(G28+C29-F29-10*$D$14) -> 2.150237e-07 | J29: =H29-(H28+D29+F29-10*$D$15) -> 110.87891 | K29: =MAX(0,K28+C29-10*$D$14) -> 36.838038 | L29: =MAX(0,L28+D29-10*$D$15) -> 0 | M29: =C29-F29 -> 200 | N29: =D29+F29 -> 89.12109
A30: 13:10 | B30: ='S15 Queuing'!$C$40 -> 374.35746 | C30: =B30*$D$12 -> 298.36289 | D30: =B30*(1-$D$12) -> 75.994564 | E30: =$D$13*C30 -> 179.01774 | F30: 98.362892 | G30: 0 | H30: 0 | I30: =G30-(G29+C30-F30-10*$D$14) -> -4.5490293e-07 | J30: =H30-(H29+D30+F30-10*$D$15) -> 25.642544 | K30: =MAX(0,K29+C30-10*$D$14) -> 135.20093 | L30: =MAX(0,L29+D30-10*$D$15) -> 0 | M30: =C30-F30 -> 200 | N30: =D30+F30 -> 174.35746
A31: 13:20 | B31: ='S15 Queuing'!$C$41 -> 355.06664 | C31: =B31*$D$12 -> 282.98812 | D31: =B31*(1-$D$12) -> 72.078529 | E31: =$D$13*C31 -> 169.79287 | F31: 82.988115 | G31: 0 | H31: 0 | I31: =G31-(G30+C31-F31-10*$D$14) -> -2.496534e-07 | J31: =H31-(H30+D31+F31-10*$D$15) -> 44.933356 | K31: =MAX(0,K30+C31-10*$D$14) -> 218.18905 | L31: =MAX(0,L30+D31-10*$D$15) -> 0 | M31: =C31-F31 -> 200 | N31: =D31+F31 -> 155.06664
A32: 13:30 | B32: ='S15 Queuing'!$C$42 -> 269.60471 | C32: =B32*$D$12 -> 214.87495 | D32: =B32*(1-$D$12) -> 54.729756 | E32: =$D$13*C32 -> 128.92497 | F32: 14.874952 | G32: 0 | H32: 0 | I32: =G32-(G31+C32-F32-10*$D$14) -> 3.5179852e-08 | J32: =H32-(H31+D32+F32-10*$D$15) -> 130.39529 | K32: =MAX(0,K31+C32-10*$D$14) -> 233.064 | L32: =MAX(0,L31+D32-10*$D$15) -> 0 | M32: =C32-F32 -> 200 | N32: =D32+F32 -> 69.604708
A33: 13:40 | B33: ='S15 Queuing'!$C$43 -> 175.31048 | C33: =B33*$D$12 -> 139.72245 | D33: =B33*(1-$D$12) -> 35.588028 | E33: =$D$13*C33 -> 83.833472 | F33: 0 | G33: 0 | H33: 0 | I33: =G33-(G32+C33-F33-10*$D$14) -> 60.277547 | J33: =H33-(H32+D33+F33-10*$D$15) -> 164.41197 | K33: =MAX(0,K32+C33-10*$D$14) -> 172.78645 | L33: =MAX(0,L32+D33-10*$D$15) -> 0 | M33: =C33-F33 -> 139.72245 | N33: =D33+F33 -> 35.588028
A34: 13:50 | B34: ='S15 Queuing'!$C$44 -> 90.415601 | C34: =B34*$D$12 -> 72.061234 | D34: =B34*(1-$D$12) -> 18.354367 | E34: =$D$13*C34 -> 43.23674 | F34: 0 | G34: 0 | H34: 0 | I34: =G34-(G33+C34-F34-10*$D$14) -> 127.93877 | J34: =H34-(H33+D34+F34-10*$D$15) -> 181.64563 | K34: =MAX(0,K33+C34-10*$D$14) -> 44.847684 | L34: =MAX(0,L33+D34-10*$D$15) -> 0 | M34: =C34-F34 -> 72.061234 | N34: =D34+F34 -> 18.354367
A35: 14:00 | B35: ='S15 Queuing'!$C$45 -> 0 | C35: =B35*$D$12 -> 0 | D35: =B35*(1-$D$12) -> 0 | E35: =$D$13*C35 -> 0 | F35: 0 | G35: 0 | H35: 0 | I35: =G35-(G34+C35-F35-10*$D$14) -> 200 | J35: =H35-(H34+D35+F35-10*$D$15) -> 200 | K35: =MAX(0,K34+C35-10*$D$14) -> 0 | L35: =MAX(0,L34+D35-10*$D$15) -> 0 | M35: =C35-F35 -> 0 | N35: =D35+F35 -> 0
A36: 14:10 | B36: ='S15 Queuing'!$C$46 -> 0 | C36: =B36*$D$12 -> 0 | D36: =B36*(1-$D$12) -> 0 | E36: =$D$13*C36 -> 0 | F36: 0 | G36: 0 | H36: 0 | I36: =G36-(G35+C36-F36-10*$D$14) -> 200 | J36: =H36-(H35+D36+F36-10*$D$15) -> 200 | K36: =MAX(0,K35+C36-10*$D$14) -> 0 | L36: =MAX(0,L35+D36-10*$D$15) -> 0 | M36: =C36-F36 -> 0 | N36: =D36+F36 -> 0
A37: 14:20 | B37: ='S15 Queuing'!$C$47 -> 0 | C37: =B37*$D$12 -> 0 | D37: =B37*(1-$D$12) -> 0 | E37: =$D$13*C37 -> 0 | F37: 0 | G37: 0 | H37: 0 | I37: =G37-(G36+C37-F37-10*$D$14) -> 200 | J37: =H37-(H36+D37+F37-10*$D$15) -> 200 | K37: =MAX(0,K36+C37-10*$D$14) -> 0 | L37: =MAX(0,L36+D37-10*$D$15) -> 0 | M37: =C37-F37 -> 0 | N37: =D37+F37 -> 0
A38: Total | B38: =SUM(B20:B37) -> 2960 | C38: =SUM(C20:C37) -> 2359.12 | D38: =SUM(D20:D37) -> 600.88 | E38: =SUM(E20:E37) -> 1415.472 | F38: =SUM(F20:F37) -> 261.06579 | G38: =SUM(G20:G37) -> 0 | H38: =SUM(H20:H37) -> 0 | K38: =SUM(K20:K37) -> 908.68909 | L38: =SUM(L20:L37) -> 0 | M38: =SUM(M20:M37) -> 2098.0542 | N38: =SUM(N20:N37) -> 861.94579
A40: Results
A41: Objective: student-minutes waiting + walking (LP optimum) | B41: =10*SUM(G20:H37)+$D$16*SUM(F20:F37) -> 130.53289
A42: Today (no redirection): student-minutes waiting | B42: =10*SUM(K20:L37) -> 9086.8909
A43: Average per student, LP optimum (min) | B43: =B41/B38 -> 0.04409895
A44: Average per student, today (min) | B44: =B42/B38 -> 3.0698956
A45: Students redirected to Munch | B45: =F38 -> 261.06579
A46: Share of all students redirected | B46: =F38/B38 -> 0.088197901
A47: Munch star-dish portions used (must be ≤ F_B) | B47: =N38 -> 861.94579
A48: Food constraint satisfied? | B48: =IF(B47<=$D$17+0.5,"Yes","No") -> Yes
A49: Smallest constraint slack (must be ≥ 0) | B49: =MIN(I20:J37) -> -4.5490293e-07
A50: Every y(t) within 0 and κ·h·D(t)? | B50: =IF(SUMPRODUCT(--(F20:F37>E20:E37+0.01))+COUNTIF(F20:F37,"<0")=0,"Yes","No") -> Yes
A53: Sensitivity: how Munch's star-dish portions limit the plan (LP re-solved for each value)
A54: Munch portions F_B | B54: Student-minutes | C54: Avg per student (min) | D54: Redirected | E54: Shadow price: student-min saved per extra portion
A55: 650 | B55: 6138 | C55: 2.07 | D55: 49 | E55: 39.5
A56: 700 | B56: 4163 | C56: 1.41 | D56: 99 | E56: 39.5
A57: 800 | B57: 1115 | C57: 0.38 | D57: 199 | E57: 19.5
A58: 900 | B58: 131 | C58: 0.04 | D58: 261 | E58: 0
A59: 1000 | B59: 131 | C59: 0.04 | D59: 261 | E59: 0
A60: 1200 | B60: 131 | C60: 0.04 | D60: 261 | E60: 0
A61: Reading it: Munch needs about 862 star-dish portions to carry the optimal flow. Below that, food becomes the binding constraint and every extra portion saves the student-minutes shown (the shadow price): routing and food allocation must be planned together. The LP is a fluid model with no randomness, so its optimum is a lower bound on waiting; the simulator adds random arrivals and service, live estimates with a delay, and run-outs (Scenarios, Reconciliation).
A63: Re-solve in Excel
A64: Data → Solver. Set objective B41 to Min. By changing F20:H37. Constraints: I20:J37 ≥ 0; F20:F37 ≤ E20:E37; N38 ≤ $D$17; F20:H37 ≥ 0. Method: Simplex LP. If you change any input, re-run Solver: the yellow decision cells hold the optimum for the current Inputs.

Sheet LP Food Allocation
A1: Linear programming (secondary model): splitting the star dish between the messes to support the student flow
A2: Sessions 10–11: LP formulation, graphical method (corner points), Solver/simplex
A4: Formulation
A5: Decision variables: x1 = star-dish portions ready at Central before the peak, x2 = portions ready at Munch
A6: Objective: maximise Σ vᵢ·xᵢ, where vᵢ = students per minute who would meet an empty tray at mess i (its peak arrival rate under the flow plan)
A7: Subject to: x1 + x2 ≤ K (portions the kitchen can have ready); xᵢ ≤ dᵢ (no point sending more than that mess's demand under the flow plan); x ≥ 0
A9: Data (all linked: change Inputs or the flow plan, not these)
A10: K: portions the kitchen can have ready before the peak | B10: =Inputs!$B$70 -> 2400
A11: d1: Central demand under the flow plan (students × servings) | B11: ='LP Student Flow'!$M$38*Inputs!$B$68 -> 2098.0542
A12: d2: Munch demand under the flow plan | B12: ='LP Student Flow'!$N$38*Inputs!$B$68 -> 861.94579
A13: v1: students/min at Central's peak under the plan | B13: =MAX('LP Student Flow'!$M$20:$M$37)/10 -> 20
A14: v2: students/min at Munch's peak under the plan | B14: =MAX('LP Student Flow'!$N$20:$N$37)/10 -> 17.435746
A16: Decision cells (Solver changes these)
A17: x1 (Central) | B17: =IF(B13>=B14,MIN(B11,B10),MAX(0,MIN(B11,B10-MIN(B12,B10)))) -> 2098.0542 | C17: Filled by the greedy rule that solves this LP exactly (fill the mess with the larger v first, then the other). Solver gives the same answer.
A18: x2 (Munch) | B18: =IF(B13>=B14,MAX(0,MIN(B12,B10-B17)),MIN(B12,B10)) -> 301.94579
A19: Objective Σ v·x (student-minutes of run-out exposure avoided per minute) | B19: =B13*B17+B14*B18 -> 47225.734
A21: Constraints
A22: Constraint | B22: Left side | C22: Sign | D22: Right side | E22: OK?
A23: Kitchen batch: x1 + x2 ≤ K | B23: =B17+B18 -> 2400 | C23: ≤ | D23: =B10 -> 2400 | E23: =IF(B23<=D23,"OK","Violated") -> OK
A24: Central demand: x1 ≤ d1 | B24: =B17 -> 2098.0542 | C24: ≤ | D24: =B11 -> 2098.0542 | E24: =IF(B24<=D24+0.5,"OK","Violated") -> OK
A25: Munch demand: x2 ≤ d2 | B25: =B18 -> 301.94579 | C25: ≤ | D25: =B12 -> 861.94579 | E25: =IF(B25<=D25+0.5,"OK","Violated") -> OK
A26: Non-negativity | B26: =MIN(B17:B18) -> 301.94579 | C26: ≥ | D26: 0 | E26: =IF(B26>=0,"OK","Violated") -> OK
A28: Graphical method: evaluate every corner point of the feasible region
A29: Corner point | B29: x1 | C29: x2 | D29: Feasible? | E29: Objective
A30: Origin | B30: 0 | C30: 0 | D30: =IF(AND(B30+C30<=$B$10+0.5,B30<=$B$11+0.5,C30<=$B$12+0.5),"Yes","No") -> Yes | E30: =$B$13*B30+$B$14*C30 -> 0
A31: Central at demand, Munch 0 | B31: =MIN(B11,B10) -> 2098.0542 | C31: 0 | D31: =IF(AND(B31+C31<=$B$10+0.5,B31<=$B$11+0.5,C31<=$B$12+0.5),"Yes","No") -> Yes | E31: =$B$13*B31+$B$14*C31 -> 41961.084
A32: Central at demand, rest to Munch | B32: =MIN(B11,B10) -> 2098.0542 | C32: =MAX(0,MIN(B12,B10-MIN(B11,B10))) -> 301.94579 | D32: =IF(AND(B32+C32<=$B$10+0.5,B32<=$B$11+0.5,C32<=$B$12+0.5),"Yes","No") -> Yes | E32: =$B$13*B32+$B$14*C32 -> 47225.734
A33: Munch at demand, rest to Central | B33: =MAX(0,MIN(B11,B10-MIN(B12,B10))) -> 1538.0542 | C33: =MIN(B12,B10) -> 861.94579 | D33: =IF(AND(B33+C33<=$B$10+0.5,B33<=$B$11+0.5,C33<=$B$12+0.5),"Yes","No") -> Yes | E33: =$B$13*B33+$B$14*C33 -> 45789.752
A34: Munch at demand, Central 0 | B34: 0 | C34: =MIN(B12,B10) -> 861.94579 | D34: =IF(AND(B34+C34<=$B$10+0.5,B34<=$B$11+0.5,C34<=$B$12+0.5),"Yes","No") -> Yes | E34: =$B$13*B34+$B$14*C34 -> 15028.667
A36: Optimal corner (graphical method) | B36: =INDEX(A30:A34,MATCH(MAX(E30:E34),E30:E34,0)) -> Central at demand, rest to Munch
A38: How this connects to the primary model: the flow plan (LP Student Flow) decides where students go; this tab then decides where the limited star dish should be before the peak. If K covers both demands, the constraint is slack and both messes are fully stocked. If not, the mess whose queue grows faster gets priority. Refills during service are handled by the Decision Rule (refill clock from the 'running low' call).

Sheet S7 Payoff Matrix
A1: Decision making under uncertainty and risk: payoff matrix, with and without the system
A2: Session 7: maximax, maximin, minimax regret, Hurwicz, Laplace, EMV, EVPI · every wait below is simulated, not estimated
A4: Average queue wait per student (minutes). Simulated: python -m messq.scenarios, 20 lunches per row (seeds 0–19, the same students in every scenario); ± = 95% confidence interval. Kinds of day: S1 = 20% fewer students; S2 = 2,960; S3 = 20% more students and the next batch never ready.
A6: Average wait (minutes) [lower is better] | B6: S1 Normal day | C6: S2 Busy day | D6: S3 Surge + late refills | F6: S1 Normal day (±95% CI) | G6: S2 Busy day (±95% CI) | H6: S3 Surge + late refills (±95% CI)
A7: A1 No system (today) | B7: 0.81 | C7: 4.31 | D7: 14.82 | F7: ±0.13 | G7: ±0.63 | H7: ±0.55
A8: A2 Door screens, queue information only | B8: 0.37 | C8: 1.19 | D8: 4.99 | F8: ±0.05 | G8: ±0.33 | H8: ±0.24
A9: A3 Door screens + food status (proposal) | B9: 0.38 | C9: 0.8 | D9: 4.13 | F9: ±0.05 | G9: ±0.10 | H9: ±0.31
A10: A4 3rd serving station at Central (no screens) | B10: 0.06 | C10: 0.64 | D10: 7.45 | F10: ±0.02 | G10: ±0.38 | H10: ±0.45
A11: A5 Proposal + 3rd serving station | B11: 0.05 | C11: 0.31 | D11: 3.17 | F11: ±0.01 | G11: ±0.16 | H11: ±0.26
A13: Probability of each kind of day (Inputs) | B13: S1 Normal day | C13: S2 Busy day | D13: S3 Surge + late refills
A14: P(kind of day): from the biometric logs once available | B14: =Inputs!$B$72 -> 0.3 | C14: =Inputs!$B$73 -> 0.5 | D14: =Inputs!$B$74 -> 0.2 | E14: =SUM(B14:D14) -> 1 | F14: ← must be 100%
A15: Students per lunch (busy day) | B15: =Inputs!$B$6 -> 2960
A17: Payoff = minutes saved per student compared with today = wait(A1) − wait(alternative) [higher is better]
A18: Alternative | B18: S1 Normal day | C18: S2 Busy day | D18: S3 Surge + late refills | E18: Maximax (optimistic) | F18: Maximin (pessimistic) | G18: Hurwicz | H18: Laplace (equal likelihood) | I18: EMV (with probabilities) | J18: Student-hours saved per lunch (EMV)
A19: A1 No system (today) | B19: =B$7-B7 -> 0 | C19: =C$7-C7 -> 0 | D19: =D$7-D7 -> 0 | E19: =MAX(B19:D19) -> 0 | F19: =MIN(B19:D19) -> 0 | G19: =$B$27*E19+(1-$B$27)*F19 -> 0 | H19: =AVERAGE(B19:D19) -> 0 | I19: =SUMPRODUCT(B19:D19,$B$14:$D$14) -> 0 | J19: =I19*$B$15/60 -> 0
A20: A2 Door screens, queue information only | B20: =B$7-B8 -> 0.44 | C20: =C$7-C8 -> 3.12 | D20: =D$7-D8 -> 9.83 | E20: =MAX(B20:D20) -> 9.83 | F20: =MIN(B20:D20) -> 0.44 | G20: =$B$27*E20+(1-$B$27)*F20 -> 4.196 | H20: =AVERAGE(B20:D20) -> 4.4633333 | I20: =SUMPRODUCT(B20:D20,$B$14:$D$14) -> 3.658 | J20: =I20*$B$15/60 -> 180.46133
A21: A3 Door screens + food status (proposal) | B21: =B$7-B9 -> 0.43 | C21: =C$7-C9 -> 3.51 | D21: =D$7-D9 -> 10.69 | E21: =MAX(B21:D21) -> 10.69 | F21: =MIN(B21:D21) -> 0.43 | G21: =$B$27*E21+(1-$B$27)*F21 -> 4.534 | H21: =AVERAGE(B21:D21) -> 4.8766667 | I21: =SUMPRODUCT(B21:D21,$B$14:$D$14) -> 4.022 | J21: =I21*$B$15/60 -> 198.41867
A22: A4 3rd serving station at Central (no screens) | B22: =B$7-B10 -> 0.75 | C22: =C$7-C10 -> 3.67 | D22: =D$7-D10 -> 7.37 | E22: =MAX(B22:D22) -> 7.37 | F22: =MIN(B22:D22) -> 0.75 | G22: =$B$27*E22+(1-$B$27)*F22 -> 3.398 | H22: =AVERAGE(B22:D22) -> 3.93 | I22: =SUMPRODUCT(B22:D22,$B$14:$D$14) -> 3.534 | J22: =I22*$B$15/60 -> 174.344
A23: A5 Proposal + 3rd serving station | B23: =B$7-B11 -> 0.76 | C23: =C$7-C11 -> 4 | D23: =D$7-D11 -> 11.65 | E23: =MAX(B23:D23) -> 11.65 | F23: =MIN(B23:D23) -> 0.76 | G23: =$B$27*E23+(1-$B$27)*F23 -> 5.116 | H23: =AVERAGE(B23:D23) -> 5.47 | I23: =SUMPRODUCT(B23:D23,$B$14:$D$14) -> 4.558 | J23: =I23*$B$15/60 -> 224.86133
A24: Best alternative by criterion | E24: =INDEX($A$19:$A$23,MATCH(MAX(E19:E23),E19:E23,0)) -> A5 Proposal + 3rd serving station | F24: =INDEX($A$19:$A$23,MATCH(MAX(F19:F23),F19:F23,0)) -> A5 Proposal + 3rd serving station | G24: =INDEX($A$19:$A$23,MATCH(MAX(G19:G23),G19:G23,0)) -> A5 Proposal + 3rd serving station | H24: =INDEX($A$19:$A$23,MATCH(MAX(H19:H23),H19:H23,0)) -> A5 Proposal + 3rd serving station | I24: =INDEX($A$19:$A$23,MATCH(MAX(I19:I23),I19:I23,0)) -> A5 Proposal + 3rd serving station
A25: Best without an extra station's staff (A1–A3 only) | E25: =INDEX($A$19:$A$21,MATCH(MAX(E19:E21),E19:E21,0)) -> A3 Door screens + food status (proposal) | F25: =INDEX($A$19:$A$21,MATCH(MAX(F19:F21),F19:F21,0)) -> A2 Door screens, queue information only | G25: =INDEX($A$19:$A$21,MATCH(MAX(G19:G21),G19:G21,0)) -> A3 Door screens + food status (proposal) | H25: =INDEX($A$19:$A$21,MATCH(MAX(H19:H21),H19:H21,0)) -> A3 Door screens + food status (proposal) | I25: =INDEX($A$19:$A$21,MATCH(MAX(I19:I21),I19:I21,0)) -> A3 Door screens + food status (proposal)
A27: Hurwicz α (degree of optimism, analyst's choice) | B27: 0.4
A28: Regret (opportunity loss, minutes) = best payoff on that kind of day − this payoff
A29: Alternative | B29: S1 Normal day | C29: S2 Busy day | D29: S3 Surge + late refills | E29: Maximum regret | F29: Expected regret (EOL)
A30: A1 No system (today) | B30: =MAX(B$19:B$23)-B19 -> 0.76 | C30: =MAX(C$19:C$23)-C19 -> 4 | D30: =MAX(D$19:D$23)-D19 -> 11.65 | E30: =MAX(B30:D30) -> 11.65 | F30: =SUMPRODUCT(B30:D30,$B$14:$D$14) -> 4.558
A31: A2 Door screens, queue information only | B31: =MAX(B$19:B$23)-B20 -> 0.32 | C31: =MAX(C$19:C$23)-C20 -> 0.88 | D31: =MAX(D$19:D$23)-D20 -> 1.82 | E31: =MAX(B31:D31) -> 1.82 | F31: =SUMPRODUCT(B31:D31,$B$14:$D$14) -> 0.9
A32: A3 Door screens + food status (proposal) | B32: =MAX(B$19:B$23)-B21 -> 0.33 | C32: =MAX(C$19:C$23)-C21 -> 0.49 | D32: =MAX(D$19:D$23)-D21 -> 0.96 | E32: =MAX(B32:D32) -> 0.96 | F32: =SUMPRODUCT(B32:D32,$B$14:$D$14) -> 0.536
A33: A4 3rd serving station at Central (no screens) | B33: =MAX(B$19:B$23)-B22 -> 0.01 | C33: =MAX(C$19:C$23)-C22 -> 0.33 | D33: =MAX(D$19:D$23)-D22 -> 4.28 | E33: =MAX(B33:D33) -> 4.28 | F33: =SUMPRODUCT(B33:D33,$B$14:$D$14) -> 1.024
A34: A5 Proposal + 3rd serving station | B34: =MAX(B$19:B$23)-B23 -> 0 | C34: =MAX(C$19:C$23)-C23 -> 0 | D34: =MAX(D$19:D$23)-D23 -> 0 | E34: =MAX(B34:D34) -> 0 | F34: =SUMPRODUCT(B34:D34,$B$14:$D$14) -> 0
A35: Minimax regret choice | E35: =INDEX($A$30:$A$34,MATCH(MIN(E30:E34),E30:E34,0)) -> A5 Proposal + 3rd serving station
A36: Minimum expected regret (= EMV choice) | F36: =INDEX($A$30:$A$34,MATCH(MIN(F30:F34),F30:F34,0)) -> A5 Proposal + 3rd serving station
A38: Value of perfect information (minutes per student)
A39: Expected payoff WITH perfect information (best alternative for each kind of day) | B39: =B14*MAX(B19:B23)+C14*MAX(C19:C23)+D14*MAX(D19:D23) -> 4.558
A40: Best EMV without perfect information | B40: =MAX(I19:I23) -> 4.558
A41: EVPI = extra minutes per student if we knew the kind of day in advance | B41: =B39-B40 -> 0
A42: Check: EVPI equals the minimum expected regret | B42: =MIN(F30:F34) -> 0
A44: Reading it: the payoff is waiting time only, so the objective stays explicit. A5 has the lowest wait on every kind of day, so EVPI is 0: knowing the kind of day in advance would not change the choice. Staff cost is not in these minutes: A4 and A5 need a third station's staff every day, while A3 needs two screens and the manager's taps. Without extra staff, the proposal (A3) is the best choice (row 25). On normal days a third station alone does a little better (0.1 vs 0.4 min). A1 and A4 are without the system; A2, A3 and A5 are with it. For a table of waits (lower is better) the criteria would be minimin and minimax; turning waits into minutes saved makes higher better, so the maximax / maximin names apply.

Sheet S18 Heuristics
A1: Heuristics: simple rules that give good answers fast
A2: Session 18: Heuristics and metaheuristics — concepts and business applications
A4: 1. Door-screen switching rule (used in the prototype)
A5: Predicted wait if you stay (min) | B5: 6
A6: Predicted wait at the other mess (min) | B6: 2
A7: Walk between doors (min) | B7: =Inputs!$B$37 -> 0.5
A8: Minimum saving to suggest a switch (min) | B8: =Inputs!$B$77 -> 2
A9: Saving after the walk (min) | B9: =B5-(B6+B7) -> 3.5
A10: Screen says | B10: =IF(B9>=B8,"Other mess is faster → walk over",IF(B9>0,"Small saving: stay","Come on in")) -> Other mess is faster → walk over
A12: 2. When should the manager tap 'running low' (call the kitchen)? A reorder point
A13: Star dish served per minute at peak (= Central's serving capacity) | B13: =Inputs!$B$82 -> 20
A14: Lead time from the call (worst case: has to be made, then sent) | B14: =Inputs!$B$18 -> 30
A15: Lead time from the call (expected: 70% already made) | B15: =Inputs!$B$91 -> 17.4
A16: Reorder point, worst case (portions left when the call must go) | B16: =B13*B14 -> 600 | C16: The protocol (20 min of food) covers the expected refill but not the worst case (30 min): in that case a gap opens, and the Decision Rule charges it only to students who would reach the empty tray.
A17: Reorder point, expected case | B17: =B13*B15 -> 348
A18: Our protocol: tap 'running low' with this many minutes of food left | B18: =Inputs!$B$67 -> 20
A19: Portions left at the tap (at peak) | B19: =B13*B18 -> 400
A21: 3. Heuristic vs full model (busy day, 60% follow the screens)
A22: Policy | B22: Average wait (min) | C22: 90th pct wait (min) | D22: Comment
A23: No advice (today) | B23: 4.31 | C23: 13.9 | D23: Baseline (simulated)
A24: Naive heuristic: send people to the shorter queue (≥ 2 min saving) | B24: 0.76 | C24: 2 | D24: Simple rule; works at the doors because feedback is fast (30 s walk)
A25: Equal-wait split, queues only | B25: 1.19 | C25: 3.1 | D25: Ignores food status
A26: Equal-wait split + food status (proposal) | B26: 0.8 | C26: 2.1 | D26: Bisection search for the split; food delays only for students who would meet an empty tray
A27: LP lower bound (fluid model, perfect foresight) | B27: ='LP Student Flow'!$B$43 -> 0.04409895 | D27: Not achievable live: no randomness, no estimation delay
A29: 4. Metaheuristics (next step)
A30: A replenishment schedule that minimises waiting + waste over a whole lunch has no closed-form answer because of the queues. A metaheuristic (simulated annealing or a genetic algorithm) can search over schedules, scoring each candidate by running our simulator: 'simulation-optimisation'.

Sheet Decision Rule
A1: Decision rule: when the screen outside Central recommends Munch, and when it gives no advice
A2: The objective stays explicit: minimise each student's expected time to food (queue + walk + any food delay), without overloading the other mess
A4: The rule (the same logic the prototype runs; config/default.toml)
A5: 1. No advice if the data are stale: a scanner silent for longer than the limit on the Inputs tab.
A6: 2. No advice if the star dish is out at both messes (no better option).
A7: 3. Time if you stay = queue wait here + food delay here. Time if you switch = walk + queue wait there + food delay there.
A8: 4. Food delay for a tray marked 'running low' or 'out': only if you would reach the counter after it empties and before its refill (refill clock runs from the call).
A9: 5. Recommend switching only if it saves at least the minimum saving + an uncertainty margin, AND the other mess still has spare capacity after the move.
A10: 6. Never send everyone: move only enough students to equalise utilisation (capacity-weighted), so the other mess doesn't become the new bottleneck.
A13: Situation | B13: Wait at Central (min) | C13: Wait at Munch (min) | D13: Central star dish | E13: Min since Central called kitchen | F13: Munch star dish | G13: Min since Munch called kitchen | H13: Arrivals Central (/min) | I13: Arrivals Munch (/min) | J13: Min since last scan | K13: Central refill due in (min) | L13: Central food delay (min) | M13: Munch refill due in (min) | N13: Munch food delay (min) | O13: Time if you stay | P13: Time if you switch | Q13: Saving (min) | R13: Move /min to equalise | S13: Munch ρ after the move | T13: Screen outside Central says
A14: Quiet start of lunch | B14: 0.2 | C14: 0.1 | D14: OK | E14: 0 | F14: OK | G14: 0 | H14: 5 | I14: 1 | J14: 0.2 | K14: =IF(D14="OK","",IF((Inputs!$B$66*IF(E14<=Inputs!$B$19,1,MAX(0,(Inputs!$B$20-E14)/(Inputs!$B$20-Inputs!$B$19))))+((1-Inputs!$B$66)*IF(E14<Inputs!$B$18,1,0))=0,0,((Inputs!$B$66*IF(E14<=Inputs!$B$19,1,MAX(0,(Inputs!$B$20-E14)/(Inputs!$B$20-Inputs!$B$19))))*(IF(E14<Inputs!$B$20,(MAX(E14,Inputs!$B$19)+Inputs!$B$20)/2-E14,0))+((1-Inputs!$B$66)*IF(E14<Inputs!$B$18,1,0))*(Inputs!$B$18-E14))/((Inputs!$B$66*IF(E14<=Inputs!$B$19,1,MAX(0,(Inputs!$B$20-E14)/(Inputs!$B$20-Inputs!$B$19))))+((1-Inputs!$B$66)*IF(E14<Inputs!$B$18,1,0))))) | L14: =IF(D14="OUT",MAX(0,K14-B14),IF(D14="LOW",IF(AND(B14>=MAX(0,Inputs!$B$67-E14),B14<K14),K14-B14,0),0)) -> 0 | M14: =IF(F14="OK","",IF((Inputs!$B$66*IF(G14<=Inputs!$B$19,1,MAX(0,(Inputs!$B$20-G14)/(Inputs!$B$20-Inputs!$B$19))))+((1-Inputs!$B$66)*IF(G14<Inputs!$B$18,1,0))=0,0,((Inputs!$B$66*IF(G14<=Inputs!$B$19,1,MAX(0,(Inputs!$B$20-G14)/(Inputs!$B$20-Inputs!$B$19))))*(IF(G14<Inputs!$B$20,(MAX(G14,Inputs!$B$19)+Inputs!$B$20)/2-G14,0))+((1-Inputs!$B$66)*IF(G14<Inputs!$B$18,1,0))*(Inputs!$B$18-G14))/((Inputs!$B$66*IF(G14<=Inputs!$B$19,1,MAX(0,(Inputs!$B$20-G14)/(Inputs!$B$20-Inputs!$B$19))))+((1-Inputs!$B$66)*IF(G14<Inputs!$B$18,1,0))))) | N14: =IF(F14="OUT",MAX(0,M14-(Inputs!$B$37+C14)),IF(F14="LOW",IF(AND((Inputs!$B$37+C14)>=MAX(0,Inputs!$B$67-G14),(Inputs!$B$37+C14)<M14),M14-(Inputs!$B$37+C14),0),0)) -> 0 | O14: =B14+L14 -> 0.2 | P14: =Inputs!$B$37+C14+N14 -> 0.6 | Q14: =O14-P14 -> -0.4 | R14: =MAX(0,(H14*Inputs!$B$83-I14*Inputs!$B$82)/(Inputs!$B$82+Inputs!$B$83)) -> 2 | S14: =(I14+MIN(R14,Inputs!$B$36*H14))/Inputs!$B$83 -> 0.15 | T14: =IF(J14>Inputs!$B$79,"No advice: scan data stale",IF(AND(D14="OUT",F14="OUT"),"No advice: star dish out at both messes",IF(Q14<Inputs!$B$77+Inputs!$B$78,"Come on in (saving under "&TEXT(Inputs!$B$77+Inputs!$B$78,"0.0")&" min)",IF(S14>=1,"Come on in: Munch has no spare capacity","Munch is faster → save ~"&TEXT(Q14,"0")&" min")))) -> Come on in (saving under 2.5 min)
A15: Peak: Central queue, Munch quiet | B15: 9 | C15: 1 | D15: OK | E15: 0 | F15: OK | G15: 0 | H15: 29 | I15: 5 | J15: 0.2 | K15: =IF(D15="OK","",IF((Inputs!$B$66*IF(E15<=Inputs!$B$19,1,MAX(0,(Inputs!$B$20-E15)/(Inputs!$B$20-Inputs!$B$19))))+((1-Inputs!$B$66)*IF(E15<Inputs!$B$18,1,0))=0,0,((Inputs!$B$66*IF(E15<=Inputs!$B$19,1,MAX(0,(Inputs!$B$20-E15)/(Inputs!$B$20-Inputs!$B$19))))*(IF(E15<Inputs!$B$20,(MAX(E15,Inputs!$B$19)+Inputs!$B$20)/2-E15,0))+((1-Inputs!$B$66)*IF(E15<Inputs!$B$18,1,0))*(Inputs!$B$18-E15))/((Inputs!$B$66*IF(E15<=Inputs!$B$19,1,MAX(0,(Inputs!$B$20-E15)/(Inputs!$B$20-Inputs!$B$19))))+((1-Inputs!$B$66)*IF(E15<Inputs!$B$18,1,0))))) | L15: =IF(D15="OUT",MAX(0,K15-B15),IF(D15="LOW",IF(AND(B15>=MAX(0,Inputs!$B$67-E15),B15<K15),K15-B15,0),0)) -> 0 | M15: =IF(F15="OK","",IF((Inputs!$B$66*IF(G15<=Inputs!$B$19,1,MAX(0,(Inputs!$B$20-G15)/(Inputs!$B$20-Inputs!$B$19))))+((1-Inputs!$B$66)*IF(G15<Inputs!$B$18,1,0))=0,0,((Inputs!$B$66*IF(G15<=Inputs!$B$19,1,MAX(0,(Inputs!$B$20-G15)/(Inputs!$B$20-Inputs!$B$19))))*(IF(G15<Inputs!$B$20,(MAX(G15,Inputs!$B$19)+Inputs!$B$20)/2-G15,0))+((1-Inputs!$B$66)*IF(G15<Inputs!$B$18,1,0))*(Inputs!$B$18-G15))/((Inputs!$B$66*IF(G15<=Inputs!$B$19,1,MAX(0,(Inputs!$B$20-G15)/(Inputs!$B$20-Inputs!$B$19))))+((1-Inputs!$B$66)*IF(G15<Inputs!$B$18,1,0))))) | N15: =IF(F15="OUT",MAX(0,M15-(Inputs!$B$37+C15)),IF(F15="LOW",IF(AND((Inputs!$B$37+C15)>=MAX(0,Inputs!$B$67-G15),(Inputs!$B$37+C15)<M15),M15-(Inputs!$B$37+C15),0),0)) -> 0 | O15: =B15+L15 -> 9 | P15: =Inputs!$B$37+C15+N15 -> 1.5 | Q15: =O15-P15 -> 7.5 | R15: =MAX(0,(H15*Inputs!$B$83-I15*Inputs!$B$82)/(Inputs!$B$82+Inputs!$B$83)) -> 12 | S15: =(I15+MIN(R15,Inputs!$B$36*H15))/Inputs!$B$83 -> 0.85 | T15: =IF(J15>Inputs!$B$79,"No advice: scan data stale",IF(AND(D15="OUT",F15="OUT"),"No advice: star dish out at both messes",IF(Q15<Inputs!$B$77+Inputs!$B$78,"Come on in (saving under "&TEXT(Inputs!$B$77+Inputs!$B$78,"0.0")&" min)",IF(S15>=1,"Come on in: Munch has no spare capacity","Munch is faster → save ~"&TEXT(Q15,"0")&" min")))) -> Munch is faster → save ~8 min
A16: Peak, but Munch is nearly full too | B16: 9 | C16: 6 | D16: OK | E16: 0 | F16: OK | G16: 0 | H16: 29 | I16: 19 | J16: 0.2 | K16: =IF(D16="OK","",IF((Inputs!$B$66*IF(E16<=Inputs!$B$19,1,MAX(0,(Inputs!$B$20-E16)/(Inputs!$B$20-Inputs!$B$19))))+((1-Inputs!$B$66)*IF(E16<Inputs!$B$18,1,0))=0,0,((Inputs!$B$66*IF(E16<=Inputs!$B$19,1,MAX(0,(Inputs!$B$20-E16)/(Inputs!$B$20-Inputs!$B$19))))*(IF(E16<Inputs!$B$20,(MAX(E16,Inputs!$B$19)+Inputs!$B$20)/2-E16,0))+((1-Inputs!$B$66)*IF(E16<Inputs!$B$18,1,0))*(Inputs!$B$18-E16))/((Inputs!$B$66*IF(E16<=Inputs!$B$19,1,MAX(0,(Inputs!$B$20-E16)/(Inputs!$B$20-Inputs!$B$19))))+((1-Inputs!$B$66)*IF(E16<Inputs!$B$18,1,0))))) | L16: =IF(D16="OUT",MAX(0,K16-B16),IF(D16="LOW",IF(AND(B16>=MAX(0,Inputs!$B$67-E16),B16<K16),K16-B16,0),0)) -> 0 | M16: =IF(F16="OK","",IF((Inputs!$B$66*IF(G16<=Inputs!$B$19,1,MAX(0,(Inputs!$B$20-G16)/(Inputs!$B$20-Inputs!$B$19))))+((1-Inputs!$B$66)*IF(G16<Inputs!$B$18,1,0))=0,0,((Inputs!$B$66*IF(G16<=Inputs!$B$19,1,MAX(0,(Inputs!$B$20-G16)/(Inputs!$B$20-Inputs!$B$19))))*(IF(G16<Inputs!$B$20,(MAX(G16,Inputs!$B$19)+Inputs!$B$20)/2-G16,0))+((1-Inputs!$B$66)*IF(G16<Inputs!$B$18,1,0))*(Inputs!$B$18-G16))/((Inputs!$B$66*IF(G16<=Inputs!$B$19,1,MAX(0,(Inputs!$B$20-G16)/(Inputs!$B$20-Inputs!$B$19))))+((1-Inputs!$B$66)*IF(G16<Inputs!$B$18,1,0))))) | N16: =IF(F16="OUT",MAX(0,M16-(Inputs!$B$37+C16)),IF(F16="LOW",IF(AND((Inputs!$B$37+C16)>=MAX(0,Inputs!$B$67-G16),(Inputs!$B$37+C16)<M16),M16-(Inputs!$B$37+C16),0),0)) -> 0 | O16: =B16+L16 -> 9 | P16: =Inputs!$B$37+C16+N16 -> 6.5 | Q16: =O16-P16 -> 2.5 | R16: =MAX(0,(H16*Inputs!$B$83-I16*Inputs!$B$82)/(Inputs!$B$82+Inputs!$B$83)) -> 5 | S16: =(I16+MIN(R16,Inputs!$B$36*H16))/Inputs!$B$83 -> 1.2 | T16: =IF(J16>Inputs!$B$79,"No advice: scan data stale",IF(AND(D16="OUT",F16="OUT"),"No advice: star dish out at both messes",IF(Q16<Inputs!$B$77+Inputs!$B$78,"Come on in (saving under "&TEXT(Inputs!$B$77+Inputs!$B$78,"0.0")&" min)",IF(S16>=1,"Come on in: Munch has no spare capacity","Munch is faster → save ~"&TEXT(Q16,"0")&" min")))) -> Come on in: Munch has no spare capacity
A17: Central star dish OUT, kitchen just called | B17: 3 | C17: 1 | D17: OUT | E17: 0 | F17: OK | G17: 0 | H17: 25 | I17: 6 | J17: 0.2 | K17: =IF(D17="OK","",IF((Inputs!$B$66*IF(E17<=Inputs!$B$19,1,MAX(0,(Inputs!$B$20-E17)/(Inputs!$B$20-Inputs!$B$19))))+((1-Inputs!$B$66)*IF(E17<Inputs!$B$18,1,0))=0,0,((Inputs!$B$66*IF(E17<=Inputs!$B$19,1,MAX(0,(Inputs!$B$20-E17)/(Inputs!$B$20-Inputs!$B$19))))*(IF(E17<Inputs!$B$20,(MAX(E17,Inputs!$B$19)+Inputs!$B$20)/2-E17,0))+((1-Inputs!$B$66)*IF(E17<Inputs!$B$18,1,0))*(Inputs!$B$18-E17))/((Inputs!$B$66*IF(E17<=Inputs!$B$19,1,MAX(0,(Inputs!$B$20-E17)/(Inputs!$B$20-Inputs!$B$19))))+((1-Inputs!$B$66)*IF(E17<Inputs!$B$18,1,0))))) -> 17.4 | L17: =IF(D17="OUT",MAX(0,K17-B17),IF(D17="LOW",IF(AND(B17>=MAX(0,Inputs!$B$67-E17),B17<K17),K17-B17,0),0)) -> 14.4 | M17: =IF(F17="OK","",IF((Inputs!$B$66*IF(G17<=Inputs!$B$19,1,MAX(0,(Inputs!$B$20-G17)/(Inputs!$B$20-Inputs!$B$19))))+((1-Inputs!$B$66)*IF(G17<Inputs!$B$18,1,0))=0,0,((Inputs!$B$66*IF(G17<=Inputs!$B$19,1,MAX(0,(Inputs!$B$20-G17)/(Inputs!$B$20-Inputs!$B$19))))*(IF(G17<Inputs!$B$20,(MAX(G17,Inputs!$B$19)+Inputs!$B$20)/2-G17,0))+((1-Inputs!$B$66)*IF(G17<Inputs!$B$18,1,0))*(Inputs!$B$18-G17))/((Inputs!$B$66*IF(G17<=Inputs!$B$19,1,MAX(0,(Inputs!$B$20-G17)/(Inputs!$B$20-Inputs!$B$19))))+((1-Inputs!$B$66)*IF(G17<Inputs!$B$18,1,0))))) | N17: =IF(F17="OUT",MAX(0,M17-(Inputs!$B$37+C17)),IF(F17="LOW",IF(AND((Inputs!$B$37+C17)>=MAX(0,Inputs!$B$67-G17),(Inputs!$B$37+C17)<M17),M17-(Inputs!$B$37+C17),0),0)) -> 0 | O17: =B17+L17 -> 17.4 | P17: =Inputs!$B$37+C17+N17 -> 1.5 | Q17: =O17-P17 -> 15.9 | R17: =MAX(0,(H17*Inputs!$B$83-I17*Inputs!$B$82)/(Inputs!$B$82+Inputs!$B$83)) -> 9.5 | S17: =(I17+MIN(R17,Inputs!$B$36*H17))/Inputs!$B$83 -> 0.775 | T17: =IF(J17>Inputs!$B$79,"No advice: scan data stale",IF(AND(D17="OUT",F17="OUT"),"No advice: star dish out at both messes",IF(Q17<Inputs!$B$77+Inputs!$B$78,"Come on in (saving under "&TEXT(Inputs!$B$77+Inputs!$B$78,"0.0")&" min)",IF(S17>=1,"Come on in: Munch has no spare capacity","Munch is faster → save ~"&TEXT(Q17,"0")&" min")))) -> Munch is faster → save ~16 min
A18: Central star dish OUT, called 16 min ago (late batch) | B18: 3 | C18: 1 | D18: OUT | E18: 16 | F18: OK | G18: 0 | H18: 25 | I18: 6 | J18: 0.2 | K18: =IF(D18="OK","",IF((Inputs!$B$66*IF(E18<=Inputs!$B$19,1,MAX(0,(Inputs!$B$20-E18)/(Inputs!$B$20-Inputs!$B$19))))+((1-Inputs!$B$66)*IF(E18<Inputs!$B$18,1,0))=0,0,((Inputs!$B$66*IF(E18<=Inputs!$B$19,1,MAX(0,(Inputs!$B$20-E18)/(Inputs!$B$20-Inputs!$B$19))))*(IF(E18<Inputs!$B$20,(MAX(E18,Inputs!$B$19)+Inputs!$B$20)/2-E18,0))+((1-Inputs!$B$66)*IF(E18<Inputs!$B$18,1,0))*(Inputs!$B$18-E18))/((Inputs!$B$66*IF(E18<=Inputs!$B$19,1,MAX(0,(Inputs!$B$20-E18)/(Inputs!$B$20-Inputs!$B$19))))+((1-Inputs!$B$66)*IF(E18<Inputs!$B$18,1,0))))) -> 14 | L18: =IF(D18="OUT",MAX(0,K18-B18),IF(D18="LOW",IF(AND(B18>=MAX(0,Inputs!$B$67-E18),B18<K18),K18-B18,0),0)) -> 11 | M18: =IF(F18="OK","",IF((Inputs!$B$66*IF(G18<=Inputs!$B$19,1,MAX(0,(Inputs!$B$20-G18)/(Inputs!$B$20-Inputs!$B$19))))+((1-Inputs!$B$66)*IF(G18<Inputs!$B$18,1,0))=0,0,((Inputs!$B$66*IF(G18<=Inputs!$B$19,1,MAX(0,(Inputs!$B$20-G18)/(Inputs!$B$20-Inputs!$B$19))))*(IF(G18<Inputs!$B$20,(MAX(G18,Inputs!$B$19)+Inputs!$B$20)/2-G18,0))+((1-Inputs!$B$66)*IF(G18<Inputs!$B$18,1,0))*(Inputs!$B$18-G18))/((Inputs!$B$66*IF(G18<=Inputs!$B$19,1,MAX(0,(Inputs!$B$20-G18)/(Inputs!$B$20-Inputs!$B$19))))+((1-Inputs!$B$66)*IF(G18<Inputs!$B$18,1,0))))) | N18: =IF(F18="OUT",MAX(0,M18-(Inputs!$B$37+C18)),IF(F18="LOW",IF(AND((Inputs!$B$37+C18)>=MAX(0,Inputs!$B$67-G18),(Inputs!$B$37+C18)<M18),M18-(Inputs!$B$37+C18),0),0)) -> 0 | O18: =B18+L18 -> 14 | P18: =Inputs!$B$37+C18+N18 -> 1.5 | Q18: =O18-P18 -> 12.5 | R18: =MAX(0,(H18*Inputs!$B$83-I18*Inputs!$B$82)/(Inputs!$B$82+Inputs!$B$83)) -> 9.5 | S18: =(I18+MIN(R18,Inputs!$B$36*H18))/Inputs!$B$83 -> 0.775 | T18: =IF(J18>Inputs!$B$79,"No advice: scan data stale",IF(AND(D18="OUT",F18="OUT"),"No advice: star dish out at both messes",IF(Q18<Inputs!$B$77+Inputs!$B$78,"Come on in (saving under "&TEXT(Inputs!$B$77+Inputs!$B$78,"0.0")&" min)",IF(S18>=1,"Come on in: Munch has no spare capacity","Munch is faster → save ~"&TEXT(Q18,"0")&" min")))) -> Munch is faster → save ~13 min
A19: Central running low, called 2 min ago | B19: 2 | C19: 1 | D19: LOW | E19: 2 | F19: OK | G19: 0 | H19: 25 | I19: 6 | J19: 0.2 | K19: =IF(D19="OK","",IF((Inputs!$B$66*IF(E19<=Inputs!$B$19,1,MAX(0,(Inputs!$B$20-E19)/(Inputs!$B$20-Inputs!$B$19))))+((1-Inputs!$B$66)*IF(E19<Inputs!$B$18,1,0))=0,0,((Inputs!$B$66*IF(E19<=Inputs!$B$19,1,MAX(0,(Inputs!$B$20-E19)/(Inputs!$B$20-Inputs!$B$19))))*(IF(E19<Inputs!$B$20,(MAX(E19,Inputs!$B$19)+Inputs!$B$20)/2-E19,0))+((1-Inputs!$B$66)*IF(E19<Inputs!$B$18,1,0))*(Inputs!$B$18-E19))/((Inputs!$B$66*IF(E19<=Inputs!$B$19,1,MAX(0,(Inputs!$B$20-E19)/(Inputs!$B$20-Inputs!$B$19))))+((1-Inputs!$B$66)*IF(E19<Inputs!$B$18,1,0))))) -> 15.4 | L19: =IF(D19="OUT",MAX(0,K19-B19),IF(D19="LOW",IF(AND(B19>=MAX(0,Inputs!$B$67-E19),B19<K19),K19-B19,0),0)) -> 0 | M19: =IF(F19="OK","",IF((Inputs!$B$66*IF(G19<=Inputs!$B$19,1,MAX(0,(Inputs!$B$20-G19)/(Inputs!$B$20-Inputs!$B$19))))+((1-Inputs!$B$66)*IF(G19<Inputs!$B$18,1,0))=0,0,((Inputs!$B$66*IF(G19<=Inputs!$B$19,1,MAX(0,(Inputs!$B$20-G19)/(Inputs!$B$20-Inputs!$B$19))))*(IF(G19<Inputs!$B$20,(MAX(G19,Inputs!$B$19)+Inputs!$B$20)/2-G19,0))+((1-Inputs!$B$66)*IF(G19<Inputs!$B$18,1,0))*(Inputs!$B$18-G19))/((Inputs!$B$66*IF(G19<=Inputs!$B$19,1,MAX(0,(Inputs!$B$20-G19)/(Inputs!$B$20-Inputs!$B$19))))+((1-Inputs!$B$66)*IF(G19<Inputs!$B$18,1,0))))) | N19: =IF(F19="OUT",MAX(0,M19-(Inputs!$B$37+C19)),IF(F19="LOW",IF(AND((Inputs!$B$37+C19)>=MAX(0,Inputs!$B$67-G19),(Inputs!$B$37+C19)<M19),M19-(Inputs!$B$37+C19),0),0)) -> 0 | O19: =B19+L19 -> 2 | P19: =Inputs!$B$37+C19+N19 -> 1.5 | Q19: =O19-P19 -> 0.5 | R19: =MAX(0,(H19*Inputs!$B$83-I19*Inputs!$B$82)/(Inputs!$B$82+Inputs!$B$83)) -> 9.5 | S19: =(I19+MIN(R19,Inputs!$B$36*H19))/Inputs!$B$83 -> 0.775 | T19: =IF(J19>Inputs!$B$79,"No advice: scan data stale",IF(AND(D19="OUT",F19="OUT"),"No advice: star dish out at both messes",IF(Q19<Inputs!$B$77+Inputs!$B$78,"Come on in (saving under "&TEXT(Inputs!$B$77+Inputs!$B$78,"0.0")&" min)",IF(S19>=1,"Come on in: Munch has no spare capacity","Munch is faster → save ~"&TEXT(Q19,"0")&" min")))) -> Come on in (saving under 2.5 min)
A20: Central running low, called 18 min ago, 4-min queue | B20: 4 | C20: 1 | D20: LOW | E20: 18 | F20: OK | G20: 0 | H20: 25 | I20: 6 | J20: 0.2 | K20: =IF(D20="OK","",IF((Inputs!$B$66*IF(E20<=Inputs!$B$19,1,MAX(0,(Inputs!$B$20-E20)/(Inputs!$B$20-Inputs!$B$19))))+((1-Inputs!$B$66)*IF(E20<Inputs!$B$18,1,0))=0,0,((Inputs!$B$66*IF(E20<=Inputs!$B$19,1,MAX(0,(Inputs!$B$20-E20)/(Inputs!$B$20-Inputs!$B$19))))*(IF(E20<Inputs!$B$20,(MAX(E20,Inputs!$B$19)+Inputs!$B$20)/2-E20,0))+((1-Inputs!$B$66)*IF(E20<Inputs!$B$18,1,0))*(Inputs!$B$18-E20))/((Inputs!$B$66*IF(E20<=Inputs!$B$19,1,MAX(0,(Inputs!$B$20-E20)/(Inputs!$B$20-Inputs!$B$19))))+((1-Inputs!$B$66)*IF(E20<Inputs!$B$18,1,0))))) -> 12 | L20: =IF(D20="OUT",MAX(0,K20-B20),IF(D20="LOW",IF(AND(B20>=MAX(0,Inputs!$B$67-E20),B20<K20),K20-B20,0),0)) -> 8 | M20: =IF(F20="OK","",IF((Inputs!$B$66*IF(G20<=Inputs!$B$19,1,MAX(0,(Inputs!$B$20-G20)/(Inputs!$B$20-Inputs!$B$19))))+((1-Inputs!$B$66)*IF(G20<Inputs!$B$18,1,0))=0,0,((Inputs!$B$66*IF(G20<=Inputs!$B$19,1,MAX(0,(Inputs!$B$20-G20)/(Inputs!$B$20-Inputs!$B$19))))*(IF(G20<Inputs!$B$20,(MAX(G20,Inputs!$B$19)+Inputs!$B$20)/2-G20,0))+((1-Inputs!$B$66)*IF(G20<Inputs!$B$18,1,0))*(Inputs!$B$18-G20))/((Inputs!$B$66*IF(G20<=Inputs!$B$19,1,MAX(0,(Inputs!$B$20-G20)/(Inputs!$B$20-Inputs!$B$19))))+((1-Inputs!$B$66)*IF(G20<Inputs!$B$18,1,0))))) | N20: =IF(F20="OUT",MAX(0,M20-(Inputs!$B$37+C20)),IF(F20="LOW",IF(AND((Inputs!$B$37+C20)>=MAX(0,Inputs!$B$67-G20),(Inputs!$B$37+C20)<M20),M20-(Inputs!$B$37+C20),0),0)) -> 0 | O20: =B20+L20 -> 12 | P20: =Inputs!$B$37+C20+N20 -> 1.5 | Q20: =O20-P20 -> 10.5 | R20: =MAX(0,(H20*Inputs!$B$83-I20*Inputs!$B$82)/(Inputs!$B$82+Inputs!$B$83)) -> 9.5 | S20: =(I20+MIN(R20,Inputs!$B$36*H20))/Inputs!$B$83 -> 0.775 | T20: =IF(J20>Inputs!$B$79,"No advice: scan data stale",IF(AND(D20="OUT",F20="OUT"),"No advice: star dish out at both messes",IF(Q20<Inputs!$B$77+Inputs!$B$78,"Come on in (saving under "&TEXT(Inputs!$B$77+Inputs!$B$78,"0.0")&" min)",IF(S20>=1,"Come on in: Munch has no spare capacity","Munch is faster → save ~"&TEXT(Q20,"0")&" min")))) -> Munch is faster → save ~11 min
A21: Central scanner silent for 5 minutes | B21: 9 | C21: 1 | D21: OK | E21: 0 | F21: OK | G21: 0 | H21: 29 | I21: 5 | J21: 5 | K21: =IF(D21="OK","",IF((Inputs!$B$66*IF(E21<=Inputs!$B$19,1,MAX(0,(Inputs!$B$20-E21)/(Inputs!$B$20-Inputs!$B$19))))+((1-Inputs!$B$66)*IF(E21<Inputs!$B$18,1,0))=0,0,((Inputs!$B$66*IF(E21<=Inputs!$B$19,1,MAX(0,(Inputs!$B$20-E21)/(Inputs!$B$20-Inputs!$B$19))))*(IF(E21<Inputs!$B$20,(MAX(E21,Inputs!$B$19)+Inputs!$B$20)/2-E21,0))+((1-Inputs!$B$66)*IF(E21<Inputs!$B$18,1,0))*(Inputs!$B$18-E21))/((Inputs!$B$66*IF(E21<=Inputs!$B$19,1,MAX(0,(Inputs!$B$20-E21)/(Inputs!$B$20-Inputs!$B$19))))+((1-Inputs!$B$66)*IF(E21<Inputs!$B$18,1,0))))) | L21: =IF(D21="OUT",MAX(0,K21-B21),IF(D21="LOW",IF(AND(B21>=MAX(0,Inputs!$B$67-E21),B21<K21),K21-B21,0),0)) -> 0 | M21: =IF(F21="OK","",IF((Inputs!$B$66*IF(G21<=Inputs!$B$19,1,MAX(0,(Inputs!$B$20-G21)/(Inputs!$B$20-Inputs!$B$19))))+((1-Inputs!$B$66)*IF(G21<Inputs!$B$18,1,0))=0,0,((Inputs!$B$66*IF(G21<=Inputs!$B$19,1,MAX(0,(Inputs!$B$20-G21)/(Inputs!$B$20-Inputs!$B$19))))*(IF(G21<Inputs!$B$20,(MAX(G21,Inputs!$B$19)+Inputs!$B$20)/2-G21,0))+((1-Inputs!$B$66)*IF(G21<Inputs!$B$18,1,0))*(Inputs!$B$18-G21))/((Inputs!$B$66*IF(G21<=Inputs!$B$19,1,MAX(0,(Inputs!$B$20-G21)/(Inputs!$B$20-Inputs!$B$19))))+((1-Inputs!$B$66)*IF(G21<Inputs!$B$18,1,0))))) | N21: =IF(F21="OUT",MAX(0,M21-(Inputs!$B$37+C21)),IF(F21="LOW",IF(AND((Inputs!$B$37+C21)>=MAX(0,Inputs!$B$67-G21),(Inputs!$B$37+C21)<M21),M21-(Inputs!$B$37+C21),0),0)) -> 0 | O21: =B21+L21 -> 9 | P21: =Inputs!$B$37+C21+N21 -> 1.5 | Q21: =O21-P21 -> 7.5 | R21: =MAX(0,(H21*Inputs!$B$83-I21*Inputs!$B$82)/(Inputs!$B$82+Inputs!$B$83)) -> 12 | S21: =(I21+MIN(R21,Inputs!$B$36*H21))/Inputs!$B$83 -> 0.85 | T21: =IF(J21>Inputs!$B$79,"No advice: scan data stale",IF(AND(D21="OUT",F21="OUT"),"No advice: star dish out at both messes",IF(Q21<Inputs!$B$77+Inputs!$B$78,"Come on in (saving under "&TEXT(Inputs!$B$77+Inputs!$B$78,"0.0")&" min)",IF(S21>=1,"Come on in: Munch has no spare capacity","Munch is faster → save ~"&TEXT(Q21,"0")&" min")))) -> No advice: scan data stale
A22: Star dish out at both messes | B22: 3 | C22: 3 | D22: OUT | E22: 5 | F22: OUT | G22: 5 | H22: 20 | I22: 10 | J22: 0.2 | K22: =IF(D22="OK","",IF((Inputs!$B$66*IF(E22<=Inputs!$B$19,1,MAX(0,(Inputs!$B$20-E22)/(Inputs!$B$20-Inputs!$B$19))))+((1-Inputs!$B$66)*IF(E22<Inputs!$B$18,1,0))=0,0,((Inputs!$B$66*IF(E22<=Inputs!$B$19,1,MAX(0,(Inputs!$B$20-E22)/(Inputs!$B$20-Inputs!$B$19))))*(IF(E22<Inputs!$B$20,(MAX(E22,Inputs!$B$19)+Inputs!$B$20)/2-E22,0))+((1-Inputs!$B$66)*IF(E22<Inputs!$B$18,1,0))*(Inputs!$B$18-E22))/((Inputs!$B$66*IF(E22<=Inputs!$B$19,1,MAX(0,(Inputs!$B$20-E22)/(Inputs!$B$20-Inputs!$B$19))))+((1-Inputs!$B$66)*IF(E22<Inputs!$B$18,1,0))))) -> 12.4 | L22: =IF(D22="OUT",MAX(0,K22-B22),IF(D22="LOW",IF(AND(B22>=MAX(0,Inputs!$B$67-E22),B22<K22),K22-B22,0),0)) -> 9.4 | M22: =IF(F22="OK","",IF((Inputs!$B$66*IF(G22<=Inputs!$B$19,1,MAX(0,(Inputs!$B$20-G22)/(Inputs!$B$20-Inputs!$B$19))))+((1-Inputs!$B$66)*IF(G22<Inputs!$B$18,1,0))=0,0,((Inputs!$B$66*IF(G22<=Inputs!$B$19,1,MAX(0,(Inputs!$B$20-G22)/(Inputs!$B$20-Inputs!$B$19))))*(IF(G22<Inputs!$B$20,(MAX(G22,Inputs!$B$19)+Inputs!$B$20)/2-G22,0))+((1-Inputs!$B$66)*IF(G22<Inputs!$B$18,1,0))*(Inputs!$B$18-G22))/((Inputs!$B$66*IF(G22<=Inputs!$B$19,1,MAX(0,(Inputs!$B$20-G22)/(Inputs!$B$20-Inputs!$B$19))))+((1-Inputs!$B$66)*IF(G22<Inputs!$B$18,1,0))))) -> 12.4 | N22: =IF(F22="OUT",MAX(0,M22-(Inputs!$B$37+C22)),IF(F22="LOW",IF(AND((Inputs!$B$37+C22)>=MAX(0,Inputs!$B$67-G22),(Inputs!$B$37+C22)<M22),M22-(Inputs!$B$37+C22),0),0)) -> 8.9 | O22: =B22+L22 -> 12.4 | P22: =Inputs!$B$37+C22+N22 -> 12.4 | Q22: =O22-P22 -> 0 | R22: =MAX(0,(H22*Inputs!$B$83-I22*Inputs!$B$82)/(Inputs!$B$82+Inputs!$B$83)) -> 5 | S22: =(I22+MIN(R22,Inputs!$B$36*H22))/Inputs!$B$83 -> 0.75 | T22: =IF(J22>Inputs!$B$79,"No advice: scan data stale",IF(AND(D22="OUT",F22="OUT"),"No advice: star dish out at both messes",IF(Q22<Inputs!$B$77+Inputs!$B$78,"Come on in (saving under "&TEXT(Inputs!$B$77+Inputs!$B$78,"0.0")&" min)",IF(S22>=1,"Come on in: Munch has no spare capacity","Munch is faster → save ~"&TEXT(Q22,"0")&" min")))) -> No advice: star dish out at both messes
A24: Blue cells are example situations: change them to test the rule. 'Refill due in' is the expected time still to wait given the minutes since the call and no refill yet: if 15 minutes have passed, the 10–14 minute 'already made' case is ruled out, so only the 30-minute case remains. 'Move /min to equalise' is how many students per minute would make both messes equally busy; the screen asks only that share (never everyone). The simulator applies the same rule through an equal-wait split (bisection), which also accounts for the walk and the queues the moved students create.

Sheet Scenarios
A1: Baseline vs intervention: four scenarios and stress tests (simulated, same students in every scenario)
A2: Simulated: python -m messq.scenarios, 20 lunches per row (seeds 0–19, the same students in every scenario); ± = 95% confidence interval
A4: 1. The four scenarios on a busy day (2,960 students, 60% follow the screens)
A5: Scenario | B5: Avg queue wait (min) | C5: ±95% CI | D5: 90th pct wait (min) | E5: Avg throughput, door to leaving (min) | F5: 90th pct throughput (min) | G5: Total incl. walk, decision to leaving (min) | H5: Central stations busy | I5: Munch stations busy | J5: Central peak load (30 min) | K5: Munch peak load (30 min) | L5: Run-outs per lunch | M5: Redirected students | N5: Followed the advice | O5: Unsuccessful redirects
A6: 1 Current system | B6: 4.31 | C6: ±0.63 | D6: 13.906 | E6: 32.94 | F6: 42.212 | G6: 32.94 | H6: 0.658 | I6: 0.165 | J6: 1.345 | K6: 0.347 | L6: 0.45 | M6: 0 | N6: – | O6: –
A7: 2 Queue information only | B7: 1.191 | C7: ±0.33 | D7: 3.126 | E7: 29.815 | F7: 32.38 | G7: 29.856 | H7: 0.591 | I7: 0.232 | J7: 1.04 | K7: 0.684 | L7: 0.45 | M7: 239 | N7: 0.61 | O7: 0.016
A8: 3 Queue + food (proposal) | B8: 0.798 | C8: ±0.10 | D8: 2.104 | E8: 29.423 | F8: 31.423 | G8: 29.467 | H8: 0.584 | I8: 0.237 | J8: 1.034 | K8: 0.688 | L8: 0.35 | M8: 260.95 | N8: 0.612 | O8: 0.015
A9: N Naive: go to the shorter queue | B9: 0.76 | C9: ±0.10 | D9: 2.008 | E9: 29.383 | F9: 31.355 | G9: 29.429 | H9: 0.583 | I9: 0.241 | J9: 1.035 | K9: 0.697 | L9: 0.5 | M9: 271.3 | N9: 0.611 | O9: 0.051
A11: Change vs today (proposal) | B11: =B8-B6 -> -3.512 | C11: =1-B8/B6 -> 0.81484919 | D11: =D8-D6 -> -11.802 | E11: =E8-E6 -> -3.517
A12: Definitions. Queue wait = minutes queueing for the scanner, a serving station and a seat (eating, the food line and disposal are activity time, not waiting). Throughput = door to leaving, all four stages. 90th percentile = the wait that 1 in 10 students exceed, per lunch, then averaged. Stations busy = share of 11:30–14:30 the serving stations were in use; peak load = arrivals ÷ capacity in the busiest 30 minutes (above 100% the queue grows). Unsuccessful redirect = a redirected student whose wait + walk exceeded the average wait of students who stayed at the mess they left and arrived within 2 minutes. Scenario 2 = the screens use queues but never hear about food; N = a naive 'go to the shorter queue' rule, shown for the herding point.
A15: 2. Stress tests: does the benefit persist? One input changed at a time
A16: Stress test | B16: 1 Current: wait | C16: 2 Queue only: wait | D16: 3 Proposal: wait | E16: 3 Proposal: ±95% CI | F16: 1 Current: p90 | G16: 3 Proposal: p90 | H16: Reduction (3 vs 1) | I16: 3 beats 2? | J16: Run-outs: 1 | K16: Run-outs: 3 | L16: Unsuccessful: 2 | M16: Unsuccessful: 3
A17: Demand +20% (3,552 students) | B17: 12.046 | C17: 2.243 | D17: 2.047 | E17: ±0.47 | F17: 32.16 | G17: 5.764 | H17: =1-D17/B17 -> 0.83006807 | I17: =IF(D17+0.466<C17-0.392,"Yes",IF(D17<C17,"Tie (within noise)","No")) -> Tie (within noise) | J17: 1 | K17: 1.05 | L17: 0.082 | M17: 0.08
A18: Students rush at the bell (lag 15 +/- 10 min, not 20 +/- 20) | B18: 8.524 | C18: 2.052 | D18: 1.694 | E18: ±0.14 | F18: 22.574 | G18: 4.428 | H18: =1-D18/B18 -> 0.80126701 | I18: =IF(D18+0.139<C18-0.266,"Yes",IF(D18<C18,"Tie (within noise)","No")) -> Tie (within noise) | J18: 0.55 | K18: 0.75 | L18: 0.02 | M18: 0.029
A19: Heavy lab day: 70% of MIT eat 13:00-14:00 | B19: 5.955 | C19: 1.441 | D19: 1.359 | E19: ±0.36 | F19: 19.684 | G19: 4.567 | H19: =1-D19/B19 -> 0.77178841 | I19: =IF(D19+0.359<C19-0.242,"Yes",IF(D19<C19,"Tie (within noise)","No")) -> Tie (within noise) | J19: 0.7 | K19: 1.15 | L19: 0.131 | M19: 0.063
A20: No MIT labs: all MIT eat 12:00-13:00 | B20: 8.778 | C20: 1.203 | D20: 0.953 | E20: ±0.17 | F20: 17.315 | G20: 2.531 | H20: =1-D20/B20 -> 0.89143313 | I20: =IF(D20+0.17<C20-0.298,"Yes",IF(D20<C20,"Tie (within noise)","No")) -> Tie (within noise) | J20: 0.5 | K20: 0.75 | L20: 0.064 | M20: 0.04
A21: Stagger: SMI lunch 15 min earlier (11:45-12:45) | B21: 3.275 | C21: 0.694 | D21: 0.56 | E21: ±0.07 | F21: 12.306 | G21: 1.903 | H21: =1-D21/B21 -> 0.82900763 | I21: =IF(D21+0.069<C21-0.131,"Yes",IF(D21<C21,"Tie (within noise)","No")) -> Tie (within noise) | J21: 0.5 | K21: 0.35 | L21: 0.008 | M21: 0.065
A22: Stagger: TAPMI lunch 15 min later (13:20-14:15) | B22: 1.654 | C22: 0.851 | D22: 0.548 | E22: ±0.06 | F22: 5.023 | G22: 1.467 | H22: =1-D22/B22 -> 0.66868198 | I22: =IF(D22+0.062<C22-0.176,"Yes",IF(D22<C22,"Tie (within noise)","No")) -> Yes | J22: 0.5 | K22: 0.55 | L22: 0.041 | M22: 0.072
A23: One bell curve (old assumption: peak 13:05, spread 35) | B23: 5.757 | C23: 1.571 | D23: 0.878 | E23: ±0.23 | F23: 14.914 | G23: 2.54 | H23: =1-D23/B23 -> 0.84749001 | I23: =IF(D23+0.228<C23-0.392,"Yes",IF(D23<C23,"Tie (within noise)","No")) -> Yes | J23: 0.55 | K23: 0.9 | L23: 0.073 | M23: 0.093
A24: Only 30% follow the screens | B24: 4.31 | C24: 1.176 | D24: 1.104 | E24: ±0.13 | F24: 13.906 | G24: 3.014 | H24: =1-D24/B24 -> 0.74385151 | I24: =IF(D24+0.134<C24-0.293,"Yes",IF(D24<C24,"Tie (within noise)","No")) -> Tie (within noise) | J24: 0.45 | K24: 0.65 | L24: 0 | M24: 0.001
A25: Everyone follows the screens | B25: 4.31 | C25: 1.159 | D25: 0.756 | E25: ±0.10 | F25: 13.906 | G25: 2.004 | H25: =1-D25/B25 -> 0.82459397 | I25: =IF(D25+0.103<C25-0.335,"Yes",IF(D25<C25,"Tie (within noise)","No")) -> Tie (within noise) | J25: 0.45 | K25: 0.75 | L25: 0.034 | M25: 0.071
A26: Slower serving: 8 students/min per station | B26: 12.883 | C26: 1.826 | D26: 1.857 | E26: ±0.16 | F26: 33.864 | G26: 4.945 | H26: =1-D26/B26 -> 0.85585656 | I26: =IF(D26+0.162<C26-0.155,"Yes",IF(D26<C26,"Tie (within noise)","No")) -> No | J26: 0.05 | K26: 0.35 | L26: 0.065 | M26: 0.055
A27: Faster serving: 12 students/min per station | B27: 1.793 | C27: 1.031 | D27: 0.557 | E27: ±0.06 | F27: 6.807 | G27: 1.73 | H27: =1-D27/B27 -> 0.68934746 | I27: =IF(D27+0.056<C27-0.375,"Yes",IF(D27<C27,"Tie (within noise)","No")) -> Yes | J27: 0.5 | K27: 0.45 | L27: 0.007 | M27: 0.017
A28: More stock-outs: next batch never ready | B28: 6.524 | C28: 2.558 | D28: 0.938 | E28: ±0.12 | F28: 20.512 | G28: 2.312 | H28: =1-D28/B28 -> 0.85622318 | I28: =IF(D28+0.122<C28-0.236,"Yes",IF(D28<C28,"Tie (within noise)","No")) -> Yes | J28: 2 | K28: 2.2 | L28: 0.003 | M28: 0.054
A29: No stock-outs: next batch always ready | B29: 3.611 | C29: 0.78 | D29: 0.762 | E29: ±0.09 | F29: 11.778 | G29: 2.102 | H29: =1-D29/B29 -> 0.78897812 | I29: =IF(D29+0.092<C29-0.09,"Yes",IF(D29<C29,"Tie (within noise)","No")) -> Tie (within noise) | J29: 0 | K29: 0 | L29: 0.012 | M29: 0.013
A30: Slower eating: 17-21 min | B30: 4.31 | C30: 1.191 | D30: 0.798 | E30: ±0.10 | F30: 13.906 | G30: 2.104 | H30: =1-D30/B30 -> 0.81484919 | I30: =IF(D30+0.101<C30-0.328,"Yes",IF(D30<C30,"Tie (within noise)","No")) -> Tie (within noise) | J30: 0.45 | K30: 0.35 | L30: 0.016 | M30: 0.015
A31: Smallest reduction across all stress tests | H31: =MIN(H17:H30) -> 0.66868198
A33: Reading it: the proposal cuts the average wait in every stress test and beats or ties 'queue information only' in every one. With no stock-outs the food signal adds nothing (2 and 3 converge); with more stock-outs it matters most. The timetable matters as much as any operational input: the stagger rows show what moving one department's lunch by 15 minutes does with no screens at all. One limitation: everything here rests on the assumed 10 students/min per station, the rough department sizes and the calibrated arrival lag until the biometric logs and a stopwatch replace them (Data Collection).

Sheet Reconciliation
A1: Why the spreadsheet (S15) and the simulator give different numbers
A2: Start the simulator with the spreadsheet's simplifications, then add one real-world feature at a time. Same students in every row.
A4: Model | B4: Without screens: avg wait | C4: With screens: avg wait | D4: Without: 90th pct | E4: With: 90th pct | F4: What changes
A5: S15 spreadsheet (analytic: M/M/c + fluid queue per 10-min slot) | B5: ='S15 Queuing'!$I$51 -> 3.5694685 | C5: ='S15 Queuing'!$J$51 -> 0.57398734 | F5: Deterministic slots; 'with screens' moves the complying share toward equal utilisation with perfect knowledge, every slot
A6: Simulator 1 Spreadsheet-like: exponential serving, no run-outs, no scanner or seat limits | B6: 3.77 | C6: 0.84 | D6: 11.6 | E6: 2.2 | F6: Same assumptions as S15 except that arrivals and service are random and routing uses live estimates (with a delay and the 2-min rule). Without screens it matches S15; with screens it is worse than S15's perfect routing
A7: Simulator 2 + realistic serving variability (cv 0.6) | B7: 3.5 | C7: 0.66 | D7: 11.4 | E7: 1.9 | F7: Real serving is more regular than exponential: slightly shorter queues
A8: Simulator 3 + one face scanner per mess (2 s each) | B8: 3.62 | C8: 0.75 | D8: 11.6 | E8: 2 | F8: A single 2 s scanner rarely limits flow: almost no change
A9: Simulator 4 + seat limits | B9: 3.62 | C9: 0.75 | D9: 11.6 | E9: 2 | F9: Seats rarely fill (eating 14–18 min): no change
A10: Simulator 5 + food run-outs and refills (full model) | B10: 4.31 | C10: 0.8 | D10: 13.9 | E10: 2.1 | F10: Run-outs stop service until the refill: today's waits rise; the screens absorb most of it
A11: LP Student Flow: fluid optimum (perfect foresight, no randomness) | B11: ='LP Student Flow'!$B$44 -> 3.0698956 | C11: ='LP Student Flow'!$B$43 -> 0.04409895 | F11: A lower bound: the best any routing could do in a smooth-flow world
A12: Gap without screens: spreadsheet vs spreadsheet-like simulator (should be small) | B12: =B6-B5 -> 0.20053154
A13: Gap as a share of the simulator's figure (the check allows 15%) | B13: =B12/B6 -> 0.053191391
A14: Conclusion: the two models agree when they make the same assumptions (first two rows, without screens), within 15%. The spreadsheet is a little higher because it adds the steady-state M/M/c wait in every 10-minute slot; near 100% busy a slot is too short for the queue to reach steady state, and the department surge passes through several such slots. The headline numbers come from the full simulator (last simulator row) because it includes the things the spreadsheet cannot: randomness, live estimation, the scanner, seats and run-outs. The spreadsheet's 'with screens' figure is optimistic because it routes with perfect knowledge; the LP is the theoretical best case. 20 lunches per simulator row.

Sheet Simulation Method
A1: How the simulator works (messq/simulation.py, messq/engine.py)
A2: Reproduce every number: python -m messq.scenarios [--payoff | --reconcile] --runs 20
A4: Component | B4: How it is modelled | C4: Parameters (Inputs / config) | D4: Status
A5: Time | B5: Discrete steps of 5 seconds (the scanner poll interval), 11:30–14:30; the run continues until everyone has food | C5: step_s = 5 | D5: Design
A6: Arrivals | B6: Random (Poisson) arrivals; the rate is the department lunch breaks added up (Arrival Curve tab): each department starts arriving when its break starts, lag Normal(20, 20) min cut off at the end of the break; total = students per lunch | C6: students, department breaks, lag_m, lag_sd | D6: Total and timetable measured; sizes rough; lag calibrated
A7: Where students head | B7: Each student heads to Central with probability h (habit), else Munch | C7: habit share h | D7: Assumed
A8: Advice at the door | B8: The screen at the mess they reach asks a share of students to walk to the other mess (none in scenario 1) | C8: Decision Rule; min saving 2 min | D8: Policy
A9: Compliance | B9: Each advised student follows with probability κ; followers walk 30 s to the other door | C9: comply κ, walk | D9: Assumed
A10: Stage 1: entrance | B10: FCFS queue for the face scanner (2 s each, cv 0.3), then collecting a plate (uniform 28–43 s; 30–45 s with the scan). The scan time is what the biometric log records | C10: scan_s, plate_lo/hi | D10: Assumed
A11: Stage 2: food | B11: FCFS queue for 2 serving stations; service time gamma with mean 6 s and cv 0.6 (M/G/c); then the rest of food collection (uniform 54–114 s; 1–2 min in all) | C11: mu, line_lo/hi, service_cv | D11: Stations measured; times assumed
A12: Food stock | B12: Star dish in batches (Central 900, Munch 500). At the call level the mess calls the kitchen; refill arrives in 10–14 min (70%) or 30 min. At zero stock nobody is served until the refill | C12: food_batch, refill trigger, ready_p, lead times | D12: Lead times measured; batches assumed
A13: Manager taps | B13: 'Running low' at the call, 'out' at zero, 'refilled' on arrival; each tap made 90% of the time (forgotten taps expire) | C13: staff_signal_prob 0.9 | D13: Assumed
A14: Stage 3: eating | B14: Take a seat if free (900 / 492), else wait; eat for uniform 14–18 min, then stay at the table ~9 min (seat held ~25 min) | C14: seats, eat_lo/hi, linger | D14: Seats measured; eating group estimate
A15: Stage 4: disposal | B15: Dispose of plate and leftovers, uniform 1–2 min (the seat is already free) | C15: disp_lo/hi | D15: Group estimate
... A20: Runs | B20: 20 lunches per scenario, seeds 0–19; the same seeds in every scenario (paired comparison). ± = 1.96 × sd ÷ √20 across lunches | C20: --runs | D20: Design
A22: Validation so far: the simulated normal visit and peak throughput fall in the group's 17–35 min range (Checks), the no-screen 90th percentile wait is close to the ~15 min observed, and the spreadsheet-like simulator reproduces S15 without screens (Reconciliation). Not yet validated: the arrival curve, the habit split and the service rate (Data Collection).

Sheet Data Collection
A1: Stage 2: collect the minimum data to prove (or disprove) the bottleneck
A2: Fill the blue grid from logs or a manual pilot at BOTH messes over the same lunch. The diagnosis below updates itself.
A4: Data | B4: How to capture it | C4: Why it matters | D4: Who / when
A5: Arrivals per 10 min | B5: Biometric logs (aggregated), or a tally counter at each door | C5: Demand distribution and the habit split | D5: IT logs / 2 volunteers per mess
A6: Queue length | B6: Count people queueing at the stations every 10 min | C6: Validates congestion | D6: 1 volunteer per mess
A7: Sampled waiting time | B7: Note time joining the queue and reaching the station for ~20 students per hour | C7: Measures actual delay | D7: 1 volunteer per mess
A8: Service rate | B8: Count plates completed per station per minute while there is a queue | C8: Usable capacity (μ) | D8: Stopwatch, 3 × 5 min at peak
A9: Food availability | B9: Time-stamped 'running low' / 'out' / 'refilled' taps (or notes) | C9: Tests whether food drives routing | D9: Mess manager
A10: Replenishment time | B10: Time of the call and time the refill arrives | C10: Lead time (30 vs 10–14 min) | D10: Mess manager
A11: Destination preference | B11: Short neutral survey at the door: 'why this mess today?' | C11: Tests the bias hypotheses (S4) | D11: Survey, 50+ students
A12: Measure arrivals and service capacity separately: a mess can be quiet because demand is low, because it cannot serve faster, or because its food is less attractive. Each points to a different intervention. If live logs are not available, run a structured manual pilot and label its limits.
A15: Slot | B15: Central: arrivals | C15: Central: served | D15: Central: queue at slot start | E15: Central: sampled avg wait (min) | F15: Munch: arrivals | G15: Munch: served | H15: Munch: queue at slot start | I15: Munch: sampled avg wait (min) | J15: Central share of arrivals | K15: Central ρ (assumed μ) | L15: Munch ρ (assumed μ)
A16: Example (not counted) | B16: 240 | C16: 200 | D16: 35 | E16: 6.5 | F16: 40 | G16: 40 | H16: 0 | I16: 0.3
A17: 11:30 | J17: =IF(COUNT(B17,F17)<2,"",B17/MAX(1,B17+F17)) | K17: =IF(COUNT(B17)=0,"",B17/10/Inputs!$B$82) | L17: =IF(COUNT(F17)=0,"",F17/10/Inputs!$B$83)
A18: 11:40 | J18: =IF(COUNT(B18,F18)<2,"",B18/MAX(1,B18+F18)) | K18: =IF(COUNT(B18)=0,"",B18/10/Inputs!$B$82) | L18: =IF(COUNT(F18)=0,"",F18/10/Inputs!$B$83)
A19: 11:50 | J19: =IF(COUNT(B19,F19)<2,"",B19/MAX(1,B19+F19)) | K19: =IF(COUNT(B19)=0,"",B19/10/Inputs!$B$82) | L19: =IF(COUNT(F19)=0,"",F19/10/Inputs!$B$83)
A20: 12:00 | J20: =IF(COUNT(B20,F20)<2,"",B20/MAX(1,B20+F20)) | K20: =IF(COUNT(B20)=0,"",B20/10/Inputs!$B$82) | L20: =IF(COUNT(F20)=0,"",F20/10/Inputs!$B$83)
A21: 12:10 | J21: =IF(COUNT(B21,F21)<2,"",B21/MAX(1,B21+F21)) | K21: =IF(COUNT(B21)=0,"",B21/10/Inputs!$B$82) | L21: =IF(COUNT(F21)=0,"",F21/10/Inputs!$B$83)
A22: 12:20 | J22: =IF(COUNT(B22,F22)<2,"",B22/MAX(1,B22+F22)) | K22: =IF(COUNT(B22)=0,"",B22/10/Inputs!$B$82) | L22: =IF(COUNT(F22)=0,"",F22/10/Inputs!$B$83)
A23: 12:30 | J23: =IF(COUNT(B23,F23)<2,"",B23/MAX(1,B23+F23)) | K23: =IF(COUNT(B23)=0,"",B23/10/Inputs!$B$82) | L23: =IF(COUNT(F23)=0,"",F23/10/Inputs!$B$83)
A24: 12:40 | J24: =IF(COUNT(B24,F24)<2,"",B24/MAX(1,B24+F24)) | K24: =IF(COUNT(B24)=0,"",B24/10/Inputs!$B$82) | L24: =IF(COUNT(F24)=0,"",F24/10/Inputs!$B$83)
A25: 12:50 | J25: =IF(COUNT(B25,F25)<2,"",B25/MAX(1,B25+F25)) | K25: =IF(COUNT(B25)=0,"",B25/10/Inputs!$B$82) | L25: =IF(COUNT(F25)=0,"",F25/10/Inputs!$B$83)
A26: 13:00 | J26: =IF(COUNT(B26,F26)<2,"",B26/MAX(1,B26+F26)) | K26: =IF(COUNT(B26)=0,"",B26/10/Inputs!$B$82) | L26: =IF(COUNT(F26)=0,"",F26/10/Inputs!$B$83)
A27: 13:10 | J27: =IF(COUNT(B27,F27)<2,"",B27/MAX(1,B27+F27)) | K27: =IF(COUNT(B27)=0,"",B27/10/Inputs!$B$82) | L27: =IF(COUNT(F27)=0,"",F27/10/Inputs!$B$83)
A28: 13:20 | J28: =IF(COUNT(B28,F28)<2,"",B28/MAX(1,B28+F28)) | K28: =IF(COUNT(B28)=0,"",B28/10/Inputs!$B$82) | L28: =IF(COUNT(F28)=0,"",F28/10/Inputs!$B$83)
... A34: 14:20 | J34: =IF(COUNT(B34,F34)<2,"",B34/MAX(1,B34+F34)) | K34: =IF(COUNT(B34)=0,"",B34/10/Inputs!$B$82) | L34: =IF(COUNT(F34)=0,"",F34/10/Inputs!$B$83)
A36: Automatic diagnosis (blank until data are entered)
A37: Slots with data | G37: =COUNT(B17:B34) -> 0
A38: Central share of all arrivals (measured habit split) | G38: =IF(B37=0,"",SUM(B17:B34)/MAX(1,SUM(B17:B34)+SUM(F17:F34)))
A39: Central's share of the seats (900 ÷ 1,400) for comparison | G39: =Inputs!$B$9/(Inputs!$B$9+Inputs!$B$10) -> 0.64655172
A40: Peak Central ρ (busiest slot) | G40: =IF(B37=0,"",MAX(K17:K34))
A41: Peak Munch ρ in the same lunch | G41: =IF(B37=0,"",MAX(L17:L34))
A42: Measured service rate at Central (served ÷ stations ÷ 10, busiest slot with a queue) | G42: =IF(B37=0,"",SUMPRODUCT(MAX((D17:D34>0)*C17:C34))/Inputs!$B$11/10)
A43: Is Central disproportionately busy? | G43: =IF(B37=0,"",IF(AND(B38>B39,B40>=Inputs!$B$76),"Yes: more than its seat share and above target utilisation","No: revise the diagnosis"))
A44: Does Munch have usable spare capacity at Central's peak? | G44: =IF(B37=0,"",IF(B41<0.7,"Yes: below 70% busy","No: redistribution would just move the queue"))
A46: If the answers are 'No', don't force the original hypothesis: update the Inputs (habit split, service rate) and let the scenarios show what the evidence implies. Changing course on evidence is a strength in an MDS project.

Sheet Checks
A1: Validation checks: every one should say OK
A2: Recalculate (F9) after changing inputs; a CHECK means something needs a look
A4: Check | B4: Value | C4: Result | D4: What it tests
A5: Every numeric input is a number (no text such as '14-15') | B5: =COUNT(Inputs!$B$5:$B$79) -> 67 | C5: =IF(B5=67,"OK","CHECK") -> OK | D5: 67 numeric inputs expected
A6: No formula errors in S15 Queuing | B6: =SUMPRODUCT(--ISERROR('S15 Queuing'!$A$30:$AN$47)) -> 0 | C6: =IF(B6=0,"OK","CHECK") -> OK | D6: The earlier errors came from a text input ('14-15')
A7: No formula errors in LP Student Flow | B7: =SUMPRODUCT(--ISERROR('LP Student Flow'!$A$19:$N$40)) -> 0 | C7: =IF(B7=0,"OK","CHECK") -> OK
A8: No formula errors in Decision Rule | B8: =SUMPRODUCT(--ISERROR('Decision Rule'!$A$14:$T$22)) -> 0 | C8: =IF(B8=0,"OK","CHECK") -> OK
A9: Arrival curve shares sum to 100% | B9: =SUM('S15 Queuing'!$B$30:$B$47) -> 1 | C9: =IF(ABS(B9-1)<0.0001,"OK","CHECK") -> OK | D9: Demand balance
A10: S15 arrivals add up to students per lunch | B10: =SUM('S15 Queuing'!$C$30:$C$47)-Inputs!$B$6 -> 0 | C10: =IF(ABS(B10)<0.5,"OK","CHECK") -> OK | D10: Demand balance
A11: Habit share and compliance are between 0 and 1 | B11: =AND(Inputs!$B$35>=0,Inputs!$B$35<=1,Inputs!$B$36>=0,Inputs!$B$36<=1) -> 1 | C11: =IF(B11,"OK","CHECK") -> OK
A12: Kinds of day sum to 100% | B12: =Inputs!$B$72+Inputs!$B$73+Inputs!$B$74 -> 1 | C12: =IF(ABS(B12-1)<0.0001,"OK","CHECK") -> OK | D12: Payoff matrix probabilities
A13: LP: every constraint holds (smallest slack ≥ 0) | B13: ='LP Student Flow'!$B$49 -> -4.5490293e-07 | C13: =IF(B13>=-0.01,"OK","CHECK (re-run Solver)") -> OK | D13: Fluid queue recursions
A14: LP: redirects within compliance limits | B14: ='LP Student Flow'!$B$50 -> Yes | C14: =IF(B14="Yes","OK","CHECK (re-run Solver)") -> OK | D14: 0 ≤ y ≤ κ·h·D
A15: LP: Munch's food constraint holds | B15: ='LP Student Flow'!$B$48 -> Yes | C15: =IF(B15="Yes","OK","CHECK (re-run Solver)") -> OK | D15: Food as the operational constraint
A16: LP improves on today | B16: ='LP Student Flow'!$B$43-'LP Student Flow'!$B$44 -> -3.0257966 | C16: =IF(B16<0,"OK","CHECK") -> OK
A17: Response: a faster serving rate lowers the M/M/c wait (λ = 17/min, c = 2) | B17: =IF(17/(2*(1.1*Inputs!$B$26))<1,((17/(1.1*Inputs!$B$26))^2/2*2/(2-17/(1.1*Inputs!$B$26)))/(1+17/(1.1*Inputs!$B$26)+(17/(1.1*Inputs!$B$26))^2/2*2/(2-17/(1.1*Inputs!$B$26)))/(2*(1.1*Inputs!$B$26)-17),99)-IF(17/(2*Inputs!$B$26)<1,((17/Inputs!$B$26)^2/2*2/(2-17/Inputs!$B$26))/(1+17/Inputs!$B$26+(17/Inputs!$B$26)^2/2*2/(2-17/Inputs!$B$26))/(2*Inputs!$B$26-17),99) -> -0.12562843 | C17: =IF(B17<0,"OK","CHECK") -> OK | D17: Outputs move in the right direction
A18: With screens, Munch's peak utilisation stays below 100% (S15) | B18: ='S15 Queuing'!$H$53 -> 0.71352531 | C18: =IF(B18<1,"OK","CHECK") -> OK | D18: Redistribution must not overload Munch
A19: Throughput with no queues is within the measured range | B19: =Inputs!$B$90 -> 28.625 | C19: =IF(AND(B19>=Inputs!$B$16-1,B19<=Inputs!$B$17),"OK","CHECK") -> OK | D19: 17–35 min (group); quiet visit ~18
A20: Simulated throughput for students who met no queue (today) | B20: 28.8 | C20: =IF(AND(B20>=Inputs!$B$16-1,B20<=Inputs!$B$17),"OK","CHECK") -> OK | D20: Simulator calibration
A21: Simulated throughput at the peak (today) | B21: 34.6 | C21: =IF(AND(B21>=Inputs!$B$16,B21<=Inputs!$B$17+3),"OK","CHECK") -> OK | D21: Group: up to ~25 min in a surge
