Workbook

Sheet Start Here
A1: MDS decision workbook — Mess queue and allocation project (Group WGB3)
A2: Every Management Decision Science course topic applied to the Chefs Touch lunch problem (Central CT and Munch Mess, lunch 11:30–14:30).
A4: How to use
A5: 1. Change only BLUE cells. Black cells are formulas; GREEN cells pull values from another tab.
A6: 2. YELLOW-filled cells are assumed or illustrative. Replace them with measurements when you have them (biometric logs, stopwatch, CT data).
A7: 3. Start with the Inputs tab — most tabs read from it, so one change updates the whole workbook.
A8: 4. Green-filled cells are the key results of each tab.
A10: Status tags used
A11: Tag | B11: Meaning | C11: Example
A12: Measured | B12: From our field work, the Phase 1 deck or the group | C12: 2,960 students (= plates); seats 900 / 500; 2 stations + 1 scanner per mess; ~18 min visit
A13: Assumed | B13: A placeholder until measured | C13: 85% go to Central by habit; 10 students/min per serving station
A14: Illustrative | B14: Made-up numbers to demonstrate a method | C14: Probabilities, ₹ values in the decision tree, AHP judgements
A15: Simulated | B15: Output of our prototype's simulator | C15: Average wait 7.1 → 0.8 min
A17: Tabs and course sessions
A18: Tab | B18: Session(s) | C18: What it does
A19: Inputs | B19: — | C19: All shared numbers, with status and source
A20: S2-3 Problem & Root Cause | B20: 2–3 | C20: Nature of the decision; problem statement; 5 Whys; fishbone; issue tree
A21: S4 Biases & Ethics | B21: 4 | C21: Decision biases in the mess problem and how we counter them; ethics checklist (DPDP)
A22: S5-6 Priority Matrix | B22: 5–6 | C22: ABC/XYZ menu matrix; impact–effort matrix of interventions; decision dilemmas
A23: S7 Payoff Matrix | B23: 7 | C23: With vs without the system across normal / busy / surge days, in minutes saved: maximax, maximin, minimax regret, Hurwicz, Laplace, EMV, EVPI
A24: S7 Decision Tree | B24: 7 | C24: Pre-stage a batch or wait and react: EMV, break-even probability, sensitivity
A25: S10-11 LP Allocation | B25: 10–11 | C25: LP formulation, constraints, graphical method (corner points), Solver/simplex
A26: S12-14 IP Staffing | B26: 12–14 | C26: Integer serving stations per slot, with vs without screens; branch-and-bound illustration
A27: S15 Queuing | B27: 15 | C27: Lecture check (Hatti Kaapi), utilisation curve, M/M/c by 10-min bin with overload, without vs with screens, Little's Law
A28: S16-17 AHP | B28: 16–17 | C28: Pairwise comparisons, weights, consistency ratio, ranking of alternatives
A29: S16-17 BWM | B29: 16–17 | C29: Best–Worst Method weights and consistency; comparison with AHP
... A32: Simulation Results | B32: — | C32: Prototype simulator results used as anchors
A34: Only the queuing tab's arrival curve and the decision models' costs and probabilities are placeholders. Once the biometric logs arrive, paste arrivals per 10 minutes into S15 Queuing column B, and the share of normal / busy / surge days into S7 Payoff Matrix row 14.

Sheet Inputs
A1: Inputs: every number the workbook uses
A2: Change BLUE cells only. Yellow = assumed or illustrative: replace with measured data when available.
A4: Parameter | B4: Value | C4: Unit | D4: Status | E4: Source / notes
A5: MEASURED (from Phase 1 field work / the group)
A6: Students per lunch at Central CT + Munch (= plates served) | B6: 2960 | C6: students | D6: Measured | E6: Phase 1 deck: ~2,960 plates; one plate per student
A7: Lunch opens | B7: 11:30 | C7: time | D7: Measured | E7: Mess timings 11:30–14:30
A8: Lunch window length | B8: 180 | C8: minutes | D8: Measured | E8: 11:30–14:30
A9: Seats: Central CT | B9: 900 | C9: seats | D9: Measured | E9: Group measurement
A10: Seats: Munch Mess | B10: 500 | C10: seats | D10: Measured | E10: Group measurement
A11: Serving stations: Central CT | B11: 2 | C11: stations | D11: Measured | E11: Group observation
A12: Serving stations: Munch Mess | B12: 2 | C12: stations | D12: Measured | E12: Group observation
A13: Face scanners at the entrance: Central CT | B13: 1 | C13: scanners | D13: Measured | E13: Group observation
A14: Face scanners at the entrance: Munch Mess | B14: 1 | C14: scanners | D14: Measured | E14: Group observation
A15: Normal visit, scan to leaving | B15: 18 | C15: minutes | D15: Measured | E15: Group observation; normal day. Surges add queue time
A16: Restock after a 'running low' call: kitchen makes it and sends it (total) | B16: 30 | C16: minutes | D16: Measured | E16: Group: the 30 min starts when the mess calls the kitchen
A17: Restock when the food is already made: sending only (low) | B17: 10 | C17: minutes | D17: Measured | E17: Group: 10–14 min
A18: Restock when the food is already made: sending only (high) | B18: 14 | C18: minutes | D18: Measured | E18: Group: 10–14 min
A19: Chance the next batch is already made when the mess calls | B19: 0.5 | C19: share | D19: Assumed | E19: Simulator default; ask CT how often food is cooked ahead
A20: Delay faced by students (observed) | B20: 15 | C20: minutes | D20: Measured | E20: Phase 1 deck: ~15 min
A21: ASSUMED (replace with measurements)
A22: Share who go to Central CT by habit | B22: 0.85 | C22: fraction | D22: Assumed | E22: Pure assumption (group's estimate). A day of biometric logs without screens will measure it
A23: Service rate per serving station | B23: 10 | C23: students/min | D23: Assumed | E23: ≈6 s per student. Must be about this fast: 2 stations serve ~2,500 Central students in 3 hours. Stopwatch it
A24: Time for one face scan | B24: 2 | C24: seconds | D24: Assumed | E24: Step up, recognise, move on. Stopwatch it
A25: Eating time after being served | B25: 17 | C25: minutes | D25: Derived | E25: Calibrated so a normal visit ≈ 18 min (simulator)
A26: Walk between the two mess doors | B26: 0.5 | C26: minutes | D26: Assumed | E26: 30 s; time it
A27: Share of students who follow the screen | B27: 0.6 | C27: fraction | D27: Assumed | E27: Pilot will measure
A28: POLICY SETTINGS (our choice)
A29: Target maximum utilisation per station | B29: 0.85 | C29: fraction | D29: Policy | E29: Above ~85% waits rise steeply (see S15 Queuing)
A30: Minimum saving before suggesting a switch | B30: 2 | C30: minutes | D30: Policy | E30: Prototype setting
A31: MONEY VALUES — used ONLY in 'S7 Decision Tree' and 'S12-14 IP Staffing' (see the note below)
A32: Value of one student-minute of waiting | B32: 5 | C32: ₹ per student-min | D32: Illustrative | E32: Used in S7 Decision Tree to compare students' time with wasted food. A value judgement, not a price
A33: Cost of one portion wasted | B33: 30 | C33: ₹ per portion | D33: Illustrative | E33: Used in S7 Decision Tree. Ask CT for food cost per portion
A34: Staff cost per staff-hour | B34: 150 | C34: ₹ per hour | D34: Illustrative | E34: Used in S12-14 IP Staffing. Ask CT
A35: Staff needed per serving station | B35: 2 | C35: staff | D35: Assumed | E35: Used in S12-14 IP Staffing. Observe
A36: Derived capacity
A37: Capacity: Central CT (lines × service rate) | B37: =B11*B23 -> 20 | C37: students/min
A38: Capacity: Munch Mess (lines × service rate) | B38: =B12*B23 -> 20 | C38: students/min
A39: Max arrivals seats can absorb: Central (Little's Law N/W) | B39: =Inputs!$B$9/Inputs!$B$15 -> 50 | C39: students/min
A40: Max arrivals seats can absorb: Munch (Little's Law N/W) | B40: =Inputs!$B$10/Inputs!$B$15 -> 27.777778 | C40: students/min
A41: Scanner capacity: Central (scanners × 60 ÷ seconds per scan) | B41: =Inputs!$B$13*60/Inputs!$B$24 -> 30 | C41: students/min
A42: Scanner capacity: Munch (scanners × 60 ÷ seconds per scan) | B42: =Inputs!$B$14*60/Inputs!$B$24 -> 30 | C42: students/min
A44: About the money values
A45: Most tabs work in minutes and students, not rupees. Money appears in only two places, where two different things must be compared on one scale: (1) S7 Decision Tree weighs food thrown away against students' waiting time, so it needs a rupee value for each; the ₹5 per student-minute is a judgement you can change, and the tab shows the break-even point so the answer is clear whatever value you pick. (2) S12-14 IP Staffing uses staff cost to count what extra serving stations cost. The payoff matrix (S7) uses minutes only.

Sheet S2-3 Problem & Root Cause
A1: Problem definition, decision context and root causes
A2: Sessions 2–3: Nature of business decisions · Problem identification, structuring, root cause analysis
A4: Problem statement
A5: During the 11:30–14:30 lunch window, Chefs Touch serves about 2,960 plates. Demand is concentrated while kitchen, delivery and serving capacity are fixed, so students wait (~15 min observed), star dishes run out mid-service and replenishment arrives during the peak. Decision question: are resources (food, serving lines, students' choice of mess) reaching the right centre, in the right quantity, at the right time?
A7: Session 2: nature of the decision
A8: Dimension | B8: Classification | C8: Why
A9: Level | B9: Operational | C9: Made every lunch, at centre and kitchen level
A10: Structure | B10: Structured / programmable | C10: Same choice repeats daily; inputs can be measured (scans, stock, lines)
A11: Certainty | B11: Under risk / uncertainty | C11: Daily demand varies; probabilities can be estimated from biometric logs
A12: Frequency | B12: Recurring (daily, 5 centres) | C12: Justifies building a model instead of ad-hoc judgement
A13: Decision makers | B13: CT operations, centre teams, students | C13: Students' choice of mess is itself a decision we can influence
A15: Session 3: 5 Whys
A16: Why? | B16: Answer | C16: Evidence
A17: 1. Why do students wait ~15 min? | B17: The serving line runs at or above capacity at peak | C17: Phase 1 deck; field notes O5, O15
A18: 2. Why is it above capacity? | B18: Arrivals cluster at peak times, and service stops when a dish runs out | C18: Run-outs 13:20–13:23 (O4, O10); timing of arrivals to be confirmed by logs
A19: 3. Why do dishes run out? | B19: Replenishment is triggered when stock is already low | C19: Top-up arrives inside the peak (O2, O7)
A20: 4. Why is it triggered late? | B20: The mess only calls the kitchen when the dish is running low; if it has to be made, the refill takes 30 min in total (10–14 min if already made) | C20: Phase 1 deck
A21: 5. Why is there no early warning? | B21: Entry data (biometric scans) is not used for operations | C21: Root cause → our project
A23: Session 3: fishbone (cause-and-effect) for 'long wait at lunch'
A24: People | B24: Process | C24: Policy | D24: Information | E24: Logistics / place
A25: Students arrive together at peak | B25: 2 serving stations and 1 face scanner per hall | C25: Replenishment is reactive | D25: No live view of demand | E25: Delivery shares the student walkway (O3, O8)
A26: Habit: same mess every day | B26: Refilling at the counter stops the line (O14) | C26: Base foods under-buffered (O13) | D26: Published menu ≠ served menu | E26: Return station/waste point unmeasured (O19)
A27: Students queue for dishes already gone (O11) | B27: Serving rate not measured | C27: No reorder point | D27: No per-centre forecast | E27: One kitchen supplies five centres
A29: Issue tree (problem structuring)
A30: Branch | B30: Sub-question | C30: Tool in this workbook
A31: Demand side | B31: When and where do students arrive? | C31: S15 Queuing (λ per 10 min)
A32: Capacity side | B32: How many lines, how fast? | C32: S15 Queuing, S12-14 IP Staffing
A33: Allocation | B33: How much of each dish to each centre? | C33: S10-11 LP Allocation, S5-6 Priority Matrix
A34: Timing | B34: When to replenish? | C34: S7 Decision Tree, S18 Heuristics (reorder point)
A35: Choice of intervention | B35: Which option is best overall? | C35: S7 Payoff Matrix, S16-17 AHP / BWM
A36: Cause structure | B36: Which causes drive the others? | C36: S16-17 ISM-MICMAC

Sheet S4 Biases & Ethics
A1: Decision biases and ethical decision making
A2: Session 4: Decision-making frameworks, decision biases, ethical decision making
A4: Bias | B4: Where it shows up in the mess problem | C4: How the project counters it
A5: Status quo / habit | B5: Students go to the same mess daily even when the other is faster | C5: Door screens set a default ('Recommended'), show concrete gains, fresh-batch cues
A6: Herding | B6: If everyone follows one signal, the 'empty' mess becomes the busy one | C6: Equilibrium split + 2-minute minimum saving; soft vs strong messages
A7: Anchoring | B7: Kitchen plans from the published menu; served menu differed on the day | C7: Record the actual menu; forecast from observed arrivals, not the plan
A8: Availability | B8: Managers remember the worst day and over-react | C8: Use logged data (distribution of days) and EMV, not memorable events
A9: Confirmation | B9: Our team wants the screens to look good | C9: Report simulated vs measured separately; A/B test with screens on/off
A10: Overconfidence | B10: Point estimates of waits shown as exact | C10: Show '~' and ranges; explain estimates come from scans
A12: Ethics checklist
A13: Principle | B13: What we do | C13: Status
A14: Data minimisation (DPDP Act 2023) | B14: Request only scan time + mess; no face data or templates | C14: Built into data request
A15: Pseudonymisation | B15: IDs hashed on reading; names hidden by default | C15: Built into prototype
A16: Purpose limitation & retention | B16: Use for this project only; delete at semester end | C16: Committed in email
A17: Honesty to students | B17: Never suggest switching unless it saves ≥ 2 min; stale kitchen taps expire | C17: Built into prototype
A18: Consent / approval | B18: Written approval from college and vendor before any live connection | C18: Pending
A19: Fairness | B19: Advice is the same for everyone; no priority for any group | C19: Built into prototype

Sheet S5-6 Priority Matrix
A1: Decision dilemma and priority matrices
A2: Sessions 5–6: Decision dilemma and project priority matrix
A4: 1. Menu criticality × predictability (ABC/XYZ) — from our CT Priority Matrix workbook, menu week 31 Aug–6 Sep
A5: Policy | B5: Class | C5: Menu entries | D5: Share | E5: What to do
A6: Tight Control | B6: AZ | C6: 20 | D6: =C6/$C$10 -> 0.19417476 | E6: Measure and model (chapattis, star dishes)
A7: Calculated Issue | B7: AX | C7: 16 | D7: =C7/$C$10 -> 0.15533981 | E7: Derive from plate count (curd, raitha, sweets)
A8: Buffered Issue | B8: CZ | C8: 40 | D8: =C8/$C$10 -> 0.38834951 | E8: Issue with a safety margin (rice, dal, sambar)
A9: Free Issue | B9: CX | C9: 27 | D9: =C9/$C$10 -> 0.26213592 | E9: Issue without control (pickle, salt, sugar)
A10: Total | C10: =SUM(C6:C9) -> 103 | D10: =SUM(D6:D9) -> 1
A12: 2. Intervention priority matrix (impact vs effort). Scores 1–5 are illustrative: agree them as a group.
A13: Quadrant threshold (score above this = high) | C13: 3
A15: Intervention | B15: Impact (1–5) | C15: Effort (1–5) | D15: Quadrant | E15: Reason (impact) | F15: Reason (effort)
A16: A2 Door screens + routing | B16: 4 | C16: 3 | D16: =IF(B16>$C$13,IF(C16>$C$13,"Major project","Quick win"),IF(C16>$C$13,"Thankless task","Fill-in")) -> Quick win | E16: Spreads students; ~halves waits in simulation | F16: Two screens + a laptop; needs data access
A17: A3 Screens + kitchen early alerts | B17: 5 | C17: 3 | D17: =IF(B17>$C$13,IF(C17>$C$13,"Major project","Quick win"),IF(C17>$C$13,"Thankless task","Fill-in")) -> Quick win | E17: Also attacks stock-outs (root cause) | F17: Same as A2 + kitchen page habit
A18: A4 3rd serving station at peak | B18: 4 | C18: 4 | D18: =IF(B18>$C$13,IF(C18>$C$13,"Major project","Quick win"),IF(C18>$C$13,"Thankless task","Fill-in")) -> Major project | E18: Raises capacity directly | F18: Recurring staff cost; space at counter
A19: A6 Larger buffers for base foods (CZ) | B19: 3 | C19: 1 | D19: =IF(B19>$C$13,IF(C19>$C$13,"Major project","Quick win"),IF(C19>$C$13,"Thankless task","Fill-in")) -> Fill-in | E19: Base foods ran dry (O13) | F19: Just send more rice/dal/sambar
A20: A7 Stagger class end times | B20: 4 | C20: 5 | D20: =IF(B20>$C$13,IF(C20>$C$13,"Major project","Quick win"),IF(C20>$C$13,"Thankless task","Fill-in")) -> Major project | E20: Lowers peak arrivals | F20: Needs academic administration
A21: A8 Separate counter for one-per-plate items | B21: 2 | C21: 2 | D21: =IF(B21>$C$13,IF(C21>$C$13,"Major project","Quick win"),IF(C21>$C$13,"Thankless task","Fill-in")) -> Fill-in | E21: Shortens main line slightly | F21: Small layout change
A23: 3. Decision dilemma
A24: Dilemma | B24: Option 1 | C24: Option 2 | E24: Trade-off | F24: How we resolve it
A25: Send more food early? | B25: Pre-stage (risk waste) | C25: Wait and react (risk run-out) | E25: Waste ₹ vs students' time | F25: S7 Decision Tree: break-even probability
A26: Send students to the other mess? | B26: Strong advice (risk herding) | C26: No advice (uneven load) | E26: Balance vs trust | F26: Equilibrium split + 2-min threshold (S18)
A27: Add a serving station? | B27: Yes (cost every day) | C27: No (long peak waits) | E27: Staff cost vs waiting | F27: S12-14 IP Staffing; S7 Payoff Matrix

Sheet S15 Queuing
A1: Queuing analysis: M/M/1, M/M/c and lunch-peak overload, without vs with the screens
A2: Session 15: Introduction to queuing theory and waiting-line models
A4: 1. Check against the lecture example (Hatti Kaapi, M/M/1) | J4: 2. Why waits explode near 100% busy (M/M/1, one serving station)
A5: λ /hour | B5: μ /hour | C5: ρ | D5: Wq (hours) | E5: Wq (min) | F5: W (min) | G5: Lq | H5: L | J5: μ per hour | K5: =Inputs!$B$23*60 -> 600
A6: 18 | B6: 24 | C6: =A6/B6 -> 0.75 | D6: =A6/(B6*(B6-A6)) -> 0.125 | E6: =D6*60 -> 7.5 | F6: =60/(B6-A6) -> 10 | G6: =A6*D6 -> 2.25 | H6: =A6*F6/60 -> 3 | J6: ρ | K6: λ /hour | L6: Wq (min) | M6: Lq
A7: Lecture answers: ρ = 75%, Wq = 7.5 min, W = 10 min, Lq = 2.25. If these match, the formulas below are right. | J7: 0.5 | K7: =J7*$K$5 -> 300 | L7: =K7/($K$5*($K$5-K7))*60 -> 0.1 | M7: =K7*L7/60 -> 0.5
J8: 0.6 | K8: =J8*$K$5 -> 360 | L8: =K8/($K$5*($K$5-K8))*60 -> 0.15 | M8: =K8*L8/60 -> 0.9
J9: 0.7 | K9: =J9*$K$5 -> 420 | L9: =K9/($K$5*($K$5-K9))*60 -> 0.23333333 | M9: =K9*L9/60 -> 1.6333333
J10: 0.75 | K10: =J10*$K$5 -> 450 | L10: =K10/($K$5*($K$5-K10))*60 -> 0.3 | M10: =K10*L10/60 -> 2.25
J11: 0.8 | K11: =J11*$K$5 -> 480 | L11: =K11/($K$5*($K$5-K11))*60 -> 0.4 | M11: =K11*L11/60 -> 3.2
J12: 0.85 | K12: =J12*$K$5 -> 510 | L12: =K12/($K$5*($K$5-K12))*60 -> 0.56666667 | M12: =K12*L12/60 -> 4.8166667
J13: 0.9 | K13: =J13*$K$5 -> 540 | L13: =K13/($K$5*($K$5-K13))*60 -> 0.9 | M13: =K13*L13/60 -> 8.1
J14: 0.93 | K14: =J14*$K$5 -> 558 | L14: =K14/($K$5*($K$5-K14))*60 -> 1.3285714 | M14: =K14*L14/60 -> 12.355714
J15: 0.95 | K15: =J15*$K$5 -> 570 | L15: =K15/($K$5*($K$5-K15))*60 -> 1.9 | M15: =K15*L15/60 -> 18.05
J16: 0.96 | K16: =J16*$K$5 -> 576 | L16: =K16/($K$5*($K$5-K16))*60 -> 2.4 | M16: =K16*L16/60 -> 23.04
J17: 0.97 | K17: =J17*$K$5 -> 582 | L17: =K17/($K$5*($K$5-K17))*60 -> 3.2333333 | M17: =K17*L17/60 -> 31.363333
J18: 0.98 | K18: =J18*$K$5 -> 588 | L18: =K18/($K$5*($K$5-K18))*60 -> 4.9 | M18: =K18*L18/60 -> 48.02
A22: 3. Lunch peak by 10-minute bin: without vs with the door screens (M/M/c + overload)
A23: Blue column B = arrivals per 10 min at both messes together, 11:30–14:30. ILLUSTRATIVE: 2,960 students (measured total) on an assumed bell-shaped curve. Replace them with counts from the biometric logs. 'With screens' moves students from the busier mess toward equal utilisation; only the share who comply move. When ρ ≥ 1 the steady-state formula does not apply, so the queue is carried forward (fluid model): backlog = max(0, previous + arrivals − capacity).
A25: Equal-utilisation share for Central | E25: =Inputs!$B$37/(Inputs!$B$37+Inputs!$B$38) -> 0.5 | F25: Formula: capacity of Central ÷ (capacity of Central + capacity of Munch)
A26: Realised share for Central with screens | E26: =Inputs!$B$22+Inputs!$B$27*(E25-Inputs!$B$22) -> 0.64 | F26: Formula: habit + compliance × (target − habit). Only students who follow the screen move
D28: Without screens — Central CT | L28: Without screens — Munch | T28: With screens — Central CT | AB28: With screens — Munch
A29: Bin start | B29: Arrivals (both messes) | C29: λ total /min | D29: λ /min | E29: Scanner ρ | F29: ρ | G29: P(wait) | H29: Wq steady (min) | I29: Backlog end | J29: Est. wait (min) | K29: People inside | L29: λ /min | M29: Scanner ρ | N29: ρ | O29: P(wait) | P29: Wq steady (min) | Q29: Backlog end | R29: Est. wait (min) | S29: People inside | T29: λ /min | U29: Scanner ρ | V29: ρ | W29: P(wait) | X29: Wq steady (min) | Y29: Backlog end | Z29: Est. wait (min) | AA29: People inside | AB29: λ /min | AC29: Scanner ρ | AD29: ρ | AE29: P(wait) | AF29: Wq steady (min) | AG29: Backlog end | AH29: Est. wait (min) | AI29: People inside
A30: 11:30 | B30: 13 | C30: =B30/10 -> 1.3 | D30: =$C30*Inputs!$B$22 -> 1.105 | E30: =D30/Inputs!$B$41 -> 0.036833333 | F30: =D30/(Inputs!$B$11*Inputs!$B$23) -> 0.05525 | G30: =IF(F30<1,((D30/Inputs!$B$23)^Inputs!$B$11/FACT(Inputs!$B$11)*Inputs!$B$11/(Inputs!$B$11-(D30/Inputs!$B$23)))/(SUMPRODUCT(--({0,1,2,3,4,5,6,7,8,9}<Inputs!$B$11),(D30/Inputs!$B$23)^{0,1,2,3,4,5,6,7,8,9}/FACT({0,1,2,3,4,5,6,7,8,9}))+((D30/Inputs!$B$23)^Inputs!$B$11/FACT(Inputs!$B$11)*Inputs!$B$11/(Inputs!$B$11-(D30/Inputs!$B$23)))),1) -> 0.0057854774 | H30: =IF(F30<1,G30/(Inputs!$B$11*Inputs!$B$23-D30),0) -> 0.00030619092 | I30: =MAX(0,0+(D30-Inputs!$B$11*Inputs!$B$23)*10) -> 0 | J30: =I30/(Inputs!$B$11*Inputs!$B$23)+H30 -> 0.00030619092 | K30: =D30*(J30+1/Inputs!$B$23+Inputs!$B$25) -> 18.895838 | L30: =$C30*(1-Inputs!$B$22) -> 0.195 | M30: =L30/Inputs!$B$42 -> 0.0065 | N30: =L30/(Inputs!$B$12*Inputs!$B$23) -> 0.00975 | O30: =IF(N30<1,((L30/Inputs!$B$23)^Inputs!$B$12/FACT(Inputs!$B$12)*Inputs!$B$12/(Inputs!$B$12-(L30/Inputs!$B$23)))/(SUMPRODUCT(--({0,1,2,3,4,5,6,7,8,9}<Inputs!$B$12),(L30/Inputs!$B$23)^{0,1,2,3,4,5,6,7,8,9}/FACT({0,1,2,3,4,5,6,7,8,9}))+((L30/Inputs!$B$23)^Inputs!$B$12/FACT(Inputs!$B$12)*Inputs!$B$12/(Inputs!$B$12-(L30/Inputs!$B$23)))),1) -> 0.00018828918 | P30: =IF(N30<1,O30/(Inputs!$B$12*Inputs!$B$23-L30),0) -> 9.5071538e-06 | Q30: =MAX(0,0+(L30-Inputs!$B$12*Inputs!$B$23)*10) -> 0 | R30: =Q30/(Inputs!$B$12*Inputs!$B$23)+P30 -> 9.5071538e-06 | S30: =L30*(R30+1/Inputs!$B$23+Inputs!$B$25) -> 3.3345019 | T30: =$C30*$E$26 -> 0.832 | U30: =T30/Inputs!$B$41 -> 0.027733333 | V30: =T30/(Inputs!$B$11*Inputs!$B$23) -> 0.0416 | W30: =IF(V30<1,((T30/Inputs!$B$23)^Inputs!$B$11/FACT(Inputs!$B$11)*Inputs!$B$11/(Inputs!$B$11-(T30/Inputs!$B$23)))/(SUMPRODUCT(--({0,1,2,3,4,5,6,7,8,9}<Inputs!$B$11),(T30/Inputs!$B$23)^{0,1,2,3,4,5,6,7,8,9}/FACT({0,1,2,3,4,5,6,7,8,9}))+((T30/Inputs!$B$23)^Inputs!$B$11/FACT(Inputs!$B$11)*Inputs!$B$11/(Inputs!$B$11-(T30/Inputs!$B$23)))),1) -> 0.0033228879 | X30: =IF(V30<1,W30/(Inputs!$B$11*Inputs!$B$23-T30),0) -> 0.000173356 | Y30: =MAX(0,0+(T30-Inputs!$B$11*Inputs!$B$23)*10) -> 0 | Z30: =Y30/(Inputs!$B$11*Inputs!$B$23)+X30 -> 0.000173356 | AA30: =T30*(Z30+1/Inputs!$B$23+Inputs!$B$25) -> 14.227344 | AB30: =$C30*(1-$E$26) -> 0.468 | AC30: =AB30/Inputs!$B$42 -> 0.0156 | AD30: =AB30/(Inputs!$B$12*Inputs!$B$23) -> 0.0234 | AE30: =IF(AD30<1,((AB30/Inputs!$B$23)^Inputs!$B$12/FACT(Inputs!$B$12)*Inputs!$B$12/(Inputs!$B$12-(AB30/Inputs!$B$23)))/(SUMPRODUCT(--({0,1,2,3,4,5,6,7,8,9}<Inputs!$B$12),(AB30/Inputs!$B$23)^{0,1,2,3,4,5,6,7,8,9}/FACT({0,1,2,3,4,5,6,7,8,9}))+((AB30/Inputs!$B$23)^Inputs!$B$12/FACT(Inputs!$B$12)*Inputs!$B$12/(Inputs!$B$12-(AB30/Inputs!$B$23)))),1) -> 0.0010700801 | AF30: =IF(AD30<1,AE30/(Inputs!$B$12*Inputs!$B$23-AB30),0) -> 5.4785999e-05 | AG30: =MAX(0,0+(AB30-Inputs!$B$12*Inputs!$B$23)*10) -> 0 | AH30: =AG30/(Inputs!$B$12*Inputs!$B$23)+AF30 -> 5.4785999e-05 | AI30: =AB30*(AH30+1/Inputs!$B$23+Inputs!$B$25) -> 8.0028256
A31: 11:40 | B31: 25 | C31: =B31/10 -> 2.5 | D31: =$C31*Inputs!$B$22 -> 2.125 | E31: =D31/Inputs!$B$41 -> 0.070833333 | F31: =D31/(Inputs!$B$11*Inputs!$B$23) -> 0.10625 | G31: =IF(F31<1,((D31/Inputs!$B$23)^Inputs!$B$11/FACT(Inputs!$B$11)*Inputs!$B$11/(Inputs!$B$11-(D31/Inputs!$B$23)))/(SUMPRODUCT(--({0,1,2,3,4,5,6,7,8,9}<Inputs!$B$11),(D31/Inputs!$B$23)^{0,1,2,3,4,5,6,7,8,9}/FACT({0,1,2,3,4,5,6,7,8,9}))+((D31/Inputs!$B$23)^Inputs!$B$11/FACT(Inputs!$B$11)*Inputs!$B$11/(Inputs!$B$11-(D31/Inputs!$B$23)))),1) -> 0.020409605 | H31: =IF(F31<1,G31/(Inputs!$B$11*Inputs!$B$23-D31),0) -> 0.0011417961 | I31: =MAX(0,I30+(D31-Inputs!$B$11*Inputs!$B$23)*10) -> 0 | J31: =I31/(Inputs!$B$11*Inputs!$B$23)+H31 -> 0.0011417961 | K31: =D31*(J31+1/Inputs!$B$23+Inputs!$B$25) -> 36.339926 | L31: =$C31*(1-Inputs!$B$22) -> 0.375 | M31: =L31/Inputs!$B$42 -> 0.0125 | N31: =L31/(Inputs!$B$12*Inputs!$B$23) -> 0.01875 | O31: =IF(N31<1,((L31/Inputs!$B$23)^Inputs!$B$12/FACT(Inputs!$B$12)*Inputs!$B$12/(Inputs!$B$12-(L31/Inputs!$B$23)))/(SUMPRODUCT(--({0,1,2,3,4,5,6,7,8,9}<Inputs!$B$12),(L31/Inputs!$B$23)^{0,1,2,3,4,5,6,7,8,9}/FACT({0,1,2,3,4,5,6,7,8,9}))+((L31/Inputs!$B$23)^Inputs!$B$12/FACT(Inputs!$B$12)*Inputs!$B$12/(Inputs!$B$12-(L31/Inputs!$B$23)))),1) -> 0.00069018405 | P31: =IF(N31<1,O31/(Inputs!$B$12*Inputs!$B$23-L31),0) -> 3.5168614e-05 | Q31: =MAX(0,Q30+(L31-Inputs!$B$12*Inputs!$B$23)*10) -> 0 | R31: =Q31/(Inputs!$B$12*Inputs!$B$23)+P31 -> 3.5168614e-05 | S31: =L31*(R31+1/Inputs!$B$23+Inputs!$B$25) -> 6.4125132 | T31: =$C31*$E$26 -> 1.6 | U31: =T31/Inputs!$B$41 -> 0.053333333 | V31: =T31/(Inputs!$B$11*Inputs!$B$23) -> 0.08 | W31: =IF(V31<1,((T31/Inputs!$B$23)^Inputs!$B$11/FACT(Inputs!$B$11)*Inputs!$B$11/(Inputs!$B$11-(T31/Inputs!$B$23)))/(SUMPRODUCT(--({0,1,2,3,4,5,6,7,8,9}<Inputs!$B$11),(T31/Inputs!$B$23)^{0,1,2,3,4,5,6,7,8,9}/FACT({0,1,2,3,4,5,6,7,8,9}))+((T31/Inputs!$B$23)^Inputs!$B$11/FACT(Inputs!$B$11)*Inputs!$B$11/(Inputs!$B$11-(T31/Inputs!$B$23)))),1) -> 0.011851852 | X31: =IF(V31<1,W31/(Inputs!$B$11*Inputs!$B$23-T31),0) -> 0.00064412238 | Y31: =MAX(0,Y30+(T31-Inputs!$B$11*Inputs!$B$23)*10) -> 0 | Z31: =Y31/(Inputs!$B$11*Inputs!$B$23)+X31 -> 0.00064412238 | AA31: =T31*(Z31+1/Inputs!$B$23+Inputs!$B$25) -> 27.361031 | AB31: =$C31*(1-$E$26) -> 0.9 | AC31: =AB31/Inputs!$B$42 -> 0.03 | AD31: =AB31/(Inputs!$B$12*Inputs!$B$23) -> 0.045 | AE31: =IF(AD31<1,((AB31/Inputs!$B$23)^Inputs!$B$12/FACT(Inputs!$B$12)*Inputs!$B$12/(Inputs!$B$12-(AB31/Inputs!$B$23)))/(SUMPRODUCT(--({0,1,2,3,4,5,6,7,8,9}<Inputs!$B$12),(AB31/Inputs!$B$23)^{0,1,2,3,4,5,6,7,8,9}/FACT({0,1,2,3,4,5,6,7,8,9}))+((AB31/Inputs!$B$23)^Inputs!$B$12/FACT(Inputs!$B$12)*Inputs!$B$12/(Inputs!$B$12-(AB31/Inputs!$B$23)))),1) -> 0.0038755981 | AF31: =IF(AD31<1,AE31/(Inputs!$B$12*Inputs!$B$23-AB31),0) -> 0.00020291089 | AG31: =MAX(0,AG30+(AB31-Inputs!$B$12*Inputs!$B$23)*10) -> 0 | AH31: =AG31/(Inputs!$B$12*Inputs!$B$23)+AF31 -> 0.00020291089 | AI31: =AB31*(AH31+1/Inputs!$B$23+Inputs!$B$25) -> 15.390183
A32: 11:50 | B32: 47 | C32: =B32/10 -> 4.7 | D32: =$C32*Inputs!$B$22 -> 3.995 | E32: =D32/Inputs!$B$41 -> 0.13316667 | F32: =D32/(Inputs!$B$11*Inputs!$B$23) -> 0.19975 | G32: =IF(F32<1,((D32/Inputs!$B$23)^Inputs!$B$11/FACT(Inputs!$B$11)*Inputs!$B$11/(Inputs!$B$11-(D32/Inputs!$B$23)))/(SUMPRODUCT(--({0,1,2,3,4,5,6,7,8,9}<Inputs!$B$11),(D32/Inputs!$B$23)^{0,1,2,3,4,5,6,7,8,9}/FACT({0,1,2,3,4,5,6,7,8,9}))+((D32/Inputs!$B$23)^Inputs!$B$11/FACT(Inputs!$B$11)*Inputs!$B$11/(Inputs!$B$11-(D32/Inputs!$B$23)))),1) -> 0.066513961 | H32: =IF(F32<1,G32/(Inputs!$B$11*Inputs!$B$23-D32),0) -> 0.0041558239 | I32: =MAX(0,I31+(D32-Inputs!$B$11*Inputs!$B$23)*10) -> 0 | J32: =I32/(Inputs!$B$11*Inputs!$B$23)+H32 -> 0.0041558239 | K32: =D32*(J32+1/Inputs!$B$23+Inputs!$B$25) -> 68.331103 | L32: =$C32*(1-Inputs!$B$22) -> 0.705 | M32: =L32/Inputs!$B$42 -> 0.0235 | N32: =L32/(Inputs!$B$12*Inputs!$B$23) -> 0.03525 | O32: =IF(N32<1,((L32/Inputs!$B$23)^Inputs!$B$12/FACT(Inputs!$B$12)*Inputs!$B$12/(Inputs!$B$12-(L32/Inputs!$B$23)))/(SUMPRODUCT(--({0,1,2,3,4,5,6,7,8,9}<Inputs!$B$12),(L32/Inputs!$B$23)^{0,1,2,3,4,5,6,7,8,9}/FACT({0,1,2,3,4,5,6,7,8,9}))+((L32/Inputs!$B$23)^Inputs!$B$12/FACT(Inputs!$B$12)*Inputs!$B$12/(Inputs!$B$12-(L32/Inputs!$B$23)))),1) -> 0.0024005071 | P32: =IF(N32<1,O32/(Inputs!$B$12*Inputs!$B$23-L32),0) -> 0.00012441084 | Q32: =MAX(0,Q31+(L32-Inputs!$B$12*Inputs!$B$23)*10) -> 0 | R32: =Q32/(Inputs!$B$12*Inputs!$B$23)+P32 -> 0.00012441084 | S32: =L32*(R32+1/Inputs!$B$23+Inputs!$B$25) -> 12.055588 | T32: =$C32*$E$26 -> 3.008 | U32: =T32/Inputs!$B$41 -> 0.10026667 | V32: =T32/(Inputs!$B$11*Inputs!$B$23) -> 0.1504 | W32: =IF(V32<1,((T32/Inputs!$B$23)^Inputs!$B$11/FACT(Inputs!$B$11)*Inputs!$B$11/(Inputs!$B$11-(T32/Inputs!$B$23)))/(SUMPRODUCT(--({0,1,2,3,4,5,6,7,8,9}<Inputs!$B$11),(T32/Inputs!$B$23)^{0,1,2,3,4,5,6,7,8,9}/FACT({0,1,2,3,4,5,6,7,8,9}))+((T32/Inputs!$B$23)^Inputs!$B$11/FACT(Inputs!$B$11)*Inputs!$B$11/(Inputs!$B$11-(T32/Inputs!$B$23)))),1) -> 0.03932573 | X32: =IF(V32<1,W32/(Inputs!$B$11*Inputs!$B$23-T32),0) -> 0.0023143674 | Y32: =MAX(0,Y31+(T32-Inputs!$B$11*Inputs!$B$23)*10) -> 0 | Z32: =Y32/(Inputs!$B$11*Inputs!$B$23)+X32 -> 0.0023143674 | AA32: =T32*(Z32+1/Inputs!$B$23+Inputs!$B$25) -> 51.443762 | AB32: =$C32*(1-$E$26) -> 1.692 | AC32: =AB32/Inputs!$B$42 -> 0.0564 | AD32: =AB32/(Inputs!$B$12*Inputs!$B$23) -> 0.0846 | AE32: =IF(AD32<1,((AB32/Inputs!$B$23)^Inputs!$B$12/FACT(Inputs!$B$12)*Inputs!$B$12/(Inputs!$B$12-(AB32/Inputs!$B$23)))/(SUMPRODUCT(--({0,1,2,3,4,5,6,7,8,9}<Inputs!$B$12),(AB32/Inputs!$B$23)^{0,1,2,3,4,5,6,7,8,9}/FACT({0,1,2,3,4,5,6,7,8,9}))+((AB32/Inputs!$B$23)^Inputs!$B$12/FACT(Inputs!$B$12)*Inputs!$B$12/(Inputs!$B$12-(AB32/Inputs!$B$23)))),1) -> 0.013197787 | AF32: =IF(AD32<1,AE32/(Inputs!$B$12*Inputs!$B$23-AB32),0) -> 0.00072087542 | AG32: =MAX(0,AG31+(AB32-Inputs!$B$12*Inputs!$B$23)*10) -> 0 | AH32: =AG32/(Inputs!$B$12*Inputs!$B$23)+AF32 -> 0.00072087542 | AI32: =AB32*(AH32+1/Inputs!$B$23+Inputs!$B$25) -> 28.93442
A33: 12:00 | B33: 79 | C33: =B33/10 -> 7.9 | D33: =$C33*Inputs!$B$22 -> 6.715 | E33: =D33/Inputs!$B$41 -> 0.22383333 | F33: =D33/(Inputs!$B$11*Inputs!$B$23) -> 0.33575 | G33: =IF(F33<1,((D33/Inputs!$B$23)^Inputs!$B$11/FACT(Inputs!$B$11)*Inputs!$B$11/(Inputs!$B$11-(D33/Inputs!$B$23)))/(SUMPRODUCT(--({0,1,2,3,4,5,6,7,8,9}<Inputs!$B$11),(D33/Inputs!$B$23)^{0,1,2,3,4,5,6,7,8,9}/FACT({0,1,2,3,4,5,6,7,8,9}))+((D33/Inputs!$B$23)^Inputs!$B$11/FACT(Inputs!$B$11)*Inputs!$B$11/(Inputs!$B$11-(D33/Inputs!$B$23)))),1) -> 0.16878617 | H33: =IF(F33<1,G33/(Inputs!$B$11*Inputs!$B$23-D33),0) -> 0.012705018 | I33: =MAX(0,I32+(D33-Inputs!$B$11*Inputs!$B$23)*10) -> 0 | J33: =I33/(Inputs!$B$11*Inputs!$B$23)+H33 -> 0.012705018 | K33: =D33*(J33+1/Inputs!$B$23+Inputs!$B$25) -> 114.91181 | L33: =$C33*(1-Inputs!$B$22) -> 1.185 | M33: =L33/Inputs!$B$42 -> 0.0395 | N33: =L33/(Inputs!$B$12*Inputs!$B$23) -> 0.05925 | O33: =IF(N33<1,((L33/Inputs!$B$23)^Inputs!$B$12/FACT(Inputs!$B$12)*Inputs!$B$12/(Inputs!$B$12-(L33/Inputs!$B$23)))/(SUMPRODUCT(--({0,1,2,3,4,5,6,7,8,9}<Inputs!$B$12),(L33/Inputs!$B$23)^{0,1,2,3,4,5,6,7,8,9}/FACT({0,1,2,3,4,5,6,7,8,9}))+((L33/Inputs!$B$23)^Inputs!$B$12/FACT(Inputs!$B$12)*Inputs!$B$12/(Inputs!$B$12-(L33/Inputs!$B$23)))),1) -> 0.0066283927 | P33: =IF(N33<1,O33/(Inputs!$B$12*Inputs!$B$23-L33),0) -> 0.000352293 | Q33: =MAX(0,Q32+(L33-Inputs!$B$12*Inputs!$B$23)*10) -> 0 | R33: =Q33/(Inputs!$B$12*Inputs!$B$23)+P33 -> 0.000352293 | S33: =L33*(R33+1/Inputs!$B$23+Inputs!$B$25) -> 20.263917 | T33: =$C33*$E$26 -> 5.056 | U33: =T33/Inputs!$B$41 -> 0.16853333 | V33: =T33/(Inputs!$B$11*Inputs!$B$23) -> 0.2528 | W33: =IF(V33<1,((T33/Inputs!$B$23)^Inputs!$B$11/FACT(Inputs!$B$11)*Inputs!$B$11/(Inputs!$B$11-(T33/Inputs!$B$23)))/(SUMPRODUCT(--({0,1,2,3,4,5,6,7,8,9}<Inputs!$B$11),(T33/Inputs!$B$23)^{0,1,2,3,4,5,6,7,8,9}/FACT({0,1,2,3,4,5,6,7,8,9}))+((T33/Inputs!$B$23)^Inputs!$B$11/FACT(Inputs!$B$11)*Inputs!$B$11/(Inputs!$B$11-(T33/Inputs!$B$23)))),1) -> 0.10202401 | X33: =IF(V33<1,W33/(Inputs!$B$11*Inputs!$B$23-T33),0) -> 0.0068270885 | Y33: =MAX(0,Y32+(T33-Inputs!$B$11*Inputs!$B$23)*10) -> 0 | Z33: =Y33/(Inputs!$B$11*Inputs!$B$23)+X33 -> 0.0068270885 | AA33: =T33*(Z33+1/Inputs!$B$23+Inputs!$B$25) -> 86.492118 | AB33: =$C33*(1-$E$26) -> 2.844 | AC33: =AB33/Inputs!$B$42 -> 0.0948 | AD33: =AB33/(Inputs!$B$12*Inputs!$B$23) -> 0.1422 | AE33: =IF(AD33<1,((AB33/Inputs!$B$23)^Inputs!$B$12/FACT(Inputs!$B$12)*Inputs!$B$12/(Inputs!$B$12-(AB33/Inputs!$B$23)))/(SUMPRODUCT(--({0,1,2,3,4,5,6,7,8,9}<Inputs!$B$12),(AB33/Inputs!$B$23)^{0,1,2,3,4,5,6,7,8,9}/FACT({0,1,2,3,4,5,6,7,8,9}))+((AB33/Inputs!$B$23)^Inputs!$B$12/FACT(Inputs!$B$12)*Inputs!$B$12/(Inputs!$B$12-(AB33/Inputs!$B$23)))),1) -> 0.035406829 | AF33: =IF(AD33<1,AE33/(Inputs!$B$12*Inputs!$B$23-AB33),0) -> 0.0020638161 | AG33: =MAX(0,AG32+(AB33-Inputs!$B$12*Inputs!$B$23)*10) -> 0 | AH33: =AG33/(Inputs!$B$12*Inputs!$B$23)+AF33 -> 0.0020638161 | AI33: =AB33*(AH33+1/Inputs!$B$23+Inputs!$B$25) -> 48.638269
A34: 12:10 | B34: 123 | C34: =B34/10 -> 12.3 | D34: =$C34*Inputs!$B$22 -> 10.455 | E34: =D34/Inputs!$B$41 -> 0.3485 | F34: =D34/(Inputs!$B$11*Inputs!$B$23) -> 0.52275 | G34: =IF(F34<1,((D34/Inputs!$B$23)^Inputs!$B$11/FACT(Inputs!$B$11)*Inputs!$B$11/(Inputs!$B$11-(D34/Inputs!$B$23)))/(SUMPRODUCT(--({0,1,2,3,4,5,6,7,8,9}<Inputs!$B$11),(D34/Inputs!$B$23)^{0,1,2,3,4,5,6,7,8,9}/FACT({0,1,2,3,4,5,6,7,8,9}))+((D34/Inputs!$B$23)^Inputs!$B$11/FACT(Inputs!$B$11)*Inputs!$B$11/(Inputs!$B$11-(D34/Inputs!$B$23)))),1) -> 0.35891323 | H34: =IF(F34<1,G34/(Inputs!$B$11*Inputs!$B$23-D34),0) -> 0.037602224 | I34: =MAX(0,I33+(D34-Inputs!$B$11*Inputs!$B$23)*10) -> 0 | J34: =I34/(Inputs!$B$11*Inputs!$B$23)+H34 -> 0.037602224 | K34: =D34*(J34+1/Inputs!$B$23+Inputs!$B$25) -> 179.17363 | L34: =$C34*(1-Inputs!$B$22) -> 1.845 | M34: =L34/Inputs!$B$42 -> 0.0615 | N34: =L34/(Inputs!$B$12*Inputs!$B$23) -> 0.09225 | O34: =IF(N34<1,((L34/Inputs!$B$23)^Inputs!$B$12/FACT(Inputs!$B$12)*Inputs!$B$12/(Inputs!$B$12-(L34/Inputs!$B$23)))/(SUMPRODUCT(--({0,1,2,3,4,5,6,7,8,9}<Inputs!$B$12),(L34/Inputs!$B$23)^{0,1,2,3,4,5,6,7,8,9}/FACT({0,1,2,3,4,5,6,7,8,9}))+((L34/Inputs!$B$23)^Inputs!$B$12/FACT(Inputs!$B$12)*Inputs!$B$12/(Inputs!$B$12-(L34/Inputs!$B$23)))),1) -> 0.015582628 | P34: =IF(N34<1,O34/(Inputs!$B$12*Inputs!$B$23-L34),0) -> 0.00085831053 | Q34: =MAX(0,Q33+(L34-Inputs!$B$12*Inputs!$B$23)*10) -> 0 | R34: =Q34/(Inputs!$B$12*Inputs!$B$23)+P34 -> 0.00085831053 | S34: =L34*(R34+1/Inputs!$B$23+Inputs!$B$25) -> 31.551084 | T34: =$C34*$E$26 -> 7.872 | U34: =T34/Inputs!$B$41 -> 0.2624 | V34: =T34/(Inputs!$B$11*Inputs!$B$23) -> 0.3936 | W34: =IF(V34<1,((T34/Inputs!$B$23)^Inputs!$B$11/FACT(Inputs!$B$11)*Inputs!$B$11/(Inputs!$B$11-(T34/Inputs!$B$23)))/(SUMPRODUCT(--({0,1,2,3,4,5,6,7,8,9}<Inputs!$B$11),(T34/Inputs!$B$23)^{0,1,2,3,4,5,6,7,8,9}/FACT({0,1,2,3,4,5,6,7,8,9}))+((T34/Inputs!$B$23)^Inputs!$B$11/FACT(Inputs!$B$11)*Inputs!$B$11/(Inputs!$B$11-(T34/Inputs!$B$23)))),1) -> 0.22233203 | X34: =IF(V34<1,W34/(Inputs!$B$11*Inputs!$B$23-T34),0) -> 0.018332127 | Y34: =MAX(0,Y33+(T34-Inputs!$B$11*Inputs!$B$23)*10) -> 0 | Z34: =Y34/(Inputs!$B$11*Inputs!$B$23)+X34 -> 0.018332127 | AA34: =T34*(Z34+1/Inputs!$B$23+Inputs!$B$25) -> 134.75551 | AB34: =$C34*(1-$E$26) -> 4.428 | AC34: =AB34/Inputs!$B$42 -> 0.1476 | AD34: =AB34/(Inputs!$B$12*Inputs!$B$23) -> 0.2214 | AE34: =IF(AD34<1,((AB34/Inputs!$B$23)^Inputs!$B$12/FACT(Inputs!$B$12)*Inputs!$B$12/(Inputs!$B$12-(AB34/Inputs!$B$23)))/(SUMPRODUCT(--({0,1,2,3,4,5,6,7,8,9}<Inputs!$B$12),(AB34/Inputs!$B$23)^{0,1,2,3,4,5,6,7,8,9}/FACT({0,1,2,3,4,5,6,7,8,9}))+((AB34/Inputs!$B$23)^Inputs!$B$12/FACT(Inputs!$B$12)*Inputs!$B$12/(Inputs!$B$12-(AB34/Inputs!$B$23)))),1) -> 0.080265204 | AF34: =IF(AD34<1,AE34/(Inputs!$B$12*Inputs!$B$23-AB34),0) -> 0.005154457 | AG34: =MAX(0,AG33+(AB34-Inputs!$B$12*Inputs!$B$23)*10) -> 0 | AH34: =AG34/(Inputs!$B$12*Inputs!$B$23)+AF34 -> 0.005154457 | AI34: =AB34*(AH34+1/Inputs!$B$23+Inputs!$B$25) -> 75.741624
A35: 12:20 | B35: 178 | C35: =B35/10 -> 17.8 | D35: =$C35*Inputs!$B$22 -> 15.13 | E35: =D35/Inputs!$B$41 -> 0.50433333 | F35: =D35/(Inputs!$B$11*Inputs!$B$23) -> 0.7565 | G35: =IF(F35<1,((D35/Inputs!$B$23)^Inputs!$B$11/FACT(Inputs!$B$11)*Inputs!$B$11/(Inputs!$B$11-(D35/Inputs!$B$23)))/(SUMPRODUCT(--({0,1,2,3,4,5,6,7,8,9}<Inputs!$B$11),(D35/Inputs!$B$23)^{0,1,2,3,4,5,6,7,8,9}/FACT({0,1,2,3,4,5,6,7,8,9}))+((D35/Inputs!$B$23)^Inputs!$B$11/FACT(Inputs!$B$11)*Inputs!$B$11/(Inputs!$B$11-(D35/Inputs!$B$23)))),1) -> 0.65162795 | H35: =IF(F35<1,G35/(Inputs!$B$11*Inputs!$B$23-D35),0) -> 0.13380451 | I35: =MAX(0,I34+(D35-Inputs!$B$11*Inputs!$B$23)*10) -> 0 | J35: =I35/(Inputs!$B$11*Inputs!$B$23)+H35 -> 0.13380451 | K35: =D35*(J35+1/Inputs!$B$23+Inputs!$B$25) -> 260.74746 | L35: =$C35*(1-Inputs!$B$22) -> 2.67 | M35: =L35/Inputs!$B$42 -> 0.089 | N35: =L35/(Inputs!$B$12*Inputs!$B$23) -> 0.1335 | O35: =IF(N35<1,((L35/Inputs!$B$23)^Inputs!$B$12/FACT(Inputs!$B$12)*Inputs!$B$12/(Inputs!$B$12-(L35/Inputs!$B$23)))/(SUMPRODUCT(--({0,1,2,3,4,5,6,7,8,9}<Inputs!$B$12),(L35/Inputs!$B$23)^{0,1,2,3,4,5,6,7,8,9}/FACT({0,1,2,3,4,5,6,7,8,9}))+((L35/Inputs!$B$23)^Inputs!$B$12/FACT(Inputs!$B$12)*Inputs!$B$12/(Inputs!$B$12-(L35/Inputs!$B$23)))),1) -> 0.031446405 | P35: =IF(N35<1,O35/(Inputs!$B$12*Inputs!$B$23-L35),0) -> 0.0018145646 | Q35: =MAX(0,Q34+(L35-Inputs!$B$12*Inputs!$B$23)*10) -> 0 | R35: =Q35/(Inputs!$B$12*Inputs!$B$23)+P35 -> 0.0018145646 | S35: =L35*(R35+1/Inputs!$B$23+Inputs!$B$25) -> 45.661845 | T35: =$C35*$E$26 -> 11.392 | U35: =T35/Inputs!$B$41 -> 0.37973333 | V35: =T35/(Inputs!$B$11*Inputs!$B$23) -> 0.5696 | W35: =IF(V35<1,((T35/Inputs!$B$23)^Inputs!$B$11/FACT(Inputs!$B$11)*Inputs!$B$11/(Inputs!$B$11-(T35/Inputs!$B$23)))/(SUMPRODUCT(--({0,1,2,3,4,5,6,7,8,9}<Inputs!$B$11),(T35/Inputs!$B$23)^{0,1,2,3,4,5,6,7,8,9}/FACT({0,1,2,3,4,5,6,7,8,9}))+((T35/Inputs!$B$23)^Inputs!$B$11/FACT(Inputs!$B$11)*Inputs!$B$11/(Inputs!$B$11-(T35/Inputs!$B$23)))),1) -> 0.41340999 | X35: =IF(V35<1,W35/(Inputs!$B$11*Inputs!$B$23-T35),0) -> 0.048026253 | Y35: =MAX(0,Y34+(T35-Inputs!$B$11*Inputs!$B$23)*10) -> 0 | Z35: =Y35/(Inputs!$B$11*Inputs!$B$23)+X35 -> 0.048026253 | AA35: =T35*(Z35+1/Inputs!$B$23+Inputs!$B$25) -> 195.35032 | AB35: =$C35*(1-$E$26) -> 6.408 | AC35: =AB35/Inputs!$B$42 -> 0.2136 | AD35: =AB35/(Inputs!$B$12*Inputs!$B$23) -> 0.3204 | AE35: =IF(AD35<1,((AB35/Inputs!$B$23)^Inputs!$B$12/FACT(Inputs!$B$12)*Inputs!$B$12/(Inputs!$B$12-(AB35/Inputs!$B$23)))/(SUMPRODUCT(--({0,1,2,3,4,5,6,7,8,9}<Inputs!$B$12),(AB35/Inputs!$B$23)^{0,1,2,3,4,5,6,7,8,9}/FACT({0,1,2,3,4,5,6,7,8,9}))+((AB35/Inputs!$B$23)^Inputs!$B$12/FACT(Inputs!$B$12)*Inputs!$B$12/(Inputs!$B$12-(AB35/Inputs!$B$23)))),1) -> 0.15549252 | AF35: =IF(AD35<1,AE35/(Inputs!$B$12*Inputs!$B$23-AB35),0) -> 0.011440003 | AG35: =MAX(0,AG34+(AB35-Inputs!$B$12*Inputs!$B$23)*10) -> 0 | AH35: =AG35/(Inputs!$B$12*Inputs!$B$23)+AF35 -> 0.011440003 | AI35: =AB35*(AH35+1/Inputs!$B$23+Inputs!$B$25) -> 109.65011
A36: 12:30 | B36: 236 | C36: =B36/10 -> 23.6 | D36: =$C36*Inputs!$B$22 -> 20.06 | E36: =D36/Inputs!$B$41 -> 0.66866667 | F36: =D36/(Inputs!$B$11*Inputs!$B$23) -> 1.003 | G36: =IF(F36<1,((D36/Inputs!$B$23)^Inputs!$B$11/FACT(Inputs!$B$11)*Inputs!$B$11/(Inputs!$B$11-(D36/Inputs!$B$23)))/(SUMPRODUCT(--({0,1,2,3,4,5,6,7,8,9}<Inputs!$B$11),(D36/Inputs!$B$23)^{0,1,2,3,4,5,6,7,8,9}/FACT({0,1,2,3,4,5,6,7,8,9}))+((D36/Inputs!$B$23)^Inputs!$B$11/FACT(Inputs!$B$11)*Inputs!$B$11/(Inputs!$B$11-(D36/Inputs!$B$23)))),1) -> 1 | H36: =IF(F36<1,G36/(Inputs!$B$11*Inputs!$B$23-D36),0) -> 0 | I36: =MAX(0,I35+(D36-Inputs!$B$11*Inputs!$B$23)*10) -> 0.6 | J36: =I36/(Inputs!$B$11*Inputs!$B$23)+H36 -> 0.03 | K36: =D36*(J36+1/Inputs!$B$23+Inputs!$B$25) -> 343.6278 | L36: =$C36*(1-Inputs!$B$22) -> 3.54 | M36: =L36/Inputs!$B$42 -> 0.118 | N36: =L36/(Inputs!$B$12*Inputs!$B$23) -> 0.177 | O36: =IF(N36<1,((L36/Inputs!$B$23)^Inputs!$B$12/FACT(Inputs!$B$12)*Inputs!$B$12/(Inputs!$B$12-(L36/Inputs!$B$23)))/(SUMPRODUCT(--({0,1,2,3,4,5,6,7,8,9}<Inputs!$B$12),(L36/Inputs!$B$23)^{0,1,2,3,4,5,6,7,8,9}/FACT({0,1,2,3,4,5,6,7,8,9}))+((L36/Inputs!$B$23)^Inputs!$B$12/FACT(Inputs!$B$12)*Inputs!$B$12/(Inputs!$B$12-(L36/Inputs!$B$23)))),1) -> 0.053235344 | P36: =IF(N36<1,O36/(Inputs!$B$12*Inputs!$B$23-L36),0) -> 0.003234225 | Q36: =MAX(0,Q35+(L36-Inputs!$B$12*Inputs!$B$23)*10) -> 0 | R36: =Q36/(Inputs!$B$12*Inputs!$B$23)+P36 -> 0.003234225 | S36: =L36*(R36+1/Inputs!$B$23+Inputs!$B$25) -> 60.545449 | T36: =$C36*$E$26 -> 15.104 | U36: =T36/Inputs!$B$41 -> 0.50346667 | V36: =T36/(Inputs!$B$11*Inputs!$B$23) -> 0.7552 | W36: =IF(V36<1,((T36/Inputs!$B$23)^Inputs!$B$11/FACT(Inputs!$B$11)*Inputs!$B$11/(Inputs!$B$11-(T36/Inputs!$B$23)))/(SUMPRODUCT(--({0,1,2,3,4,5,6,7,8,9}<Inputs!$B$11),(T36/Inputs!$B$23)^{0,1,2,3,4,5,6,7,8,9}/FACT({0,1,2,3,4,5,6,7,8,9}))+((T36/Inputs!$B$23)^Inputs!$B$11/FACT(Inputs!$B$11)*Inputs!$B$11/(Inputs!$B$11-(T36/Inputs!$B$23)))),1) -> 0.64987129 | X36: =IF(V36<1,W36/(Inputs!$B$11*Inputs!$B$23-T36),0) -> 0.13273515 | Y36: =MAX(0,Y35+(T36-Inputs!$B$11*Inputs!$B$23)*10) -> 0 | Z36: =Y36/(Inputs!$B$11*Inputs!$B$23)+X36 -> 0.13273515 | AA36: =T36*(Z36+1/Inputs!$B$23+Inputs!$B$25) -> 260.28323 | AB36: =$C36*(1-$E$26) -> 8.496 | AC36: =AB36/Inputs!$B$42 -> 0.2832 | AD36: =AB36/(Inputs!$B$12*Inputs!$B$23) -> 0.4248 | AE36: =IF(AD36<1,((AB36/Inputs!$B$23)^Inputs!$B$12/FACT(Inputs!$B$12)*Inputs!$B$12/(Inputs!$B$12-(AB36/Inputs!$B$23)))/(SUMPRODUCT(--({0,1,2,3,4,5,6,7,8,9}<Inputs!$B$12),(AB36/Inputs!$B$23)^{0,1,2,3,4,5,6,7,8,9}/FACT({0,1,2,3,4,5,6,7,8,9}))+((AB36/Inputs!$B$23)^Inputs!$B$12/FACT(Inputs!$B$12)*Inputs!$B$12/(Inputs!$B$12-(AB36/Inputs!$B$23)))),1) -> 0.25330578 | AF36: =IF(AD36<1,AE36/(Inputs!$B$12*Inputs!$B$23-AB36),0) -> 0.022018931 | AG36: =MAX(0,AG35+(AB36-Inputs!$B$12*Inputs!$B$23)*10) -> 0 | AH36: =AG36/(Inputs!$B$12*Inputs!$B$23)+AF36 -> 0.022018931 | AI36: =AB36*(AH36+1/Inputs!$B$23+Inputs!$B$25) -> 145.46867
A37: 12:40 | B37: 289 | C37: =B37/10 -> 28.9 | D37: =$C37*Inputs!$B$22 -> 24.565 | E37: =D37/Inputs!$B$41 -> 0.81883333 | F37: =D37/(Inputs!$B$11*Inputs!$B$23) -> 1.22825 | G37: =IF(F37<1,((D37/Inputs!$B$23)^Inputs!$B$11/FACT(Inputs!$B$11)*Inputs!$B$11/(Inputs!$B$11-(D37/Inputs!$B$23)))/(SUMPRODUCT(--({0,1,2,3,4,5,6,7,8,9}<Inputs!$B$11),(D37/Inputs!$B$23)^{0,1,2,3,4,5,6,7,8,9}/FACT({0,1,2,3,4,5,6,7,8,9}))+((D37/Inputs!$B$23)^Inputs!$B$11/FACT(Inputs!$B$11)*Inputs!$B$11/(Inputs!$B$11-(D37/Inputs!$B$23)))),1) -> 1 | H37: =IF(F37<1,G37/(Inputs!$B$11*Inputs!$B$23-D37),0) -> 0 | I37: =MAX(0,I36+(D37-Inputs!$B$11*Inputs!$B$23)*10) -> 46.25 | J37: =I37/(Inputs!$B$11*Inputs!$B$23)+H37 -> 2.3125 | K37: =D37*(J37+1/Inputs!$B$23+Inputs!$B$25) -> 476.86806 | L37: =$C37*(1-Inputs!$B$22) -> 4.335 | M37: =L37/Inputs!$B$42 -> 0.1445 | N37: =L37/(Inputs!$B$12*Inputs!$B$23) -> 0.21675 | O37: =IF(N37<1,((L37/Inputs!$B$23)^Inputs!$B$12/FACT(Inputs!$B$12)*Inputs!$B$12/(Inputs!$B$12-(L37/Inputs!$B$23)))/(SUMPRODUCT(--({0,1,2,3,4,5,6,7,8,9}<Inputs!$B$12),(L37/Inputs!$B$23)^{0,1,2,3,4,5,6,7,8,9}/FACT({0,1,2,3,4,5,6,7,8,9}))+((L37/Inputs!$B$23)^Inputs!$B$12/FACT(Inputs!$B$12)*Inputs!$B$12/(Inputs!$B$12-(L37/Inputs!$B$23)))),1) -> 0.077223033 | P37: =IF(N37<1,O37/(Inputs!$B$12*Inputs!$B$23-L37),0) -> 0.0049296542 | Q37: =MAX(0,Q36+(L37-Inputs!$B$12*Inputs!$B$23)*10) -> 0 | R37: =Q37/(Inputs!$B$12*Inputs!$B$23)+P37 -> 0.0049296542 | S37: =L37*(R37+1/Inputs!$B$23+Inputs!$B$25) -> 74.14987 | T37: =$C37*$E$26 -> 18.496 | U37: =T37/Inputs!$B$41 -> 0.61653333 | V37: =T37/(Inputs!$B$11*Inputs!$B$23) -> 0.9248 | W37: =IF(V37<1,((T37/Inputs!$B$23)^Inputs!$B$11/FACT(Inputs!$B$11)*Inputs!$B$11/(Inputs!$B$11-(T37/Inputs!$B$23)))/(SUMPRODUCT(--({0,1,2,3,4,5,6,7,8,9}<Inputs!$B$11),(T37/Inputs!$B$23)^{0,1,2,3,4,5,6,7,8,9}/FACT({0,1,2,3,4,5,6,7,8,9}))+((T37/Inputs!$B$23)^Inputs!$B$11/FACT(Inputs!$B$11)*Inputs!$B$11/(Inputs!$B$11-(T37/Inputs!$B$23)))),1) -> 0.88866899 | X37: =IF(V37<1,W37/(Inputs!$B$11*Inputs!$B$23-T37),0) -> 0.59087034 | Y37: =MAX(0,Y36+(T37-Inputs!$B$11*Inputs!$B$23)*10) -> 0 | Z37: =Y37/(Inputs!$B$11*Inputs!$B$23)+X37 -> 0.59087034 | AA37: =T37*(Z37+1/Inputs!$B$23+Inputs!$B$25) -> 327.21034 | AB37: =$C37*(1-$E$26) -> 10.404 | AC37: =AB37/Inputs!$B$42 -> 0.3468 | AD37: =AB37/(Inputs!$B$12*Inputs!$B$23) -> 0.5202 | AE37: =IF(AD37<1,((AB37/Inputs!$B$23)^Inputs!$B$12/FACT(Inputs!$B$12)*Inputs!$B$12/(Inputs!$B$12-(AB37/Inputs!$B$23)))/(SUMPRODUCT(--({0,1,2,3,4,5,6,7,8,9}<Inputs!$B$12),(AB37/Inputs!$B$23)^{0,1,2,3,4,5,6,7,8,9}/FACT({0,1,2,3,4,5,6,7,8,9}))+((AB37/Inputs!$B$23)^Inputs!$B$12/FACT(Inputs!$B$12)*Inputs!$B$12/(Inputs!$B$12-(AB37/Inputs!$B$23)))),1) -> 0.35601637 | AF37: =IF(AD37<1,AE37/(Inputs!$B$12*Inputs!$B$23-AB37),0) -> 0.037100497 | AG37: =MAX(0,AG36+(AB37-Inputs!$B$12*Inputs!$B$23)*10) -> 0 | AH37: =AG37/(Inputs!$B$12*Inputs!$B$23)+AF37 -> 0.037100497 | AI37: =AB37*(AH37+1/Inputs!$B$23+Inputs!$B$25) -> 178.29439
A38: 12:50 | B38: 326 | C38: =B38/10 -> 32.6 | D38: =$C38*Inputs!$B$22 -> 27.71 | E38: =D38/Inputs!$B$41 -> 0.92366667 | F38: =D38/(Inputs!$B$11*Inputs!$B$23) -> 1.3855 | G38: =IF(F38<1,((D38/Inputs!$B$23)^Inputs!$B$11/FACT(Inputs!$B$11)*Inputs!$B$11/(Inputs!$B$11-(D38/Inputs!$B$23)))/(SUMPRODUCT(--({0,1,2,3,4,5,6,7,8,9}<Inputs!$B$11),(D38/Inputs!$B$23)^{0,1,2,3,4,5,6,7,8,9}/FACT({0,1,2,3,4,5,6,7,8,9}))+((D38/Inputs!$B$23)^Inputs!$B$11/FACT(Inputs!$B$11)*Inputs!$B$11/(Inputs!$B$11-(D38/Inputs!$B$23)))),1) -> 1 | H38: =IF(F38<1,G38/(Inputs!$B$11*Inputs!$B$23-D38),0) -> 0 | I38: =MAX(0,I37+(D38-Inputs!$B$11*Inputs!$B$23)*10) -> 123.35 | J38: =I38/(Inputs!$B$11*Inputs!$B$23)+H38 -> 6.1675 | K38: =D38*(J38+1/Inputs!$B$23+Inputs!$B$25) -> 644.74243 | L38: =$C38*(1-Inputs!$B$22) -> 4.89 | M38: =L38/Inputs!$B$42 -> 0.163 | N38: =L38/(Inputs!$B$12*Inputs!$B$23) -> 0.2445 | O38: =IF(N38<1,((L38/Inputs!$B$23)^Inputs!$B$12/FACT(Inputs!$B$12)*Inputs!$B$12/(Inputs!$B$12-(L38/Inputs!$B$23)))/(SUMPRODUCT(--({0,1,2,3,4,5,6,7,8,9}<Inputs!$B$12),(L38/Inputs!$B$23)^{0,1,2,3,4,5,6,7,8,9}/FACT({0,1,2,3,4,5,6,7,8,9}))+((L38/Inputs!$B$23)^Inputs!$B$12/FACT(Inputs!$B$12)*Inputs!$B$12/(Inputs!$B$12-(L38/Inputs!$B$23)))),1) -> 0.096071113 | P38: =IF(N38<1,O38/(Inputs!$B$12*Inputs!$B$23-L38),0) -> 0.0063581147 | Q38: =MAX(0,Q37+(L38-Inputs!$B$12*Inputs!$B$23)*10) -> 0 | R38: =Q38/(Inputs!$B$12*Inputs!$B$23)+P38 -> 0.0063581147 | S38: =L38*(R38+1/Inputs!$B$23+Inputs!$B$25) -> 83.650091 | T38: =$C38*$E$26 -> 20.864 | U38: =T38/Inputs!$B$41 -> 0.69546667 | V38: =T38/(Inputs!$B$11*Inputs!$B$23) -> 1.0432 | W38: =IF(V38<1,((T38/Inputs!$B$23)^Inputs!$B$11/FACT(Inputs!$B$11)*Inputs!$B$11/(Inputs!$B$11-(T38/Inputs!$B$23)))/(SUMPRODUCT(--({0,1,2,3,4,5,6,7,8,9}<Inputs!$B$11),(T38/Inputs!$B$23)^{0,1,2,3,4,5,6,7,8,9}/FACT({0,1,2,3,4,5,6,7,8,9}))+((T38/Inputs!$B$23)^Inputs!$B$11/FACT(Inputs!$B$11)*Inputs!$B$11/(Inputs!$B$11-(T38/Inputs!$B$23)))),1) -> 1 | X38: =IF(V38<1,W38/(Inputs!$B$11*Inputs!$B$23-T38),0) -> 0 | Y38: =MAX(0,Y37+(T38-Inputs!$B$11*Inputs!$B$23)*10) -> 8.64 | Z38: =Y38/(Inputs!$B$11*Inputs!$B$23)+X38 -> 0.432 | AA38: =T38*(Z38+1/Inputs!$B$23+Inputs!$B$25) -> 365.78765 | AB38: =$C38*(1-$E$26) -> 11.736 | AC38: =AB38/Inputs!$B$42 -> 0.3912 | AD38: =AB38/(Inputs!$B$12*Inputs!$B$23) -> 0.5868 | AE38: =IF(AD38<1,((AB38/Inputs!$B$23)^Inputs!$B$12/FACT(Inputs!$B$12)*Inputs!$B$12/(Inputs!$B$12-(AB38/Inputs!$B$23)))/(SUMPRODUCT(--({0,1,2,3,4,5,6,7,8,9}<Inputs!$B$12),(AB38/Inputs!$B$23)^{0,1,2,3,4,5,6,7,8,9}/FACT({0,1,2,3,4,5,6,7,8,9}))+((AB38/Inputs!$B$23)^Inputs!$B$12/FACT(Inputs!$B$12)*Inputs!$B$12/(Inputs!$B$12-(AB38/Inputs!$B$23)))),1) -> 0.43399829 | AF38: =IF(AD38<1,AE38/(Inputs!$B$12*Inputs!$B$23-AB38),0) -> 0.052516734 | AG38: =MAX(0,AG37+(AB38-Inputs!$B$12*Inputs!$B$23)*10) -> 0 | AH38: =AG38/(Inputs!$B$12*Inputs!$B$23)+AF38 -> 0.052516734 | AI38: =AB38*(AH38+1/Inputs!$B$23+Inputs!$B$25) -> 201.30194
A39: 13:00 | B39: 340 | C39: =B39/10 -> 34 | D39: =$C39*Inputs!$B$22 -> 28.9 | E39: =D39/Inputs!$B$41 -> 0.96333333 | F39: =D39/(Inputs!$B$11*Inputs!$B$23) -> 1.445 | G39: =IF(F39<1,((D39/Inputs!$B$23)^Inputs!$B$11/FACT(Inputs!$B$11)*Inputs!$B$11/(Inputs!$B$11-(D39/Inputs!$B$23)))/(SUMPRODUCT(--({0,1,2,3,4,5,6,7,8,9}<Inputs!$B$11),(D39/Inputs!$B$23)^{0,1,2,3,4,5,6,7,8,9}/FACT({0,1,2,3,4,5,6,7,8,9}))+((D39/Inputs!$B$23)^Inputs!$B$11/FACT(Inputs!$B$11)*Inputs!$B$11/(Inputs!$B$11-(D39/Inputs!$B$23)))),1) -> 1 | H39: =IF(F39<1,G39/(Inputs!$B$11*Inputs!$B$23-D39),0) -> 0 | I39: =MAX(0,I38+(D39-Inputs!$B$11*Inputs!$B$23)*10) -> 212.35 | J39: =I39/(Inputs!$B$11*Inputs!$B$23)+H39 -> 10.6175 | K39: =D39*(J39+1/Inputs!$B$23+Inputs!$B$25) -> 801.03575 | L39: =$C39*(1-Inputs!$B$22) -> 5.1 | M39: =L39/Inputs!$B$42 -> 0.17 | N39: =L39/(Inputs!$B$12*Inputs!$B$23) -> 0.255 | O39: =IF(N39<1,((L39/Inputs!$B$23)^Inputs!$B$12/FACT(Inputs!$B$12)*Inputs!$B$12/(Inputs!$B$12-(L39/Inputs!$B$23)))/(SUMPRODUCT(--({0,1,2,3,4,5,6,7,8,9}<Inputs!$B$12),(L39/Inputs!$B$23)^{0,1,2,3,4,5,6,7,8,9}/FACT({0,1,2,3,4,5,6,7,8,9}))+((L39/Inputs!$B$23)^Inputs!$B$12/FACT(Inputs!$B$12)*Inputs!$B$12/(Inputs!$B$12-(L39/Inputs!$B$23)))),1) -> 0.1036255 | P39: =IF(N39<1,O39/(Inputs!$B$12*Inputs!$B$23-L39),0) -> 0.0069547314 | Q39: =MAX(0,Q38+(L39-Inputs!$B$12*Inputs!$B$23)*10) -> 0 | R39: =Q39/(Inputs!$B$12*Inputs!$B$23)+P39 -> 0.0069547314 | S39: =L39*(R39+1/Inputs!$B$23+Inputs!$B$25) -> 87.245469 | T39: =$C39*$E$26 -> 21.76 | U39: =T39/Inputs!$B$41 -> 0.72533333 | V39: =T39/(Inputs!$B$11*Inputs!$B$23) -> 1.088 | W39: =IF(V39<1,((T39/Inputs!$B$23)^Inputs!$B$11/FACT(Inputs!$B$11)*Inputs!$B$11/(Inputs!$B$11-(T39/Inputs!$B$23)))/(SUMPRODUCT(--({0,1,2,3,4,5,6,7,8,9}<Inputs!$B$11),(T39/Inputs!$B$23)^{0,1,2,3,4,5,6,7,8,9}/FACT({0,1,2,3,4,5,6,7,8,9}))+((T39/Inputs!$B$23)^Inputs!$B$11/FACT(Inputs!$B$11)*Inputs!$B$11/(Inputs!$B$11-(T39/Inputs!$B$23)))),1) -> 1 | X39: =IF(V39<1,W39/(Inputs!$B$11*Inputs!$B$23-T39),0) -> 0 | Y39: =MAX(0,Y38+(T39-Inputs!$B$11*Inputs!$B$23)*10) -> 26.24 | Z39: =Y39/(Inputs!$B$11*Inputs!$B$23)+X39 -> 1.312 | AA39: =T39*(Z39+1/Inputs!$B$23+Inputs!$B$25) -> 400.64512 | AB39: =$C39*(1-$E$26) -> 12.24 | AC39: =AB39/Inputs!$B$42 -> 0.408 | AD39: =AB39/(Inputs!$B$12*Inputs!$B$23) -> 0.612 | AE39: =IF(AD39<1,((AB39/Inputs!$B$23)^Inputs!$B$12/FACT(Inputs!$B$12)*Inputs!$B$12/(Inputs!$B$12-(AB39/Inputs!$B$23)))/(SUMPRODUCT(--({0,1,2,3,4,5,6,7,8,9}<Inputs!$B$12),(AB39/Inputs!$B$23)^{0,1,2,3,4,5,6,7,8,9}/FACT({0,1,2,3,4,5,6,7,8,9}))+((AB39/Inputs!$B$23)^Inputs!$B$12/FACT(Inputs!$B$12)*Inputs!$B$12/(Inputs!$B$12-(AB39/Inputs!$B$23)))),1) -> 0.46469479 | AF39: =IF(AD39<1,AE39/(Inputs!$B$12*Inputs!$B$23-AB39),0) -> 0.059883349 | AG39: =MAX(0,AG38+(AB39-Inputs!$B$12*Inputs!$B$23)*10) -> 0 | AH39: =AG39/(Inputs!$B$12*Inputs!$B$23)+AF39 -> 0.059883349 | AI39: =AB39*(AH39+1/Inputs!$B$23+Inputs!$B$25) -> 210.03697
A40: 13:10 | B40: 326 | C40: =B40/10 -> 32.6 | D40: =$C40*Inputs!$B$22 -> 27.71 | E40: =D40/Inputs!$B$41 -> 0.92366667 | F40: =D40/(Inputs!$B$11*Inputs!$B$23) -> 1.3855 | G40: =IF(F40<1,((D40/Inputs!$B$23)^Inputs!$B$11/FACT(Inputs!$B$11)*Inputs!$B$11/(Inputs!$B$11-(D40/Inputs!$B$23)))/(SUMPRODUCT(--({0,1,2,3,4,5,6,7,8,9}<Inputs!$B$11),(D40/Inputs!$B$23)^{0,1,2,3,4,5,6,7,8,9}/FACT({0,1,2,3,4,5,6,7,8,9}))+((D40/Inputs!$B$23)^Inputs!$B$11/FACT(Inputs!$B$11)*Inputs!$B$11/(Inputs!$B$11-(D40/Inputs!$B$23)))),1) -> 1 | H40: =IF(F40<1,G40/(Inputs!$B$11*Inputs!$B$23-D40),0) -> 0 | I40: =MAX(0,I39+(D40-Inputs!$B$11*Inputs!$B$23)*10) -> 289.45 | J40: =I40/(Inputs!$B$11*Inputs!$B$23)+H40 -> 14.4725 | K40: =D40*(J40+1/Inputs!$B$23+Inputs!$B$25) -> 874.87397 | L40: =$C40*(1-Inputs!$B$22) -> 4.89 | M40: =L40/Inputs!$B$42 -> 0.163 | N40: =L40/(Inputs!$B$12*Inputs!$B$23) -> 0.2445 | O40: =IF(N40<1,((L40/Inputs!$B$23)^Inputs!$B$12/FACT(Inputs!$B$12)*Inputs!$B$12/(Inputs!$B$12-(L40/Inputs!$B$23)))/(SUMPRODUCT(--({0,1,2,3,4,5,6,7,8,9}<Inputs!$B$12),(L40/Inputs!$B$23)^{0,1,2,3,4,5,6,7,8,9}/FACT({0,1,2,3,4,5,6,7,8,9}))+((L40/Inputs!$B$23)^Inputs!$B$12/FACT(Inputs!$B$12)*Inputs!$B$12/(Inputs!$B$12-(L40/Inputs!$B$23)))),1) -> 0.096071113 | P40: =IF(N40<1,O40/(Inputs!$B$12*Inputs!$B$23-L40),0) -> 0.0063581147 | Q40: =MAX(0,Q39+(L40-Inputs!$B$12*Inputs!$B$23)*10) -> 0 | R40: =Q40/(Inputs!$B$12*Inputs!$B$23)+P40 -> 0.0063581147 | S40: =L40*(R40+1/Inputs!$B$23+Inputs!$B$25) -> 83.650091 | T40: =$C40*$E$26 -> 20.864 | U40: =T40/Inputs!$B$41 -> 0.69546667 | V40: =T40/(Inputs!$B$11*Inputs!$B$23) -> 1.0432 | W40: =IF(V40<1,((T40/Inputs!$B$23)^Inputs!$B$11/FACT(Inputs!$B$11)*Inputs!$B$11/(Inputs!$B$11-(T40/Inputs!$B$23)))/(SUMPRODUCT(--({0,1,2,3,4,5,6,7,8,9}<Inputs!$B$11),(T40/Inputs!$B$23)^{0,1,2,3,4,5,6,7,8,9}/FACT({0,1,2,3,4,5,6,7,8,9}))+((T40/Inputs!$B$23)^Inputs!$B$11/FACT(Inputs!$B$11)*Inputs!$B$11/(Inputs!$B$11-(T40/Inputs!$B$23)))),1) -> 1 | X40: =IF(V40<1,W40/(Inputs!$B$11*Inputs!$B$23-T40),0) -> 0 | Y40: =MAX(0,Y39+(T40-Inputs!$B$11*Inputs!$B$23)*10) -> 34.88 | Z40: =Y40/(Inputs!$B$11*Inputs!$B$23)+X40 -> 1.744 | AA40: =T40*(Z40+1/Inputs!$B$23+Inputs!$B$25) -> 393.16122 | AB40: =$C40*(1-$E$26) -> 11.736 | AC40: =AB40/Inputs!$B$42 -> 0.3912 | AD40: =AB40/(Inputs!$B$12*Inputs!$B$23) -> 0.5868 | AE40: =IF(AD40<1,((AB40/Inputs!$B$23)^Inputs!$B$12/FACT(Inputs!$B$12)*Inputs!$B$12/(Inputs!$B$12-(AB40/Inputs!$B$23)))/(SUMPRODUCT(--({0,1,2,3,4,5,6,7,8,9}<Inputs!$B$12),(AB40/Inputs!$B$23)^{0,1,2,3,4,5,6,7,8,9}/FACT({0,1,2,3,4,5,6,7,8,9}))+((AB40/Inputs!$B$23)^Inputs!$B$12/FACT(Inputs!$B$12)*Inputs!$B$12/(Inputs!$B$12-(AB40/Inputs!$B$23)))),1) -> 0.43399829 | AF40: =IF(AD40<1,AE40/(Inputs!$B$12*Inputs!$B$23-AB40),0) -> 0.052516734 | AG40: =MAX(0,AG39+(AB40-Inputs!$B$12*Inputs!$B$23)*10) -> 0 | AH40: =AG40/(Inputs!$B$12*Inputs!$B$23)+AF40 -> 0.052516734 | AI40: =AB40*(AH40+1/Inputs!$B$23+Inputs!$B$25) -> 201.30194
A41: 13:20 | B41: 289 | C41: =B41/10 -> 28.9 | D41: =$C41*Inputs!$B$22 -> 24.565 | E41: =D41/Inputs!$B$41 -> 0.81883333 | F41: =D41/(Inputs!$B$11*Inputs!$B$23) -> 1.22825 | G41: =IF(F41<1,((D41/Inputs!$B$23)^Inputs!$B$11/FACT(Inputs!$B$11)*Inputs!$B$11/(Inputs!$B$11-(D41/Inputs!$B$23)))/(SUMPRODUCT(--({0,1,2,3,4,5,6,7,8,9}<Inputs!$B$11),(D41/Inputs!$B$23)^{0,1,2,3,4,5,6,7,8,9}/FACT({0,1,2,3,4,5,6,7,8,9}))+((D41/Inputs!$B$23)^Inputs!$B$11/FACT(Inputs!$B$11)*Inputs!$B$11/(Inputs!$B$11-(D41/Inputs!$B$23)))),1) -> 1 | H41: =IF(F41<1,G41/(Inputs!$B$11*Inputs!$B$23-D41),0) -> 0 | I41: =MAX(0,I40+(D41-Inputs!$B$11*Inputs!$B$23)*10) -> 335.1 | J41: =I41/(Inputs!$B$11*Inputs!$B$23)+H41 -> 16.755 | K41: =D41*(J41+1/Inputs!$B$23+Inputs!$B$25) -> 831.64807 | L41: =$C41*(1-Inputs!$B$22) -> 4.335 | M41: =L41/Inputs!$B$42 -> 0.1445 | N41: =L41/(Inputs!$B$12*Inputs!$B$23) -> 0.21675 | O41: =IF(N41<1,((L41/Inputs!$B$23)^Inputs!$B$12/FACT(Inputs!$B$12)*Inputs!$B$12/(Inputs!$B$12-(L41/Inputs!$B$23)))/(SUMPRODUCT(--({0,1,2,3,4,5,6,7,8,9}<Inputs!$B$12),(L41/Inputs!$B$23)^{0,1,2,3,4,5,6,7,8,9}/FACT({0,1,2,3,4,5,6,7,8,9}))+((L41/Inputs!$B$23)^Inputs!$B$12/FACT(Inputs!$B$12)*Inputs!$B$12/(Inputs!$B$12-(L41/Inputs!$B$23)))),1) -> 0.077223033 | P41: =IF(N41<1,O41/(Inputs!$B$12*Inputs!$B$23-L41),0) -> 0.0049296542 | Q41: =MAX(0,Q40+(L41-Inputs!$B$12*Inputs!$B$23)*10) -> 0 | R41: =Q41/(Inputs!$B$12*Inputs!$B$23)+P41 -> 0.0049296542 | S41: =L41*(R41+1/Inputs!$B$23+Inputs!$B$25) -> 74.14987 | T41: =$C41*$E$26 -> 18.496 | U41: =T41/Inputs!$B$41 -> 0.61653333 | V41: =T41/(Inputs!$B$11*Inputs!$B$23) -> 0.9248 | W41: =IF(V41<1,((T41/Inputs!$B$23)^Inputs!$B$11/FACT(Inputs!$B$11)*Inputs!$B$11/(Inputs!$B$11-(T41/Inputs!$B$23)))/(SUMPRODUCT(--({0,1,2,3,4,5,6,7,8,9}<Inputs!$B$11),(T41/Inputs!$B$23)^{0,1,2,3,4,5,6,7,8,9}/FACT({0,1,2,3,4,5,6,7,8,9}))+((T41/Inputs!$B$23)^Inputs!$B$11/FACT(Inputs!$B$11)*Inputs!$B$11/(Inputs!$B$11-(T41/Inputs!$B$23)))),1) -> 0.88866899 | X41: =IF(V41<1,W41/(Inputs!$B$11*Inputs!$B$23-T41),0) -> 0.59087034 | Y41: =MAX(0,Y40+(T41-Inputs!$B$11*Inputs!$B$23)*10) -> 19.84 | Z41: =Y41/(Inputs!$B$11*Inputs!$B$23)+X41 -> 1.5828703 | AA41: =T41*(Z41+1/Inputs!$B$23+Inputs!$B$25) -> 345.55837 | AB41: =$C41*(1-$E$26) -> 10.404 | AC41: =AB41/Inputs!$B$42 -> 0.3468 | AD41: =AB41/(Inputs!$B$12*Inputs!$B$23) -> 0.5202 | AE41: =IF(AD41<1,((AB41/Inputs!$B$23)^Inputs!$B$12/FACT(Inputs!$B$12)*Inputs!$B$12/(Inputs!$B$12-(AB41/Inputs!$B$23)))/(SUMPRODUCT(--({0,1,2,3,4,5,6,7,8,9}<Inputs!$B$12),(AB41/Inputs!$B$23)^{0,1,2,3,4,5,6,7,8,9}/FACT({0,1,2,3,4,5,6,7,8,9}))+((AB41/Inputs!$B$23)^Inputs!$B$12/FACT(Inputs!$B$12)*Inputs!$B$12/(Inputs!$B$12-(AB41/Inputs!$B$23)))),1) -> 0.35601637 | AF41: =IF(AD41<1,AE41/(Inputs!$B$12*Inputs!$B$23-AB41),0) -> 0.037100497 | AG41: =MAX(0,AG40+(AB41-Inputs!$B$12*Inputs!$B$23)*10) -> 0 | AH41: =AG41/(Inputs!$B$12*Inputs!$B$23)+AF41 -> 0.037100497 | AI41: =AB41*(AH41+1/Inputs!$B$23+Inputs!$B$25) -> 178.29439
A42: 13:30 | B42: 236 | C42: =B42/10 -> 23.6 | D42: =$C42*Inputs!$B$22 -> 20.06 | E42: =D42/Inputs!$B$41 -> 0.66866667 | F42: =D42/(Inputs!$B$11*Inputs!$B$23) -> 1.003 | G42: =IF(F42<1,((D42/Inputs!$B$23)^Inputs!$B$11/FACT(Inputs!$B$11)*Inputs!$B$11/(Inputs!$B$11-(D42/Inputs!$B$23)))/(SUMPRODUCT(--({0,1,2,3,4,5,6,7,8,9}<Inputs!$B$11),(D42/Inputs!$B$23)^{0,1,2,3,4,5,6,7,8,9}/FACT({0,1,2,3,4,5,6,7,8,9}))+((D42/Inputs!$B$23)^Inputs!$B$11/FACT(Inputs!$B$11)*Inputs!$B$11/(Inputs!$B$11-(D42/Inputs!$B$23)))),1) -> 1 | H42: =IF(F42<1,G42/(Inputs!$B$11*Inputs!$B$23-D42),0) -> 0 | I42: =MAX(0,I41+(D42-Inputs!$B$11*Inputs!$B$23)*10) -> 335.7 | J42: =I42/(Inputs!$B$11*Inputs!$B$23)+H42 -> 16.785 | K42: =D42*(J42+1/Inputs!$B$23+Inputs!$B$25) -> 679.7331 | L42: =$C42*(1-Inputs!$B$22) -> 3.54 | M42: =L42/Inputs!$B$42 -> 0.118 | N42: =L42/(Inputs!$B$12*Inputs!$B$23) -> 0.177 | O42: =IF(N42<1,((L42/Inputs!$B$23)^Inputs!$B$12/FACT(Inputs!$B$12)*Inputs!$B$12/(Inputs!$B$12-(L42/Inputs!$B$23)))/(SUMPRODUCT(--({0,1,2,3,4,5,6,7,8,9}<Inputs!$B$12),(L42/Inputs!$B$23)^{0,1,2,3,4,5,6,7,8,9}/FACT({0,1,2,3,4,5,6,7,8,9}))+((L42/Inputs!$B$23)^Inputs!$B$12/FACT(Inputs!$B$12)*Inputs!$B$12/(Inputs!$B$12-(L42/Inputs!$B$23)))),1) -> 0.053235344 | P42: =IF(N42<1,O42/(Inputs!$B$12*Inputs!$B$23-L42),0) -> 0.003234225 | Q42: =MAX(0,Q41+(L42-Inputs!$B$12*Inputs!$B$23)*10) -> 0 | R42: =Q42/(Inputs!$B$12*Inputs!$B$23)+P42 -> 0.003234225 | S42: =L42*(R42+1/Inputs!$B$23+Inputs!$B$25) -> 60.545449 | T42: =$C42*$E$26 -> 15.104 | U42: =T42/Inputs!$B$41 -> 0.50346667 | V42: =T42/(Inputs!$B$11*Inputs!$B$23) -> 0.7552 | W42: =IF(V42<1,((T42/Inputs!$B$23)^Inputs!$B$11/FACT(Inputs!$B$11)*Inputs!$B$11/(Inputs!$B$11-(T42/Inputs!$B$23)))/(SUMPRODUCT(--({0,1,2,3,4,5,6,7,8,9}<Inputs!$B$11),(T42/Inputs!$B$23)^{0,1,2,3,4,5,6,7,8,9}/FACT({0,1,2,3,4,5,6,7,8,9}))+((T42/Inputs!$B$23)^Inputs!$B$11/FACT(Inputs!$B$11)*Inputs!$B$11/(Inputs!$B$11-(T42/Inputs!$B$23)))),1) -> 0.64987129 | X42: =IF(V42<1,W42/(Inputs!$B$11*Inputs!$B$23-T42),0) -> 0.13273515 | Y42: =MAX(0,Y41+(T42-Inputs!$B$11*Inputs!$B$23)*10) -> 0 | Z42: =Y42/(Inputs!$B$11*Inputs!$B$23)+X42 -> 0.13273515 | AA42: =T42*(Z42+1/Inputs!$B$23+Inputs!$B$25) -> 260.28323 | AB42: =$C42*(1-$E$26) -> 8.496 | AC42: =AB42/Inputs!$B$42 -> 0.2832 | AD42: =AB42/(Inputs!$B$12*Inputs!$B$23) -> 0.4248 | AE42: =IF(AD42<1,((AB42/Inputs!$B$23)^Inputs!$B$12/FACT(Inputs!$B$12)*Inputs!$B$12/(Inputs!$B$12-(AB42/Inputs!$B$23)))/(SUMPRODUCT(--({0,1,2,3,4,5,6,7,8,9}<Inputs!$B$12),(AB42/Inputs!$B$23)^{0,1,2,3,4,5,6,7,8,9}/FACT({0,1,2,3,4,5,6,7,8,9}))+((AB42/Inputs!$B$23)^Inputs!$B$12/FACT(Inputs!$B$12)*Inputs!$B$12/(Inputs!$B$12-(AB42/Inputs!$B$23)))),1) -> 0.25330578 | AF42: =IF(AD42<1,AE42/(Inputs!$B$12*Inputs!$B$23-AB42),0) -> 0.022018931 | AG42: =MAX(0,AG41+(AB42-Inputs!$B$12*Inputs!$B$23)*10) -> 0 | AH42: =AG42/(Inputs!$B$12*Inputs!$B$23)+AF42 -> 0.022018931 | AI42: =AB42*(AH42+1/Inputs!$B$23+Inputs!$B$25) -> 145.46867
... A47: 14:20 | B47: 25 | C47: =B47/10 -> 2.5 | D47: =$C47*Inputs!$B$22 -> 2.125 | E47: =D47/Inputs!$B$41 -> 0.070833333 | F47: =D47/(Inputs!$B$11*Inputs!$B$23) -> 0.10625 | G47: =IF(F47<1,((D47/Inputs!$B$23)^Inputs!$B$11/FACT(Inputs!$B$11)*Inputs!$B$11/(Inputs!$B$11-(D47/Inputs!$B$23)))/(SUMPRODUCT(--({0,1,2,3,4,5,6,7,8,9}<Inputs!$B$11),(D47/Inputs!$B$23)^{0,1,2,3,4,5,6,7,8,9}/FACT({0,1,2,3,4,5,6,7,8,9}))+((D47/Inputs!$B$23)^Inputs!$B$11/FACT(Inputs!$B$11)*Inputs!$B$11/(Inputs!$B$11-(D47/Inputs!$B$23)))),1) -> 0.020409605 | H47: =IF(F47<1,G47/(Inputs!$B$11*Inputs!$B$23-D47),0) -> 0.0011417961 | I47: =MAX(0,I46+(D47-Inputs!$B$11*Inputs!$B$23)*10) -> 0 | J47: =I47/(Inputs!$B$11*Inputs!$B$23)+H47 -> 0.0011417961 | K47: =D47*(J47+1/Inputs!$B$23+Inputs!$B$25) -> 36.339926 | L47: =$C47*(1-Inputs!$B$22) -> 0.375 | M47: =L47/Inputs!$B$42 -> 0.0125 | N47: =L47/(Inputs!$B$12*Inputs!$B$23) -> 0.01875 | O47: =IF(N47<1,((L47/Inputs!$B$23)^Inputs!$B$12/FACT(Inputs!$B$12)*Inputs!$B$12/(Inputs!$B$12-(L47/Inputs!$B$23)))/(SUMPRODUCT(--({0,1,2,3,4,5,6,7,8,9}<Inputs!$B$12),(L47/Inputs!$B$23)^{0,1,2,3,4,5,6,7,8,9}/FACT({0,1,2,3,4,5,6,7,8,9}))+((L47/Inputs!$B$23)^Inputs!$B$12/FACT(Inputs!$B$12)*Inputs!$B$12/(Inputs!$B$12-(L47/Inputs!$B$23)))),1) -> 0.00069018405 | P47: =IF(N47<1,O47/(Inputs!$B$12*Inputs!$B$23-L47),0) -> 3.5168614e-05 | Q47: =MAX(0,Q46+(L47-Inputs!$B$12*Inputs!$B$23)*10) -> 0 | R47: =Q47/(Inputs!$B$12*Inputs!$B$23)+P47 -> 3.5168614e-05 | S47: =L47*(R47+1/Inputs!$B$23+Inputs!$B$25) -> 6.4125132 | T47: =$C47*$E$26 -> 1.6 | U47: =T47/Inputs!$B$41 -> 0.053333333 | V47: =T47/(Inputs!$B$11*Inputs!$B$23) -> 0.08 | W47: =IF(V47<1,((T47/Inputs!$B$23)^Inputs!$B$11/FACT(Inputs!$B$11)*Inputs!$B$11/(Inputs!$B$11-(T47/Inputs!$B$23)))/(SUMPRODUCT(--({0,1,2,3,4,5,6,7,8,9}<Inputs!$B$11),(T47/Inputs!$B$23)^{0,1,2,3,4,5,6,7,8,9}/FACT({0,1,2,3,4,5,6,7,8,9}))+((T47/Inputs!$B$23)^Inputs!$B$11/FACT(Inputs!$B$11)*Inputs!$B$11/(Inputs!$B$11-(T47/Inputs!$B$23)))),1) -> 0.011851852 | X47: =IF(V47<1,W47/(Inputs!$B$11*Inputs!$B$23-T47),0) -> 0.00064412238 | Y47: =MAX(0,Y46+(T47-Inputs!$B$11*Inputs!$B$23)*10) -> 0 | Z47: =Y47/(Inputs!$B$11*Inputs!$B$23)+X47 -> 0.00064412238 | AA47: =T47*(Z47+1/Inputs!$B$23+Inputs!$B$25) -> 27.361031 | AB47: =$C47*(1-$E$26) -> 0.9 | AC47: =AB47/Inputs!$B$42 -> 0.03 | AD47: =AB47/(Inputs!$B$12*Inputs!$B$23) -> 0.045 | AE47: =IF(AD47<1,((AB47/Inputs!$B$23)^Inputs!$B$12/FACT(Inputs!$B$12)*Inputs!$B$12/(Inputs!$B$12-(AB47/Inputs!$B$23)))/(SUMPRODUCT(--({0,1,2,3,4,5,6,7,8,9}<Inputs!$B$12),(AB47/Inputs!$B$23)^{0,1,2,3,4,5,6,7,8,9}/FACT({0,1,2,3,4,5,6,7,8,9}))+((AB47/Inputs!$B$23)^Inputs!$B$12/FACT(Inputs!$B$12)*Inputs!$B$12/(Inputs!$B$12-(AB47/Inputs!$B$23)))),1) -> 0.0038755981 | AF47: =IF(AD47<1,AE47/(Inputs!$B$12*Inputs!$B$23-AB47),0) -> 0.00020291089 | AG47: =MAX(0,AG46+(AB47-Inputs!$B$12*Inputs!$B$23)*10) -> 0 | AH47: =AG47/(Inputs!$B$12*Inputs!$B$23)+AF47 -> 0.00020291089 | AI47: =AB47*(AH47+1/Inputs!$B$23+Inputs!$B$25) -> 15.390183
A49: Summary
A50: Measure | D50: Without: Central | E50: Without: Munch | F50: With: Central | G50: With: Munch | H50: Without: both | I50: With: both
A51: Average wait per student (min) | D51: =SUMPRODUCT(J30:J47,D30:D47)/SUM(D30:D47) -> 8.0571067 | E51: =SUMPRODUCT(R30:R47,L30:L47)/SUM(L30:L47) -> 0.0039920115 | F51: =SUMPRODUCT(Z30:Z47,T30:T47)/SUM(T30:T47) -> 0.63171875 | G51: =SUMPRODUCT(AH30:AH47,AB30:AB47)/SUM(AB30:AB47) -> 0.031153637 | H51: =(D51*SUM(D30:D47)+E51*SUM(L30:L47))/SUM(C30:C47) -> 6.8491395 | I51: =(F51*SUM(T30:T47)+G51*SUM(AB30:AB47))/SUM(C30:C47) -> 0.41551531
A52: Peak utilisation ρ (serving) | D52: =MAX(F30:F47) -> 1.445 | E52: =MAX(N30:N47) -> 0.255 | F52: =MAX(V30:V47) -> 1.088 | G52: =MAX(AD30:AD47) -> 0.612
A53: Peak scanner utilisation | D53: =MAX(E30:E47) -> 0.96333333 | E53: =MAX(M30:M47) -> 0.17 | F53: =MAX(U30:U47) -> 0.72533333 | G53: =MAX(AC30:AC47) -> 0.408
A54: Largest queue (students) | D54: =MAX(I30:I47) -> 335.7 | E54: =MAX(Q30:Q47) -> 0 | F54: =MAX(Y30:Y47) -> 34.88 | G54: =MAX(AG30:AG47) -> 0
A55: Longest wait (min) | D55: =MAX(J30:J47) -> 16.785 | E55: =MAX(R30:R47) -> 0.0069547314 | F55: =MAX(Z30:Z47) -> 1.744 | G55: =MAX(AH30:AH47) -> 0.059883349
A56: Peak people inside (Little's Law) | D56: =MAX(K30:K47) -> 874.87397 | E56: =MAX(S30:S47) -> 87.245469 | F56: =MAX(AA30:AA47) -> 400.64512 | G56: =MAX(AI30:AI47) -> 210.03697
A57: Seats | D57: =Inputs!$B$9 -> 900 | E57: =Inputs!$B$10 -> 500 | F57: =Inputs!$B$9 -> 900 | G57: =Inputs!$B$10 -> 500
A59: Reading it: utilisation above ~85–90% makes waits climb steeply; above 100% the queue grows every minute (backlog column). The screens lower the peak utilisation of the busier mess by moving some students to the other one. A scanner near 100% means a queue is forming OUTSIDE, before anyone is scanned, so the system cannot see it (multi-phase system: scanner → serving station → seat). Results depend on the assumed service rate μ — measure it.

Sheet S7 Payoff Matrix
A1: Decision making under uncertainty and risk: payoff matrix, with and without the system
A2: Session 7: Decision making under certainty, risk and uncertainty (maximax, maximin, minimax regret, Hurwicz, Laplace, EMV, EVPI)
A4: Everything on this tab is in MINUTES of waiting per student, so no rupee values are needed. Blue = input. S2 values for A1 and A2 come from our simulator (7.1 → 0.8 min); the other cells are illustrative estimates.
A6: Average wait per student (minutes) [lower is better] | B6: S1 Normal day | C6: S2 Busy day | D6: S3 Surge + food run-out | F6: Why these numbers: A1/A2 on a busy day are simulator results (Simulation Results tab). A surge with a run-out adds the restock gap (up to 30 min after the call), which screens can only partly hide (A2) and early kitchen alerts mostly prevent (A3). A 3rd station (A4) raises Central's serving capacity from 20 to 30/min but leaves the 85/15 imbalance and the single scanner. Replace with simulator runs or logs when available.
A7: A1 No system (today) | B7: 2.5 | C7: 7.1 | D7: 15
A8: A2 Door screens + routing | B8: 0.7 | C8: 0.8 | D8: 6
A9: A3 Screens + kitchen early alerts | B9: 0.7 | C9: 0.8 | D9: 3.5
A10: A4 3rd serving station at peak (no screens) | B10: 1.5 | C10: 3.5 | D10: 9
A11: A5 Screens + 3rd serving station | B11: 0.5 | C11: 0.6 | D11: 4.5
A13: Probability of each situation | B13: S1 Normal day | C13: S2 Busy day | D13: S3 Surge + food run-out
A14: P(situation) — from biometric logs: share of lunches that are normal / busy / surge | B14: 0.3 | C14: 0.5 | D14: 0.2 | E14: =SUM(B14:D14) -> 1 | F14: ← must be 100%
A15: Students per lunch (to turn minutes per student into hours per lunch) | B15: =Inputs!$B$6 -> 2960
A17: Payoff = minutes saved per student compared with today = wait(A1) − wait(alternative) [higher is better]
A18: Alternative | B18: S1 Normal day | C18: S2 Busy day | D18: S3 Surge + food run-out | E18: Maximax (optimistic) | F18: Maximin (pessimistic) | G18: Hurwicz | H18: Laplace (equal likelihood) | I18: EMV (with probabilities) | J18: Student-hours saved per lunch (EMV)
A19: A1 No system (today) | B19: =B$7-B7 -> 0 | C19: =C$7-C7 -> 0 | D19: =D$7-D7 -> 0 | E19: =MAX(B19:D19) -> 0 | F19: =MIN(B19:D19) -> 0 | G19: =$B$26*E19+(1-$B$26)*F19 -> 0 | H19: =AVERAGE(B19:D19) -> 0 | I19: =SUMPRODUCT(B19:D19,$B$14:$D$14) -> 0 | J19: =I19*$B$15/60 -> 0
A20: A2 Door screens + routing | B20: =B$7-B8 -> 1.8 | C20: =C$7-C8 -> 6.3 | D20: =D$7-D8 -> 9 | E20: =MAX(B20:D20) -> 9 | F20: =MIN(B20:D20) -> 1.8 | G20: =$B$26*E20+(1-$B$26)*F20 -> 4.68 | H20: =AVERAGE(B20:D20) -> 5.7 | I20: =SUMPRODUCT(B20:D20,$B$14:$D$14) -> 5.49 | J20: =I20*$B$15/60 -> 270.84
A21: A3 Screens + kitchen early alerts | B21: =B$7-B9 -> 1.8 | C21: =C$7-C9 -> 6.3 | D21: =D$7-D9 -> 11.5 | E21: =MAX(B21:D21) -> 11.5 | F21: =MIN(B21:D21) -> 1.8 | G21: =$B$26*E21+(1-$B$26)*F21 -> 5.68 | H21: =AVERAGE(B21:D21) -> 6.5333333 | I21: =SUMPRODUCT(B21:D21,$B$14:$D$14) -> 5.99 | J21: =I21*$B$15/60 -> 295.50667
A22: A4 3rd serving station at peak (no screens) | B22: =B$7-B10 -> 1 | C22: =C$7-C10 -> 3.6 | D22: =D$7-D10 -> 6 | E22: =MAX(B22:D22) -> 6 | F22: =MIN(B22:D22) -> 1 | G22: =$B$26*E22+(1-$B$26)*F22 -> 3 | H22: =AVERAGE(B22:D22) -> 3.5333333 | I22: =SUMPRODUCT(B22:D22,$B$14:$D$14) -> 3.3 | J22: =I22*$B$15/60 -> 162.8
A23: A5 Screens + 3rd serving station | B23: =B$7-B11 -> 2 | C23: =C$7-C11 -> 6.5 | D23: =D$7-D11 -> 10.5 | E23: =MAX(B23:D23) -> 10.5 | F23: =MIN(B23:D23) -> 2 | G23: =$B$26*E23+(1-$B$26)*F23 -> 5.4 | H23: =AVERAGE(B23:D23) -> 6.3333333 | I23: =SUMPRODUCT(B23:D23,$B$14:$D$14) -> 5.95 | J23: =I23*$B$15/60 -> 293.53333
A24: Best alternative by criterion | E24: =INDEX($A$19:$A$23,MATCH(MAX(E19:E23),E19:E23,0)) -> A3 Screens + kitchen early alerts | F24: =INDEX($A$19:$A$23,MATCH(MAX(F19:F23),F19:F23,0)) -> A5 Screens + 3rd serving station | G24: =INDEX($A$19:$A$23,MATCH(MAX(G19:G23),G19:G23,0)) -> A3 Screens + kitchen early alerts | H24: =INDEX($A$19:$A$23,MATCH(MAX(H19:H23),H19:H23,0)) -> A3 Screens + kitchen early alerts | I24: =INDEX($A$19:$A$23,MATCH(MAX(I19:I23),I19:I23,0)) -> A3 Screens + kitchen early alerts
A26: Hurwicz α (degree of optimism) | B26: 0.4
A28: Regret (opportunity loss, minutes) = best payoff in that situation − this payoff
A29: Alternative | B29: S1 Normal day | C29: S2 Busy day | D29: S3 Surge + food run-out | E29: Maximum regret | F29: Expected regret (EOL)
A30: A1 No system (today) | B30: =MAX(B$19:B$23)-B19 -> 2 | C30: =MAX(C$19:C$23)-C19 -> 6.5 | D30: =MAX(D$19:D$23)-D19 -> 11.5 | E30: =MAX(B30:D30) -> 11.5 | F30: =SUMPRODUCT(B30:D30,$B$14:$D$14) -> 6.15
A31: A2 Door screens + routing | B31: =MAX(B$19:B$23)-B20 -> 0.2 | C31: =MAX(C$19:C$23)-C20 -> 0.2 | D31: =MAX(D$19:D$23)-D20 -> 2.5 | E31: =MAX(B31:D31) -> 2.5 | F31: =SUMPRODUCT(B31:D31,$B$14:$D$14) -> 0.66
A32: A3 Screens + kitchen early alerts | B32: =MAX(B$19:B$23)-B21 -> 0.2 | C32: =MAX(C$19:C$23)-C21 -> 0.2 | D32: =MAX(D$19:D$23)-D21 -> 0 | E32: =MAX(B32:D32) -> 0.2 | F32: =SUMPRODUCT(B32:D32,$B$14:$D$14) -> 0.16
A33: A4 3rd serving station at peak (no screens) | B33: =MAX(B$19:B$23)-B22 -> 1 | C33: =MAX(C$19:C$23)-C22 -> 2.9 | D33: =MAX(D$19:D$23)-D22 -> 5.5 | E33: =MAX(B33:D33) -> 5.5 | F33: =SUMPRODUCT(B33:D33,$B$14:$D$14) -> 2.85
A34: A5 Screens + 3rd serving station | B34: =MAX(B$19:B$23)-B23 -> 0 | C34: =MAX(C$19:C$23)-C23 -> 0 | D34: =MAX(D$19:D$23)-D23 -> 1 | E34: =MAX(B34:D34) -> 1 | F34: =SUMPRODUCT(B34:D34,$B$14:$D$14) -> 0.2
A35: Minimax regret choice | E35: =INDEX($A$30:$A$34,MATCH(MIN(E30:E34),E30:E34,0)) -> A3 Screens + kitchen early alerts
A36: Minimum expected regret (= EMV choice) | F36: =INDEX($A$30:$A$34,MATCH(MIN(F30:F34),F30:F34,0)) -> A3 Screens + kitchen early alerts
A38: Value of perfect information (in minutes per student)
A39: Expected payoff WITH perfect information (pick the best alternative in each situation) | B39: =B14*MAX(B19:B23)+C14*MAX(C19:C23)+D14*MAX(D19:D23) -> 6.15
A40: Best EMV without perfect information | B40: =MAX(I19:I23) -> 5.99
A41: EVPI = extra minutes per student we could save if we knew the situation in advance | B41: =B39-B40 -> 0.16
A42: Check: EVPI equals the minimum expected regret | B42: =MIN(F30:F34) -> 0.16
A44: Why minutes and not rupees: a rupee value for a student's minute is a judgement nobody can verify, so the payoff matrix compares options only on waiting time. Cost and food waste are not ignored: they are separate criteria in S16-17 AHP, and staff cost is in S12-14 IP Staffing. Naming: for a table of waits (lower is better) the criteria would be called minimin and minimax; turning waits into minutes saved makes higher better, so the classic maximax / maximin names apply. 'With and without' the system: A1 and A4 are without; A2, A3 and A5 are with.

Sheet S7 Decision Tree
A1: Decision tree: pre-stage an extra batch of the star dish, or wait and react?
A2: Session 7: Decision tree analysis and decision making under risk
A4: Inputs (illustrative) | H4: Why rupees here: the two branches lose different things (pre-staging can waste FOOD; reacting late makes students WAIT). To add them up we need one unit, so each is given a rupee value on the Inputs tab: ₹30 per wasted portion (ask CT for the real food cost) and ₹5 per student-minute (a judgement, not a price). Cost of a branch = portions wasted × ₹30, or students delayed × minutes × ₹5. The break-even probability below shows how much the answer depends on these two values: change them on the Inputs tab and watch it move.
A5: P(high-demand day) | B5: 0.4 | C5: Share of days with lunch arrivals above plan — from biometric logs
A6: Portions wasted if pre-staged on a normal day | B6: 40 | C6: Ask CT
A7: Students delayed if the dish runs out (high day, reacting) | B7: 300 | C7: Estimate from logs: arrivals during the refill gap
A8: Delay per student during a run-out (minutes) | B8: 10 | C8: Field observation
A9: ₹ per portion wasted | B9: =Inputs!$B$33 -> 30
A10: ₹ per student-minute waited | B10: =Inputs!$B$32 -> 5
A12: Tree (□ decision node, ○ chance node)
A13: Branch | B13: Probability | C13: Cost (₹) | D13: Prob × cost | E13: EMV of branch
A14: □ Cook the next batch ahead, before the ~13:05 peak (refill then takes 10–14 min, not 30) | E14: =D15+D16 -> 720
A15: ○ High-demand day | B15: =B5 -> 0.4 | C15: =0 -> 0 | D15: =B15*C15 -> 0
A16: ○ Normal day | B16: =1-B5 -> 0.6 | C16: =B6*B9 -> 1200 | D16: =B16*C16 -> 720
A17: □ Wait and react when it runs low | E17: =D18+D19 -> 6000
A18: ○ High-demand day | B18: =B5 -> 0.4 | C18: =B7*B8*B10 -> 15000 | D18: =B18*C18 -> 6000
A19: ○ Normal day | B19: =1-B5 -> 0.6 | C19: =0 -> 0 | D19: =B19*C19 -> 0
A21: Decision (lower expected cost) | B21: =IF(E14<=E17,"Pre-stage","Wait and react") -> Pre-stage
A22: Break-even probability of a high-demand day | B22: =(C16-C19)/((C16-C19)+(C18-C15)) -> 0.074074074 | C22: If high-demand days are more likely than this, pre-staging is cheaper on average.
A24: Sensitivity: expected cost as P(high) varies
A25: P(high) | B25: EMV pre-stage | C25: EMV react | D25: Better
A26: 0 | B26: =A26*$C$15+(1-A26)*$C$16 -> 1200 | C26: =A26*$C$18+(1-A26)*$C$19 -> 0 | D26: =IF(B26<=C26,"Pre-stage","React") -> React
A27: 0.1 | B27: =A27*$C$15+(1-A27)*$C$16 -> 1080 | C27: =A27*$C$18+(1-A27)*$C$19 -> 1500 | D27: =IF(B27<=C27,"Pre-stage","React") -> Pre-stage
A28: 0.2 | B28: =A28*$C$15+(1-A28)*$C$16 -> 960 | C28: =A28*$C$18+(1-A28)*$C$19 -> 3000 | D28: =IF(B28<=C28,"Pre-stage","React") -> Pre-stage
A29: 0.3 | B29: =A29*$C$15+(1-A29)*$C$16 -> 840 | C29: =A29*$C$18+(1-A29)*$C$19 -> 4500 | D29: =IF(B29<=C29,"Pre-stage","React") -> Pre-stage
A30: 0.4 | B30: =A30*$C$15+(1-A30)*$C$16 -> 720 | C30: =A30*$C$18+(1-A30)*$C$19 -> 6000 | D30: =IF(B30<=C30,"Pre-stage","React") -> Pre-stage
A31: 0.5 | B31: =A31*$C$15+(1-A31)*$C$16 -> 600 | C31: =A31*$C$18+(1-A31)*$C$19 -> 7500 | D31: =IF(B31<=C31,"Pre-stage","React") -> Pre-stage
A32: 0.6 | B32: =A32*$C$15+(1-A32)*$C$16 -> 480 | C32: =A32*$C$18+(1-A32)*$C$19 -> 9000 | D32: =IF(B32<=C32,"Pre-stage","React") -> Pre-stage
A33: 0.7 | B33: =A33*$C$15+(1-A33)*$C$16 -> 360 | C33: =A33*$C$18+(1-A33)*$C$19 -> 10500 | D33: =IF(B33<=C33,"Pre-stage","React") -> Pre-stage
A34: 0.8 | B34: =A34*$C$15+(1-A34)*$C$16 -> 240 | C34: =A34*$C$18+(1-A34)*$C$19 -> 12000 | D34: =IF(B34<=C34,"Pre-stage","React") -> Pre-stage
A35: 0.9 | B35: =A35*$C$15+(1-A35)*$C$16 -> 120 | C35: =A35*$C$18+(1-A35)*$C$19 -> 13500 | D35: =IF(B35<=C35,"Pre-stage","React") -> Pre-stage
A36: 1 | B36: =A36*$C$15+(1-A36)*$C$16 -> 0 | C36: =A36*$C$18+(1-A36)*$C$19 -> 15000 | D36: =IF(B36<=C36,"Pre-stage","React") -> Pre-stage

Sheet S10-11 LP Allocation
A1: Linear programming: splitting a limited batch of the star dish between the two messes
A2: Sessions 10–11: Linear programming, model formulation, graphical method, simplex
A4: Formulation
A5: Decision variables: x1 = portions sent to Central CT, x2 = portions sent to Munch Mess
A6: Objective: maximise value of shortages avoided = v1·x1 + v2·x2 (v = cost of one portion short at that mess)
A7: Subject to: x1 + x2 ≤ K (portions ready before the peak); x1 ≤ d1; x2 ≤ d2 (no point sending more than demand); x1, x2 ≥ 0
A9: Inputs (illustrative)
A10: K: portions ready before the peak | B10: 1000
A11: d1: forecast demand, Central CT | B11: 650 | C11: d = forecast students × portions per student. Biometric arrival forecasts feed this.
A12: d2: forecast demand, Munch Mess | B12: 400
A13: v1: ₹ per portion short at Central (bigger queue) | B13: 60
A14: v2: ₹ per portion short at Munch | B14: 45
A16: Decision cells (Solver changes these)
A17: x1 (Central) | B17: 650
A18: x2 (Munch) | B18: 350
A19: Objective: value of shortages avoided | B19: =B13*B17+B14*B18 -> 54750
A21: Constraints
A22: Constraint | B22: Left side | C22: Sign | D22: Right side | E22: OK?
A23: Kitchen batch: x1 + x2 ≤ K | B23: =B17+B18 -> 1000 | C23: ≤ | D23: =B10 -> 1000 | E23: =IF(B23<=D23,"OK","Violated") -> OK
A24: Central demand: x1 ≤ d1 | B24: =B17 -> 650 | C24: ≤ | D24: =B11 -> 650 | E24: =IF(B24<=D24,"OK","Violated") -> OK
A25: Munch demand: x2 ≤ d2 | B25: =B18 -> 350 | C25: ≤ | D25: =B12 -> 400 | E25: =IF(B25<=D25,"OK","Violated") -> OK
A26: Non-negativity | B26: =MIN(B17:B18) -> 350 | C26: ≥ | D26: 0 | E26: =IF(B26>=0,"OK","Violated") -> OK
A28: Graphical method: evaluate every corner point of the feasible region
A29: Corner point | B29: x1 | C29: x2 | D29: Feasible? | E29: Objective (₹)
A30: Origin | B30: 0 | C30: 0 | D30: =IF(AND(B30+C30<=$B$10,B30<=$B$11,C30<=$B$12),"Yes","No") -> Yes | E30: =$B$13*B30+$B$14*C30 -> 0
A31: Central at demand, Munch 0 | B31: =B11 -> 650 | C31: 0 | D31: =IF(AND(B31+C31<=$B$10,B31<=$B$11,C31<=$B$12),"Yes","No") -> Yes | E31: =$B$13*B31+$B$14*C31 -> 39000
A32: Central at demand, rest to Munch | B32: =B11 -> 650 | C32: =MIN(B12,B10-B11) -> 350 | D32: =IF(AND(B32+C32<=$B$10,B32<=$B$11,C32<=$B$12),"Yes","No") -> Yes | E32: =$B$13*B32+$B$14*C32 -> 54750
A33: Munch at demand, rest to Central | B33: =MIN(B11,B10-B12) -> 600 | C33: =B12 -> 400 | D33: =IF(AND(B33+C33<=$B$10,B33<=$B$11,C33<=$B$12),"Yes","No") -> Yes | E33: =$B$13*B33+$B$14*C33 -> 54000
A34: Munch at demand, Central 0 | B34: 0 | C34: =B12 -> 400 | D34: =IF(AND(B34+C34<=$B$10,B34<=$B$11,C34<=$B$12),"Yes","No") -> Yes | E34: =$B$13*B34+$B$14*C34 -> 18000
A36: Optimal corner (graphical method) | B36: =INDEX(A30:A34,MATCH(MAX(E30:E34),E30:E34,0)) -> Central at demand, rest to Munch
A38: Simplex / Excel Solver check: Data → Solver. Set objective B19, To: Max, By changing B17:B18. Constraints: B23 ≤ D23, B24 ≤ D24, B25 ≤ D25. Tick 'Make unconstrained variables non-negative'; method: Simplex LP. Solver returns x1 = 650, x2 = 350 with these inputs: fill Central first because a shortage there costs more, then give Munch the rest.
A40: Link to queuing: staffing as an LP
A41: Choosing serving stations cᵢ so utilisation stays ≤ ρmax gives the linear constraint λᵢ ≤ ρmax·μ·cᵢ. Minimising staff cost subject to it is an LP; because lines must be whole numbers, it becomes an integer programme (next tab).

Sheet S12-14 IP Staffing
A1: Integer programming: how many serving stations to open in each 30-minute slot
A2: Sessions 12–14: Integer programming and branch-and-bound
A4: Decision variables: c(i,t) = number of serving stations at mess i in slot t (whole numbers ≥ 1)
A5: Objective: minimise staff cost = Σ c(i,t) × staff per line × ₹/staff-hour × 0.5 h
A6: Subject to: λ(i,t) ≤ ρmax × μ × c(i,t) (keep utilisation at or below the target); c(i,t) integer ≥ 1
A8: Arrivals come from the S15 Queuing tab (three 10-min bins per slot). Without screens = habit split; with screens = rebalanced split.
A10: Slot start | B10: λ Central /min (without) | C10: λ Munch /min (without) | D10: LP relaxation Central | E10: LP relaxation Munch | F10: Integer stations Central | G10: Integer stations Munch | H10: λ Central /min (with) | I10: λ Munch /min (with) | J10: Integer stations Central (with) | K10: Integer stations Munch (with)
A11: =('S15 Queuing'!A30) -> 11:30 | B11: =AVERAGE('S15 Queuing'!D30:D32) -> 2.4083333 | C11: =AVERAGE('S15 Queuing'!L30:L32) -> 0.425 | D11: =B11/(Inputs!$B$29*Inputs!$B$23) -> 0.28333333 | E11: =C11/(Inputs!$B$29*Inputs!$B$23) -> 0.05 | F11: =MAX(1,ROUNDUP(D11,0)) -> 1 | G11: =MAX(1,ROUNDUP(E11,0)) -> 1 | H11: =AVERAGE('S15 Queuing'!T30:T32) -> 1.8133333 | I11: =AVERAGE('S15 Queuing'!AB30:AB32) -> 1.02 | J11: =MAX(1,ROUNDUP(H11/(Inputs!$B$29*Inputs!$B$23),0)) -> 1 | K11: =MAX(1,ROUNDUP(I11/(Inputs!$B$29*Inputs!$B$23),0)) -> 1
A12: =('S15 Queuing'!A33) -> 12:00 | B12: =AVERAGE('S15 Queuing'!D33:D35) -> 10.766667 | C12: =AVERAGE('S15 Queuing'!L33:L35) -> 1.9 | D12: =B12/(Inputs!$B$29*Inputs!$B$23) -> 1.2666667 | E12: =C12/(Inputs!$B$29*Inputs!$B$23) -> 0.22352941 | F12: =MAX(1,ROUNDUP(D12,0)) -> 2 | G12: =MAX(1,ROUNDUP(E12,0)) -> 1 | H12: =AVERAGE('S15 Queuing'!T33:T35) -> 8.1066667 | I12: =AVERAGE('S15 Queuing'!AB33:AB35) -> 4.56 | J12: =MAX(1,ROUNDUP(H12/(Inputs!$B$29*Inputs!$B$23),0)) -> 1 | K12: =MAX(1,ROUNDUP(I12/(Inputs!$B$29*Inputs!$B$23),0)) -> 1
A13: =('S15 Queuing'!A36) -> 12:30 | B13: =AVERAGE('S15 Queuing'!D36:D38) -> 24.111667 | C13: =AVERAGE('S15 Queuing'!L36:L38) -> 4.255 | D13: =B13/(Inputs!$B$29*Inputs!$B$23) -> 2.8366667 | E13: =C13/(Inputs!$B$29*Inputs!$B$23) -> 0.50058824 | F13: =MAX(1,ROUNDUP(D13,0)) -> 3 | G13: =MAX(1,ROUNDUP(E13,0)) -> 1 | H13: =AVERAGE('S15 Queuing'!T36:T38) -> 18.154667 | I13: =AVERAGE('S15 Queuing'!AB36:AB38) -> 10.212 | J13: =MAX(1,ROUNDUP(H13/(Inputs!$B$29*Inputs!$B$23),0)) -> 3 | K13: =MAX(1,ROUNDUP(I13/(Inputs!$B$29*Inputs!$B$23),0)) -> 2
A14: =('S15 Queuing'!A39) -> 13:00 | B14: =AVERAGE('S15 Queuing'!D39:D41) -> 27.058333 | C14: =AVERAGE('S15 Queuing'!L39:L41) -> 4.775 | D14: =B14/(Inputs!$B$29*Inputs!$B$23) -> 3.1833333 | E14: =C14/(Inputs!$B$29*Inputs!$B$23) -> 0.56176471 | F14: =MAX(1,ROUNDUP(D14,0)) -> 4 | G14: =MAX(1,ROUNDUP(E14,0)) -> 1 | H14: =AVERAGE('S15 Queuing'!T39:T41) -> 20.373333 | I14: =AVERAGE('S15 Queuing'!AB39:AB41) -> 11.46 | J14: =MAX(1,ROUNDUP(H14/(Inputs!$B$29*Inputs!$B$23),0)) -> 3 | K14: =MAX(1,ROUNDUP(I14/(Inputs!$B$29*Inputs!$B$23),0)) -> 2
A15: =('S15 Queuing'!A42) -> 13:30 | B15: =AVERAGE('S15 Queuing'!D42:D44) -> 15.215 | C15: =AVERAGE('S15 Queuing'!L42:L44) -> 2.685 | D15: =B15/(Inputs!$B$29*Inputs!$B$23) -> 1.79 | E15: =C15/(Inputs!$B$29*Inputs!$B$23) -> 0.31588235 | F15: =MAX(1,ROUNDUP(D15,0)) -> 2 | G15: =MAX(1,ROUNDUP(E15,0)) -> 1 | H15: =AVERAGE('S15 Queuing'!T42:T44) -> 11.456 | I15: =AVERAGE('S15 Queuing'!AB42:AB44) -> 6.444 | J15: =MAX(1,ROUNDUP(H15/(Inputs!$B$29*Inputs!$B$23),0)) -> 2 | K15: =MAX(1,ROUNDUP(I15/(Inputs!$B$29*Inputs!$B$23),0)) -> 1
A16: =('S15 Queuing'!A45) -> 14:00 | B16: =AVERAGE('S15 Queuing'!D45:D47) -> 4.2783333 | C16: =AVERAGE('S15 Queuing'!L45:L47) -> 0.755 | D16: =B16/(Inputs!$B$29*Inputs!$B$23) -> 0.50333333 | E16: =C16/(Inputs!$B$29*Inputs!$B$23) -> 0.088823529 | F16: =MAX(1,ROUNDUP(D16,0)) -> 1 | G16: =MAX(1,ROUNDUP(E16,0)) -> 1 | H16: =AVERAGE('S15 Queuing'!T45:T47) -> 3.2213333 | I16: =AVERAGE('S15 Queuing'!AB45:AB47) -> 1.812 | J16: =MAX(1,ROUNDUP(H16/(Inputs!$B$29*Inputs!$B$23),0)) -> 1 | K16: =MAX(1,ROUNDUP(I16/(Inputs!$B$29*Inputs!$B$23),0)) -> 1
A18: Station-slots needed | F18: =SUM(F11:F16) -> 13 | G18: =SUM(G11:G16) -> 6 | J18: =SUM(J11:J16) -> 11 | K18: =SUM(K11:K16) -> 8
A19: Staff cost (₹) | E19: Without: | F19: =(F18+G18)*Inputs!$B$35*Inputs!$B$34*0.5 -> 2850 | I19: With: | J19: =(J18+K18)*Inputs!$B$35*Inputs!$B$34*0.5 -> 2850
A20: Saving from screens | J20: =F19-J19 -> 0
A21: Stations today (measured) | F21: =Inputs!$B$11 -> 2 | G21: =Inputs!$B$12 -> 2
A22: Most stations needed at once (peak slot) | F22: =MAX(F11:F16) -> 4 | G22: =MAX(G11:G16) -> 1 | J22: =MAX(J11:J16) -> 3 | K22: =MAX(K11:K16) -> 2
A23: Read this with the row above: screens move work from Central to Munch, so the total station-slots (and staff cost) barely change. What changes is the PEAK: without screens Central needs more stations than it has; with screens the need at Central drops and Munch's spare station gets used.
A25: Why ROUNDUP is optimal here: each slot and mess is a separate constraint, so the smallest integer ≥ the LP value is feasible and cheapest. With a shared limit (for example, a staff cap across both messes), the problem couples and branch-and-bound is needed. Tree for the busiest slot (computed live):
A27: Node | B27: Constraint added | D27: LP solution (Central, Munch) | F27: Stations | H27: Status
A28: 0 (root) | B28: ="LP relaxation, slot "&INDEX($A$11:$A$16,MATCH(MAX($B$11:$B$16),$B$11:$B$16,0)) -> LP relaxation, slot 13:00 | D28: ="("&TEXT(INDEX($D$11:$D$16,MATCH(MAX($B$11:$B$16),$B$11:$B$16,0)),"0.00")&", "&TEXT(INDEX($E$11:$E$16,MATCH(MAX($B$11:$B$16),$B$11:$B$16,0)),"0.00")&")" -> (3.18, 0.56) | F28: =TEXT(INDEX($D$11:$D$16,MATCH(MAX($B$11:$B$16),$B$11:$B$16,0))+INDEX($E$11:$E$16,MATCH(MAX($B$11:$B$16),$B$11:$B$16,0)),"0.00") -> 3.75 | H28: Fractional → branch on Central
A29: 1 | B29: ="Central ≤ "&INT(INDEX($D$11:$D$16,MATCH(MAX($B$11:$B$16),$B$11:$B$16,0))) -> Central ≤ 3 | D29: — | F29: — | H29: Infeasible: Central would exceed ρmax
A30: 2 | B30: ="Central ≥ "&ROUNDUP(INDEX($D$11:$D$16,MATCH(MAX($B$11:$B$16),$B$11:$B$16,0)),0) -> Central ≥ 4 | D30: ="("&ROUNDUP(INDEX($D$11:$D$16,MATCH(MAX($B$11:$B$16),$B$11:$B$16,0)),0)&", "&TEXT(INDEX($E$11:$E$16,MATCH(MAX($B$11:$B$16),$B$11:$B$16,0)),"0.00")&")" -> (4, 0.56) | F30: =TEXT(ROUNDUP(INDEX($D$11:$D$16,MATCH(MAX($B$11:$B$16),$B$11:$B$16,0)),0)+INDEX($E$11:$E$16,MATCH(MAX($B$11:$B$16),$B$11:$B$16,0)),"0.00") -> 4.56 | H30: Fractional → branch on Munch
A31: 3 | B31: ="Central ≥ "&ROUNDUP(INDEX($D$11:$D$16,MATCH(MAX($B$11:$B$16),$B$11:$B$16,0)),0)&", Munch ≤ "&INT(INDEX($E$11:$E$16,MATCH(MAX($B$11:$B$16),$B$11:$B$16,0))) -> Central ≥ 4, Munch ≤ 0 | D31: — | F31: — | H31: Infeasible: Munch would exceed ρmax
A32: 4 | B32: ="Central ≥ "&ROUNDUP(INDEX($D$11:$D$16,MATCH(MAX($B$11:$B$16),$B$11:$B$16,0)),0)&", Munch ≥ "&ROUNDUP(INDEX($E$11:$E$16,MATCH(MAX($B$11:$B$16),$B$11:$B$16,0)),0) -> Central ≥ 4, Munch ≥ 1 | D32: ="("&ROUNDUP(INDEX($D$11:$D$16,MATCH(MAX($B$11:$B$16),$B$11:$B$16,0)),0)&", "&ROUNDUP(INDEX($E$11:$E$16,MATCH(MAX($B$11:$B$16),$B$11:$B$16,0)),0)&")" -> (4, 1) | F32: =ROUNDUP(INDEX($D$11:$D$16,MATCH(MAX($B$11:$B$16),$B$11:$B$16,0)),0)+ROUNDUP(INDEX($E$11:$E$16,MATCH(MAX($B$11:$B$16),$B$11:$B$16,0)),0) -> 5 | H32: Integer → optimal (same as ROUNDUP). Compare with today's 2 + 2 stations
A34: If the integer answer needs more stations than exist today (2 per mess), the peak cannot meet the 85% target: that is the case for an extra station at peak (alternative A4) or for rebalancing with the screens. Replenishment trips can be modelled the same way: binary y(t) = 1 if the vehicle leaves at time t; each trip carries ≤ Q portions and arrives 30 min after a call if it must be made, or 10–14 min if already made.

Sheet S16-17 AHP
A1: AHP: weighting the decision criteria and ranking the alternatives
A2: Sessions 16–17: Multi-criteria decision making — Analytic Hierarchy Process
A4: Pairwise comparison matrix (Saaty 1–9 scale). Fill the BLUE upper triangle; the rest is computed. Values are illustrative.
B5: Service level | C5: Stock-out risk | D5: Waste | E5: Utilisation
A6: Service level | B6: 1 | C6: 1 | D6: 3 | E6: 5
A7: Stock-out risk | B7: =1/C6 -> 1 | C7: 1 | D7: 3 | E7: 5
A8: Waste | B8: =1/D6 -> 0.33333333 | C8: =1/D7 -> 0.33333333 | D8: 1 | E8: 2
A9: Utilisation | B9: =1/E6 -> 0.2 | C9: =1/E7 -> 0.2 | D9: =1/E8 -> 0.5 | E9: 1
A10: Column sum | B10: =SUM(B6:B9) -> 2.5333333 | C10: =SUM(C6:C9) -> 2.5333333 | D10: =SUM(D6:D9) -> 7.5 | E10: =SUM(E6:E9) -> 13
A12: Normalised matrix (each cell ÷ its column sum) and weights (row average)
B13: Service level | C13: Stock-out risk | D13: Waste | E13: Utilisation | F13: Weight
A14: Service level | B14: =B6/B$10 -> 0.39473684 | C14: =C6/C$10 -> 0.39473684 | D14: =D6/D$10 -> 0.4 | E14: =E6/E$10 -> 0.38461538 | F14: =AVERAGE(B14:E14) -> 0.39352227
A15: Stock-out risk | B15: =B7/B$10 -> 0.39473684 | C15: =C7/C$10 -> 0.39473684 | D15: =D7/D$10 -> 0.4 | E15: =E7/E$10 -> 0.38461538 | F15: =AVERAGE(B15:E15) -> 0.39352227
A16: Waste | B16: =B8/B$10 -> 0.13157895 | C16: =C8/C$10 -> 0.13157895 | D16: =D8/D$10 -> 0.13333333 | E16: =E8/E$10 -> 0.15384615 | F16: =AVERAGE(B16:E16) -> 0.13758435
A17: Utilisation | B17: =B9/B$10 -> 0.078947368 | C17: =C9/C$10 -> 0.078947368 | D17: =D9/D$10 -> 0.066666667 | E17: =E9/E$10 -> 0.076923077 | F17: =AVERAGE(B17:E17) -> 0.07537112
A19: Consistency check
A20: λmax | B20: =B10*F14+C10*F15+D10*F16+E10*F17 -> 4.0055533
A21: CI = (λmax − n)/(n − 1) | B21: =(B20-4)/3 -> 0.0018511021
A22: RI (random index, n = 4) | B22: 0.9
A23: CR = CI / RI | B23: =B21/B22 -> 0.0020567801 | C23: =IF(B23<0.1,"Consistent (CR < 0.10)","Revise judgements") -> Consistent (CR < 0.10)
A25: Scoring the alternatives (1–10, higher = better on that criterion; for risk and waste, higher = LESS risk / waste). Illustrative.
A26: Alternative | B26: Service level | C26: Stock-out risk | D26: Waste | E26: Utilisation | F26: Weighted score | G26: Rank
A27: A1 No system (today) | B27: 3 | C27: 3 | D27: 6 | E27: 5 | F27: =B27*$F$14+C27*$F$15+D27*$F$16+E27*$F$17 -> 3.5634953 | G27: =RANK(F27,$F$27:$F$31) -> 5
A28: A2 Door screens + routing | B28: 7 | C28: 4 | D28: 6 | E28: 7 | F28: =B28*$F$14+C28*$F$15+D28*$F$16+E28*$F$17 -> 5.6818489 | G28: =RANK(F28,$F$27:$F$31) -> 3
A29: A3 Screens + kitchen early alerts | B29: 7 | C29: 8 | D29: 4 | E29: 7 | F29: =B29*$F$14+C29*$F$15+D29*$F$16+E29*$F$17 -> 6.9807692 | G29: =RANK(F29,$F$27:$F$31) -> 1
A30: A4 3rd serving station at peak (no screens) | B30: 7 | C30: 4 | D30: 6 | E30: 4 | F30: =B30*$F$14+C30*$F$15+D30*$F$16+E30*$F$17 -> 5.4557355 | G30: =RANK(F30,$F$27:$F$31) -> 4
A31: A5 Screens + 3rd serving station | B31: 9 | C31: 5 | D31: 6 | E31: 5 | F31: =B31*$F$14+C31*$F$15+D31*$F$16+E31*$F$17 -> 6.7116734 | G31: =RANK(F31,$F$27:$F$31) -> 2
A33: Best alternative (AHP) | B33: =INDEX(A27:A31,MATCH(MAX(F27:F31),F27:F31,0)) -> A3 Screens + kitchen early alerts
A35: Service-level scores can be anchored to the queuing results (S15) and the payoff matrix (S7): e.g. average wait 7.1 min → 3, 0.8 min → 8. Criteria come from our Phase 1 deck's weighted decision table.

Sheet S16-17 BWM
A1: Best–Worst Method: the same criteria weights with fewer comparisons
A2: Sessions 16–17: Multi-criteria decision making — Best–Worst Method
A4: Best criterion | B4: Service level
A5: Worst criterion | B5: Utilisation
A7: Comparisons (1–9). Illustrative.
A8: Criterion | B8: Best-to-Others (a_Bj) | C8: Others-to-Worst (a_jW) | D8: Weight w_j | E8: |w_B − a_Bj·w_j| | F8: |w_j − a_jW·w_W|
A9: Service level | B9: 1 | C9: 7 | D9: 0.5123 | E9: =ABS($D$9-B9*D9) -> 0 | F9: =ABS(D9-C9*$D$12) -> 0.0545
A10: Stock-out risk | B10: 2 | C10: 5 | D10: 0.2806 | E10: =ABS($D$9-B10*D10) -> 0.0489 | F10: =ABS(D10-C10*$D$12) -> 0.0464
A11: Waste | B11: 4 | C11: 3 | D11: 0.1417 | E11: =ABS($D$9-B11*D11) -> 0.0545 | F11: =ABS(D11-C11*$D$12) -> 0.0545
A12: Utilisation | B12: 7 | C12: 1 | D12: 0.0654 | E12: =ABS($D$9-B12*D12) -> 0.0545 | F12: =ABS(D12-C12*$D$12) -> 0
A13: Sum of weights (must be 1) | D13: =SUM(D9:D12) -> 1
A14: ξ* = largest deviation (the BWM objective) | D14: =MAX(E9:F12) -> 0.0545
A15: Consistency index for a_BW (table, a_BW = 7) | D15: =INDEX({0,0.44,1,1.63,2.3,3,3.73,4.47,5.23},B12) -> 3.73
A16: Consistency ratio = ξ* / CI (closer to 0 = more consistent) | D16: =D14/D15 -> 0.01461126
A18: The weights in yellow were found by solving the linear BWM model: minimise ξ subject to |w_B − a_Bj·w_j| ≤ ξ, |w_j − a_jW·w_W| ≤ ξ, Σw = 1, w ≥ 0. If you change the comparisons, re-solve with Solver: set D14 to Min by changing D9:D12, with D13 = 1 and D9:D12 ≥ 0 (Simplex LP or GRG Nonlinear).
A20: Compare with AHP
A21: Criterion | B21: BWM weight | C21: AHP weight | D21: Difference
A22: Service level | B22: =D9 -> 0.5123 | C22: ='S16-17 AHP'!F14 -> 0.39352227 | D22: =B22-C22 -> 0.11877773
A23: Stock-out risk | B23: =D10 -> 0.2806 | C23: ='S16-17 AHP'!F15 -> 0.39352227 | D23: =B23-C23 -> -0.11292227
A24: Waste | B24: =D11 -> 0.1417 | C24: ='S16-17 AHP'!F16 -> 0.13758435 | D24: =B24-C24 -> 0.0041156545
A25: Utilisation | B25: =D12 -> 0.0654 | C25: ='S16-17 AHP'!F17 -> 0.07537112 | D25: =B25-C25 -> -0.0099711201

Sheet S16-17 ISM-MICMAC
A1: ISM and MICMAC: which causes drive the others?
A2: Sessions 16–17: Interpretive Structural Modelling (ISM) and MICMAC analysis
A4: Initial reachability matrix: 1 if the row factor influences the column factor (diagonal = 1). Group judgements — illustrative.
A5: Step 1 — Initial reachability matrix (IRM)
B6: F1 | C6: F2 | D6: F3 | E6: F4 | F6: F5 | G6: F6 | H6: F7 | I6: F8 | J6: F9 | K6: F10
A7: F1 No live demand data | B7: 1 | C7: 0 | D7: 1 | E7: 0 | F7: 1 | G7: 1 | H7: 1 | I7: 0 | J7: 0 | K7: 0
A8: F2 Peak arrival concentration | B8: 0 | C8: 1 | D8: 0 | E8: 0 | F8: 0 | G8: 0 | H8: 0 | I8: 0 | J8: 1 | K8: 0
A9: F3 Habitual choice of mess | B9: 0 | C9: 0 | D9: 1 | E9: 0 | F9: 0 | G9: 0 | H9: 0 | I9: 0 | J9: 1 | K9: 0
A10: F4 Serving rate per line | B10: 0 | C10: 0 | D10: 0 | E10: 1 | F10: 0 | G10: 0 | H10: 0 | I10: 0 | J10: 1 | K10: 0
A11: F5 Number of serving stations | B11: 0 | C11: 0 | D11: 0 | E11: 0 | F11: 1 | G11: 0 | H11: 0 | I11: 0 | J11: 1 | K11: 0
A12: F6 Reactive replenishment | B12: 0 | C12: 0 | D12: 0 | E12: 0 | F12: 0 | G12: 1 | H12: 0 | I12: 1 | J12: 0 | K12: 0
A13: F7 Base-food buffer sizing | B13: 0 | C13: 0 | D13: 0 | E13: 0 | F13: 0 | G13: 0 | H13: 1 | I13: 1 | J13: 0 | K13: 0
A14: F8 Stock-outs | B14: 0 | C14: 0 | D14: 0 | E14: 1 | F14: 0 | G14: 0 | H14: 0 | I14: 1 | J14: 1 | K14: 0
A15: F9 Queue length at counter | B15: 0 | C15: 0 | D15: 0 | E15: 0 | F15: 0 | G15: 0 | H15: 0 | I15: 0 | J15: 1 | K15: 1
A16: F10 Student waiting time | B16: 0 | C16: 0 | D16: 0 | E16: 0 | F16: 0 | G16: 0 | H16: 0 | I16: 0 | J16: 0 | K16: 1
A18: Step 2.1 — transitivity (Boolean matrix squared; paths up to 2 steps)
B19: F1 | C19: F2 | D19: F3 | E19: F4 | F19: F5 | G19: F6 | H19: F7 | I19: F8 | J19: F9 | K19: F10
A20: F1 No live demand data | B20: =IF(MMULT($B7:$K7,B$7:B$16)>0,1,0) -> 1 | C20: =IF(MMULT($B7:$K7,C$7:C$16)>0,1,0) -> 0 | D20: =IF(MMULT($B7:$K7,D$7:D$16)>0,1,0) -> 1 | E20: =IF(MMULT($B7:$K7,E$7:E$16)>0,1,0) -> 0 | F20: =IF(MMULT($B7:$K7,F$7:F$16)>0,1,0) -> 1 | G20: =IF(MMULT($B7:$K7,G$7:G$16)>0,1,0) -> 1 | H20: =IF(MMULT($B7:$K7,H$7:H$16)>0,1,0) -> 1 | I20: =IF(MMULT($B7:$K7,I$7:I$16)>0,1,0) -> 1 | ... K20: =IF(MMULT($B7:$K7,K$7:K$16)>0,1,0) -> 0
A21: F2 Peak arrival concentration | B21: =IF(MMULT($B8:$K8,B$7:B$16)>0,1,0) -> 0 | C21: =IF(MMULT($B8:$K8,C$7:C$16)>0,1,0) -> 1 | D21: =IF(MMULT($B8:$K8,D$7:D$16)>0,1,0) -> 0 | E21: =IF(MMULT($B8:$K8,E$7:E$16)>0,1,0) -> 0 | F21: =IF(MMULT($B8:$K8,F$7:F$16)>0,1,0) -> 0 | G21: =IF(MMULT($B8:$K8,G$7:G$16)>0,1,0) -> 0 | H21: =IF(MMULT($B8:$K8,H$7:H$16)>0,1,0) -> 0 | I21: =IF(MMULT($B8:$K8,I$7:I$16)>0,1,0) -> 0 | ... K21: =IF(MMULT($B8:$K8,K$7:K$16)>0,1,0) -> 1
A22: F3 Habitual choice of mess | B22: =IF(MMULT($B9:$K9,B$7:B$16)>0,1,0) -> 0 | C22: =IF(MMULT($B9:$K9,C$7:C$16)>0,1,0) -> 0 | D22: =IF(MMULT($B9:$K9,D$7:D$16)>0,1,0) -> 1 | E22: =IF(MMULT($B9:$K9,E$7:E$16)>0,1,0) -> 0 | F22: =IF(MMULT($B9:$K9,F$7:F$16)>0,1,0) -> 0 | G22: =IF(MMULT($B9:$K9,G$7:G$16)>0,1,0) -> 0 | H22: =IF(MMULT($B9:$K9,H$7:H$16)>0,1,0) -> 0 | I22: =IF(MMULT($B9:$K9,I$7:I$16)>0,1,0) -> 0 | ... K22: =IF(MMULT($B9:$K9,K$7:K$16)>0,1,0) -> 1
A23: F4 Serving rate per line | B23: =IF(MMULT($B10:$K10,B$7:B$16)>0,1,0) -> 0 | C23: =IF(MMULT($B10:$K10,C$7:C$16)>0,1,0) -> 0 | D23: =IF(MMULT($B10:$K10,D$7:D$16)>0,1,0) -> 0 | E23: =IF(MMULT($B10:$K10,E$7:E$16)>0,1,0) -> 1 | F23: =IF(MMULT($B10:$K10,F$7:F$16)>0,1,0) -> 0 | G23: =IF(MMULT($B10:$K10,G$7:G$16)>0,1,0) -> 0 | H23: =IF(MMULT($B10:$K10,H$7:H$16)>0,1,0) -> 0 | I23: =IF(MMULT($B10:$K10,I$7:I$16)>0,1,0) -> 0 | ... K23: =IF(MMULT($B10:$K10,K$7:K$16)>0,1,0) -> 1
A24: F5 Number of serving stations | B24: =IF(MMULT($B11:$K11,B$7:B$16)>0,1,0) -> 0 | C24: =IF(MMULT($B11:$K11,C$7:C$16)>0,1,0) -> 0 | D24: =IF(MMULT($B11:$K11,D$7:D$16)>0,1,0) -> 0 | E24: =IF(MMULT($B11:$K11,E$7:E$16)>0,1,0) -> 0 | F24: =IF(MMULT($B11:$K11,F$7:F$16)>0,1,0) -> 1 | G24: =IF(MMULT($B11:$K11,G$7:G$16)>0,1,0) -> 0 | H24: =IF(MMULT($B11:$K11,H$7:H$16)>0,1,0) -> 0 | I24: =IF(MMULT($B11:$K11,I$7:I$16)>0,1,0) -> 0 | ... K24: =IF(MMULT($B11:$K11,K$7:K$16)>0,1,0) -> 1
A25: F6 Reactive replenishment | B25: =IF(MMULT($B12:$K12,B$7:B$16)>0,1,0) -> 0 | C25: =IF(MMULT($B12:$K12,C$7:C$16)>0,1,0) -> 0 | D25: =IF(MMULT($B12:$K12,D$7:D$16)>0,1,0) -> 0 | E25: =IF(MMULT($B12:$K12,E$7:E$16)>0,1,0) -> 1 | F25: =IF(MMULT($B12:$K12,F$7:F$16)>0,1,0) -> 0 | G25: =IF(MMULT($B12:$K12,G$7:G$16)>0,1,0) -> 1 | H25: =IF(MMULT($B12:$K12,H$7:H$16)>0,1,0) -> 0 | I25: =IF(MMULT($B12:$K12,I$7:I$16)>0,1,0) -> 1 | ... K25: =IF(MMULT($B12:$K12,K$7:K$16)>0,1,0) -> 0
A26: F7 Base-food buffer sizing | B26: =IF(MMULT($B13:$K13,B$7:B$16)>0,1,0) -> 0 | C26: =IF(MMULT($B13:$K13,C$7:C$16)>0,1,0) -> 0 | D26: =IF(MMULT($B13:$K13,D$7:D$16)>0,1,0) -> 0 | E26: =IF(MMULT($B13:$K13,E$7:E$16)>0,1,0) -> 1 | F26: =IF(MMULT($B13:$K13,F$7:F$16)>0,1,0) -> 0 | G26: =IF(MMULT($B13:$K13,G$7:G$16)>0,1,0) -> 0 | H26: =IF(MMULT($B13:$K13,H$7:H$16)>0,1,0) -> 1 | I26: =IF(MMULT($B13:$K13,I$7:I$16)>0,1,0) -> 1 | ... K26: =IF(MMULT($B13:$K13,K$7:K$16)>0,1,0) -> 0
A27: F8 Stock-outs | B27: =IF(MMULT($B14:$K14,B$7:B$16)>0,1,0) -> 0 | C27: =IF(MMULT($B14:$K14,C$7:C$16)>0,1,0) -> 0 | D27: =IF(MMULT($B14:$K14,D$7:D$16)>0,1,0) -> 0 | E27: =IF(MMULT($B14:$K14,E$7:E$16)>0,1,0) -> 1 | F27: =IF(MMULT($B14:$K14,F$7:F$16)>0,1,0) -> 0 | G27: =IF(MMULT($B14:$K14,G$7:G$16)>0,1,0) -> 0 | H27: =IF(MMULT($B14:$K14,H$7:H$16)>0,1,0) -> 0 | I27: =IF(MMULT($B14:$K14,I$7:I$16)>0,1,0) -> 1 | ... K27: =IF(MMULT($B14:$K14,K$7:K$16)>0,1,0) -> 1
A28: F9 Queue length at counter | B28: =IF(MMULT($B15:$K15,B$7:B$16)>0,1,0) -> 0 | C28: =IF(MMULT($B15:$K15,C$7:C$16)>0,1,0) -> 0 | D28: =IF(MMULT($B15:$K15,D$7:D$16)>0,1,0) -> 0 | E28: =IF(MMULT($B15:$K15,E$7:E$16)>0,1,0) -> 0 | F28: =IF(MMULT($B15:$K15,F$7:F$16)>0,1,0) -> 0 | G28: =IF(MMULT($B15:$K15,G$7:G$16)>0,1,0) -> 0 | H28: =IF(MMULT($B15:$K15,H$7:H$16)>0,1,0) -> 0 | I28: =IF(MMULT($B15:$K15,I$7:I$16)>0,1,0) -> 0 | ... K28: =IF(MMULT($B15:$K15,K$7:K$16)>0,1,0) -> 1
A29: F10 Student waiting time | B29: =IF(MMULT($B16:$K16,B$7:B$16)>0,1,0) -> 0 | C29: =IF(MMULT($B16:$K16,C$7:C$16)>0,1,0) -> 0 | D29: =IF(MMULT($B16:$K16,D$7:D$16)>0,1,0) -> 0 | E29: =IF(MMULT($B16:$K16,E$7:E$16)>0,1,0) -> 0 | F29: =IF(MMULT($B16:$K16,F$7:F$16)>0,1,0) -> 0 | G29: =IF(MMULT($B16:$K16,G$7:G$16)>0,1,0) -> 0 | H29: =IF(MMULT($B16:$K16,H$7:H$16)>0,1,0) -> 0 | I29: =IF(MMULT($B16:$K16,I$7:I$16)>0,1,0) -> 0 | ... K29: =IF(MMULT($B16:$K16,K$7:K$16)>0,1,0) -> 1
A31: Step 2.2 — transitivity (Boolean matrix squared; paths up to 4 steps)
B32: F1 | C32: F2 | D32: F3 | E32: F4 | F32: F5 | G32: F6 | H32: F7 | I32: F8 | J32: F9 | K32: F10
A33: F1 No live demand data | B33: =IF(MMULT($B20:$K20,B$20:B$29)>0,1,0) -> 1 | C33: =IF(MMULT($B20:$K20,C$20:C$29)>0,1,0) -> 0 | D33: =IF(MMULT($B20:$K20,D$20:D$29)>0,1,0) -> 1 | E33: =IF(MMULT($B20:$K20,E$20:E$29)>0,1,0) -> 1 | F33: =IF(MMULT($B20:$K20,F$20:F$29)>0,1,0) -> 1 | G33: =IF(MMULT($B20:$K20,G$20:G$29)>0,1,0) -> 1 | H33: =IF(MMULT($B20:$K20,H$20:H$29)>0,1,0) -> 1 | I33: =IF(MMULT($B20:$K20,I$20:I$29)>0,1,0) -> 1 | ... K33: =IF(MMULT($B20:$K20,K$20:K$29)>0,1,0) -> 1
A34: F2 Peak arrival concentration | B34: =IF(MMULT($B21:$K21,B$20:B$29)>0,1,0) -> 0 | C34: =IF(MMULT($B21:$K21,C$20:C$29)>0,1,0) -> 1 | D34: =IF(MMULT($B21:$K21,D$20:D$29)>0,1,0) -> 0 | E34: =IF(MMULT($B21:$K21,E$20:E$29)>0,1,0) -> 0 | F34: =IF(MMULT($B21:$K21,F$20:F$29)>0,1,0) -> 0 | G34: =IF(MMULT($B21:$K21,G$20:G$29)>0,1,0) -> 0 | H34: =IF(MMULT($B21:$K21,H$20:H$29)>0,1,0) -> 0 | I34: =IF(MMULT($B21:$K21,I$20:I$29)>0,1,0) -> 0 | ... K34: =IF(MMULT($B21:$K21,K$20:K$29)>0,1,0) -> 1
A35: F3 Habitual choice of mess | B35: =IF(MMULT($B22:$K22,B$20:B$29)>0,1,0) -> 0 | C35: =IF(MMULT($B22:$K22,C$20:C$29)>0,1,0) -> 0 | D35: =IF(MMULT($B22:$K22,D$20:D$29)>0,1,0) -> 1 | E35: =IF(MMULT($B22:$K22,E$20:E$29)>0,1,0) -> 0 | F35: =IF(MMULT($B22:$K22,F$20:F$29)>0,1,0) -> 0 | G35: =IF(MMULT($B22:$K22,G$20:G$29)>0,1,0) -> 0 | H35: =IF(MMULT($B22:$K22,H$20:H$29)>0,1,0) -> 0 | I35: =IF(MMULT($B22:$K22,I$20:I$29)>0,1,0) -> 0 | ... K35: =IF(MMULT($B22:$K22,K$20:K$29)>0,1,0) -> 1
A36: F4 Serving rate per line | B36: =IF(MMULT($B23:$K23,B$20:B$29)>0,1,0) -> 0 | C36: =IF(MMULT($B23:$K23,C$20:C$29)>0,1,0) -> 0 | D36: =IF(MMULT($B23:$K23,D$20:D$29)>0,1,0) -> 0 | E36: =IF(MMULT($B23:$K23,E$20:E$29)>0,1,0) -> 1 | F36: =IF(MMULT($B23:$K23,F$20:F$29)>0,1,0) -> 0 | G36: =IF(MMULT($B23:$K23,G$20:G$29)>0,1,0) -> 0 | H36: =IF(MMULT($B23:$K23,H$20:H$29)>0,1,0) -> 0 | I36: =IF(MMULT($B23:$K23,I$20:I$29)>0,1,0) -> 0 | ... K36: =IF(MMULT($B23:$K23,K$20:K$29)>0,1,0) -> 1
A37: F5 Number of serving stations | B37: =IF(MMULT($B24:$K24,B$20:B$29)>0,1,0) -> 0 | C37: =IF(MMULT($B24:$K24,C$20:C$29)>0,1,0) -> 0 | D37: =IF(MMULT($B24:$K24,D$20:D$29)>0,1,0) -> 0 | E37: =IF(MMULT($B24:$K24,E$20:E$29)>0,1,0) -> 0 | F37: =IF(MMULT($B24:$K24,F$20:F$29)>0,1,0) -> 1 | G37: =IF(MMULT($B24:$K24,G$20:G$29)>0,1,0) -> 0 | H37: =IF(MMULT($B24:$K24,H$20:H$29)>0,1,0) -> 0 | I37: =IF(MMULT($B24:$K24,I$20:I$29)>0,1,0) -> 0 | ... K37: =IF(MMULT($B24:$K24,K$20:K$29)>0,1,0) -> 1
A38: F6 Reactive replenishment | B38: =IF(MMULT($B25:$K25,B$20:B$29)>0,1,0) -> 0 | C38: =IF(MMULT($B25:$K25,C$20:C$29)>0,1,0) -> 0 | D38: =IF(MMULT($B25:$K25,D$20:D$29)>0,1,0) -> 0 | E38: =IF(MMULT($B25:$K25,E$20:E$29)>0,1,0) -> 1 | F38: =IF(MMULT($B25:$K25,F$20:F$29)>0,1,0) -> 0 | G38: =IF(MMULT($B25:$K25,G$20:G$29)>0,1,0) -> 1 | H38: =IF(MMULT($B25:$K25,H$20:H$29)>0,1,0) -> 0 | I38: =IF(MMULT($B25:$K25,I$20:I$29)>0,1,0) -> 1 | ... K38: =IF(MMULT($B25:$K25,K$20:K$29)>0,1,0) -> 1
A39: F7 Base-food buffer sizing | B39: =IF(MMULT($B26:$K26,B$20:B$29)>0,1,0) -> 0 | C39: =IF(MMULT($B26:$K26,C$20:C$29)>0,1,0) -> 0 | D39: =IF(MMULT($B26:$K26,D$20:D$29)>0,1,0) -> 0 | E39: =IF(MMULT($B26:$K26,E$20:E$29)>0,1,0) -> 1 | F39: =IF(MMULT($B26:$K26,F$20:F$29)>0,1,0) -> 0 | G39: =IF(MMULT($B26:$K26,G$20:G$29)>0,1,0) -> 0 | H39: =IF(MMULT($B26:$K26,H$20:H$29)>0,1,0) -> 1 | I39: =IF(MMULT($B26:$K26,I$20:I$29)>0,1,0) -> 1 | ... K39: =IF(MMULT($B26:$K26,K$20:K$29)>0,1,0) -> 1
A40: F8 Stock-outs | B40: =IF(MMULT($B27:$K27,B$20:B$29)>0,1,0) -> 0 | C40: =IF(MMULT($B27:$K27,C$20:C$29)>0,1,0) -> 0 | D40: =IF(MMULT($B27:$K27,D$20:D$29)>0,1,0) -> 0 | E40: =IF(MMULT($B27:$K27,E$20:E$29)>0,1,0) -> 1 | F40: =IF(MMULT($B27:$K27,F$20:F$29)>0,1,0) -> 0 | G40: =IF(MMULT($B27:$K27,G$20:G$29)>0,1,0) -> 0 | H40: =IF(MMULT($B27:$K27,H$20:H$29)>0,1,0) -> 0 | I40: =IF(MMULT($B27:$K27,I$20:I$29)>0,1,0) -> 1 | ... K40: =IF(MMULT($B27:$K27,K$20:K$29)>0,1,0) -> 1
A41: F9 Queue length at counter | B41: =IF(MMULT($B28:$K28,B$20:B$29)>0,1,0) -> 0 | C41: =IF(MMULT($B28:$K28,C$20:C$29)>0,1,0) -> 0 | D41: =IF(MMULT($B28:$K28,D$20:D$29)>0,1,0) -> 0 | E41: =IF(MMULT($B28:$K28,E$20:E$29)>0,1,0) -> 0 | F41: =IF(MMULT($B28:$K28,F$20:F$29)>0,1,0) -> 0 | G41: =IF(MMULT($B28:$K28,G$20:G$29)>0,1,0) -> 0 | H41: =IF(MMULT($B28:$K28,H$20:H$29)>0,1,0) -> 0 | I41: =IF(MMULT($B28:$K28,I$20:I$29)>0,1,0) -> 0 | ... K41: =IF(MMULT($B28:$K28,K$20:K$29)>0,1,0) -> 1
A42: F10 Student waiting time | B42: =IF(MMULT($B29:$K29,B$20:B$29)>0,1,0) -> 0 | C42: =IF(MMULT($B29:$K29,C$20:C$29)>0,1,0) -> 0 | D42: =IF(MMULT($B29:$K29,D$20:D$29)>0,1,0) -> 0 | E42: =IF(MMULT($B29:$K29,E$20:E$29)>0,1,0) -> 0 | F42: =IF(MMULT($B29:$K29,F$20:F$29)>0,1,0) -> 0 | G42: =IF(MMULT($B29:$K29,G$20:G$29)>0,1,0) -> 0 | H42: =IF(MMULT($B29:$K29,H$20:H$29)>0,1,0) -> 0 | I42: =IF(MMULT($B29:$K29,I$20:I$29)>0,1,0) -> 0 | ... K42: =IF(MMULT($B29:$K29,K$20:K$29)>0,1,0) -> 1
A44: Step 2.3 — transitivity (Boolean matrix squared; paths up to 8 steps)
B45: F1 | C45: F2 | D45: F3 | E45: F4 | F45: F5 | G45: F6 | H45: F7 | I45: F8 | J45: F9 | K45: F10
A46: F1 No live demand data | B46: =IF(MMULT($B33:$K33,B$33:B$42)>0,1,0) -> 1 | C46: =IF(MMULT($B33:$K33,C$33:C$42)>0,1,0) -> 0 | D46: =IF(MMULT($B33:$K33,D$33:D$42)>0,1,0) -> 1 | E46: =IF(MMULT($B33:$K33,E$33:E$42)>0,1,0) -> 1 | F46: =IF(MMULT($B33:$K33,F$33:F$42)>0,1,0) -> 1 | G46: =IF(MMULT($B33:$K33,G$33:G$42)>0,1,0) -> 1 | H46: =IF(MMULT($B33:$K33,H$33:H$42)>0,1,0) -> 1 | I46: =IF(MMULT($B33:$K33,I$33:I$42)>0,1,0) -> 1 | ... K46: =IF(MMULT($B33:$K33,K$33:K$42)>0,1,0) -> 1
A47: F2 Peak arrival concentration | B47: =IF(MMULT($B34:$K34,B$33:B$42)>0,1,0) -> 0 | C47: =IF(MMULT($B34:$K34,C$33:C$42)>0,1,0) -> 1 | D47: =IF(MMULT($B34:$K34,D$33:D$42)>0,1,0) -> 0 | E47: =IF(MMULT($B34:$K34,E$33:E$42)>0,1,0) -> 0 | F47: =IF(MMULT($B34:$K34,F$33:F$42)>0,1,0) -> 0 | G47: =IF(MMULT($B34:$K34,G$33:G$42)>0,1,0) -> 0 | H47: =IF(MMULT($B34:$K34,H$33:H$42)>0,1,0) -> 0 | I47: =IF(MMULT($B34:$K34,I$33:I$42)>0,1,0) -> 0 | ... K47: =IF(MMULT($B34:$K34,K$33:K$42)>0,1,0) -> 1
A48: F3 Habitual choice of mess | B48: =IF(MMULT($B35:$K35,B$33:B$42)>0,1,0) -> 0 | C48: =IF(MMULT($B35:$K35,C$33:C$42)>0,1,0) -> 0 | D48: =IF(MMULT($B35:$K35,D$33:D$42)>0,1,0) -> 1 | E48: =IF(MMULT($B35:$K35,E$33:E$42)>0,1,0) -> 0 | F48: =IF(MMULT($B35:$K35,F$33:F$42)>0,1,0) -> 0 | G48: =IF(MMULT($B35:$K35,G$33:G$42)>0,1,0) -> 0 | H48: =IF(MMULT($B35:$K35,H$33:H$42)>0,1,0) -> 0 | I48: =IF(MMULT($B35:$K35,I$33:I$42)>0,1,0) -> 0 | ... K48: =IF(MMULT($B35:$K35,K$33:K$42)>0,1,0) -> 1
A49: F4 Serving rate per line | B49: =IF(MMULT($B36:$K36,B$33:B$42)>0,1,0) -> 0 | C49: =IF(MMULT($B36:$K36,C$33:C$42)>0,1,0) -> 0 | D49: =IF(MMULT($B36:$K36,D$33:D$42)>0,1,0) -> 0 | E49: =IF(MMULT($B36:$K36,E$33:E$42)>0,1,0) -> 1 | F49: =IF(MMULT($B36:$K36,F$33:F$42)>0,1,0) -> 0 | G49: =IF(MMULT($B36:$K36,G$33:G$42)>0,1,0) -> 0 | H49: =IF(MMULT($B36:$K36,H$33:H$42)>0,1,0) -> 0 | I49: =IF(MMULT($B36:$K36,I$33:I$42)>0,1,0) -> 0 | ... K49: =IF(MMULT($B36:$K36,K$33:K$42)>0,1,0) -> 1
A50: F5 Number of serving stations | B50: =IF(MMULT($B37:$K37,B$33:B$42)>0,1,0) -> 0 | C50: =IF(MMULT($B37:$K37,C$33:C$42)>0,1,0) -> 0 | D50: =IF(MMULT($B37:$K37,D$33:D$42)>0,1,0) -> 0 | E50: =IF(MMULT($B37:$K37,E$33:E$42)>0,1,0) -> 0 | F50: =IF(MMULT($B37:$K37,F$33:F$42)>0,1,0) -> 1 | G50: =IF(MMULT($B37:$K37,G$33:G$42)>0,1,0) -> 0 | H50: =IF(MMULT($B37:$K37,H$33:H$42)>0,1,0) -> 0 | I50: =IF(MMULT($B37:$K37,I$33:I$42)>0,1,0) -> 0 | ... K50: =IF(MMULT($B37:$K37,K$33:K$42)>0,1,0) -> 1
A51: F6 Reactive replenishment | B51: =IF(MMULT($B38:$K38,B$33:B$42)>0,1,0) -> 0 | C51: =IF(MMULT($B38:$K38,C$33:C$42)>0,1,0) -> 0 | D51: =IF(MMULT($B38:$K38,D$33:D$42)>0,1,0) -> 0 | E51: =IF(MMULT($B38:$K38,E$33:E$42)>0,1,0) -> 1 | F51: =IF(MMULT($B38:$K38,F$33:F$42)>0,1,0) -> 0 | G51: =IF(MMULT($B38:$K38,G$33:G$42)>0,1,0) -> 1 | H51: =IF(MMULT($B38:$K38,H$33:H$42)>0,1,0) -> 0 | I51: =IF(MMULT($B38:$K38,I$33:I$42)>0,1,0) -> 1 | ... K51: =IF(MMULT($B38:$K38,K$33:K$42)>0,1,0) -> 1
A52: F7 Base-food buffer sizing | B52: =IF(MMULT($B39:$K39,B$33:B$42)>0,1,0) -> 0 | C52: =IF(MMULT($B39:$K39,C$33:C$42)>0,1,0) -> 0 | D52: =IF(MMULT($B39:$K39,D$33:D$42)>0,1,0) -> 0 | E52: =IF(MMULT($B39:$K39,E$33:E$42)>0,1,0) -> 1 | F52: =IF(MMULT($B39:$K39,F$33:F$42)>0,1,0) -> 0 | G52: =IF(MMULT($B39:$K39,G$33:G$42)>0,1,0) -> 0 | H52: =IF(MMULT($B39:$K39,H$33:H$42)>0,1,0) -> 1 | I52: =IF(MMULT($B39:$K39,I$33:I$42)>0,1,0) -> 1 | ... K52: =IF(MMULT($B39:$K39,K$33:K$42)>0,1,0) -> 1
A53: F8 Stock-outs | B53: =IF(MMULT($B40:$K40,B$33:B$42)>0,1,0) -> 0 | C53: =IF(MMULT($B40:$K40,C$33:C$42)>0,1,0) -> 0 | D53: =IF(MMULT($B40:$K40,D$33:D$42)>0,1,0) -> 0 | E53: =IF(MMULT($B40:$K40,E$33:E$42)>0,1,0) -> 1 | F53: =IF(MMULT($B40:$K40,F$33:F$42)>0,1,0) -> 0 | G53: =IF(MMULT($B40:$K40,G$33:G$42)>0,1,0) -> 0 | H53: =IF(MMULT($B40:$K40,H$33:H$42)>0,1,0) -> 0 | I53: =IF(MMULT($B40:$K40,I$33:I$42)>0,1,0) -> 1 | ... K53: =IF(MMULT($B40:$K40,K$33:K$42)>0,1,0) -> 1
A54: F9 Queue length at counter | B54: =IF(MMULT($B41:$K41,B$33:B$42)>0,1,0) -> 0 | C54: =IF(MMULT($B41:$K41,C$33:C$42)>0,1,0) -> 0 | D54: =IF(MMULT($B41:$K41,D$33:D$42)>0,1,0) -> 0 | E54: =IF(MMULT($B41:$K41,E$33:E$42)>0,1,0) -> 0 | F54: =IF(MMULT($B41:$K41,F$33:F$42)>0,1,0) -> 0 | G54: =IF(MMULT($B41:$K41,G$33:G$42)>0,1,0) -> 0 | H54: =IF(MMULT($B41:$K41,H$33:H$42)>0,1,0) -> 0 | I54: =IF(MMULT($B41:$K41,I$33:I$42)>0,1,0) -> 0 | ... K54: =IF(MMULT($B41:$K41,K$33:K$42)>0,1,0) -> 1
A55: F10 Student waiting time | B55: =IF(MMULT($B42:$K42,B$33:B$42)>0,1,0) -> 0 | C55: =IF(MMULT($B42:$K42,C$33:C$42)>0,1,0) -> 0 | D55: =IF(MMULT($B42:$K42,D$33:D$42)>0,1,0) -> 0 | E55: =IF(MMULT($B42:$K42,E$33:E$42)>0,1,0) -> 0 | F55: =IF(MMULT($B42:$K42,F$33:F$42)>0,1,0) -> 0 | G55: =IF(MMULT($B42:$K42,G$33:G$42)>0,1,0) -> 0 | H55: =IF(MMULT($B42:$K42,H$33:H$42)>0,1,0) -> 0 | I55: =IF(MMULT($B42:$K42,I$33:I$42)>0,1,0) -> 0 | ... K55: =IF(MMULT($B42:$K42,K$33:K$42)>0,1,0) -> 1
A57: Step 2.4 — transitivity (Boolean matrix squared; paths up to 16 steps)
B58: F1 | C58: F2 | D58: F3 | E58: F4 | F58: F5 | G58: F6 | H58: F7 | I58: F8 | J58: F9 | K58: F10
A59: F1 No live demand data | B59: =IF(MMULT($B46:$K46,B$46:B$55)>0,1,0) -> 1 | C59: =IF(MMULT($B46:$K46,C$46:C$55)>0,1,0) -> 0 | D59: =IF(MMULT($B46:$K46,D$46:D$55)>0,1,0) -> 1 | E59: =IF(MMULT($B46:$K46,E$46:E$55)>0,1,0) -> 1 | F59: =IF(MMULT($B46:$K46,F$46:F$55)>0,1,0) -> 1 | G59: =IF(MMULT($B46:$K46,G$46:G$55)>0,1,0) -> 1 | H59: =IF(MMULT($B46:$K46,H$46:H$55)>0,1,0) -> 1 | I59: =IF(MMULT($B46:$K46,I$46:I$55)>0,1,0) -> 1 | ... K59: =IF(MMULT($B46:$K46,K$46:K$55)>0,1,0) -> 1
A60: F2 Peak arrival concentration | B60: =IF(MMULT($B47:$K47,B$46:B$55)>0,1,0) -> 0 | C60: =IF(MMULT($B47:$K47,C$46:C$55)>0,1,0) -> 1 | D60: =IF(MMULT($B47:$K47,D$46:D$55)>0,1,0) -> 0 | E60: =IF(MMULT($B47:$K47,E$46:E$55)>0,1,0) -> 0 | F60: =IF(MMULT($B47:$K47,F$46:F$55)>0,1,0) -> 0 | G60: =IF(MMULT($B47:$K47,G$46:G$55)>0,1,0) -> 0 | H60: =IF(MMULT($B47:$K47,H$46:H$55)>0,1,0) -> 0 | I60: =IF(MMULT($B47:$K47,I$46:I$55)>0,1,0) -> 0 | ... K60: =IF(MMULT($B47:$K47,K$46:K$55)>0,1,0) -> 1
A61: F3 Habitual choice of mess | B61: =IF(MMULT($B48:$K48,B$46:B$55)>0,1,0) -> 0 | C61: =IF(MMULT($B48:$K48,C$46:C$55)>0,1,0) -> 0 | D61: =IF(MMULT($B48:$K48,D$46:D$55)>0,1,0) -> 1 | E61: =IF(MMULT($B48:$K48,E$46:E$55)>0,1,0) -> 0 | F61: =IF(MMULT($B48:$K48,F$46:F$55)>0,1,0) -> 0 | G61: =IF(MMULT($B48:$K48,G$46:G$55)>0,1,0) -> 0 | H61: =IF(MMULT($B48:$K48,H$46:H$55)>0,1,0) -> 0 | I61: =IF(MMULT($B48:$K48,I$46:I$55)>0,1,0) -> 0 | ... K61: =IF(MMULT($B48:$K48,K$46:K$55)>0,1,0) -> 1
A62: F4 Serving rate per line | B62: =IF(MMULT($B49:$K49,B$46:B$55)>0,1,0) -> 0 | C62: =IF(MMULT($B49:$K49,C$46:C$55)>0,1,0) -> 0 | D62: =IF(MMULT($B49:$K49,D$46:D$55)>0,1,0) -> 0 | E62: =IF(MMULT($B49:$K49,E$46:E$55)>0,1,0) -> 1 | F62: =IF(MMULT($B49:$K49,F$46:F$55)>0,1,0) -> 0 | G62: =IF(MMULT($B49:$K49,G$46:G$55)>0,1,0) -> 0 | H62: =IF(MMULT($B49:$K49,H$46:H$55)>0,1,0) -> 0 | I62: =IF(MMULT($B49:$K49,I$46:I$55)>0,1,0) -> 0 | ... K62: =IF(MMULT($B49:$K49,K$46:K$55)>0,1,0) -> 1
A63: F5 Number of serving stations | B63: =IF(MMULT($B50:$K50,B$46:B$55)>0,1,0) -> 0 | C63: =IF(MMULT($B50:$K50,C$46:C$55)>0,1,0) -> 0 | D63: =IF(MMULT($B50:$K50,D$46:D$55)>0,1,0) -> 0 | E63: =IF(MMULT($B50:$K50,E$46:E$55)>0,1,0) -> 0 | F63: =IF(MMULT($B50:$K50,F$46:F$55)>0,1,0) -> 1 | G63: =IF(MMULT($B50:$K50,G$46:G$55)>0,1,0) -> 0 | H63: =IF(MMULT($B50:$K50,H$46:H$55)>0,1,0) -> 0 | I63: =IF(MMULT($B50:$K50,I$46:I$55)>0,1,0) -> 0 | ... K63: =IF(MMULT($B50:$K50,K$46:K$55)>0,1,0) -> 1
A64: F6 Reactive replenishment | B64: =IF(MMULT($B51:$K51,B$46:B$55)>0,1,0) -> 0 | C64: =IF(MMULT($B51:$K51,C$46:C$55)>0,1,0) -> 0 | D64: =IF(MMULT($B51:$K51,D$46:D$55)>0,1,0) -> 0 | E64: =IF(MMULT($B51:$K51,E$46:E$55)>0,1,0) -> 1 | F64: =IF(MMULT($B51:$K51,F$46:F$55)>0,1,0) -> 0 | G64: =IF(MMULT($B51:$K51,G$46:G$55)>0,1,0) -> 1 | H64: =IF(MMULT($B51:$K51,H$46:H$55)>0,1,0) -> 0 | I64: =IF(MMULT($B51:$K51,I$46:I$55)>0,1,0) -> 1 | ... K64: =IF(MMULT($B51:$K51,K$46:K$55)>0,1,0) -> 1
A65: F7 Base-food buffer sizing | B65: =IF(MMULT($B52:$K52,B$46:B$55)>0,1,0) -> 0 | C65: =IF(MMULT($B52:$K52,C$46:C$55)>0,1,0) -> 0 | D65: =IF(MMULT($B52:$K52,D$46:D$55)>0,1,0) -> 0 | E65: =IF(MMULT($B52:$K52,E$46:E$55)>0,1,0) -> 1 | F65: =IF(MMULT($B52:$K52,F$46:F$55)>0,1,0) -> 0 | G65: =IF(MMULT($B52:$K52,G$46:G$55)>0,1,0) -> 0 | H65: =IF(MMULT($B52:$K52,H$46:H$55)>0,1,0) -> 1 | I65: =IF(MMULT($B52:$K52,I$46:I$55)>0,1,0) -> 1 | ... K65: =IF(MMULT($B52:$K52,K$46:K$55)>0,1,0) -> 1
A66: F8 Stock-outs | B66: =IF(MMULT($B53:$K53,B$46:B$55)>0,1,0) -> 0 | C66: =IF(MMULT($B53:$K53,C$46:C$55)>0,1,0) -> 0 | D66: =IF(MMULT($B53:$K53,D$46:D$55)>0,1,0) -> 0 | E66: =IF(MMULT($B53:$K53,E$46:E$55)>0,1,0) -> 1 | F66: =IF(MMULT($B53:$K53,F$46:F$55)>0,1,0) -> 0 | G66: =IF(MMULT($B53:$K53,G$46:G$55)>0,1,0) -> 0 | H66: =IF(MMULT($B53:$K53,H$46:H$55)>0,1,0) -> 0 | I66: =IF(MMULT($B53:$K53,I$46:I$55)>0,1,0) -> 1 | ... K66: =IF(MMULT($B53:$K53,K$46:K$55)>0,1,0) -> 1
A67: F9 Queue length at counter | B67: =IF(MMULT($B54:$K54,B$46:B$55)>0,1,0) -> 0 | C67: =IF(MMULT($B54:$K54,C$46:C$55)>0,1,0) -> 0 | D67: =IF(MMULT($B54:$K54,D$46:D$55)>0,1,0) -> 0 | E67: =IF(MMULT($B54:$K54,E$46:E$55)>0,1,0) -> 0 | F67: =IF(MMULT($B54:$K54,F$46:F$55)>0,1,0) -> 0 | G67: =IF(MMULT($B54:$K54,G$46:G$55)>0,1,0) -> 0 | H67: =IF(MMULT($B54:$K54,H$46:H$55)>0,1,0) -> 0 | I67: =IF(MMULT($B54:$K54,I$46:I$55)>0,1,0) -> 0 | ... K67: =IF(MMULT($B54:$K54,K$46:K$55)>0,1,0) -> 1
A68: F10 Student waiting time | B68: =IF(MMULT($B55:$K55,B$46:B$55)>0,1,0) -> 0 | C68: =IF(MMULT($B55:$K55,C$46:C$55)>0,1,0) -> 0 | D68: =IF(MMULT($B55:$K55,D$46:D$55)>0,1,0) -> 0 | E68: =IF(MMULT($B55:$K55,E$46:E$55)>0,1,0) -> 0 | F68: =IF(MMULT($B55:$K55,F$46:F$55)>0,1,0) -> 0 | G68: =IF(MMULT($B55:$K55,G$46:G$55)>0,1,0) -> 0 | H68: =IF(MMULT($B55:$K55,H$46:H$55)>0,1,0) -> 0 | I68: =IF(MMULT($B55:$K55,I$46:I$55)>0,1,0) -> 0 | ... K68: =IF(MMULT($B55:$K55,K$46:K$55)>0,1,0) -> 1
A70: Step 3 — Final reachability matrix → driving power and dependence | L70: Driving power | M70: Dependence | N70: MICMAC class
A71: F1 No live demand data | L71: =SUM(B59:K59) -> 9 | M71: =SUM(B59:B68) -> 1 | N71: =IF(L71>5,IF(M71>5,"Linkage","Driver"),IF(M71>5,"Dependent","Autonomous")) -> Driver
A72: F2 Peak arrival concentration | L72: =SUM(B60:K60) -> 3 | M72: =SUM(C59:C68) -> 1 | N72: =IF(L72>5,IF(M72>5,"Linkage","Driver"),IF(M72>5,"Dependent","Autonomous")) -> Autonomous
A73: F3 Habitual choice of mess | L73: =SUM(B61:K61) -> 3 | M73: =SUM(D59:D68) -> 2 | N73: =IF(L73>5,IF(M73>5,"Linkage","Driver"),IF(M73>5,"Dependent","Autonomous")) -> Autonomous
A74: F4 Serving rate per line | L74: =SUM(B62:K62) -> 3 | M74: =SUM(E59:E68) -> 5 | N74: =IF(L74>5,IF(M74>5,"Linkage","Driver"),IF(M74>5,"Dependent","Autonomous")) -> Autonomous
A75: F5 Number of serving stations | L75: =SUM(B63:K63) -> 3 | M75: =SUM(F59:F68) -> 2 | N75: =IF(L75>5,IF(M75>5,"Linkage","Driver"),IF(M75>5,"Dependent","Autonomous")) -> Autonomous
A76: F6 Reactive replenishment | L76: =SUM(B64:K64) -> 5 | M76: =SUM(G59:G68) -> 2 | N76: =IF(L76>5,IF(M76>5,"Linkage","Driver"),IF(M76>5,"Dependent","Autonomous")) -> Autonomous
A77: F7 Base-food buffer sizing | L77: =SUM(B65:K65) -> 5 | M77: =SUM(H59:H68) -> 2 | N77: =IF(L77>5,IF(M77>5,"Linkage","Driver"),IF(M77>5,"Dependent","Autonomous")) -> Autonomous
A78: F8 Stock-outs | L78: =SUM(B66:K66) -> 4 | M78: =SUM(I59:I68) -> 4 | N78: =IF(L78>5,IF(M78>5,"Linkage","Driver"),IF(M78>5,"Dependent","Autonomous")) -> Autonomous
A79: F9 Queue length at counter | L79: =SUM(B67:K67) -> 2 | M79: =SUM(J59:J68) -> 9 | N79: =IF(L79>5,IF(M79>5,"Linkage","Driver"),IF(M79>5,"Dependent","Autonomous")) -> Dependent
A80: F10 Student waiting time | L80: =SUM(B68:K68) -> 1 | M80: =SUM(K59:K68) -> 10 | N80: =IF(L80>5,IF(M80>5,"Linkage","Driver"),IF(M80>5,"Dependent","Autonomous")) -> Dependent
A82: Drivers (high driving power, low dependence) are the levers to pull first; dependent factors are outcomes. Expect F1 'No live demand data' to come out as the strongest driver and F10 'Student waiting time' as the main outcome — which is the case for the project.

Sheet S18 Heuristics
A1: Heuristics: simple rules that give good answers fast
A2: Session 18: Heuristics and metaheuristics — concepts and business applications
A4: 1. Door-screen switching rule (used in the prototype)
A5: Predicted wait if you stay (min) | B5: 6
A6: Predicted wait at the other mess (min) | B6: 2
A7: Walk between doors (min) | B7: =Inputs!$B$26 -> 0.5
A8: Minimum saving to suggest a switch (min) | B8: =Inputs!$B$30 -> 2
A9: Saving after the walk (min) | B9: =B5-(B6+B7) -> 3.5
A10: Screen says | B10: =IF(B9>=B8,"Other mess is faster → walk over",IF(B9>0,"Small saving: stay","Come on in")) -> Other mess is faster → walk over
A12: 2. Reorder-point rule for the star dish (start cooking the next batch when stock falls to this level)
A13: Consumption rate at peak (portions/min) | B13: =Inputs!$B$37 -> 20 | C13: Central's serving capacity (2 stations × 10/min) — at peak the stations run flat out. Measure from trays issued per minute
A14: Lead time from the call (worst case: has to be made, then sent, min) | B14: =Inputs!$B$16 -> 30
A15: Safety margin | B15: 0.2
A16: Reorder point (portions left when the next batch must start) | B16: =B13*B14*(1+B15) -> 720 | C16: Today the mess calls only when the dish is running low. If the kitchen then has to make it, the call must come this many portions before empty. If the batch is already made, the lead time is 10–14 min and the reorder point falls to about 40%.
A19: 3. Heuristic vs full model (from 20 simulated lunches, door screens, 60% follow)
A20: Policy | B20: Average wait (min) | C20: 90th pct wait (min) | D20: Comment
A21: No advice (today) | B21: 7.1 | C21: 17.4 | D21: Baseline
A22: Heuristic: switch if it saves ≥ 2 min | B22: 0.8 | C22: 2.3 | D22: Simple rule; works because feedback is fast (30 s walk)
A23: Full model: equilibrium split (bisection search) | B23: 0.8 | C23: 2.4 | D23: Better when advice is read early, e.g. on phones (avoids herding)
A25: 4. Metaheuristics (next step)
A26: A replenishment schedule that minimises waiting + waste over a whole lunch has no closed-form answer because of the queues. A metaheuristic (simulated annealing or a genetic algorithm) can search over schedules, scoring each candidate by running our simulator: 'simulation-optimisation'.

Sheet Simulation Results
A1: Results from the prototype's simulator (simulated data, not measurements)
A2: Feeds S7 (payoff anchors) and S18. 20 simulated lunches per row, 2,960 students, 11:30–14:30. Measured: students, seats, stations, scanners, 18-min visit, restock 30 min after a call (10–14 min if already made). Assumed: 85% habit, 10/min per station, 2 s per scan, 50% chance food is already made, arrival curve.
A4: Setting | B4: Students who follow | C4: Average wait (min) | D4: 90th pct wait (min) | E4: Walked to other mess | F4: Peak queue (people) | G4: Food run-outs per lunch
A5: No screens (today) | B5: – | C5: 7.1 | D5: 17.4 | E5: 0 | F5: 406 | G5: 1.3
A6: Screens, equilibrium split | B6: 0.3 | C6: 1.3 | D6: 4 | E6: 0.13 | F6: 133 | G6: 1.9
A7: Screens, equilibrium split | B7: 0.6 | C7: 0.8 | D7: 2.4 | E7: 0.14 | F7: 97 | G7: 1.6
A8: Screens, equilibrium split | B8: 1 | C8: 1.1 | D8: 3.2 | E8: 0.18 | F8: 98 | G8: 1.9
A10: Reduction in average wait (60% follow) | C10: =1-C7/C5 -> 0.88732394
A12: Visit time (scan to leaving) | B12: No screens | C12: With screens
A13: Normal time of day (min) | B13: 18.3 | C13: 17.1
A14: Peak (min) | B14: 25.3 | C14: 18.1
A16: Spreadsheet queuing model (S15 tab) — average wait, both messes
A17: Without screens (min) | C17: ='S15 Queuing'!$H$51 -> 6.8491395
A18: With screens (min) | C18: ='S15 Queuing'!$I$51 -> 0.41551531
A19: The spreadsheet model is simpler than the simulator (fixed 10-min bins, no stock-outs, no seat limit), so the two will not match exactly; both should show the same direction and rough size of improvement.
A21: Findings from the simulator: (1) Moving students moves the food run-outs: with screens Munch feeds more students and a 30-min call-back restock cannot keep up, so routing and food allocation (S10-11 LP) must be planned together; if the next batch is always made before the call (10–14 min to send), run-outs disappear in the model (table below). (2) The single face scanner (~30 scans/min at an assumed 2 s each) is close to Central's peak arrival rate, so a queue of 20–25 people can form OUTSIDE the scanner, which the biometric data cannot see.
A24: Next batch already made when the mess calls? | B24: Restock time | C24: Run-outs, no screens | D24: Run-outs, screens (60%) | E24: Avg wait no screens (min) | F24: Avg wait screens (min)
A25: Never | B25: 30 min | C25: 2 | D25: 3 | E25: 7 | F25: 0.9
A26: Half the time (simulator default) | B26: 30 or 10–14 min | C26: 1.3 | D26: 1.6 | E26: 7.1 | F26: 0.8
A27: Always | B27: 10–14 min | C27: 0 | D27: 0 | E27: 7.2 | F27: 0.9
A29: Reading: run-outs depend on whether the kitchen cooks ahead, not on the queue; waits barely move, because the serving stations set the queue. This is the case for early kitchen alerts (alternative A3) and for the pre-stage decision tree (S7).
